Workbook

Sheet Resumen
C2: Pibank: programa anual 2027
C4: Escenario seleccionado | D4: =Supuestos!D5 -> Base
C5: 12 meses 2027. Hipótesis condicionadas para preparar la propuesta; no forecast bancario ni retorno garantizado.
C7: Resultado anual dentro de 2027 | D7: Caso activo | E7: Unidad
C8: Visitas adicionales | D8: =IF(COUNT(Mensual!F16:Q16)=12,SUM(Mensual!F16:Q16),"N/D") -> 3874.5 | E8: visitas
C9: Aperturas incrementales | D9: =IF(COUNT(Mensual!F21:Q21)=12,SUM(Mensual!F21:Q21),"N/D") -> 77.49 | E9: cuentas
C10: Primer fondeo incremental dentro de 2027 | D10: =IF(COUNT(Mensual!F28:Q28)=12,SUM(Mensual!F28:Q28),"N/D") -> 50.3685 | E10: cuentas
C11: Primer fondeo programado después de 2027 | D11: =IF(COUNT(Mensual!F25:Q25,Mensual!F28:Q28)=24,SUM(Mensual!F25:Q25)-SUM(Mensual!F28:Q28),"N/D") -> 0 | E11: cuentas
C12: Depósito inicial bruto dentro de 2027 | D12: =IF(COUNT(D10,Supuestos!D10)=2,D10*Supuestos!D10,"N/D") -> 125921.25 | E12: USD eq.
C13: Saldo mantenido al cierre 2027 | D13: =Mensual!Q35 -> 109054.68 | E13: USD eq.
C14: Saldo externo al cierre 2027 | D14: =Mensual!Q36 -> 76338.274 | E14: USD eq.
C15: Saldo medio externo en 2027 | D15: =IF(COUNT(Mensual!F38:Q38)=12,AVERAGE(Mensual!F38:Q38),"N/D") -> 23973.872 | E15: USD eq.
C16: Escala/meta cuentas provisional | D16: =IF(AND(COUNT(D10,Supuestos!D8)=2,Supuestos!D8>0),D10/Supuestos!D8,"N/D") -> 0.0033137171 | E16: %
C18: Inversión cliente anual pendiente | D18: =Supuestos!D23 -> N/D | E18: USD
C19: CAC de cuenta fondeada incremental | D19: =IF(AND(Supuestos!D16="Sí",COUNT(D18,D10)=2,D18>0,D10>0),D18/D10,"N/D") -> N/D | E19: USD
C20: ROI dentro de 2027 | D20: =Mensual!Q44 -> N/D | E20: %
C21: Payback dentro de 2027 | D21: =IF(COUNT(Mensual!F46:Q46)=12,IFERROR(MATCH(1,Mensual!F46:Q46,0),"No en2027"),"N/D") -> N/D | E21: mes
C23: Saldo no es revenue. ROI/payback requieren inversión y Finance validados. Ninguna cohorte aporta valor después del horizonte.
C25: Mes | D25: Visitas adicionales | E25: Primer fondeo inc. | F25: Saldo cierre USD eq. | G25: Saldo externo USD eq. | H25: Saldo medio externo
C26: =Mensual!F8 -> 46388 | D26: =Mensual!F16 -> 13.8375 | E26: =Mensual!F28 -> 0.1798875 | F26: =Mensual!F35 -> 437.72625 | G26: =Mensual!F36 -> 306.40837 | H26: =Mensual!F38 -> 170.33219
C27: =Mensual!G8 -> 46419 | D27: =Mensual!G16 -> 41.5125 | E27: =Mensual!G28 -> 0.5396625 | F27: =Mensual!G35 -> 1736.6639 | G27: =Mensual!G36 -> 1215.6647 | H27: =Mensual!G38 -> 766.15211
C28: =Mensual!H8 -> 46447 | D28: =Mensual!H16 -> 83.025 | E28: =Mensual!H28 -> 1.079325 | F28: =Mensual!H35 -> 4270.0795 | G28: =Mensual!H36 -> 2989.0557 | H28: =Mensual!H38 -> 2205.1282
C29: =Mensual!I8 -> 46478 | D29: =Mensual!I16 -> 138.375 | E29: =Mensual!I28 -> 1.798875 | F29: =Mensual!I35 -> 8437.4733 | G29: =Mensual!I36 -> 5906.2313 | H29: =Mensual!I38 -> 4570.9414
C30: =Mensual!J8 -> 46508 | D30: =Mensual!J16 -> 207.5625 | E30: =Mensual!J28 -> 2.6983125 | F30: =Mensual!J35 -> 14576.634 | G30: =Mensual!J36 -> 10203.644 | H30: =Mensual!J38 -> 8311.8575
C31: =Mensual!K8 -> 46539 | D31: =Mensual!K16 -> 276.75 | E31: =Mensual!K28 -> 3.59775 | F31: =Mensual!K35 -> 22670.072 | G31: =Mensual!K36 -> 15869.051 | H31: =Mensual!K38 -> 13282.943
C32: =Mensual!L8 -> 46569 | D32: =Mensual!L16 -> 345.9375 | E32: =Mensual!L28 -> 4.4971875 | F32: =Mensual!L35 -> 32577.309 | G32: =Mensual!L36 -> 22804.116 | H32: =Mensual!L38 -> 19764.783
C33: =Mensual!M8 -> 46600 | D33: =Mensual!M16 -> 415.125 | E33: =Mensual!M28 -> 5.396625 | F33: =Mensual!M35 -> 44305.501 | G33: =Mensual!M36 -> 31013.851 | H33: =Mensual!M38 -> 27422.823
C34: =Mensual!N8 -> 46631 | D34: =Mensual!N16 -> 484.3125 | E34: =Mensual!N28 -> 6.2960625 | F34: =Mensual!N35 -> 57903.288 | G34: =Mensual!N36 -> 40532.301 | H34: =Mensual!N38 -> 36204.619
C35: =Mensual!O8 -> 46661 | D35: =Mensual!O16 -> 553.5 | E35: =Mensual!O28 -> 7.1955 | F35: =Mensual!O35 -> 73184.17 | G35: =Mensual!O36 -> 51228.919 | H35: =Mensual!O38 -> 46565.73
C36: =Mensual!P8 -> 46692 | D36: =Mensual!P16 -> 622.6875 | E36: =Mensual!P28 -> 8.0949375 | F36: =Mensual!P35 -> 90323.317 | G36: =Mensual!P36 -> 63226.322 | H36: =Mensual!P38 -> 57782.461
C37: =Mensual!Q8 -> 46722 | D37: =Mensual!Q16 -> 691.875 | E37: =Mensual!Q28 -> 8.994375 | F37: =Mensual!Q35 -> 109054.68 | G37: =Mensual!Q36 -> 76338.274 | H37: =Mensual!Q38 -> 70638.698
C40: M 1: acceso/medición/delivery. M 3/6/9/12: optimización trimestral. No pilotoSEO ni juicio de viabilidad a 3 meses.
C41: Demanda histórica y alcance de investigación se leen en Demanda/Historia; los drivers 2027 continúan siendo hipótesis.
C42: US$38 m y ticketUS$2500 provisionales; anualidad de la meta aún no confirmada. USD eq.no significa productoUSD disponible.
C43: Origen externo fijo por cohorte. Saldo medio pondera días activos; diciembre tiene menos tiempo de contribución que enero.
C45: Cambiar selector en SupuestosD 4. Cambiar lagD 18/díaD 19 o tasas actualiza el mismo build; fuentes históricas permanecen intactas.

Sheet Supuestos
C2: Controles y drivers 2027
C4: Selector escenario (1 / 2 / 3) | D4: 2
C5: Caso activo | D5: =CHOOSE(D4,"Conservador","Base","Favorable") -> Base
C6: 1 Conservador, 2 Base, 3 Favorable. Casos de prueba; nombres no representan probabilidades.
C8: Meta cuentas provisional | D8: 15200
C9: Meta USD provisional | D9: 38000000
C10: Ticket USD equivalente provisional | D10: 2500
C11: Inicio ilustrativo | D11: 46388
C12: US$38 m es inferencia provisional. Programa anual 2027 no confirma periodo ni definición de la meta bancaria.
C13: Relevancia/elegibilidad ilustrativa | D13: 0.75
C14: Finance validó método neto | D14: No
C15: Valor neto anual / USD saldo externo
C16: Inversión completa validada | D16: No
C17: Capacidad total con reserva (horas) | D17: 2896
C18: Lag apertura a fondeo (meses) | D18: 0
C19: Día fondeo supuesto (1–28) | D19: 15
C20: Proxy mensual de fuente histórica | D20: =Demanda!J5 -> 3690
F21: =EDATE($D$11,0) -> 46388 | G21: =EDATE($D$11,1) -> 46419 | H21: =EDATE($D$11,2) -> 46447 | I21: =EDATE($D$11,3) -> 46478 | J21: =EDATE($D$11,4) -> 46508 | K21: =EDATE($D$11,5) -> 46539 | L21: =EDATE($D$11,6) -> 46569 | M21: =EDATE($D$11,7) -> 46600 | N21: =EDATE($D$11,8) -> 46631 | O21: =EDATE($D$11,9) -> 46661 | P21: =EDATE($D$11,10) -> 46692 | Q21: =EDATE($D$11,11) -> 46722
C22: Inversión cliente por mes USD (pendiente)
C23: Inversión anual si completa | D23: =IF(COUNT(F22:Q22)=12,IF(MIN(F22:Q22)>=0,SUM(F22:Q22),"N/D"),"N/D") -> N/D
C24: Coste interno Efeonce USD (pendiente)
C25: Multiplicador crecimiento 2027 supuesto | D25: 1
C26: Estacionalidad usada | D26: Plano
C27: Factor histórico observado / promedio | F27: =IF(COUNT(Historia!F11)=1,Historia!F11,"N/D") -> 1.0884184 | G27: =IF(COUNT(Historia!G11)=1,Historia!G11,"N/D") -> 0.91905355 | H27: =IF(COUNT(Historia!H11)=1,Historia!H11,"N/D") -> 1.2104608 | I27: =IF(COUNT(Historia!I11)=1,Historia!I11,"N/D") -> 1.1058531 | J27: =IF(COUNT(Historia!J11)=1,Historia!J11,"N/D") -> 0.92403487 | K27: =IF(COUNT(Historia!K11)=1,Historia!K11,"N/D") -> 0.73723537 | L27: =IF(COUNT(Historia!L11)=1,Historia!L11,"N/D") -> 0.87920299 | M27: =IF(COUNT(Historia!M11)=1,Historia!M11,"N/D") -> 0.86924035 | ... Q27: =IF(COUNT(Historia!Q11)=1,Historia!Q11,"N/D") -> 0.90161893
C28: Factor usado en hipótesis 2027 | F28: =IF($D$26="Plano",1,F27) -> 1 | G28: =IF($D$26="Plano",1,G27) -> 1 | H28: =IF($D$26="Plano",1,H27) -> 1 | I28: =IF($D$26="Plano",1,I27) -> 1 | J28: =IF($D$26="Plano",1,J27) -> 1 | K28: =IF($D$26="Plano",1,K27) -> 1 | L28: =IF($D$26="Plano",1,L27) -> 1 | M28: =IF($D$26="Plano",1,M27) -> 1 | ... Q28: =IF($D$26="Plano",1,Q27) -> 1
C30: Captura adicional activo | F30: =IF(CHOOSE($D$4,COUNT(F31),COUNT(F32),COUNT(F33))=1,CHOOSE($D$4,F31,F32,F33),"N/D") -> 0.005 | G30: =IF(CHOOSE($D$4,COUNT(G31),COUNT(G32),COUNT(G33))=1,CHOOSE($D$4,G31,G32,G33),"N/D") -> 0.015 | H30: =IF(CHOOSE($D$4,COUNT(H31),COUNT(H32),COUNT(H33))=1,CHOOSE($D$4,H31,H32,H33),"N/D") -> 0.03 | I30: =IF(CHOOSE($D$4,COUNT(I31),COUNT(I32),COUNT(I33))=1,CHOOSE($D$4,I31,I32,I33),"N/D") -> 0.05 | J30: =IF(CHOOSE($D$4,COUNT(J31),COUNT(J32),COUNT(J33))=1,CHOOSE($D$4,J31,J32,J33),"N/D") -> 0.075 | K30: =IF(CHOOSE($D$4,COUNT(K31),COUNT(K32),COUNT(K33))=1,CHOOSE($D$4,K31,K32,K33),"N/D") -> 0.1 | L30: =IF(CHOOSE($D$4,COUNT(L31),COUNT(L32),COUNT(L33))=1,CHOOSE($D$4,L31,L32,L33),"N/D") -> 0.125 | M30: =IF(CHOOSE($D$4,COUNT(M31),COUNT(M32),COUNT(M33))=1,CHOOSE($D$4,M31,M32,M33),"N/D") -> 0.15 | ... Q30: =IF(CHOOSE($D$4,COUNT(Q31),COUNT(Q32),COUNT(Q33))=1,CHOOSE($D$4,Q31,Q32,Q33),"N/D") -> 0.25
C31: Conservador | F31: 0.0025 | G31: 0.005 | H31: 0.01 | I31: 0.02 | J31: 0.035 | K31: 0.05 | L31: 0.065 | M31: 0.08 | N31: 0.095 | O31: 0.11 | P31: 0.12 | Q31: 0.13
C32: Base | F32: 0.005 | G32: 0.015 | H32: 0.03 | I32: 0.05 | J32: 0.075 | K32: 0.1 | L32: 0.125 | M32: 0.15 | N32: 0.175 | O32: 0.2 | P32: 0.225 | Q32: 0.25
C33: Favorable | F33: 0.01 | G33: 0.025 | H33: 0.05 | I33: 0.075 | J33: 0.1 | K33: 0.15 | L33: 0.2 | M33: 0.25 | N33: 0.3 | O33: 0.35 | P33: 0.4 | Q33: 0.45
C35: Captura referencia activo | F35: =IF(CHOOSE($D$4,COUNT(F36),COUNT(F37),COUNT(F38))=1,CHOOSE($D$4,F36,F37,F38),"N/D") -> 0.01 | G35: =IF(CHOOSE($D$4,COUNT(G36),COUNT(G37),COUNT(G38))=1,CHOOSE($D$4,G36,G37,G38),"N/D") -> 0.01 | H35: =IF(CHOOSE($D$4,COUNT(H36),COUNT(H37),COUNT(H38))=1,CHOOSE($D$4,H36,H37,H38),"N/D") -> 0.01 | I35: =IF(CHOOSE($D$4,COUNT(I36),COUNT(I37),COUNT(I38))=1,CHOOSE($D$4,I36,I37,I38),"N/D") -> 0.01 | J35: =IF(CHOOSE($D$4,COUNT(J36),COUNT(J37),COUNT(J38))=1,CHOOSE($D$4,J36,J37,J38),"N/D") -> 0.01 | K35: =IF(CHOOSE($D$4,COUNT(K36),COUNT(K37),COUNT(K38))=1,CHOOSE($D$4,K36,K37,K38),"N/D") -> 0.01 | L35: =IF(CHOOSE($D$4,COUNT(L36),COUNT(L37),COUNT(L38))=1,CHOOSE($D$4,L36,L37,L38),"N/D") -> 0.01 | M35: =IF(CHOOSE($D$4,COUNT(M36),COUNT(M37),COUNT(M38))=1,CHOOSE($D$4,M36,M37,M38),"N/D") -> 0.01 | ... Q35: =IF(CHOOSE($D$4,COUNT(Q36),COUNT(Q37),COUNT(Q38))=1,CHOOSE($D$4,Q36,Q37,Q38),"N/D") -> 0.01
C36: Conservador | F36: 0.01 | G36: 0.01 | H36: 0.01 | I36: 0.01 | J36: 0.01 | K36: 0.01 | L36: 0.01 | M36: 0.01 | N36: 0.01 | O36: 0.01 | P36: 0.01 | Q36: 0.01
C37: Base | F37: 0.01 | G37: 0.01 | H37: 0.01 | I37: 0.01 | J37: 0.01 | K37: 0.01 | L37: 0.01 | M37: 0.01 | N37: 0.01 | O37: 0.01 | P37: 0.01 | Q37: 0.01
C38: Favorable | F38: 0.01 | G38: 0.01 | H38: 0.01 | I38: 0.01 | J38: 0.01 | K38: 0.01 | L38: 0.01 | M38: 0.01 | N38: 0.01 | O38: 0.01 | P38: 0.01 | Q38: 0.01
C40: Visita a apertura activo | F40: =IF(CHOOSE($D$4,COUNT(F41),COUNT(F42),COUNT(F43))=1,CHOOSE($D$4,F41,F42,F43),"N/D") -> 0.02 | G40: =IF(CHOOSE($D$4,COUNT(G41),COUNT(G42),COUNT(G43))=1,CHOOSE($D$4,G41,G42,G43),"N/D") -> 0.02 | H40: =IF(CHOOSE($D$4,COUNT(H41),COUNT(H42),COUNT(H43))=1,CHOOSE($D$4,H41,H42,H43),"N/D") -> 0.02 | I40: =IF(CHOOSE($D$4,COUNT(I41),COUNT(I42),COUNT(I43))=1,CHOOSE($D$4,I41,I42,I43),"N/D") -> 0.02 | J40: =IF(CHOOSE($D$4,COUNT(J41),COUNT(J42),COUNT(J43))=1,CHOOSE($D$4,J41,J42,J43),"N/D") -> 0.02 | K40: =IF(CHOOSE($D$4,COUNT(K41),COUNT(K42),COUNT(K43))=1,CHOOSE($D$4,K41,K42,K43),"N/D") -> 0.02 | L40: =IF(CHOOSE($D$4,COUNT(L41),COUNT(L42),COUNT(L43))=1,CHOOSE($D$4,L41,L42,L43),"N/D") -> 0.02 | M40: =IF(CHOOSE($D$4,COUNT(M41),COUNT(M42),COUNT(M43))=1,CHOOSE($D$4,M41,M42,M43),"N/D") -> 0.02 | ... Q40: =IF(CHOOSE($D$4,COUNT(Q41),COUNT(Q42),COUNT(Q43))=1,CHOOSE($D$4,Q41,Q42,Q43),"N/D") -> 0.02
C41: Conservador | F41: 0.01 | G41: 0.01 | H41: 0.01 | I41: 0.01 | J41: 0.01 | K41: 0.01 | L41: 0.01 | M41: 0.01 | N41: 0.01 | O41: 0.01 | P41: 0.01 | Q41: 0.01
C42: Base | F42: 0.02 | G42: 0.02 | H42: 0.02 | I42: 0.02 | J42: 0.02 | K42: 0.02 | L42: 0.02 | M42: 0.02 | N42: 0.02 | O42: 0.02 | P42: 0.02 | Q42: 0.02
C43: Favorable | F43: 0.03 | G43: 0.03 | H43: 0.03 | I43: 0.03 | J43: 0.03 | K43: 0.03 | L43: 0.03 | M43: 0.03 | N43: 0.03 | O43: 0.03 | P43: 0.03 | Q43: 0.03
C45: Apertura a fondeo activo | F45: =IF(CHOOSE($D$4,COUNT(F46),COUNT(F47),COUNT(F48))=1,CHOOSE($D$4,F46,F47,F48),"N/D") -> 0.65 | G45: =IF(CHOOSE($D$4,COUNT(G46),COUNT(G47),COUNT(G48))=1,CHOOSE($D$4,G46,G47,G48),"N/D") -> 0.65 | H45: =IF(CHOOSE($D$4,COUNT(H46),COUNT(H47),COUNT(H48))=1,CHOOSE($D$4,H46,H47,H48),"N/D") -> 0.65 | I45: =IF(CHOOSE($D$4,COUNT(I46),COUNT(I47),COUNT(I48))=1,CHOOSE($D$4,I46,I47,I48),"N/D") -> 0.65 | J45: =IF(CHOOSE($D$4,COUNT(J46),COUNT(J47),COUNT(J48))=1,CHOOSE($D$4,J46,J47,J48),"N/D") -> 0.65 | K45: =IF(CHOOSE($D$4,COUNT(K46),COUNT(K47),COUNT(K48))=1,CHOOSE($D$4,K46,K47,K48),"N/D") -> 0.65 | L45: =IF(CHOOSE($D$4,COUNT(L46),COUNT(L47),COUNT(L48))=1,CHOOSE($D$4,L46,L47,L48),"N/D") -> 0.65 | M45: =IF(CHOOSE($D$4,COUNT(M46),COUNT(M47),COUNT(M48))=1,CHOOSE($D$4,M46,M47,M48),"N/D") -> 0.65 | ... Q45: =IF(CHOOSE($D$4,COUNT(Q46),COUNT(Q47),COUNT(Q48))=1,CHOOSE($D$4,Q46,Q47,Q48),"N/D") -> 0.65
C46: Conservador | F46: 0.5 | G46: 0.5 | H46: 0.5 | I46: 0.5 | J46: 0.5 | K46: 0.5 | L46: 0.5 | M46: 0.5 | N46: 0.5 | O46: 0.5 | P46: 0.5 | Q46: 0.5
C47: Base | F47: 0.65 | G47: 0.65 | H47: 0.65 | I47: 0.65 | J47: 0.65 | K47: 0.65 | L47: 0.65 | M47: 0.65 | N47: 0.65 | O47: 0.65 | P47: 0.65 | Q47: 0.65
C48: Favorable | F48: 0.75 | G48: 0.75 | H48: 0.75 | I48: 0.75 | J48: 0.75 | K48: 0.75 | L48: 0.75 | M48: 0.75 | N48: 0.75 | O48: 0.75 | P48: 0.75 | Q48: 0.75
C50: Proxy demanda trasladado 2027 activo | F50: =IF(CHOOSE($D$4,COUNT(F51),COUNT(F52),COUNT(F53))=1,CHOOSE($D$4,F51,F52,F53),"N/D") -> 3690 | G50: =IF(CHOOSE($D$4,COUNT(G51),COUNT(G52),COUNT(G53))=1,CHOOSE($D$4,G51,G52,G53),"N/D") -> 3690 | H50: =IF(CHOOSE($D$4,COUNT(H51),COUNT(H52),COUNT(H53))=1,CHOOSE($D$4,H51,H52,H53),"N/D") -> 3690 | I50: =IF(CHOOSE($D$4,COUNT(I51),COUNT(I52),COUNT(I53))=1,CHOOSE($D$4,I51,I52,I53),"N/D") -> 3690 | J50: =IF(CHOOSE($D$4,COUNT(J51),COUNT(J52),COUNT(J53))=1,CHOOSE($D$4,J51,J52,J53),"N/D") -> 3690 | K50: =IF(CHOOSE($D$4,COUNT(K51),COUNT(K52),COUNT(K53))=1,CHOOSE($D$4,K51,K52,K53),"N/D") -> 3690 | L50: =IF(CHOOSE($D$4,COUNT(L51),COUNT(L52),COUNT(L53))=1,CHOOSE($D$4,L51,L52,L53),"N/D") -> 3690 | M50: =IF(CHOOSE($D$4,COUNT(M51),COUNT(M52),COUNT(M53))=1,CHOOSE($D$4,M51,M52,M53),"N/D") -> 3690 | ... Q50: =IF(CHOOSE($D$4,COUNT(Q51),COUNT(Q52),COUNT(Q53))=1,CHOOSE($D$4,Q51,Q52,Q53),"N/D") -> 3690
C51: Conservador | F51: 3690 | G51: 3690 | H51: 3690 | I51: 3690 | J51: 3690 | K51: 3690 | L51: 3690 | M51: 3690 | N51: 3690 | O51: 3690 | P51: 3690 | Q51: 3690
C52: Base | F52: 3690 | G52: 3690 | H52: 3690 | I52: 3690 | J52: 3690 | K52: 3690 | L52: 3690 | M52: 3690 | N52: 3690 | O52: 3690 | P52: 3690 | Q52: 3690
C53: Favorable | F53: 3690 | G53: 3690 | H53: 3690 | I53: 3690 | J53: 3690 | K53: 3690 | L53: 3690 | M53: 3690 | N53: 3690 | O53: 3690 | P53: 3690 | Q53: 3690
C55: Saldo relativo 30 d activo | F55: =IF(CHOOSE($D$4,COUNT(F56),COUNT(F57),COUNT(F58))=1,CHOOSE($D$4,F56,F57,F58),"N/D") -> 0.95 | G55: =IF(CHOOSE($D$4,COUNT(G56),COUNT(G57),COUNT(G58))=1,CHOOSE($D$4,G56,G57,G58),"N/D") -> 0.95 | H55: =IF(CHOOSE($D$4,COUNT(H56),COUNT(H57),COUNT(H58))=1,CHOOSE($D$4,H56,H57,H58),"N/D") -> 0.95 | I55: =IF(CHOOSE($D$4,COUNT(I56),COUNT(I57),COUNT(I58))=1,CHOOSE($D$4,I56,I57,I58),"N/D") -> 0.95 | J55: =IF(CHOOSE($D$4,COUNT(J56),COUNT(J57),COUNT(J58))=1,CHOOSE($D$4,J56,J57,J58),"N/D") -> 0.95 | K55: =IF(CHOOSE($D$4,COUNT(K56),COUNT(K57),COUNT(K58))=1,CHOOSE($D$4,K56,K57,K58),"N/D") -> 0.95 | L55: =IF(CHOOSE($D$4,COUNT(L56),COUNT(L57),COUNT(L58))=1,CHOOSE($D$4,L56,L57,L58),"N/D") -> 0.95 | M55: =IF(CHOOSE($D$4,COUNT(M56),COUNT(M57),COUNT(M58))=1,CHOOSE($D$4,M56,M57,M58),"N/D") -> 0.95 | ... Q55: =IF(CHOOSE($D$4,COUNT(Q56),COUNT(Q57),COUNT(Q58))=1,CHOOSE($D$4,Q56,Q57,Q58),"N/D") -> 0.95
C56: Conservador | F56: 0.9 | G56: 0.9 | H56: 0.9 | I56: 0.9 | J56: 0.9 | K56: 0.9 | L56: 0.9 | M56: 0.9 | N56: 0.9 | O56: 0.9 | P56: 0.9 | Q56: 0.9
C57: Base | F57: 0.95 | G57: 0.95 | H57: 0.95 | I57: 0.95 | J57: 0.95 | K57: 0.95 | L57: 0.95 | M57: 0.95 | N57: 0.95 | O57: 0.95 | P57: 0.95 | Q57: 0.95
C58: Favorable | F58: 0.97 | G58: 0.97 | H58: 0.97 | I58: 0.97 | J58: 0.97 | K58: 0.97 | L58: 0.97 | M58: 0.97 | N58: 0.97 | O58: 0.97 | P58: 0.97 | Q58: 0.97
C60: Saldo relativo 60 d activo | F60: =IF(CHOOSE($D$4,COUNT(F61),COUNT(F62),COUNT(F63))=1,CHOOSE($D$4,F61,F62,F63),"N/D") -> 0.9 | G60: =IF(CHOOSE($D$4,COUNT(G61),COUNT(G62),COUNT(G63))=1,CHOOSE($D$4,G61,G62,G63),"N/D") -> 0.9 | H60: =IF(CHOOSE($D$4,COUNT(H61),COUNT(H62),COUNT(H63))=1,CHOOSE($D$4,H61,H62,H63),"N/D") -> 0.9 | I60: =IF(CHOOSE($D$4,COUNT(I61),COUNT(I62),COUNT(I63))=1,CHOOSE($D$4,I61,I62,I63),"N/D") -> 0.9 | J60: =IF(CHOOSE($D$4,COUNT(J61),COUNT(J62),COUNT(J63))=1,CHOOSE($D$4,J61,J62,J63),"N/D") -> 0.9 | K60: =IF(CHOOSE($D$4,COUNT(K61),COUNT(K62),COUNT(K63))=1,CHOOSE($D$4,K61,K62,K63),"N/D") -> 0.9 | L60: =IF(CHOOSE($D$4,COUNT(L61),COUNT(L62),COUNT(L63))=1,CHOOSE($D$4,L61,L62,L63),"N/D") -> 0.9 | M60: =IF(CHOOSE($D$4,COUNT(M61),COUNT(M62),COUNT(M63))=1,CHOOSE($D$4,M61,M62,M63),"N/D") -> 0.9 | ... Q60: =IF(CHOOSE($D$4,COUNT(Q61),COUNT(Q62),COUNT(Q63))=1,CHOOSE($D$4,Q61,Q62,Q63),"N/D") -> 0.9
C61: Conservador | F61: 0.8 | G61: 0.8 | H61: 0.8 | I61: 0.8 | J61: 0.8 | K61: 0.8 | L61: 0.8 | M61: 0.8 | N61: 0.8 | O61: 0.8 | P61: 0.8 | Q61: 0.8
C62: Base | F62: 0.9 | G62: 0.9 | H62: 0.9 | I62: 0.9 | J62: 0.9 | K62: 0.9 | L62: 0.9 | M62: 0.9 | N62: 0.9 | O62: 0.9 | P62: 0.9 | Q62: 0.9
C63: Favorable | F63: 0.95 | G63: 0.95 | H63: 0.95 | I63: 0.95 | J63: 0.95 | K63: 0.95 | L63: 0.95 | M63: 0.95 | N63: 0.95 | O63: 0.95 | P63: 0.95 | Q63: 0.95
C65: Saldo relativo 90 d activo | F65: =IF(CHOOSE($D$4,COUNT(F66),COUNT(F67),COUNT(F68))=1,CHOOSE($D$4,F66,F67,F68),"N/D") -> 0.85 | G65: =IF(CHOOSE($D$4,COUNT(G66),COUNT(G67),COUNT(G68))=1,CHOOSE($D$4,G66,G67,G68),"N/D") -> 0.85 | H65: =IF(CHOOSE($D$4,COUNT(H66),COUNT(H67),COUNT(H68))=1,CHOOSE($D$4,H66,H67,H68),"N/D") -> 0.85 | I65: =IF(CHOOSE($D$4,COUNT(I66),COUNT(I67),COUNT(I68))=1,CHOOSE($D$4,I66,I67,I68),"N/D") -> 0.85 | J65: =IF(CHOOSE($D$4,COUNT(J66),COUNT(J67),COUNT(J68))=1,CHOOSE($D$4,J66,J67,J68),"N/D") -> 0.85 | K65: =IF(CHOOSE($D$4,COUNT(K66),COUNT(K67),COUNT(K68))=1,CHOOSE($D$4,K66,K67,K68),"N/D") -> 0.85 | L65: =IF(CHOOSE($D$4,COUNT(L66),COUNT(L67),COUNT(L68))=1,CHOOSE($D$4,L66,L67,L68),"N/D") -> 0.85 | M65: =IF(CHOOSE($D$4,COUNT(M66),COUNT(M67),COUNT(M68))=1,CHOOSE($D$4,M66,M67,M68),"N/D") -> 0.85 | ... Q65: =IF(CHOOSE($D$4,COUNT(Q66),COUNT(Q67),COUNT(Q68))=1,CHOOSE($D$4,Q66,Q67,Q68),"N/D") -> 0.85
C66: Conservador | F66: 0.7 | G66: 0.7 | H66: 0.7 | I66: 0.7 | J66: 0.7 | K66: 0.7 | L66: 0.7 | M66: 0.7 | N66: 0.7 | O66: 0.7 | P66: 0.7 | Q66: 0.7
C67: Base | F67: 0.85 | G67: 0.85 | H67: 0.85 | I67: 0.85 | J67: 0.85 | K67: 0.85 | L67: 0.85 | M67: 0.85 | N67: 0.85 | O67: 0.85 | P67: 0.85 | Q67: 0.85
C68: Favorable | F68: 0.92 | G68: 0.92 | H68: 0.92 | I68: 0.92 | J68: 0.92 | K68: 0.92 | L68: 0.92 | M68: 0.92 | N68: 0.92 | O68: 0.92 | P68: 0.92 | Q68: 0.92
C70: Saldo relativo 180 d activo | F70: =IF(CHOOSE($D$4,COUNT(F71),COUNT(F72),COUNT(F73))=1,CHOOSE($D$4,F71,F72,F73),"N/D") -> 0.8 | G70: =IF(CHOOSE($D$4,COUNT(G71),COUNT(G72),COUNT(G73))=1,CHOOSE($D$4,G71,G72,G73),"N/D") -> 0.8 | H70: =IF(CHOOSE($D$4,COUNT(H71),COUNT(H72),COUNT(H73))=1,CHOOSE($D$4,H71,H72,H73),"N/D") -> 0.8 | I70: =IF(CHOOSE($D$4,COUNT(I71),COUNT(I72),COUNT(I73))=1,CHOOSE($D$4,I71,I72,I73),"N/D") -> 0.8 | J70: =IF(CHOOSE($D$4,COUNT(J71),COUNT(J72),COUNT(J73))=1,CHOOSE($D$4,J71,J72,J73),"N/D") -> 0.8 | K70: =IF(CHOOSE($D$4,COUNT(K71),COUNT(K72),COUNT(K73))=1,CHOOSE($D$4,K71,K72,K73),"N/D") -> 0.8 | L70: =IF(CHOOSE($D$4,COUNT(L71),COUNT(L72),COUNT(L73))=1,CHOOSE($D$4,L71,L72,L73),"N/D") -> 0.8 | M70: =IF(CHOOSE($D$4,COUNT(M71),COUNT(M72),COUNT(M73))=1,CHOOSE($D$4,M71,M72,M73),"N/D") -> 0.8 | ... Q70: =IF(CHOOSE($D$4,COUNT(Q71),COUNT(Q72),COUNT(Q73))=1,CHOOSE($D$4,Q71,Q72,Q73),"N/D") -> 0.8
C71: Conservador | F71: 0.65 | G71: 0.65 | H71: 0.65 | I71: 0.65 | J71: 0.65 | K71: 0.65 | L71: 0.65 | M71: 0.65 | N71: 0.65 | O71: 0.65 | P71: 0.65 | Q71: 0.65
C72: Base | F72: 0.8 | G72: 0.8 | H72: 0.8 | I72: 0.8 | J72: 0.8 | K72: 0.8 | L72: 0.8 | M72: 0.8 | N72: 0.8 | O72: 0.8 | P72: 0.8 | Q72: 0.8
C73: Favorable | F73: 0.9 | G73: 0.9 | H73: 0.9 | I73: 0.9 | J73: 0.9 | K73: 0.9 | L73: 0.9 | M73: 0.9 | N73: 0.9 | O73: 0.9 | P73: 0.9 | Q73: 0.9
C75: Saldo relativo 365 d activo | F75: =IF(CHOOSE($D$4,COUNT(F76),COUNT(F77),COUNT(F78))=1,CHOOSE($D$4,F76,F77,F78),"N/D") -> 0.75 | G75: =IF(CHOOSE($D$4,COUNT(G76),COUNT(G77),COUNT(G78))=1,CHOOSE($D$4,G76,G77,G78),"N/D") -> 0.75 | H75: =IF(CHOOSE($D$4,COUNT(H76),COUNT(H77),COUNT(H78))=1,CHOOSE($D$4,H76,H77,H78),"N/D") -> 0.75 | I75: =IF(CHOOSE($D$4,COUNT(I76),COUNT(I77),COUNT(I78))=1,CHOOSE($D$4,I76,I77,I78),"N/D") -> 0.75 | J75: =IF(CHOOSE($D$4,COUNT(J76),COUNT(J77),COUNT(J78))=1,CHOOSE($D$4,J76,J77,J78),"N/D") -> 0.75 | K75: =IF(CHOOSE($D$4,COUNT(K76),COUNT(K77),COUNT(K78))=1,CHOOSE($D$4,K76,K77,K78),"N/D") -> 0.75 | L75: =IF(CHOOSE($D$4,COUNT(L76),COUNT(L77),COUNT(L78))=1,CHOOSE($D$4,L76,L77,L78),"N/D") -> 0.75 | M75: =IF(CHOOSE($D$4,COUNT(M76),COUNT(M77),COUNT(M78))=1,CHOOSE($D$4,M76,M77,M78),"N/D") -> 0.75 | ... Q75: =IF(CHOOSE($D$4,COUNT(Q76),COUNT(Q77),COUNT(Q78))=1,CHOOSE($D$4,Q76,Q77,Q78),"N/D") -> 0.75
C76: Conservador | F76: 0.55 | G76: 0.55 | H76: 0.55 | I76: 0.55 | J76: 0.55 | K76: 0.55 | L76: 0.55 | M76: 0.55 | N76: 0.55 | O76: 0.55 | P76: 0.55 | Q76: 0.55
C77: Base | F77: 0.75 | G77: 0.75 | H77: 0.75 | I77: 0.75 | J77: 0.75 | K77: 0.75 | L77: 0.75 | M77: 0.75 | N77: 0.75 | O77: 0.75 | P77: 0.75 | Q77: 0.75
C78: Favorable | F78: 0.88 | G78: 0.88 | H78: 0.88 | I78: 0.88 | J78: 0.88 | K78: 0.88 | L78: 0.88 | M78: 0.88 | N78: 0.88 | O78: 0.88 | P78: 0.88 | Q78: 0.88
C80: Origen externo de nueva cohorte activo | F80: =IF(CHOOSE($D$4,COUNT(F81),COUNT(F82),COUNT(F83))=1,CHOOSE($D$4,F81,F82,F83),"N/D") -> 0.7 | G80: =IF(CHOOSE($D$4,COUNT(G81),COUNT(G82),COUNT(G83))=1,CHOOSE($D$4,G81,G82,G83),"N/D") -> 0.7 | H80: =IF(CHOOSE($D$4,COUNT(H81),COUNT(H82),COUNT(H83))=1,CHOOSE($D$4,H81,H82,H83),"N/D") -> 0.7 | I80: =IF(CHOOSE($D$4,COUNT(I81),COUNT(I82),COUNT(I83))=1,CHOOSE($D$4,I81,I82,I83),"N/D") -> 0.7 | J80: =IF(CHOOSE($D$4,COUNT(J81),COUNT(J82),COUNT(J83))=1,CHOOSE($D$4,J81,J82,J83),"N/D") -> 0.7 | K80: =IF(CHOOSE($D$4,COUNT(K81),COUNT(K82),COUNT(K83))=1,CHOOSE($D$4,K81,K82,K83),"N/D") -> 0.7 | L80: =IF(CHOOSE($D$4,COUNT(L81),COUNT(L82),COUNT(L83))=1,CHOOSE($D$4,L81,L82,L83),"N/D") -> 0.7 | M80: =IF(CHOOSE($D$4,COUNT(M81),COUNT(M82),COUNT(M83))=1,CHOOSE($D$4,M81,M82,M83),"N/D") -> 0.7 | ... Q80: =IF(CHOOSE($D$4,COUNT(Q81),COUNT(Q82),COUNT(Q83))=1,CHOOSE($D$4,Q81,Q82,Q83),"N/D") -> 0.7
C81: Conservador | F81: 0.7 | G81: 0.7 | H81: 0.7 | I81: 0.7 | J81: 0.7 | K81: 0.7 | L81: 0.7 | M81: 0.7 | N81: 0.7 | O81: 0.7 | P81: 0.7 | Q81: 0.7
C82: Base | F82: 0.7 | G82: 0.7 | H82: 0.7 | I82: 0.7 | J82: 0.7 | K82: 0.7 | L82: 0.7 | M82: 0.7 | N82: 0.7 | O82: 0.7 | P82: 0.7 | Q82: 0.7
C83: Favorable | F83: 0.7 | G83: 0.7 | H83: 0.7 | I83: 0.7 | J83: 0.7 | K83: 0.7 | L83: 0.7 | M83: 0.7 | N83: 0.7 | O83: 0.7 | P83: 0.7 | Q83: 0.7
C85: M 1 establece accesos, medición y delivery. No evalúa viabilidad SEO por resultados tempranos ni activa un piloto.
C86: Programa 12 meses; revisiones 3/6/9/12 para priorizar y optimizar. No prometen ROI temprano ni justifican corte a 3 meses.
C87: Origen externo se fija en cada cohorte desde el mes de apertura. No se repondera todo el saldo por la tasa del mes actual.
C88: Retenciones son hipótesis por cuenta original y contienen retiros/abandono. Se interpola entre puntos 0/30/60/90/180/365 d.
C89: Estacionalidad Historia reusa patrón pasado como hipótesis, no forecast 2027. Plano=1 no afirma ausencia de estacionalidad.
C90: USD es equivalencia de meta/ticket; producto público Soles. Sin FX supuesto ni disponibilidad de cuenta USD inventada.
C91: Valor Finance es neto por UN método. No sumar FTP y ahorro de fondeo duplicados. Inversión cliente y coste Efeonce separados.

Sheet Mensual
C2: Adquisición, fondeo y valor mensual
C4: Escenario seleccionado | D4: =Supuestos!D5 -> Base
C7: Indicador | D7: Unidad | F7: Mes 1 | G7: Mes 2 | H7: Mes 3 | I7: Mes 4 | J7: Mes 5 | K7: Mes 6 | L7: Mes 7 | M7: Mes 8 | N7: Mes 9 | O7: Mes 10 | P7: Mes 11 | Q7: Mes 12
F8: =Supuestos!F21 -> 46388 | G8: =Supuestos!G21 -> 46419 | H8: =Supuestos!H21 -> 46447 | I8: =Supuestos!I21 -> 46478 | J8: =Supuestos!J21 -> 46508 | K8: =Supuestos!K21 -> 46539 | L8: =Supuestos!L21 -> 46569 | M8: =Supuestos!M21 -> 46600 | ... Q8: =Supuestos!Q21 -> 46722
C9: Proxy mensual histórico trasladado | D9: búsquedas | F9: =Supuestos!F50 -> 3690 | G9: =Supuestos!G50 -> 3690 | H9: =Supuestos!H50 -> 3690 | I9: =Supuestos!I50 -> 3690 | J9: =Supuestos!J50 -> 3690 | K9: =Supuestos!K50 -> 3690 | L9: =Supuestos!L50 -> 3690 | M9: =Supuestos!M50 -> 3690 | ... Q9: =Supuestos!Q50 -> 3690
C10: Estacionalidad usada | D10: factor | F10: =Supuestos!F28 -> 1 | G10: =Supuestos!G28 -> 1 | H10: =Supuestos!H28 -> 1 | I10: =Supuestos!I28 -> 1 | J10: =Supuestos!J28 -> 1 | K10: =Supuestos!K28 -> 1 | L10: =Supuestos!L28 -> 1 | M10: =Supuestos!M28 -> 1 | ... Q10: =Supuestos!Q28 -> 1
C11: Crecimiento 2027 supuesto | D11: factor | F11: =IF(COUNT(Supuestos!$D$25)=1,Supuestos!$D$25,"N/D") -> 1 | G11: =IF(COUNT(Supuestos!$D$25)=1,Supuestos!$D$25,"N/D") -> 1 | H11: =IF(COUNT(Supuestos!$D$25)=1,Supuestos!$D$25,"N/D") -> 1 | I11: =IF(COUNT(Supuestos!$D$25)=1,Supuestos!$D$25,"N/D") -> 1 | J11: =IF(COUNT(Supuestos!$D$25)=1,Supuestos!$D$25,"N/D") -> 1 | K11: =IF(COUNT(Supuestos!$D$25)=1,Supuestos!$D$25,"N/D") -> 1 | L11: =IF(COUNT(Supuestos!$D$25)=1,Supuestos!$D$25,"N/D") -> 1 | M11: =IF(COUNT(Supuestos!$D$25)=1,Supuestos!$D$25,"N/D") -> 1 | ... Q11: =IF(COUNT(Supuestos!$D$25)=1,Supuestos!$D$25,"N/D") -> 1
C12: Demanda tras relevancia | D12: búsquedas | F12: =IF(COUNT(F9,F10,F11,Supuestos!$D$13)=4,F9*F10*F11*Supuestos!$D$13,"N/D") -> 2767.5 | G12: =IF(COUNT(G9,G10,G11,Supuestos!$D$13)=4,G9*G10*G11*Supuestos!$D$13,"N/D") -> 2767.5 | H12: =IF(COUNT(H9,H10,H11,Supuestos!$D$13)=4,H9*H10*H11*Supuestos!$D$13,"N/D") -> 2767.5 | I12: =IF(COUNT(I9,I10,I11,Supuestos!$D$13)=4,I9*I10*I11*Supuestos!$D$13,"N/D") -> 2767.5 | J12: =IF(COUNT(J9,J10,J11,Supuestos!$D$13)=4,J9*J10*J11*Supuestos!$D$13,"N/D") -> 2767.5 | K12: =IF(COUNT(K9,K10,K11,Supuestos!$D$13)=4,K9*K10*K11*Supuestos!$D$13,"N/D") -> 2767.5 | L12: =IF(COUNT(L9,L10,L11,Supuestos!$D$13)=4,L9*L10*L11*Supuestos!$D$13,"N/D") -> 2767.5 | M12: =IF(COUNT(M9,M10,M11,Supuestos!$D$13)=4,M9*M10*M11*Supuestos!$D$13,"N/D") -> 2767.5 | ... Q12: =IF(COUNT(Q9,Q10,Q11,Supuestos!$D$13)=4,Q9*Q10*Q11*Supuestos!$D$13,"N/D") -> 2767.5
C13: Captura referencia | D13: % | F13: =Supuestos!F35 -> 0.01 | G13: =Supuestos!G35 -> 0.01 | H13: =Supuestos!H35 -> 0.01 | I13: =Supuestos!I35 -> 0.01 | J13: =Supuestos!J35 -> 0.01 | K13: =Supuestos!K35 -> 0.01 | L13: =Supuestos!L35 -> 0.01 | M13: =Supuestos!M35 -> 0.01 | ... Q13: =Supuestos!Q35 -> 0.01
C14: Captura adicional programa | D14: % | F14: =Supuestos!F30 -> 0.005 | G14: =Supuestos!G30 -> 0.015 | H14: =Supuestos!H30 -> 0.03 | I14: =Supuestos!I30 -> 0.05 | J14: =Supuestos!J30 -> 0.075 | K14: =Supuestos!K30 -> 0.1 | L14: =Supuestos!L30 -> 0.125 | M14: =Supuestos!M30 -> 0.15 | ... Q14: =Supuestos!Q30 -> 0.25
C15: Visitas referencia | D15: visitas | F15: =IF(COUNT(F12,F13)=2,F12*F13,"N/D") -> 27.675 | G15: =IF(COUNT(G12,G13)=2,G12*G13,"N/D") -> 27.675 | H15: =IF(COUNT(H12,H13)=2,H12*H13,"N/D") -> 27.675 | I15: =IF(COUNT(I12,I13)=2,I12*I13,"N/D") -> 27.675 | J15: =IF(COUNT(J12,J13)=2,J12*J13,"N/D") -> 27.675 | K15: =IF(COUNT(K12,K13)=2,K12*K13,"N/D") -> 27.675 | L15: =IF(COUNT(L12,L13)=2,L12*L13,"N/D") -> 27.675 | M15: =IF(COUNT(M12,M13)=2,M12*M13,"N/D") -> 27.675 | ... Q15: =IF(COUNT(Q12,Q13)=2,Q12*Q13,"N/D") -> 27.675
C16: Visitas incrementales | D16: visitas | F16: =IF(COUNT(F12,F14)=2,F12*F14,"N/D") -> 13.8375 | G16: =IF(COUNT(G12,G14)=2,G12*G14,"N/D") -> 41.5125 | H16: =IF(COUNT(H12,H14)=2,H12*H14,"N/D") -> 83.025 | I16: =IF(COUNT(I12,I14)=2,I12*I14,"N/D") -> 138.375 | J16: =IF(COUNT(J12,J14)=2,J12*J14,"N/D") -> 207.5625 | K16: =IF(COUNT(K12,K14)=2,K12*K14,"N/D") -> 276.75 | L16: =IF(COUNT(L12,L14)=2,L12*L14,"N/D") -> 345.9375 | M16: =IF(COUNT(M12,M14)=2,M12*M14,"N/D") -> 415.125 | ... Q16: =IF(COUNT(Q12,Q14)=2,Q12*Q14,"N/D") -> 691.875
C17: Visitas programa | D17: visitas | F17: =IF(COUNT(F15:F16)=2,SUM(F15:F16),"N/D") -> 41.5125 | G17: =IF(COUNT(G15:G16)=2,SUM(G15:G16),"N/D") -> 69.1875 | H17: =IF(COUNT(H15:H16)=2,SUM(H15:H16),"N/D") -> 110.7 | I17: =IF(COUNT(I15:I16)=2,SUM(I15:I16),"N/D") -> 166.05 | J17: =IF(COUNT(J15:J16)=2,SUM(J15:J16),"N/D") -> 235.2375 | K17: =IF(COUNT(K15:K16)=2,SUM(K15:K16),"N/D") -> 304.425 | L17: =IF(COUNT(L15:L16)=2,SUM(L15:L16),"N/D") -> 373.6125 | M17: =IF(COUNT(M15:M16)=2,SUM(M15:M16),"N/D") -> 442.8 | ... Q17: =IF(COUNT(Q15:Q16)=2,SUM(Q15:Q16),"N/D") -> 719.55
C18: Visita a apertura | D18: % | F18: =Supuestos!F40 -> 0.02 | G18: =Supuestos!G40 -> 0.02 | H18: =Supuestos!H40 -> 0.02 | I18: =Supuestos!I40 -> 0.02 | J18: =Supuestos!J40 -> 0.02 | K18: =Supuestos!K40 -> 0.02 | L18: =Supuestos!L40 -> 0.02 | M18: =Supuestos!M40 -> 0.02 | ... Q18: =Supuestos!Q40 -> 0.02
C19: Aperturas referencia | D19: cuentas | F19: =IF(COUNT(F15,F18)=2,F15*F18,"N/D") -> 0.5535 | G19: =IF(COUNT(G15,G18)=2,G15*G18,"N/D") -> 0.5535 | H19: =IF(COUNT(H15,H18)=2,H15*H18,"N/D") -> 0.5535 | I19: =IF(COUNT(I15,I18)=2,I15*I18,"N/D") -> 0.5535 | J19: =IF(COUNT(J15,J18)=2,J15*J18,"N/D") -> 0.5535 | K19: =IF(COUNT(K15,K18)=2,K15*K18,"N/D") -> 0.5535 | L19: =IF(COUNT(L15,L18)=2,L15*L18,"N/D") -> 0.5535 | M19: =IF(COUNT(M15,M18)=2,M15*M18,"N/D") -> 0.5535 | ... Q19: =IF(COUNT(Q15,Q18)=2,Q15*Q18,"N/D") -> 0.5535
C20: Aperturas programa | D20: cuentas | F20: =IF(COUNT(F17,F18)=2,F17*F18,"N/D") -> 0.83025 | G20: =IF(COUNT(G17,G18)=2,G17*G18,"N/D") -> 1.38375 | H20: =IF(COUNT(H17,H18)=2,H17*H18,"N/D") -> 2.214 | I20: =IF(COUNT(I17,I18)=2,I17*I18,"N/D") -> 3.321 | J20: =IF(COUNT(J17,J18)=2,J17*J18,"N/D") -> 4.70475 | K20: =IF(COUNT(K17,K18)=2,K17*K18,"N/D") -> 6.0885 | L20: =IF(COUNT(L17,L18)=2,L17*L18,"N/D") -> 7.47225 | M20: =IF(COUNT(M17,M18)=2,M17*M18,"N/D") -> 8.856 | ... Q20: =IF(COUNT(Q17,Q18)=2,Q17*Q18,"N/D") -> 14.391
C21: Aperturas incrementales | D21: cuentas | F21: =IF(COUNT(F19:F20)=2,F20-F19,"N/D") -> 0.27675 | G21: =IF(COUNT(G19:G20)=2,G20-G19,"N/D") -> 0.83025 | H21: =IF(COUNT(H19:H20)=2,H20-H19,"N/D") -> 1.6605 | I21: =IF(COUNT(I19:I20)=2,I20-I19,"N/D") -> 2.7675 | J21: =IF(COUNT(J19:J20)=2,J20-J19,"N/D") -> 4.15125 | K21: =IF(COUNT(K19:K20)=2,K20-K19,"N/D") -> 5.535 | L21: =IF(COUNT(L19:L20)=2,L20-L19,"N/D") -> 6.91875 | M21: =IF(COUNT(M19:M20)=2,M20-M19,"N/D") -> 8.3025 | ... Q21: =IF(COUNT(Q19:Q20)=2,Q20-Q19,"N/D") -> 13.8375
C22: Apertura a fondeo | D22: % | F22: =Supuestos!F45 -> 0.65 | G22: =Supuestos!G45 -> 0.65 | H22: =Supuestos!H45 -> 0.65 | I22: =Supuestos!I45 -> 0.65 | J22: =Supuestos!J45 -> 0.65 | K22: =Supuestos!K45 -> 0.65 | L22: =Supuestos!L45 -> 0.65 | M22: =Supuestos!M45 -> 0.65 | ... Q22: =Supuestos!Q45 -> 0.65
C23: Fondeo potencial referencia | D23: cuentas | F23: =IF(COUNT(F19,F22)=2,F19*F22,"N/D") -> 0.359775 | G23: =IF(COUNT(G19,G22)=2,G19*G22,"N/D") -> 0.359775 | H23: =IF(COUNT(H19,H22)=2,H19*H22,"N/D") -> 0.359775 | I23: =IF(COUNT(I19,I22)=2,I19*I22,"N/D") -> 0.359775 | J23: =IF(COUNT(J19,J22)=2,J19*J22,"N/D") -> 0.359775 | K23: =IF(COUNT(K19,K22)=2,K19*K22,"N/D") -> 0.359775 | L23: =IF(COUNT(L19,L22)=2,L19*L22,"N/D") -> 0.359775 | M23: =IF(COUNT(M19,M22)=2,M19*M22,"N/D") -> 0.359775 | ... Q23: =IF(COUNT(Q19,Q22)=2,Q19*Q22,"N/D") -> 0.359775
C24: Fondeo potencial programa | D24: cuentas | F24: =IF(COUNT(F20,F22)=2,F20*F22,"N/D") -> 0.5396625 | G24: =IF(COUNT(G20,G22)=2,G20*G22,"N/D") -> 0.8994375 | H24: =IF(COUNT(H20,H22)=2,H20*H22,"N/D") -> 1.4391 | I24: =IF(COUNT(I20,I22)=2,I20*I22,"N/D") -> 2.15865 | J24: =IF(COUNT(J20,J22)=2,J20*J22,"N/D") -> 3.0580875 | K24: =IF(COUNT(K20,K22)=2,K20*K22,"N/D") -> 3.957525 | L24: =IF(COUNT(L20,L22)=2,L20*L22,"N/D") -> 4.8569625 | M24: =IF(COUNT(M20,M22)=2,M20*M22,"N/D") -> 5.7564 | ... Q24: =IF(COUNT(Q20,Q22)=2,Q20*Q22,"N/D") -> 9.35415
C25: Fondeo potencial incremental | D25: cuentas | F25: =IF(COUNT(F23:F24)=2,F24-F23,"N/D") -> 0.1798875 | G25: =IF(COUNT(G23:G24)=2,G24-G23,"N/D") -> 0.5396625 | H25: =IF(COUNT(H23:H24)=2,H24-H23,"N/D") -> 1.079325 | I25: =IF(COUNT(I23:I24)=2,I24-I23,"N/D") -> 1.798875 | J25: =IF(COUNT(J23:J24)=2,J24-J23,"N/D") -> 2.6983125 | K25: =IF(COUNT(K23:K24)=2,K24-K23,"N/D") -> 3.59775 | L25: =IF(COUNT(L23:L24)=2,L24-L23,"N/D") -> 4.4971875 | M25: =IF(COUNT(M23:M24)=2,M24-M23,"N/D") -> 5.396625 | ... Q25: =IF(COUNT(Q23:Q24)=2,Q24-Q23,"N/D") -> 8.994375
C26: Primer fondeo referencia dentro año | D26: cuentas | F26: =IF(COUNT(Supuestos!$D$18)=1,IF(Supuestos!$D$18<=0,INDEX($F$23:$Q$23,1,1-Supuestos!$D$18),0),"N/D") -> 0.359775 | G26: =IF(COUNT(Supuestos!$D$18)=1,IF(Supuestos!$D$18<=1,INDEX($F$23:$Q$23,1,2-Supuestos!$D$18),0),"N/D") -> 0.359775 | H26: =IF(COUNT(Supuestos!$D$18)=1,IF(Supuestos!$D$18<=2,INDEX($F$23:$Q$23,1,3-Supuestos!$D$18),0),"N/D") -> 0.359775 | I26: =IF(COUNT(Supuestos!$D$18)=1,IF(Supuestos!$D$18<=3,INDEX($F$23:$Q$23,1,4-Supuestos!$D$18),0),"N/D") -> 0.359775 | J26: =IF(COUNT(Supuestos!$D$18)=1,IF(Supuestos!$D$18<=4,INDEX($F$23:$Q$23,1,5-Supuestos!$D$18),0),"N/D") -> 0.359775 | K26: =IF(COUNT(Supuestos!$D$18)=1,IF(Supuestos!$D$18<=5,INDEX($F$23:$Q$23,1,6-Supuestos!$D$18),0),"N/D") -> 0.359775 | L26: =IF(COUNT(Supuestos!$D$18)=1,IF(Supuestos!$D$18<=6,INDEX($F$23:$Q$23,1,7-Supuestos!$D$18),0),"N/D") -> 0.359775 | M26: =IF(COUNT(Supuestos!$D$18)=1,IF(Supuestos!$D$18<=7,INDEX($F$23:$Q$23,1,8-Supuestos!$D$18),0),"N/D") -> 0.359775 | N26: =IF(COUNT(Supuestos!$D$18)=1,IF(Supuestos!$D$18<=8,INDEX($F$23:$Q$23,1,9-Supuestos!$D$18),0),"N/D") -> 0.359775 | O26: =IF(COUNT(Supuestos!$D$18)=1,IF(Supuestos!$D$18<=9,INDEX($F$23:$Q$23,1,10-Supuestos!$D$18),0),"N/D") -> 0.359775 | P26: =IF(COUNT(Supuestos!$D$18)=1,IF(Supuestos!$D$18<=10,INDEX($F$23:$Q$23,1,11-Supuestos!$D$18),0),"N/D") -> 0.359775 | Q26: =IF(COUNT(Supuestos!$D$18)=1,IF(Supuestos!$D$18<=11,INDEX($F$23:$Q$23,1,12-Supuestos!$D$18),0),"N/D") -> 0.359775
C27: Primer fondeo programa dentro año | D27: cuentas | F27: =IF(COUNT(Supuestos!$D$18)=1,IF(Supuestos!$D$18<=0,INDEX($F$24:$Q$24,1,1-Supuestos!$D$18),0),"N/D") -> 0.5396625 | G27: =IF(COUNT(Supuestos!$D$18)=1,IF(Supuestos!$D$18<=1,INDEX($F$24:$Q$24,1,2-Supuestos!$D$18),0),"N/D") -> 0.8994375 | H27: =IF(COUNT(Supuestos!$D$18)=1,IF(Supuestos!$D$18<=2,INDEX($F$24:$Q$24,1,3-Supuestos!$D$18),0),"N/D") -> 1.4391 | I27: =IF(COUNT(Supuestos!$D$18)=1,IF(Supuestos!$D$18<=3,INDEX($F$24:$Q$24,1,4-Supuestos!$D$18),0),"N/D") -> 2.15865 | J27: =IF(COUNT(Supuestos!$D$18)=1,IF(Supuestos!$D$18<=4,INDEX($F$24:$Q$24,1,5-Supuestos!$D$18),0),"N/D") -> 3.0580875 | K27: =IF(COUNT(Supuestos!$D$18)=1,IF(Supuestos!$D$18<=5,INDEX($F$24:$Q$24,1,6-Supuestos!$D$18),0),"N/D") -> 3.957525 | L27: =IF(COUNT(Supuestos!$D$18)=1,IF(Supuestos!$D$18<=6,INDEX($F$24:$Q$24,1,7-Supuestos!$D$18),0),"N/D") -> 4.8569625 | M27: =IF(COUNT(Supuestos!$D$18)=1,IF(Supuestos!$D$18<=7,INDEX($F$24:$Q$24,1,8-Supuestos!$D$18),0),"N/D") -> 5.7564 | N27: =IF(COUNT(Supuestos!$D$18)=1,IF(Supuestos!$D$18<=8,INDEX($F$24:$Q$24,1,9-Supuestos!$D$18),0),"N/D") -> 6.6558375 | O27: =IF(COUNT(Supuestos!$D$18)=1,IF(Supuestos!$D$18<=9,INDEX($F$24:$Q$24,1,10-Supuestos!$D$18),0),"N/D") -> 7.555275 | P27: =IF(COUNT(Supuestos!$D$18)=1,IF(Supuestos!$D$18<=10,INDEX($F$24:$Q$24,1,11-Supuestos!$D$18),0),"N/D") -> 8.4547125 | Q27: =IF(COUNT(Supuestos!$D$18)=1,IF(Supuestos!$D$18<=11,INDEX($F$24:$Q$24,1,12-Supuestos!$D$18),0),"N/D") -> 9.35415
C28: Primer fondeo incremental dentro año | D28: cuentas | F28: =IF(COUNT(F26:F27)=2,F27-F26,"N/D") -> 0.1798875 | G28: =IF(COUNT(G26:G27)=2,G27-G26,"N/D") -> 0.5396625 | H28: =IF(COUNT(H26:H27)=2,H27-H26,"N/D") -> 1.079325 | I28: =IF(COUNT(I26:I27)=2,I27-I26,"N/D") -> 1.798875 | J28: =IF(COUNT(J26:J27)=2,J27-J26,"N/D") -> 2.6983125 | K28: =IF(COUNT(K26:K27)=2,K27-K26,"N/D") -> 3.59775 | L28: =IF(COUNT(L26:L27)=2,L27-L26,"N/D") -> 4.4971875 | M28: =IF(COUNT(M26:M27)=2,M27-M26,"N/D") -> 5.396625 | ... Q28: =IF(COUNT(Q26:Q27)=2,Q27-Q26,"N/D") -> 8.994375
C30: Lag retrasa el primer fondeo. Fondeos programados después de diciembre no cuentan para outcome ni saldo/valor 2027.
C31: Referencia y captura son hipótesis, no baseline post-lanzamiento. La demanda de mercado tampoco equivale a personas.
C35: Saldo incremental al cierre | D35: USD eq. | F35: =Cohortes!L22 -> 437.72625 | G35: =Cohortes!M22 -> 1736.6639 | H35: =Cohortes!N22 -> 4270.0795 | I35: =Cohortes!O22 -> 8437.4733 | J35: =Cohortes!P22 -> 14576.634 | K35: =Cohortes!Q22 -> 22670.072 | L35: =Cohortes!R22 -> 32577.309 | M35: =Cohortes!S22 -> 44305.501 | ... Q35: =Cohortes!W22 -> 109054.68
C36: Saldo externo al cierre | D36: USD eq. | F36: =Cohortes!L43 -> 306.40837 | G36: =Cohortes!M43 -> 1215.6647 | H36: =Cohortes!N43 -> 2989.0557 | I36: =Cohortes!O43 -> 5906.2313 | J36: =Cohortes!P43 -> 10203.644 | K36: =Cohortes!Q43 -> 15869.051 | L36: =Cohortes!R43 -> 22804.116 | M36: =Cohortes!S43 -> 31013.851 | ... Q36: =Cohortes!W43 -> 76338.274
C37: Saldo medio mensual incremental | D37: USD eq. | F37: =Cohortes!L63 -> 243.33169 | G37: =Cohortes!M63 -> 1094.503 | H37: =Cohortes!N63 -> 3150.1831 | I37: =Cohortes!O63 -> 6529.9163 | J37: =Cohortes!P63 -> 11874.082 | K37: =Cohortes!Q63 -> 18975.633 | L37: =Cohortes!R63 -> 28235.405 | M37: =Cohortes!S63 -> 39175.462 | ... Q37: =Cohortes!W63 -> 100912.43
C38: Saldo medio mensual externo | D38: USD eq. | F38: =Cohortes!L83 -> 170.33219 | G38: =Cohortes!M83 -> 766.15211 | H38: =Cohortes!N83 -> 2205.1282 | I38: =Cohortes!O83 -> 4570.9414 | J38: =Cohortes!P83 -> 8311.8575 | K38: =Cohortes!Q83 -> 13282.943 | L38: =Cohortes!R83 -> 19764.783 | M38: =Cohortes!S83 -> 27422.823 | ... Q38: =Cohortes!W83 -> 70638.698
C40: Inversión cliente pendiente | D40: USD | F40: =IF(COUNT(Supuestos!F22)=1,IF(Supuestos!F22>=0,Supuestos!F22,"N/D"),"N/D") -> N/D | G40: =IF(COUNT(Supuestos!G22)=1,IF(Supuestos!G22>=0,Supuestos!G22,"N/D"),"N/D") -> N/D | H40: =IF(COUNT(Supuestos!H22)=1,IF(Supuestos!H22>=0,Supuestos!H22,"N/D"),"N/D") -> N/D | I40: =IF(COUNT(Supuestos!I22)=1,IF(Supuestos!I22>=0,Supuestos!I22,"N/D"),"N/D") -> N/D | J40: =IF(COUNT(Supuestos!J22)=1,IF(Supuestos!J22>=0,Supuestos!J22,"N/D"),"N/D") -> N/D | K40: =IF(COUNT(Supuestos!K22)=1,IF(Supuestos!K22>=0,Supuestos!K22,"N/D"),"N/D") -> N/D | L40: =IF(COUNT(Supuestos!L22)=1,IF(Supuestos!L22>=0,Supuestos!L22,"N/D"),"N/D") -> N/D | M40: =IF(COUNT(Supuestos!M22)=1,IF(Supuestos!M22>=0,Supuestos!M22,"N/D"),"N/D") -> N/D | ... Q40: =IF(COUNT(Supuestos!Q22)=1,IF(Supuestos!Q22>=0,Supuestos!Q22,"N/D"),"N/D") -> N/D
C41: Inversión acumulada | D41: USD | F41: =IF(COUNT($F40:F40)=1,SUM($F40:F40),"N/D") -> N/D | G41: =IF(COUNT($F40:G40)=2,SUM($F40:G40),"N/D") -> N/D | H41: =IF(COUNT($F40:H40)=3,SUM($F40:H40),"N/D") -> N/D | I41: =IF(COUNT($F40:I40)=4,SUM($F40:I40),"N/D") -> N/D | J41: =IF(COUNT($F40:J40)=5,SUM($F40:J40),"N/D") -> N/D | K41: =IF(COUNT($F40:K40)=6,SUM($F40:K40),"N/D") -> N/D | L41: =IF(COUNT($F40:L40)=7,SUM($F40:L40),"N/D") -> N/D | M41: =IF(COUNT($F40:M40)=8,SUM($F40:M40),"N/D") -> N/D | N41: =IF(COUNT($F40:N40)=9,SUM($F40:N40),"N/D") -> N/D | O41: =IF(COUNT($F40:O40)=10,SUM($F40:O40),"N/D") -> N/D | P41: =IF(COUNT($F40:P40)=11,SUM($F40:P40),"N/D") -> N/D | Q41: =IF(COUNT($F40:Q40)=12,SUM($F40:Q40),"N/D") -> N/D
C42: Valor neto mensual Finance | D42: USD | F42: =IF(AND(Supuestos!$D$14="Sí",COUNT(Supuestos!$D$15,F38)=2),F38*Supuestos!$D$15/12,"N/D") -> N/D | G42: =IF(AND(Supuestos!$D$14="Sí",COUNT(Supuestos!$D$15,G38)=2),G38*Supuestos!$D$15/12,"N/D") -> N/D | H42: =IF(AND(Supuestos!$D$14="Sí",COUNT(Supuestos!$D$15,H38)=2),H38*Supuestos!$D$15/12,"N/D") -> N/D | I42: =IF(AND(Supuestos!$D$14="Sí",COUNT(Supuestos!$D$15,I38)=2),I38*Supuestos!$D$15/12,"N/D") -> N/D | J42: =IF(AND(Supuestos!$D$14="Sí",COUNT(Supuestos!$D$15,J38)=2),J38*Supuestos!$D$15/12,"N/D") -> N/D | K42: =IF(AND(Supuestos!$D$14="Sí",COUNT(Supuestos!$D$15,K38)=2),K38*Supuestos!$D$15/12,"N/D") -> N/D | L42: =IF(AND(Supuestos!$D$14="Sí",COUNT(Supuestos!$D$15,L38)=2),L38*Supuestos!$D$15/12,"N/D") -> N/D | M42: =IF(AND(Supuestos!$D$14="Sí",COUNT(Supuestos!$D$15,M38)=2),M38*Supuestos!$D$15/12,"N/D") -> N/D | ... Q42: =IF(AND(Supuestos!$D$14="Sí",COUNT(Supuestos!$D$15,Q38)=2),Q38*Supuestos!$D$15/12,"N/D") -> N/D
C43: Valor acumulado Finance | D43: USD | F43: =IF(COUNT($F42:F42)=1,SUM($F42:F42),"N/D") -> N/D | G43: =IF(COUNT($F42:G42)=2,SUM($F42:G42),"N/D") -> N/D | H43: =IF(COUNT($F42:H42)=3,SUM($F42:H42),"N/D") -> N/D | I43: =IF(COUNT($F42:I42)=4,SUM($F42:I42),"N/D") -> N/D | J43: =IF(COUNT($F42:J42)=5,SUM($F42:J42),"N/D") -> N/D | K43: =IF(COUNT($F42:K42)=6,SUM($F42:K42),"N/D") -> N/D | L43: =IF(COUNT($F42:L42)=7,SUM($F42:L42),"N/D") -> N/D | M43: =IF(COUNT($F42:M42)=8,SUM($F42:M42),"N/D") -> N/D | N43: =IF(COUNT($F42:N42)=9,SUM($F42:N42),"N/D") -> N/D | O43: =IF(COUNT($F42:O42)=10,SUM($F42:O42),"N/D") -> N/D | P43: =IF(COUNT($F42:P42)=11,SUM($F42:P42),"N/D") -> N/D | Q43: =IF(COUNT($F42:Q42)=12,SUM($F42:Q42),"N/D") -> N/D
C44: ROI acumulado con gates Finance | D44: % | F44: =IF(AND(Supuestos!$D$14="Sí",Supuestos!$D$16="Sí",COUNT(F41,F43)=2,F41>0),(F43-F41)/F41,"N/D") -> N/D | G44: =IF(AND(Supuestos!$D$14="Sí",Supuestos!$D$16="Sí",COUNT(G41,G43)=2,G41>0),(G43-G41)/G41,"N/D") -> N/D | H44: =IF(AND(Supuestos!$D$14="Sí",Supuestos!$D$16="Sí",COUNT(H41,H43)=2,H41>0),(H43-H41)/H41,"N/D") -> N/D | I44: =IF(AND(Supuestos!$D$14="Sí",Supuestos!$D$16="Sí",COUNT(I41,I43)=2,I41>0),(I43-I41)/I41,"N/D") -> N/D | J44: =IF(AND(Supuestos!$D$14="Sí",Supuestos!$D$16="Sí",COUNT(J41,J43)=2,J41>0),(J43-J41)/J41,"N/D") -> N/D | K44: =IF(AND(Supuestos!$D$14="Sí",Supuestos!$D$16="Sí",COUNT(K41,K43)=2,K41>0),(K43-K41)/K41,"N/D") -> N/D | L44: =IF(AND(Supuestos!$D$14="Sí",Supuestos!$D$16="Sí",COUNT(L41,L43)=2,L41>0),(L43-L41)/L41,"N/D") -> N/D | M44: =IF(AND(Supuestos!$D$14="Sí",Supuestos!$D$16="Sí",COUNT(M41,M43)=2,M41>0),(M43-M41)/M41,"N/D") -> N/D | ... Q44: =IF(AND(Supuestos!$D$14="Sí",Supuestos!$D$16="Sí",COUNT(Q41,Q43)=2,Q41>0),(Q43-Q41)/Q41,"N/D") -> N/D
C45: Valor menos inversión acumulada | D45: USD | F45: =IF(AND(Supuestos!$D$14="Sí",Supuestos!$D$16="Sí",COUNT(F41,F43)=2,F41>0),F43-F41,"N/D") -> N/D | G45: =IF(AND(Supuestos!$D$14="Sí",Supuestos!$D$16="Sí",COUNT(G41,G43)=2,G41>0),G43-G41,"N/D") -> N/D | H45: =IF(AND(Supuestos!$D$14="Sí",Supuestos!$D$16="Sí",COUNT(H41,H43)=2,H41>0),H43-H41,"N/D") -> N/D | I45: =IF(AND(Supuestos!$D$14="Sí",Supuestos!$D$16="Sí",COUNT(I41,I43)=2,I41>0),I43-I41,"N/D") -> N/D | J45: =IF(AND(Supuestos!$D$14="Sí",Supuestos!$D$16="Sí",COUNT(J41,J43)=2,J41>0),J43-J41,"N/D") -> N/D | K45: =IF(AND(Supuestos!$D$14="Sí",Supuestos!$D$16="Sí",COUNT(K41,K43)=2,K41>0),K43-K41,"N/D") -> N/D | L45: =IF(AND(Supuestos!$D$14="Sí",Supuestos!$D$16="Sí",COUNT(L41,L43)=2,L41>0),L43-L41,"N/D") -> N/D | M45: =IF(AND(Supuestos!$D$14="Sí",Supuestos!$D$16="Sí",COUNT(M41,M43)=2,M41>0),M43-M41,"N/D") -> N/D | ... Q45: =IF(AND(Supuestos!$D$14="Sí",Supuestos!$D$16="Sí",COUNT(Q41,Q43)=2,Q41>0),Q43-Q41,"N/D") -> N/D
C46: Recuperación alcanzada | D46: 0/1 | F46: =IF(COUNT(F45)=1,IF(F45>=0,1,0),"N/D") -> N/D | G46: =IF(COUNT(G45)=1,IF(G45>=0,1,0),"N/D") -> N/D | H46: =IF(COUNT(H45)=1,IF(H45>=0,1,0),"N/D") -> N/D | I46: =IF(COUNT(I45)=1,IF(I45>=0,1,0),"N/D") -> N/D | J46: =IF(COUNT(J45)=1,IF(J45>=0,1,0),"N/D") -> N/D | K46: =IF(COUNT(K45)=1,IF(K45>=0,1,0),"N/D") -> N/D | L46: =IF(COUNT(L45)=1,IF(L45>=0,1,0),"N/D") -> N/D | M46: =IF(COUNT(M45)=1,IF(M45>=0,1,0),"N/D") -> N/D | ... Q46: =IF(COUNT(Q45)=1,IF(Q45>=0,1,0),"N/D") -> N/D
C48: Finance aplica tasa neta anual /12 al saldo medio mensual externo. Nueva cohorte se pondera por días activa dentro del mes.
C49: La cuenta creada en diciembre no aporta doce meses de valor. Valor 2028 no se contabiliza automáticamente.
C50: Revisiones trimestrales optimizan el programa anual; la ejecución y los accesos se comprueban desdeM 1.

Sheet Cohortes
C2: Cohortes: saldo, origen externo y maduración
C4: Escenario | D4: =Supuestos!D5 -> Base
C7: Primer fondeo | D7: Cuentas potenciales | E7: Ticket USD eq. | F7: Origen externo | G7: Ret 30 d | H7: Ret 60 d | I7: Ret 90 d | J7: Ret 180 d | K7: Ret 365 d | L7: M 1 | M7: M 2 | N7: M 3 | O7: M 4 | P7: M 5 | Q7: M 6 | R7: M 7 | S7: M 8 | T7: M 9 | U7: M 10 | V7: M 11 | W7: M 12
L8: =Supuestos!F21 -> 46388 | M8: =Supuestos!G21 -> 46419 | N8: =Supuestos!H21 -> 46447 | O8: =Supuestos!I21 -> 46478 | P8: =Supuestos!J21 -> 46508 | Q8: =Supuestos!K21 -> 46539 | R8: =Supuestos!L21 -> 46569 | S8: =Supuestos!M21 -> 46600 | ... W8: =Supuestos!Q21 -> 46722
C9: =IF(COUNT(Supuestos!$D$18,Supuestos!$D$19)=2,DATE(YEAR(EDATE(Supuestos!F21,Supuestos!$D$18)),MONTH(EDATE(Supuestos!F21,Supuestos!$D$18)),Supuestos!$D$19),"N/D") -> 46402 | D9: =Mensual!F25 -> 0.1798875 | E9: =IF(COUNT(Supuestos!$D$10)=1,Supuestos!$D$10,"N/D") -> 2500 | F9: =Supuestos!F80 -> 0.7 | G9: =Supuestos!F55 -> 0.95 | H9: =Supuestos!F60 -> 0.9 | I9: =Supuestos!F65 -> 0.85 | J9: =Supuestos!F70 -> 0.8 | K9: =Supuestos!F75 -> 0.75 | L9: =IF(COUNT($D9,$E9,L129)=3,$D9*$E9*L129,"N/D") -> 437.72625 | M9: =IF(COUNT($D9,$E9,M129)=3,$D9*$E9*M129,"N/D") -> 416.73937 | N9: =IF(COUNT($D9,$E9,N129)=3,$D9*$E9*N129,"N/D") -> 393.50391 | O9: =IF(COUNT($D9,$E9,O129)=3,$D9*$E9*O129,"N/D") -> 378.51328 | P9: =IF(COUNT($D9,$E9,P129)=3,$D9*$E9*P129,"N/D") -> 370.76812 | Q9: =IF(COUNT($D9,$E9,Q129)=3,$D9*$E9*Q129,"N/D") -> 363.27281 | R9: =IF(COUNT($D9,$E9,R129)=3,$D9*$E9*R129,"N/D") -> 357.70872 | S9: =IF(COUNT($D9,$E9,S129)=3,$D9*$E9*S129,"N/D") -> 353.94081 | ... W9: =IF(COUNT($D9,$E9,W129)=3,$D9*$E9*W129,"N/D") -> 339.11225
C10: =IF(COUNT(Supuestos!$D$18,Supuestos!$D$19)=2,DATE(YEAR(EDATE(Supuestos!G21,Supuestos!$D$18)),MONTH(EDATE(Supuestos!G21,Supuestos!$D$18)),Supuestos!$D$19),"N/D") -> 46433 | D10: =Mensual!G25 -> 0.5396625 | E10: =IF(COUNT(Supuestos!$D$10)=1,Supuestos!$D$10,"N/D") -> 2500 | F10: =Supuestos!G80 -> 0.7 | G10: =Supuestos!G55 -> 0.95 | H10: =Supuestos!G60 -> 0.9 | I10: =Supuestos!G65 -> 0.85 | J10: =Supuestos!G70 -> 0.8 | K10: =Supuestos!G75 -> 0.75 | L10: =IF(COUNT($D10,$E10,L130)=3,$D10*$E10*L130,"N/D") -> 0 | M10: =IF(COUNT($D10,$E10,M130)=3,$D10*$E10*M130,"N/D") -> 1319.9245 | N10: =IF(COUNT($D10,$E10,N130)=3,$D10*$E10*N130,"N/D") -> 1250.2181 | O10: =IF(COUNT($D10,$E10,O130)=3,$D10*$E10*O130,"N/D") -> 1182.7603 | P10: =IF(COUNT($D10,$E10,P130)=3,$D10*$E10*P130,"N/D") -> 1135.5398 | Q10: =IF(COUNT($D10,$E10,Q130)=3,$D10*$E10*Q130,"N/D") -> 1113.0539 | R10: =IF(COUNT($D10,$E10,R130)=3,$D10*$E10*R130,"N/D") -> 1089.8184 | S10: =IF(COUNT($D10,$E10,S130)=3,$D10*$E10*S130,"N/D") -> 1073.1262 | ... W10: =IF(COUNT($D10,$E10,W130)=3,$D10*$E10*W130,"N/D") -> 1028.6405
C11: =IF(COUNT(Supuestos!$D$18,Supuestos!$D$19)=2,DATE(YEAR(EDATE(Supuestos!H21,Supuestos!$D$18)),MONTH(EDATE(Supuestos!H21,Supuestos!$D$18)),Supuestos!$D$19),"N/D") -> 46461 | D11: =Mensual!H25 -> 1.079325 | E11: =IF(COUNT(Supuestos!$D$10)=1,Supuestos!$D$10,"N/D") -> 2500 | F11: =Supuestos!H80 -> 0.7 | G11: =Supuestos!H55 -> 0.95 | H11: =Supuestos!H60 -> 0.9 | I11: =Supuestos!H65 -> 0.85 | J11: =Supuestos!H70 -> 0.8 | K11: =Supuestos!H75 -> 0.75 | L11: =IF(COUNT($D11,$E11,L131)=3,$D11*$E11*L131,"N/D") -> 0 | M11: =IF(COUNT($D11,$E11,M131)=3,$D11*$E11*M131,"N/D") -> 0 | N11: =IF(COUNT($D11,$E11,N131)=3,$D11*$E11*N131,"N/D") -> 2626.3575 | O11: =IF(COUNT($D11,$E11,O131)=3,$D11*$E11*O131,"N/D") -> 2491.4419 | P11: =IF(COUNT($D11,$E11,P131)=3,$D11*$E11*P131,"N/D") -> 2352.0291 | Q11: =IF(COUNT($D11,$E11,Q131)=3,$D11*$E11*Q131,"N/D") -> 2268.0816 | R11: =IF(COUNT($D11,$E11,R131)=3,$D11*$E11*R131,"N/D") -> 2221.6106 | S11: =IF(COUNT($D11,$E11,S131)=3,$D11*$E11*S131,"N/D") -> 2175.1397 | ... W11: =IF(COUNT($D11,$E11,W131)=3,$D11*$E11*W131,"N/D") -> 2077.7006
C12: =IF(COUNT(Supuestos!$D$18,Supuestos!$D$19)=2,DATE(YEAR(EDATE(Supuestos!I21,Supuestos!$D$18)),MONTH(EDATE(Supuestos!I21,Supuestos!$D$18)),Supuestos!$D$19),"N/D") -> 46492 | D12: =Mensual!I25 -> 1.798875 | E12: =IF(COUNT(Supuestos!$D$10)=1,Supuestos!$D$10,"N/D") -> 2500 | F12: =Supuestos!I80 -> 0.7 | G12: =Supuestos!I55 -> 0.95 | H12: =Supuestos!I60 -> 0.9 | I12: =Supuestos!I65 -> 0.85 | J12: =Supuestos!I70 -> 0.8 | K12: =Supuestos!I75 -> 0.75 | L12: =IF(COUNT($D12,$E12,L132)=3,$D12*$E12*L132,"N/D") -> 0 | M12: =IF(COUNT($D12,$E12,M132)=3,$D12*$E12*M132,"N/D") -> 0 | N12: =IF(COUNT($D12,$E12,N132)=3,$D12*$E12*N132,"N/D") -> 0 | O12: =IF(COUNT($D12,$E12,O132)=3,$D12*$E12*O132,"N/D") -> 4384.7578 | P12: =IF(COUNT($D12,$E12,P132)=3,$D12*$E12*P132,"N/D") -> 4152.4031 | Q12: =IF(COUNT($D12,$E12,Q132)=3,$D12*$E12*Q132,"N/D") -> 3927.5437 | R12: =IF(COUNT($D12,$E12,R132)=3,$D12*$E12*R132,"N/D") -> 3780.1359 | S12: =IF(COUNT($D12,$E12,S132)=3,$D12*$E12*S132,"N/D") -> 3702.6844 | ... W12: =IF(COUNT($D12,$E12,W132)=3,$D12*$E12*W132,"N/D") -> 3500.5135
C13: =IF(COUNT(Supuestos!$D$18,Supuestos!$D$19)=2,DATE(YEAR(EDATE(Supuestos!J21,Supuestos!$D$18)),MONTH(EDATE(Supuestos!J21,Supuestos!$D$18)),Supuestos!$D$19),"N/D") -> 46522 | D13: =Mensual!J25 -> 2.6983125 | E13: =IF(COUNT(Supuestos!$D$10)=1,Supuestos!$D$10,"N/D") -> 2500 | F13: =Supuestos!J80 -> 0.7 | G13: =Supuestos!J55 -> 0.95 | H13: =Supuestos!J60 -> 0.9 | I13: =Supuestos!J65 -> 0.85 | J13: =Supuestos!J70 -> 0.8 | K13: =Supuestos!J75 -> 0.75 | L13: =IF(COUNT($D13,$E13,L133)=3,$D13*$E13*L133,"N/D") -> 0 | M13: =IF(COUNT($D13,$E13,M133)=3,$D13*$E13*M133,"N/D") -> 0 | N13: =IF(COUNT($D13,$E13,N133)=3,$D13*$E13*N133,"N/D") -> 0 | O13: =IF(COUNT($D13,$E13,O133)=3,$D13*$E13*O133,"N/D") -> 0 | P13: =IF(COUNT($D13,$E13,P133)=3,$D13*$E13*P133,"N/D") -> 6565.8938 | Q13: =IF(COUNT($D13,$E13,Q133)=3,$D13*$E13*Q133,"N/D") -> 6228.6047 | R13: =IF(COUNT($D13,$E13,R133)=3,$D13*$E13*R133,"N/D") -> 5880.0727 | S13: =IF(COUNT($D13,$E13,S133)=3,$D13*$E13*S133,"N/D") -> 5666.4563 | ... W13: =IF(COUNT($D13,$E13,W133)=3,$D13*$E13*W133,"N/D") -> 5305.4658
C14: =IF(COUNT(Supuestos!$D$18,Supuestos!$D$19)=2,DATE(YEAR(EDATE(Supuestos!K21,Supuestos!$D$18)),MONTH(EDATE(Supuestos!K21,Supuestos!$D$18)),Supuestos!$D$19),"N/D") -> 46553 | D14: =Mensual!K25 -> 3.59775 | E14: =IF(COUNT(Supuestos!$D$10)=1,Supuestos!$D$10,"N/D") -> 2500 | F14: =Supuestos!K80 -> 0.7 | G14: =Supuestos!K55 -> 0.95 | H14: =Supuestos!K60 -> 0.9 | I14: =Supuestos!K65 -> 0.85 | J14: =Supuestos!K70 -> 0.8 | K14: =Supuestos!K75 -> 0.75 | L14: =IF(COUNT($D14,$E14,L134)=3,$D14*$E14*L134,"N/D") -> 0 | M14: =IF(COUNT($D14,$E14,M134)=3,$D14*$E14*M134,"N/D") -> 0 | N14: =IF(COUNT($D14,$E14,N134)=3,$D14*$E14*N134,"N/D") -> 0 | O14: =IF(COUNT($D14,$E14,O134)=3,$D14*$E14*O134,"N/D") -> 0 | P14: =IF(COUNT($D14,$E14,P134)=3,$D14*$E14*P134,"N/D") -> 0 | Q14: =IF(COUNT($D14,$E14,Q134)=3,$D14*$E14*Q134,"N/D") -> 8769.5156 | R14: =IF(COUNT($D14,$E14,R134)=3,$D14*$E14*R134,"N/D") -> 8304.8062 | S14: =IF(COUNT($D14,$E14,S134)=3,$D14*$E14*S134,"N/D") -> 7840.0969 | ... W14: =IF(COUNT($D14,$E14,W134)=3,$D14*$E14*W134,"N/D") -> 7149.3127
C15: =IF(COUNT(Supuestos!$D$18,Supuestos!$D$19)=2,DATE(YEAR(EDATE(Supuestos!L21,Supuestos!$D$18)),MONTH(EDATE(Supuestos!L21,Supuestos!$D$18)),Supuestos!$D$19),"N/D") -> 46583 | D15: =Mensual!L25 -> 4.4971875 | E15: =IF(COUNT(Supuestos!$D$10)=1,Supuestos!$D$10,"N/D") -> 2500 | F15: =Supuestos!L80 -> 0.7 | G15: =Supuestos!L55 -> 0.95 | H15: =Supuestos!L60 -> 0.9 | I15: =Supuestos!L65 -> 0.85 | J15: =Supuestos!L70 -> 0.8 | K15: =Supuestos!L75 -> 0.75 | L15: =IF(COUNT($D15,$E15,L135)=3,$D15*$E15*L135,"N/D") -> 0 | M15: =IF(COUNT($D15,$E15,M135)=3,$D15*$E15*M135,"N/D") -> 0 | N15: =IF(COUNT($D15,$E15,N135)=3,$D15*$E15*N135,"N/D") -> 0 | O15: =IF(COUNT($D15,$E15,O135)=3,$D15*$E15*O135,"N/D") -> 0 | P15: =IF(COUNT($D15,$E15,P135)=3,$D15*$E15*P135,"N/D") -> 0 | Q15: =IF(COUNT($D15,$E15,Q135)=3,$D15*$E15*Q135,"N/D") -> 0 | R15: =IF(COUNT($D15,$E15,R135)=3,$D15*$E15*R135,"N/D") -> 10943.156 | S15: =IF(COUNT($D15,$E15,S135)=3,$D15*$E15*S135,"N/D") -> 10362.27 | ... W15: =IF(COUNT($D15,$E15,W135)=3,$D15*$E15*W135,"N/D") -> 9063.082
C16: =IF(COUNT(Supuestos!$D$18,Supuestos!$D$19)=2,DATE(YEAR(EDATE(Supuestos!M21,Supuestos!$D$18)),MONTH(EDATE(Supuestos!M21,Supuestos!$D$18)),Supuestos!$D$19),"N/D") -> 46614 | D16: =Mensual!M25 -> 5.396625 | E16: =IF(COUNT(Supuestos!$D$10)=1,Supuestos!$D$10,"N/D") -> 2500 | F16: =Supuestos!M80 -> 0.7 | G16: =Supuestos!M55 -> 0.95 | H16: =Supuestos!M60 -> 0.9 | I16: =Supuestos!M65 -> 0.85 | J16: =Supuestos!M70 -> 0.8 | K16: =Supuestos!M75 -> 0.75 | L16: =IF(COUNT($D16,$E16,L136)=3,$D16*$E16*L136,"N/D") -> 0 | M16: =IF(COUNT($D16,$E16,M136)=3,$D16*$E16*M136,"N/D") -> 0 | N16: =IF(COUNT($D16,$E16,N136)=3,$D16*$E16*N136,"N/D") -> 0 | O16: =IF(COUNT($D16,$E16,O136)=3,$D16*$E16*O136,"N/D") -> 0 | P16: =IF(COUNT($D16,$E16,P136)=3,$D16*$E16*P136,"N/D") -> 0 | Q16: =IF(COUNT($D16,$E16,Q136)=3,$D16*$E16*Q136,"N/D") -> 0 | R16: =IF(COUNT($D16,$E16,R136)=3,$D16*$E16*R136,"N/D") -> 0 | S16: =IF(COUNT($D16,$E16,S136)=3,$D16*$E16*S136,"N/D") -> 13131.788 | ... W16: =IF(COUNT($D16,$E16,W136)=3,$D16*$E16*W136,"N/D") -> 11108.053
C17: =IF(COUNT(Supuestos!$D$18,Supuestos!$D$19)=2,DATE(YEAR(EDATE(Supuestos!N21,Supuestos!$D$18)),MONTH(EDATE(Supuestos!N21,Supuestos!$D$18)),Supuestos!$D$19),"N/D") -> 46645 | D17: =Mensual!N25 -> 6.2960625 | E17: =IF(COUNT(Supuestos!$D$10)=1,Supuestos!$D$10,"N/D") -> 2500 | F17: =Supuestos!N80 -> 0.7 | G17: =Supuestos!N55 -> 0.95 | H17: =Supuestos!N60 -> 0.9 | I17: =Supuestos!N65 -> 0.85 | J17: =Supuestos!N70 -> 0.8 | K17: =Supuestos!N75 -> 0.75 | L17: =IF(COUNT($D17,$E17,L137)=3,$D17*$E17*L137,"N/D") -> 0 | M17: =IF(COUNT($D17,$E17,M137)=3,$D17*$E17*M137,"N/D") -> 0 | N17: =IF(COUNT($D17,$E17,N137)=3,$D17*$E17*N137,"N/D") -> 0 | O17: =IF(COUNT($D17,$E17,O137)=3,$D17*$E17*O137,"N/D") -> 0 | P17: =IF(COUNT($D17,$E17,P137)=3,$D17*$E17*P137,"N/D") -> 0 | Q17: =IF(COUNT($D17,$E17,Q137)=3,$D17*$E17*Q137,"N/D") -> 0 | R17: =IF(COUNT($D17,$E17,R137)=3,$D17*$E17*R137,"N/D") -> 0 | S17: =IF(COUNT($D17,$E17,S137)=3,$D17*$E17*S137,"N/D") -> 0 | ... W17: =IF(COUNT($D17,$E17,W137)=3,$D17*$E17*W137,"N/D") -> 13230.476
C18: =IF(COUNT(Supuestos!$D$18,Supuestos!$D$19)=2,DATE(YEAR(EDATE(Supuestos!O21,Supuestos!$D$18)),MONTH(EDATE(Supuestos!O21,Supuestos!$D$18)),Supuestos!$D$19),"N/D") -> 46675 | D18: =Mensual!O25 -> 7.1955 | E18: =IF(COUNT(Supuestos!$D$10)=1,Supuestos!$D$10,"N/D") -> 2500 | F18: =Supuestos!O80 -> 0.7 | G18: =Supuestos!O55 -> 0.95 | H18: =Supuestos!O60 -> 0.9 | I18: =Supuestos!O65 -> 0.85 | J18: =Supuestos!O70 -> 0.8 | K18: =Supuestos!O75 -> 0.75 | L18: =IF(COUNT($D18,$E18,L138)=3,$D18*$E18*L138,"N/D") -> 0 | M18: =IF(COUNT($D18,$E18,M138)=3,$D18*$E18*M138,"N/D") -> 0 | N18: =IF(COUNT($D18,$E18,N138)=3,$D18*$E18*N138,"N/D") -> 0 | O18: =IF(COUNT($D18,$E18,O138)=3,$D18*$E18*O138,"N/D") -> 0 | P18: =IF(COUNT($D18,$E18,P138)=3,$D18*$E18*P138,"N/D") -> 0 | Q18: =IF(COUNT($D18,$E18,Q138)=3,$D18*$E18*Q138,"N/D") -> 0 | R18: =IF(COUNT($D18,$E18,R138)=3,$D18*$E18*R138,"N/D") -> 0 | S18: =IF(COUNT($D18,$E18,S138)=3,$D18*$E18*S138,"N/D") -> 0 | ... W18: =IF(COUNT($D18,$E18,W138)=3,$D18*$E18*W138,"N/D") -> 15680.194
C19: =IF(COUNT(Supuestos!$D$18,Supuestos!$D$19)=2,DATE(YEAR(EDATE(Supuestos!P21,Supuestos!$D$18)),MONTH(EDATE(Supuestos!P21,Supuestos!$D$18)),Supuestos!$D$19),"N/D") -> 46706 | D19: =Mensual!P25 -> 8.0949375 | E19: =IF(COUNT(Supuestos!$D$10)=1,Supuestos!$D$10,"N/D") -> 2500 | F19: =Supuestos!P80 -> 0.7 | G19: =Supuestos!P55 -> 0.95 | H19: =Supuestos!P60 -> 0.9 | I19: =Supuestos!P65 -> 0.85 | J19: =Supuestos!P70 -> 0.8 | K19: =Supuestos!P75 -> 0.75 | L19: =IF(COUNT($D19,$E19,L139)=3,$D19*$E19*L139,"N/D") -> 0 | M19: =IF(COUNT($D19,$E19,M139)=3,$D19*$E19*M139,"N/D") -> 0 | N19: =IF(COUNT($D19,$E19,N139)=3,$D19*$E19*N139,"N/D") -> 0 | O19: =IF(COUNT($D19,$E19,O139)=3,$D19*$E19*O139,"N/D") -> 0 | P19: =IF(COUNT($D19,$E19,P139)=3,$D19*$E19*P139,"N/D") -> 0 | Q19: =IF(COUNT($D19,$E19,Q139)=3,$D19*$E19*Q139,"N/D") -> 0 | R19: =IF(COUNT($D19,$E19,R139)=3,$D19*$E19*R139,"N/D") -> 0 | S19: =IF(COUNT($D19,$E19,S139)=3,$D19*$E19*S139,"N/D") -> 0 | ... W19: =IF(COUNT($D19,$E19,W139)=3,$D19*$E19*W139,"N/D") -> 18685.814
C20: =IF(COUNT(Supuestos!$D$18,Supuestos!$D$19)=2,DATE(YEAR(EDATE(Supuestos!Q21,Supuestos!$D$18)),MONTH(EDATE(Supuestos!Q21,Supuestos!$D$18)),Supuestos!$D$19),"N/D") -> 46736 | D20: =Mensual!Q25 -> 8.994375 | E20: =IF(COUNT(Supuestos!$D$10)=1,Supuestos!$D$10,"N/D") -> 2500 | F20: =Supuestos!Q80 -> 0.7 | G20: =Supuestos!Q55 -> 0.95 | H20: =Supuestos!Q60 -> 0.9 | I20: =Supuestos!Q65 -> 0.85 | J20: =Supuestos!Q70 -> 0.8 | K20: =Supuestos!Q75 -> 0.75 | L20: =IF(COUNT($D20,$E20,L140)=3,$D20*$E20*L140,"N/D") -> 0 | M20: =IF(COUNT($D20,$E20,M140)=3,$D20*$E20*M140,"N/D") -> 0 | N20: =IF(COUNT($D20,$E20,N140)=3,$D20*$E20*N140,"N/D") -> 0 | O20: =IF(COUNT($D20,$E20,O140)=3,$D20*$E20*O140,"N/D") -> 0 | P20: =IF(COUNT($D20,$E20,P140)=3,$D20*$E20*P140,"N/D") -> 0 | Q20: =IF(COUNT($D20,$E20,Q140)=3,$D20*$E20*Q140,"N/D") -> 0 | R20: =IF(COUNT($D20,$E20,R140)=3,$D20*$E20*R140,"N/D") -> 0 | S20: =IF(COUNT($D20,$E20,S140)=3,$D20*$E20*S140,"N/D") -> 0 | ... W20: =IF(COUNT($D20,$E20,W140)=3,$D20*$E20*W140,"N/D") -> 21886.312
C22: Saldo cierre USD eq. | L22: =IF(COUNT(L9:L20)=12,SUM(L9:L20),"N/D") -> 437.72625 | M22: =IF(COUNT(M9:M20)=12,SUM(M9:M20),"N/D") -> 1736.6639 | N22: =IF(COUNT(N9:N20)=12,SUM(N9:N20),"N/D") -> 4270.0795 | O22: =IF(COUNT(O9:O20)=12,SUM(O9:O20),"N/D") -> 8437.4733 | P22: =IF(COUNT(P9:P20)=12,SUM(P9:P20),"N/D") -> 14576.634 | Q22: =IF(COUNT(Q9:Q20)=12,SUM(Q9:Q20),"N/D") -> 22670.072 | R22: =IF(COUNT(R9:R20)=12,SUM(R9:R20),"N/D") -> 32577.309 | S22: =IF(COUNT(S9:S20)=12,SUM(S9:S20),"N/D") -> 44305.501 | ... W22: =IF(COUNT(W9:W20)=12,SUM(W9:W20),"N/D") -> 109054.68
C28: Saldo externo al cierre, por cohorte | L28: M 1 | M28: M 2 | N28: M 3 | O28: M 4 | P28: M 5 | Q28: M 6 | R28: M 7 | S28: M 8 | T28: M 9 | U28: M 10 | V28: M 11 | W28: M 12
C30: =C9 -> 46402 | L30: =IF(COUNT(L9,$F9)=2,L9*$F9,"N/D") -> 306.40837 | M30: =IF(COUNT(M9,$F9)=2,M9*$F9,"N/D") -> 291.71756 | N30: =IF(COUNT(N9,$F9)=2,N9*$F9,"N/D") -> 275.45273 | O30: =IF(COUNT(O9,$F9)=2,O9*$F9,"N/D") -> 264.9593 | P30: =IF(COUNT(P9,$F9)=2,P9*$F9,"N/D") -> 259.53769 | Q30: =IF(COUNT(Q9,$F9)=2,Q9*$F9,"N/D") -> 254.29097 | R30: =IF(COUNT(R9,$F9)=2,R9*$F9,"N/D") -> 250.39611 | S30: =IF(COUNT(S9,$F9)=2,S9*$F9,"N/D") -> 247.75857 | ... W30: =IF(COUNT(W9,$F9)=2,W9*$F9,"N/D") -> 237.37857
C31: =C10 -> 46433 | L31: =IF(COUNT(L10,$F10)=2,L10*$F10,"N/D") -> 0 | M31: =IF(COUNT(M10,$F10)=2,M10*$F10,"N/D") -> 923.94717 | N31: =IF(COUNT(N10,$F10)=2,N10*$F10,"N/D") -> 875.15269 | O31: =IF(COUNT(O10,$F10)=2,O10*$F10,"N/D") -> 827.93222 | P31: =IF(COUNT(P10,$F10)=2,P10*$F10,"N/D") -> 794.87789 | Q31: =IF(COUNT(Q10,$F10)=2,Q10*$F10,"N/D") -> 779.13773 | R31: =IF(COUNT(R10,$F10)=2,R10*$F10,"N/D") -> 762.87291 | S31: =IF(COUNT(S10,$F10)=2,S10*$F10,"N/D") -> 751.18832 | ... W31: =IF(COUNT(W10,$F10)=2,W10*$F10,"N/D") -> 720.04834
C32: =C11 -> 46461 | L32: =IF(COUNT(L11,$F11)=2,L11*$F11,"N/D") -> 0 | M32: =IF(COUNT(M11,$F11)=2,M11*$F11,"N/D") -> 0 | N32: =IF(COUNT(N11,$F11)=2,N11*$F11,"N/D") -> 1838.4503 | O32: =IF(COUNT(O11,$F11)=2,O11*$F11,"N/D") -> 1744.0093 | P32: =IF(COUNT(P11,$F11)=2,P11*$F11,"N/D") -> 1646.4203 | Q32: =IF(COUNT(Q11,$F11)=2,Q11*$F11,"N/D") -> 1587.6571 | R32: =IF(COUNT(R11,$F11)=2,R11*$F11,"N/D") -> 1555.1274 | S32: =IF(COUNT(S11,$F11)=2,S11*$F11,"N/D") -> 1522.5978 | ... W32: =IF(COUNT(W11,$F11)=2,W11*$F11,"N/D") -> 1454.3904
C33: =C12 -> 46492 | L33: =IF(COUNT(L12,$F12)=2,L12*$F12,"N/D") -> 0 | M33: =IF(COUNT(M12,$F12)=2,M12*$F12,"N/D") -> 0 | N33: =IF(COUNT(N12,$F12)=2,N12*$F12,"N/D") -> 0 | O33: =IF(COUNT(O12,$F12)=2,O12*$F12,"N/D") -> 3069.3305 | P33: =IF(COUNT(P12,$F12)=2,P12*$F12,"N/D") -> 2906.6822 | Q33: =IF(COUNT(Q12,$F12)=2,Q12*$F12,"N/D") -> 2749.2806 | R33: =IF(COUNT(R12,$F12)=2,R12*$F12,"N/D") -> 2646.0952 | S33: =IF(COUNT(S12,$F12)=2,S12*$F12,"N/D") -> 2591.8791 | ... W33: =IF(COUNT(W12,$F12)=2,W12*$F12,"N/D") -> 2450.3595
C34: =C13 -> 46522 | L34: =IF(COUNT(L13,$F13)=2,L13*$F13,"N/D") -> 0 | M34: =IF(COUNT(M13,$F13)=2,M13*$F13,"N/D") -> 0 | N34: =IF(COUNT(N13,$F13)=2,N13*$F13,"N/D") -> 0 | O34: =IF(COUNT(O13,$F13)=2,O13*$F13,"N/D") -> 0 | P34: =IF(COUNT(P13,$F13)=2,P13*$F13,"N/D") -> 4596.1256 | Q34: =IF(COUNT(Q13,$F13)=2,Q13*$F13,"N/D") -> 4360.0233 | R34: =IF(COUNT(R13,$F13)=2,R13*$F13,"N/D") -> 4116.0509 | S34: =IF(COUNT(S13,$F13)=2,S13*$F13,"N/D") -> 3966.5194 | ... W34: =IF(COUNT(W13,$F13)=2,W13*$F13,"N/D") -> 3713.8261
C35: =C14 -> 46553 | L35: =IF(COUNT(L14,$F14)=2,L14*$F14,"N/D") -> 0 | M35: =IF(COUNT(M14,$F14)=2,M14*$F14,"N/D") -> 0 | N35: =IF(COUNT(N14,$F14)=2,N14*$F14,"N/D") -> 0 | O35: =IF(COUNT(O14,$F14)=2,O14*$F14,"N/D") -> 0 | P35: =IF(COUNT(P14,$F14)=2,P14*$F14,"N/D") -> 0 | Q35: =IF(COUNT(Q14,$F14)=2,Q14*$F14,"N/D") -> 6138.6609 | R35: =IF(COUNT(R14,$F14)=2,R14*$F14,"N/D") -> 5813.3644 | S35: =IF(COUNT(S14,$F14)=2,S14*$F14,"N/D") -> 5488.0678 | ... W35: =IF(COUNT(W14,$F14)=2,W14*$F14,"N/D") -> 5004.5189
C36: =C15 -> 46583 | L36: =IF(COUNT(L15,$F15)=2,L15*$F15,"N/D") -> 0 | M36: =IF(COUNT(M15,$F15)=2,M15*$F15,"N/D") -> 0 | N36: =IF(COUNT(N15,$F15)=2,N15*$F15,"N/D") -> 0 | O36: =IF(COUNT(O15,$F15)=2,O15*$F15,"N/D") -> 0 | P36: =IF(COUNT(P15,$F15)=2,P15*$F15,"N/D") -> 0 | Q36: =IF(COUNT(Q15,$F15)=2,Q15*$F15,"N/D") -> 0 | R36: =IF(COUNT(R15,$F15)=2,R15*$F15,"N/D") -> 7660.2094 | S36: =IF(COUNT(S15,$F15)=2,S15*$F15,"N/D") -> 7253.5887 | ... W36: =IF(COUNT(W15,$F15)=2,W15*$F15,"N/D") -> 6344.1574
C37: =C16 -> 46614 | L37: =IF(COUNT(L16,$F16)=2,L16*$F16,"N/D") -> 0 | M37: =IF(COUNT(M16,$F16)=2,M16*$F16,"N/D") -> 0 | N37: =IF(COUNT(N16,$F16)=2,N16*$F16,"N/D") -> 0 | O37: =IF(COUNT(O16,$F16)=2,O16*$F16,"N/D") -> 0 | P37: =IF(COUNT(P16,$F16)=2,P16*$F16,"N/D") -> 0 | Q37: =IF(COUNT(Q16,$F16)=2,Q16*$F16,"N/D") -> 0 | R37: =IF(COUNT(R16,$F16)=2,R16*$F16,"N/D") -> 0 | S37: =IF(COUNT(S16,$F16)=2,S16*$F16,"N/D") -> 9192.2512 | ... W37: =IF(COUNT(W16,$F16)=2,W16*$F16,"N/D") -> 7775.6372
C38: =C17 -> 46645 | L38: =IF(COUNT(L17,$F17)=2,L17*$F17,"N/D") -> 0 | M38: =IF(COUNT(M17,$F17)=2,M17*$F17,"N/D") -> 0 | N38: =IF(COUNT(N17,$F17)=2,N17*$F17,"N/D") -> 0 | O38: =IF(COUNT(O17,$F17)=2,O17*$F17,"N/D") -> 0 | P38: =IF(COUNT(P17,$F17)=2,P17*$F17,"N/D") -> 0 | Q38: =IF(COUNT(Q17,$F17)=2,Q17*$F17,"N/D") -> 0 | R38: =IF(COUNT(R17,$F17)=2,R17*$F17,"N/D") -> 0 | S38: =IF(COUNT(S17,$F17)=2,S17*$F17,"N/D") -> 0 | ... W38: =IF(COUNT(W17,$F17)=2,W17*$F17,"N/D") -> 9261.333
C39: =C18 -> 46675 | L39: =IF(COUNT(L18,$F18)=2,L18*$F18,"N/D") -> 0 | M39: =IF(COUNT(M18,$F18)=2,M18*$F18,"N/D") -> 0 | N39: =IF(COUNT(N18,$F18)=2,N18*$F18,"N/D") -> 0 | O39: =IF(COUNT(O18,$F18)=2,O18*$F18,"N/D") -> 0 | P39: =IF(COUNT(P18,$F18)=2,P18*$F18,"N/D") -> 0 | Q39: =IF(COUNT(Q18,$F18)=2,Q18*$F18,"N/D") -> 0 | R39: =IF(COUNT(R18,$F18)=2,R18*$F18,"N/D") -> 0 | S39: =IF(COUNT(S18,$F18)=2,S18*$F18,"N/D") -> 0 | ... W39: =IF(COUNT(W18,$F18)=2,W18*$F18,"N/D") -> 10976.136
C40: =C19 -> 46706 | L40: =IF(COUNT(L19,$F19)=2,L19*$F19,"N/D") -> 0 | M40: =IF(COUNT(M19,$F19)=2,M19*$F19,"N/D") -> 0 | N40: =IF(COUNT(N19,$F19)=2,N19*$F19,"N/D") -> 0 | O40: =IF(COUNT(O19,$F19)=2,O19*$F19,"N/D") -> 0 | P40: =IF(COUNT(P19,$F19)=2,P19*$F19,"N/D") -> 0 | Q40: =IF(COUNT(Q19,$F19)=2,Q19*$F19,"N/D") -> 0 | R40: =IF(COUNT(R19,$F19)=2,R19*$F19,"N/D") -> 0 | S40: =IF(COUNT(S19,$F19)=2,S19*$F19,"N/D") -> 0 | ... W40: =IF(COUNT(W19,$F19)=2,W19*$F19,"N/D") -> 13080.07
C41: =C20 -> 46736 | L41: =IF(COUNT(L20,$F20)=2,L20*$F20,"N/D") -> 0 | M41: =IF(COUNT(M20,$F20)=2,M20*$F20,"N/D") -> 0 | N41: =IF(COUNT(N20,$F20)=2,N20*$F20,"N/D") -> 0 | O41: =IF(COUNT(O20,$F20)=2,O20*$F20,"N/D") -> 0 | P41: =IF(COUNT(P20,$F20)=2,P20*$F20,"N/D") -> 0 | Q41: =IF(COUNT(Q20,$F20)=2,Q20*$F20,"N/D") -> 0 | R41: =IF(COUNT(R20,$F20)=2,R20*$F20,"N/D") -> 0 | S41: =IF(COUNT(S20,$F20)=2,S20*$F20,"N/D") -> 0 | ... W41: =IF(COUNT(W20,$F20)=2,W20*$F20,"N/D") -> 15320.419
C43: Saldo externo cierre | L43: =IF(COUNT(L30:L41)=12,SUM(L30:L41),"N/D") -> 306.40837 | M43: =IF(COUNT(M30:M41)=12,SUM(M30:M41),"N/D") -> 1215.6647 | N43: =IF(COUNT(N30:N41)=12,SUM(N30:N41),"N/D") -> 2989.0557 | O43: =IF(COUNT(O30:O41)=12,SUM(O30:O41),"N/D") -> 5906.2313 | P43: =IF(COUNT(P30:P41)=12,SUM(P30:P41),"N/D") -> 10203.644 | Q43: =IF(COUNT(Q30:Q41)=12,SUM(Q30:Q41),"N/D") -> 15869.051 | R43: =IF(COUNT(R30:R41)=12,SUM(R30:R41),"N/D") -> 22804.116 | S43: =IF(COUNT(S30:S41)=12,SUM(S30:S41),"N/D") -> 31013.851 | ... W43: =IF(COUNT(W30:W41)=12,SUM(W30:W41),"N/D") -> 76338.274
C48: Saldo medio mensual, por cohorte | L48: M 1 | M48: M 2 | N48: M 3 | O48: M 4 | P48: M 5 | Q48: M 6 | R48: M 7 | S48: M 8 | T48: M 9 | U48: M 10 | V48: M 11 | W48: M 12
C50: =C9 -> 46402 | L50: =IF(COUNT($C9,$D9,$E9,L9,0)=5,IF($C9>EOMONTH(L$8,0),0,IF($C9>=L$8,($D9*$E9+L9)/2*(EOMONTH(L$8,0)-$C9+1)/DAY(EOMONTH(L$8,0)),(0+L9)/2)),"N/D") -> 243.33169 | M50: =IF(COUNT($C9,$D9,$E9,M9,L9)=5,IF($C9>EOMONTH(M$8,0),0,IF($C9>=M$8,($D9*$E9+M9)/2*(EOMONTH(M$8,0)-$C9+1)/DAY(EOMONTH(M$8,0)),(L9+M9)/2)),"N/D") -> 427.23281 | N50: =IF(COUNT($C9,$D9,$E9,N9,M9)=5,IF($C9>EOMONTH(N$8,0),0,IF($C9>=N$8,($D9*$E9+N9)/2*(EOMONTH(N$8,0)-$C9+1)/DAY(EOMONTH(N$8,0)),(M9+N9)/2)),"N/D") -> 405.12164 | O50: =IF(COUNT($C9,$D9,$E9,O9,N9)=5,IF($C9>EOMONTH(O$8,0),0,IF($C9>=O$8,($D9*$E9+O9)/2*(EOMONTH(O$8,0)-$C9+1)/DAY(EOMONTH(O$8,0)),(N9+O9)/2)),"N/D") -> 386.00859 | P50: =IF(COUNT($C9,$D9,$E9,P9,O9)=5,IF($C9>EOMONTH(P$8,0),0,IF($C9>=P$8,($D9*$E9+P9)/2*(EOMONTH(P$8,0)-$C9+1)/DAY(EOMONTH(P$8,0)),(O9+P9)/2)),"N/D") -> 374.6407 | Q50: =IF(COUNT($C9,$D9,$E9,Q9,P9)=5,IF($C9>EOMONTH(Q$8,0),0,IF($C9>=Q$8,($D9*$E9+Q9)/2*(EOMONTH(Q$8,0)-$C9+1)/DAY(EOMONTH(Q$8,0)),(P9+Q9)/2)),"N/D") -> 367.02047 | R50: =IF(COUNT($C9,$D9,$E9,R9,Q9)=5,IF($C9>EOMONTH(R$8,0),0,IF($C9>=R$8,($D9*$E9+R9)/2*(EOMONTH(R$8,0)-$C9+1)/DAY(EOMONTH(R$8,0)),(Q9+R9)/2)),"N/D") -> 360.49077 | S50: =IF(COUNT($C9,$D9,$E9,S9,R9)=5,IF($C9>EOMONTH(S$8,0),0,IF($C9>=S$8,($D9*$E9+S9)/2*(EOMONTH(S$8,0)-$C9+1)/DAY(EOMONTH(S$8,0)),(R9+S9)/2)),"N/D") -> 355.82477 | T50: =IF(COUNT($C9,$D9,$E9,T9,S9)=5,IF($C9>EOMONTH(T$8,0),0,IF($C9>=T$8,($D9*$E9+T9)/2*(EOMONTH(T$8,0)-$C9+1)/DAY(EOMONTH(T$8,0)),(S9+T9)/2)),"N/D") -> 352.11763 | ... W50: =IF(COUNT($C9,$D9,$E9,W9,V9)=5,IF($C9>EOMONTH(W$8,0),0,IF($C9>=W$8,($D9*$E9+W9)/2*(EOMONTH(W$8,0)-$C9+1)/DAY(EOMONTH(W$8,0)),(V9+W9)/2)),"N/D") -> 340.9962
C51: =C10 -> 46433 | L51: =IF(COUNT($C10,$D10,$E10,L10,0)=5,IF($C10>EOMONTH(L$8,0),0,IF($C10>=L$8,($D10*$E10+L10)/2*(EOMONTH(L$8,0)-$C10+1)/DAY(EOMONTH(L$8,0)),(0+L10)/2)),"N/D") -> 0 | M51: =IF(COUNT($C10,$D10,$E10,M10,L10)=5,IF($C10>EOMONTH(M$8,0),0,IF($C10>=M$8,($D10*$E10+M10)/2*(EOMONTH(M$8,0)-$C10+1)/DAY(EOMONTH(M$8,0)),(L10+M10)/2)),"N/D") -> 667.2702 | N51: =IF(COUNT($C10,$D10,$E10,N10,M10)=5,IF($C10>EOMONTH(N$8,0),0,IF($C10>=N$8,($D10*$E10+N10)/2*(EOMONTH(N$8,0)-$C10+1)/DAY(EOMONTH(N$8,0)),(M10+N10)/2)),"N/D") -> 1285.0713 | O51: =IF(COUNT($C10,$D10,$E10,O10,N10)=5,IF($C10>EOMONTH(O$8,0),0,IF($C10>=O$8,($D10*$E10+O10)/2*(EOMONTH(O$8,0)-$C10+1)/DAY(EOMONTH(O$8,0)),(N10+O10)/2)),"N/D") -> 1216.4892 | P51: =IF(COUNT($C10,$D10,$E10,P10,O10)=5,IF($C10>EOMONTH(P$8,0),0,IF($C10>=P$8,($D10*$E10+P10)/2*(EOMONTH(P$8,0)-$C10+1)/DAY(EOMONTH(P$8,0)),(O10+P10)/2)),"N/D") -> 1159.1501 | Q51: =IF(COUNT($C10,$D10,$E10,Q10,P10)=5,IF($C10>EOMONTH(Q$8,0),0,IF($C10>=Q$8,($D10*$E10+Q10)/2*(EOMONTH(Q$8,0)-$C10+1)/DAY(EOMONTH(Q$8,0)),(P10+Q10)/2)),"N/D") -> 1124.2969 | R51: =IF(COUNT($C10,$D10,$E10,R10,Q10)=5,IF($C10>EOMONTH(R$8,0),0,IF($C10>=R$8,($D10*$E10+R10)/2*(EOMONTH(R$8,0)-$C10+1)/DAY(EOMONTH(R$8,0)),(Q10+R10)/2)),"N/D") -> 1101.4362 | S51: =IF(COUNT($C10,$D10,$E10,S10,R10)=5,IF($C10>EOMONTH(S$8,0),0,IF($C10>=S$8,($D10*$E10+S10)/2*(EOMONTH(S$8,0)-$C10+1)/DAY(EOMONTH(S$8,0)),(R10+S10)/2)),"N/D") -> 1081.4723 | T51: =IF(COUNT($C10,$D10,$E10,T10,S10)=5,IF($C10>EOMONTH(T$8,0),0,IF($C10>=T$8,($D10*$E10+T10)/2*(EOMONTH(T$8,0)-$C10+1)/DAY(EOMONTH(T$8,0)),(S10+T10)/2)),"N/D") -> 1067.6566 | ... W51: =IF(COUNT($C10,$D10,$E10,W10,V10)=5,IF($C10>EOMONTH(W$8,0),0,IF($C10>=W$8,($D10*$E10+W10)/2*(EOMONTH(W$8,0)-$C10+1)/DAY(EOMONTH(W$8,0)),(V10+W10)/2)),"N/D") -> 1034.2924
C52: =C11 -> 46461 | L52: =IF(COUNT($C11,$D11,$E11,L11,0)=5,IF($C11>EOMONTH(L$8,0),0,IF($C11>=L$8,($D11*$E11+L11)/2*(EOMONTH(L$8,0)-$C11+1)/DAY(EOMONTH(L$8,0)),(0+L11)/2)),"N/D") -> 0 | M52: =IF(COUNT($C11,$D11,$E11,M11,L11)=5,IF($C11>EOMONTH(M$8,0),0,IF($C11>=M$8,($D11*$E11+M11)/2*(EOMONTH(M$8,0)-$C11+1)/DAY(EOMONTH(M$8,0)),(L11+M11)/2)),"N/D") -> 0 | N52: =IF(COUNT($C11,$D11,$E11,N11,M11)=5,IF($C11>EOMONTH(N$8,0),0,IF($C11>=N$8,($D11*$E11+N11)/2*(EOMONTH(N$8,0)-$C11+1)/DAY(EOMONTH(N$8,0)),(M11+N11)/2)),"N/D") -> 1459.9902 | O52: =IF(COUNT($C11,$D11,$E11,O11,N11)=5,IF($C11>EOMONTH(O$8,0),0,IF($C11>=O$8,($D11*$E11+O11)/2*(EOMONTH(O$8,0)-$C11+1)/DAY(EOMONTH(O$8,0)),(N11+O11)/2)),"N/D") -> 2558.8997 | P52: =IF(COUNT($C11,$D11,$E11,P11,O11)=5,IF($C11>EOMONTH(P$8,0),0,IF($C11>=P$8,($D11*$E11+P11)/2*(EOMONTH(P$8,0)-$C11+1)/DAY(EOMONTH(P$8,0)),(O11+P11)/2)),"N/D") -> 2421.7355 | Q52: =IF(COUNT($C11,$D11,$E11,Q11,P11)=5,IF($C11>EOMONTH(Q$8,0),0,IF($C11>=Q$8,($D11*$E11+Q11)/2*(EOMONTH(Q$8,0)-$C11+1)/DAY(EOMONTH(Q$8,0)),(P11+Q11)/2)),"N/D") -> 2310.0553 | R52: =IF(COUNT($C11,$D11,$E11,R11,Q11)=5,IF($C11>EOMONTH(R$8,0),0,IF($C11>=R$8,($D11*$E11+R11)/2*(EOMONTH(R$8,0)-$C11+1)/DAY(EOMONTH(R$8,0)),(Q11+R11)/2)),"N/D") -> 2244.8461 | S52: =IF(COUNT($C11,$D11,$E11,S11,R11)=5,IF($C11>EOMONTH(S$8,0),0,IF($C11>=S$8,($D11*$E11+S11)/2*(EOMONTH(S$8,0)-$C11+1)/DAY(EOMONTH(S$8,0)),(R11+S11)/2)),"N/D") -> 2198.3752 | T52: =IF(COUNT($C11,$D11,$E11,T11,S11)=5,IF($C11>EOMONTH(T$8,0),0,IF($C11>=T$8,($D11*$E11+T11)/2*(EOMONTH(T$8,0)-$C11+1)/DAY(EOMONTH(T$8,0)),(S11+T11)/2)),"N/D") -> 2159.9667 | ... W52: =IF(COUNT($C11,$D11,$E11,W11,V11)=5,IF($C11>EOMONTH(W$8,0),0,IF($C11>=W$8,($D11*$E11+W11)/2*(EOMONTH(W$8,0)-$C11+1)/DAY(EOMONTH(W$8,0)),(V11+W11)/2)),"N/D") -> 2089.0044
C53: =C12 -> 46492 | L53: =IF(COUNT($C12,$D12,$E12,L12,0)=5,IF($C12>EOMONTH(L$8,0),0,IF($C12>=L$8,($D12*$E12+L12)/2*(EOMONTH(L$8,0)-$C12+1)/DAY(EOMONTH(L$8,0)),(0+L12)/2)),"N/D") -> 0 | M53: =IF(COUNT($C12,$D12,$E12,M12,L12)=5,IF($C12>EOMONTH(M$8,0),0,IF($C12>=M$8,($D12*$E12+M12)/2*(EOMONTH(M$8,0)-$C12+1)/DAY(EOMONTH(M$8,0)),(L12+M12)/2)),"N/D") -> 0 | N53: =IF(COUNT($C12,$D12,$E12,N12,M12)=5,IF($C12>EOMONTH(N$8,0),0,IF($C12>=N$8,($D12*$E12+N12)/2*(EOMONTH(N$8,0)-$C12+1)/DAY(EOMONTH(N$8,0)),(M12+N12)/2)),"N/D") -> 0 | O53: =IF(COUNT($C12,$D12,$E12,O12,N12)=5,IF($C12>EOMONTH(O$8,0),0,IF($C12>=O$8,($D12*$E12+O12)/2*(EOMONTH(O$8,0)-$C12+1)/DAY(EOMONTH(O$8,0)),(N12+O12)/2)),"N/D") -> 2368.5188 | P53: =IF(COUNT($C12,$D12,$E12,P12,O12)=5,IF($C12>EOMONTH(P$8,0),0,IF($C12>=P$8,($D12*$E12+P12)/2*(EOMONTH(P$8,0)-$C12+1)/DAY(EOMONTH(P$8,0)),(O12+P12)/2)),"N/D") -> 4268.5805 | Q53: =IF(COUNT($C12,$D12,$E12,Q12,P12)=5,IF($C12>EOMONTH(Q$8,0),0,IF($C12>=Q$8,($D12*$E12+Q12)/2*(EOMONTH(Q$8,0)-$C12+1)/DAY(EOMONTH(Q$8,0)),(P12+Q12)/2)),"N/D") -> 4039.9734 | R53: =IF(COUNT($C12,$D12,$E12,R12,Q12)=5,IF($C12>EOMONTH(R$8,0),0,IF($C12>=R$8,($D12*$E12+R12)/2*(EOMONTH(R$8,0)-$C12+1)/DAY(EOMONTH(R$8,0)),(Q12+R12)/2)),"N/D") -> 3853.8398 | S53: =IF(COUNT($C12,$D12,$E12,S12,R12)=5,IF($C12>EOMONTH(S$8,0),0,IF($C12>=S$8,($D12*$E12+S12)/2*(EOMONTH(S$8,0)-$C12+1)/DAY(EOMONTH(S$8,0)),(R12+S12)/2)),"N/D") -> 3741.4102 | T53: =IF(COUNT($C12,$D12,$E12,T12,S12)=5,IF($C12>EOMONTH(T$8,0),0,IF($C12>=T$8,($D12*$E12+T12)/2*(EOMONTH(T$8,0)-$C12+1)/DAY(EOMONTH(T$8,0)),(S12+T12)/2)),"N/D") -> 3665.2078 | ... W53: =IF(COUNT($C12,$D12,$E12,W12,V12)=5,IF($C12>EOMONTH(W$8,0),0,IF($C12>=W$8,($D12*$E12+W12)/2*(EOMONTH(W$8,0)-$C12+1)/DAY(EOMONTH(W$8,0)),(V12+W12)/2)),"N/D") -> 3519.3531
C54: =C13 -> 46522 | L54: =IF(COUNT($C13,$D13,$E13,L13,0)=5,IF($C13>EOMONTH(L$8,0),0,IF($C13>=L$8,($D13*$E13+L13)/2*(EOMONTH(L$8,0)-$C13+1)/DAY(EOMONTH(L$8,0)),(0+L13)/2)),"N/D") -> 0 | M54: =IF(COUNT($C13,$D13,$E13,M13,L13)=5,IF($C13>EOMONTH(M$8,0),0,IF($C13>=M$8,($D13*$E13+M13)/2*(EOMONTH(M$8,0)-$C13+1)/DAY(EOMONTH(M$8,0)),(L13+M13)/2)),"N/D") -> 0 | N54: =IF(COUNT($C13,$D13,$E13,N13,M13)=5,IF($C13>EOMONTH(N$8,0),0,IF($C13>=N$8,($D13*$E13+N13)/2*(EOMONTH(N$8,0)-$C13+1)/DAY(EOMONTH(N$8,0)),(M13+N13)/2)),"N/D") -> 0 | O54: =IF(COUNT($C13,$D13,$E13,O13,N13)=5,IF($C13>EOMONTH(O$8,0),0,IF($C13>=O$8,($D13*$E13+O13)/2*(EOMONTH(O$8,0)-$C13+1)/DAY(EOMONTH(O$8,0)),(N13+O13)/2)),"N/D") -> 0 | P54: =IF(COUNT($C13,$D13,$E13,P13,O13)=5,IF($C13>EOMONTH(P$8,0),0,IF($C13>=P$8,($D13*$E13+P13)/2*(EOMONTH(P$8,0)-$C13+1)/DAY(EOMONTH(P$8,0)),(O13+P13)/2)),"N/D") -> 3649.9754 | Q54: =IF(COUNT($C13,$D13,$E13,Q13,P13)=5,IF($C13>EOMONTH(Q$8,0),0,IF($C13>=Q$8,($D13*$E13+Q13)/2*(EOMONTH(Q$8,0)-$C13+1)/DAY(EOMONTH(Q$8,0)),(P13+Q13)/2)),"N/D") -> 6397.2492 | R54: =IF(COUNT($C13,$D13,$E13,R13,Q13)=5,IF($C13>EOMONTH(R$8,0),0,IF($C13>=R$8,($D13*$E13+R13)/2*(EOMONTH(R$8,0)-$C13+1)/DAY(EOMONTH(R$8,0)),(Q13+R13)/2)),"N/D") -> 6054.3387 | S54: =IF(COUNT($C13,$D13,$E13,S13,R13)=5,IF($C13>EOMONTH(S$8,0),0,IF($C13>=S$8,($D13*$E13+S13)/2*(EOMONTH(S$8,0)-$C13+1)/DAY(EOMONTH(S$8,0)),(R13+S13)/2)),"N/D") -> 5773.2645 | T54: =IF(COUNT($C13,$D13,$E13,T13,S13)=5,IF($C13>EOMONTH(T$8,0),0,IF($C13>=T$8,($D13*$E13+T13)/2*(EOMONTH(T$8,0)-$C13+1)/DAY(EOMONTH(T$8,0)),(S13+T13)/2)),"N/D") -> 5610.2414 | ... W54: =IF(COUNT($C13,$D13,$E13,W13,V13)=5,IF($C13>EOMONTH(W$8,0),0,IF($C13>=W$8,($D13*$E13+W13)/2*(EOMONTH(W$8,0)-$C13+1)/DAY(EOMONTH(W$8,0)),(V13+W13)/2)),"N/D") -> 5333.7251
C55: =C14 -> 46553 | L55: =IF(COUNT($C14,$D14,$E14,L14,0)=5,IF($C14>EOMONTH(L$8,0),0,IF($C14>=L$8,($D14*$E14+L14)/2*(EOMONTH(L$8,0)-$C14+1)/DAY(EOMONTH(L$8,0)),(0+L14)/2)),"N/D") -> 0 | M55: =IF(COUNT($C14,$D14,$E14,M14,L14)=5,IF($C14>EOMONTH(M$8,0),0,IF($C14>=M$8,($D14*$E14+M14)/2*(EOMONTH(M$8,0)-$C14+1)/DAY(EOMONTH(M$8,0)),(L14+M14)/2)),"N/D") -> 0 | N55: =IF(COUNT($C14,$D14,$E14,N14,M14)=5,IF($C14>EOMONTH(N$8,0),0,IF($C14>=N$8,($D14*$E14+N14)/2*(EOMONTH(N$8,0)-$C14+1)/DAY(EOMONTH(N$8,0)),(M14+N14)/2)),"N/D") -> 0 | O55: =IF(COUNT($C14,$D14,$E14,O14,N14)=5,IF($C14>EOMONTH(O$8,0),0,IF($C14>=O$8,($D14*$E14+O14)/2*(EOMONTH(O$8,0)-$C14+1)/DAY(EOMONTH(O$8,0)),(N14+O14)/2)),"N/D") -> 0 | P55: =IF(COUNT($C14,$D14,$E14,P14,O14)=5,IF($C14>EOMONTH(P$8,0),0,IF($C14>=P$8,($D14*$E14+P14)/2*(EOMONTH(P$8,0)-$C14+1)/DAY(EOMONTH(P$8,0)),(O14+P14)/2)),"N/D") -> 0 | Q55: =IF(COUNT($C14,$D14,$E14,Q14,P14)=5,IF($C14>EOMONTH(Q$8,0),0,IF($C14>=Q$8,($D14*$E14+Q14)/2*(EOMONTH(Q$8,0)-$C14+1)/DAY(EOMONTH(Q$8,0)),(P14+Q14)/2)),"N/D") -> 4737.0375 | R55: =IF(COUNT($C14,$D14,$E14,R14,Q14)=5,IF($C14>EOMONTH(R$8,0),0,IF($C14>=R$8,($D14*$E14+R14)/2*(EOMONTH(R$8,0)-$C14+1)/DAY(EOMONTH(R$8,0)),(Q14+R14)/2)),"N/D") -> 8537.1609 | S55: =IF(COUNT($C14,$D14,$E14,S14,R14)=5,IF($C14>EOMONTH(S$8,0),0,IF($C14>=S$8,($D14*$E14+S14)/2*(EOMONTH(S$8,0)-$C14+1)/DAY(EOMONTH(S$8,0)),(R14+S14)/2)),"N/D") -> 8072.4516 | T55: =IF(COUNT($C14,$D14,$E14,T14,S14)=5,IF($C14>EOMONTH(T$8,0),0,IF($C14>=T$8,($D14*$E14+T14)/2*(EOMONTH(T$8,0)-$C14+1)/DAY(EOMONTH(T$8,0)),(S14+T14)/2)),"N/D") -> 7700.1844 | ... W55: =IF(COUNT($C14,$D14,$E14,W14,V14)=5,IF($C14>EOMONTH(W$8,0),0,IF($C14>=W$8,($D14*$E14+W14)/2*(EOMONTH(W$8,0)-$C14+1)/DAY(EOMONTH(W$8,0)),(V14+W14)/2)),"N/D") -> 7202.3876
C56: =C15 -> 46583 | L56: =IF(COUNT($C15,$D15,$E15,L15,0)=5,IF($C15>EOMONTH(L$8,0),0,IF($C15>=L$8,($D15*$E15+L15)/2*(EOMONTH(L$8,0)-$C15+1)/DAY(EOMONTH(L$8,0)),(0+L15)/2)),"N/D") -> 0 | M56: =IF(COUNT($C15,$D15,$E15,M15,L15)=5,IF($C15>EOMONTH(M$8,0),0,IF($C15>=M$8,($D15*$E15+M15)/2*(EOMONTH(M$8,0)-$C15+1)/DAY(EOMONTH(M$8,0)),(L15+M15)/2)),"N/D") -> 0 | N56: =IF(COUNT($C15,$D15,$E15,N15,M15)=5,IF($C15>EOMONTH(N$8,0),0,IF($C15>=N$8,($D15*$E15+N15)/2*(EOMONTH(N$8,0)-$C15+1)/DAY(EOMONTH(N$8,0)),(M15+N15)/2)),"N/D") -> 0 | O56: =IF(COUNT($C15,$D15,$E15,O15,N15)=5,IF($C15>EOMONTH(O$8,0),0,IF($C15>=O$8,($D15*$E15+O15)/2*(EOMONTH(O$8,0)-$C15+1)/DAY(EOMONTH(O$8,0)),(N15+O15)/2)),"N/D") -> 0 | P56: =IF(COUNT($C15,$D15,$E15,P15,O15)=5,IF($C15>EOMONTH(P$8,0),0,IF($C15>=P$8,($D15*$E15+P15)/2*(EOMONTH(P$8,0)-$C15+1)/DAY(EOMONTH(P$8,0)),(O15+P15)/2)),"N/D") -> 0 | Q56: =IF(COUNT($C15,$D15,$E15,Q15,P15)=5,IF($C15>EOMONTH(Q$8,0),0,IF($C15>=Q$8,($D15*$E15+Q15)/2*(EOMONTH(Q$8,0)-$C15+1)/DAY(EOMONTH(Q$8,0)),(P15+Q15)/2)),"N/D") -> 0 | R56: =IF(COUNT($C15,$D15,$E15,R15,Q15)=5,IF($C15>EOMONTH(R$8,0),0,IF($C15>=R$8,($D15*$E15+R15)/2*(EOMONTH(R$8,0)-$C15+1)/DAY(EOMONTH(R$8,0)),(Q15+R15)/2)),"N/D") -> 6083.2923 | S56: =IF(COUNT($C15,$D15,$E15,S15,R15)=5,IF($C15>EOMONTH(S$8,0),0,IF($C15>=S$8,($D15*$E15+S15)/2*(EOMONTH(S$8,0)-$C15+1)/DAY(EOMONTH(S$8,0)),(R15+S15)/2)),"N/D") -> 10652.713 | T56: =IF(COUNT($C15,$D15,$E15,T15,S15)=5,IF($C15>EOMONTH(T$8,0),0,IF($C15>=T$8,($D15*$E15+T15)/2*(EOMONTH(T$8,0)-$C15+1)/DAY(EOMONTH(T$8,0)),(S15+T15)/2)),"N/D") -> 10081.195 | ... W56: =IF(COUNT($C15,$D15,$E15,W15,V15)=5,IF($C15>EOMONTH(W$8,0),0,IF($C15>=W$8,($D15*$E15+W15)/2*(EOMONTH(W$8,0)-$C15+1)/DAY(EOMONTH(W$8,0)),(V15+W15)/2)),"N/D") -> 9159.8965
C57: =C16 -> 46614 | L57: =IF(COUNT($C16,$D16,$E16,L16,0)=5,IF($C16>EOMONTH(L$8,0),0,IF($C16>=L$8,($D16*$E16+L16)/2*(EOMONTH(L$8,0)-$C16+1)/DAY(EOMONTH(L$8,0)),(0+L16)/2)),"N/D") -> 0 | M57: =IF(COUNT($C16,$D16,$E16,M16,L16)=5,IF($C16>EOMONTH(M$8,0),0,IF($C16>=M$8,($D16*$E16+M16)/2*(EOMONTH(M$8,0)-$C16+1)/DAY(EOMONTH(M$8,0)),(L16+M16)/2)),"N/D") -> 0 | N57: =IF(COUNT($C16,$D16,$E16,N16,M16)=5,IF($C16>EOMONTH(N$8,0),0,IF($C16>=N$8,($D16*$E16+N16)/2*(EOMONTH(N$8,0)-$C16+1)/DAY(EOMONTH(N$8,0)),(M16+N16)/2)),"N/D") -> 0 | O57: =IF(COUNT($C16,$D16,$E16,O16,N16)=5,IF($C16>EOMONTH(O$8,0),0,IF($C16>=O$8,($D16*$E16+O16)/2*(EOMONTH(O$8,0)-$C16+1)/DAY(EOMONTH(O$8,0)),(N16+O16)/2)),"N/D") -> 0 | P57: =IF(COUNT($C16,$D16,$E16,P16,O16)=5,IF($C16>EOMONTH(P$8,0),0,IF($C16>=P$8,($D16*$E16+P16)/2*(EOMONTH(P$8,0)-$C16+1)/DAY(EOMONTH(P$8,0)),(O16+P16)/2)),"N/D") -> 0 | Q57: =IF(COUNT($C16,$D16,$E16,Q16,P16)=5,IF($C16>EOMONTH(Q$8,0),0,IF($C16>=Q$8,($D16*$E16+Q16)/2*(EOMONTH(Q$8,0)-$C16+1)/DAY(EOMONTH(Q$8,0)),(P16+Q16)/2)),"N/D") -> 0 | R57: =IF(COUNT($C16,$D16,$E16,R16,Q16)=5,IF($C16>EOMONTH(R$8,0),0,IF($C16>=R$8,($D16*$E16+R16)/2*(EOMONTH(R$8,0)-$C16+1)/DAY(EOMONTH(R$8,0)),(Q16+R16)/2)),"N/D") -> 0 | S57: =IF(COUNT($C16,$D16,$E16,S16,R16)=5,IF($C16>EOMONTH(S$8,0),0,IF($C16>=S$8,($D16*$E16+S16)/2*(EOMONTH(S$8,0)-$C16+1)/DAY(EOMONTH(S$8,0)),(R16+S16)/2)),"N/D") -> 7299.9508 | T57: =IF(COUNT($C16,$D16,$E16,T16,S16)=5,IF($C16>EOMONTH(T$8,0),0,IF($C16>=T$8,($D16*$E16+T16)/2*(EOMONTH(T$8,0)-$C16+1)/DAY(EOMONTH(T$8,0)),(S16+T16)/2)),"N/D") -> 12794.498 | ... W57: =IF(COUNT($C16,$D16,$E16,W16,V16)=5,IF($C16>EOMONTH(W$8,0),0,IF($C16>=W$8,($D16*$E16+W16)/2*(EOMONTH(W$8,0)-$C16+1)/DAY(EOMONTH(W$8,0)),(V16+W16)/2)),"N/D") -> 11224.23
C58: =C17 -> 46645 | L58: =IF(COUNT($C17,$D17,$E17,L17,0)=5,IF($C17>EOMONTH(L$8,0),0,IF($C17>=L$8,($D17*$E17+L17)/2*(EOMONTH(L$8,0)-$C17+1)/DAY(EOMONTH(L$8,0)),(0+L17)/2)),"N/D") -> 0 | M58: =IF(COUNT($C17,$D17,$E17,M17,L17)=5,IF($C17>EOMONTH(M$8,0),0,IF($C17>=M$8,($D17*$E17+M17)/2*(EOMONTH(M$8,0)-$C17+1)/DAY(EOMONTH(M$8,0)),(L17+M17)/2)),"N/D") -> 0 | N58: =IF(COUNT($C17,$D17,$E17,N17,M17)=5,IF($C17>EOMONTH(N$8,0),0,IF($C17>=N$8,($D17*$E17+N17)/2*(EOMONTH(N$8,0)-$C17+1)/DAY(EOMONTH(N$8,0)),(M17+N17)/2)),"N/D") -> 0 | O58: =IF(COUNT($C17,$D17,$E17,O17,N17)=5,IF($C17>EOMONTH(O$8,0),0,IF($C17>=O$8,($D17*$E17+O17)/2*(EOMONTH(O$8,0)-$C17+1)/DAY(EOMONTH(O$8,0)),(N17+O17)/2)),"N/D") -> 0 | P58: =IF(COUNT($C17,$D17,$E17,P17,O17)=5,IF($C17>EOMONTH(P$8,0),0,IF($C17>=P$8,($D17*$E17+P17)/2*(EOMONTH(P$8,0)-$C17+1)/DAY(EOMONTH(P$8,0)),(O17+P17)/2)),"N/D") -> 0 | Q58: =IF(COUNT($C17,$D17,$E17,Q17,P17)=5,IF($C17>EOMONTH(Q$8,0),0,IF($C17>=Q$8,($D17*$E17+Q17)/2*(EOMONTH(Q$8,0)-$C17+1)/DAY(EOMONTH(Q$8,0)),(P17+Q17)/2)),"N/D") -> 0 | R58: =IF(COUNT($C17,$D17,$E17,R17,Q17)=5,IF($C17>EOMONTH(R$8,0),0,IF($C17>=R$8,($D17*$E17+R17)/2*(EOMONTH(R$8,0)-$C17+1)/DAY(EOMONTH(R$8,0)),(Q17+R17)/2)),"N/D") -> 0 | S58: =IF(COUNT($C17,$D17,$E17,S17,R17)=5,IF($C17>EOMONTH(S$8,0),0,IF($C17>=S$8,($D17*$E17+S17)/2*(EOMONTH(S$8,0)-$C17+1)/DAY(EOMONTH(S$8,0)),(R17+S17)/2)),"N/D") -> 0 | T58: =IF(COUNT($C17,$D17,$E17,T17,S17)=5,IF($C17>EOMONTH(T$8,0),0,IF($C17>=T$8,($D17*$E17+T17)/2*(EOMONTH(T$8,0)-$C17+1)/DAY(EOMONTH(T$8,0)),(S17+T17)/2)),"N/D") -> 8289.8156 | ... W58: =IF(COUNT($C17,$D17,$E17,W17,V17)=5,IF($C17>EOMONTH(W$8,0),0,IF($C17>=W$8,($D17*$E17+W17)/2*(EOMONTH(W$8,0)-$C17+1)/DAY(EOMONTH(W$8,0)),(V17+W17)/2)),"N/D") -> 13488.439
C59: =C18 -> 46675 | L59: =IF(COUNT($C18,$D18,$E18,L18,0)=5,IF($C18>EOMONTH(L$8,0),0,IF($C18>=L$8,($D18*$E18+L18)/2*(EOMONTH(L$8,0)-$C18+1)/DAY(EOMONTH(L$8,0)),(0+L18)/2)),"N/D") -> 0 | M59: =IF(COUNT($C18,$D18,$E18,M18,L18)=5,IF($C18>EOMONTH(M$8,0),0,IF($C18>=M$8,($D18*$E18+M18)/2*(EOMONTH(M$8,0)-$C18+1)/DAY(EOMONTH(M$8,0)),(L18+M18)/2)),"N/D") -> 0 | N59: =IF(COUNT($C18,$D18,$E18,N18,M18)=5,IF($C18>EOMONTH(N$8,0),0,IF($C18>=N$8,($D18*$E18+N18)/2*(EOMONTH(N$8,0)-$C18+1)/DAY(EOMONTH(N$8,0)),(M18+N18)/2)),"N/D") -> 0 | O59: =IF(COUNT($C18,$D18,$E18,O18,N18)=5,IF($C18>EOMONTH(O$8,0),0,IF($C18>=O$8,($D18*$E18+O18)/2*(EOMONTH(O$8,0)-$C18+1)/DAY(EOMONTH(O$8,0)),(N18+O18)/2)),"N/D") -> 0 | P59: =IF(COUNT($C18,$D18,$E18,P18,O18)=5,IF($C18>EOMONTH(P$8,0),0,IF($C18>=P$8,($D18*$E18+P18)/2*(EOMONTH(P$8,0)-$C18+1)/DAY(EOMONTH(P$8,0)),(O18+P18)/2)),"N/D") -> 0 | Q59: =IF(COUNT($C18,$D18,$E18,Q18,P18)=5,IF($C18>EOMONTH(Q$8,0),0,IF($C18>=Q$8,($D18*$E18+Q18)/2*(EOMONTH(Q$8,0)-$C18+1)/DAY(EOMONTH(Q$8,0)),(P18+Q18)/2)),"N/D") -> 0 | R59: =IF(COUNT($C18,$D18,$E18,R18,Q18)=5,IF($C18>EOMONTH(R$8,0),0,IF($C18>=R$8,($D18*$E18+R18)/2*(EOMONTH(R$8,0)-$C18+1)/DAY(EOMONTH(R$8,0)),(Q18+R18)/2)),"N/D") -> 0 | S59: =IF(COUNT($C18,$D18,$E18,S18,R18)=5,IF($C18>EOMONTH(S$8,0),0,IF($C18>=S$8,($D18*$E18+S18)/2*(EOMONTH(S$8,0)-$C18+1)/DAY(EOMONTH(S$8,0)),(R18+S18)/2)),"N/D") -> 0 | T59: =IF(COUNT($C18,$D18,$E18,T18,S18)=5,IF($C18>EOMONTH(T$8,0),0,IF($C18>=T$8,($D18*$E18+T18)/2*(EOMONTH(T$8,0)-$C18+1)/DAY(EOMONTH(T$8,0)),(S18+T18)/2)),"N/D") -> 0 | ... W59: =IF(COUNT($C18,$D18,$E18,W18,V18)=5,IF($C18>EOMONTH(W$8,0),0,IF($C18>=W$8,($D18*$E18+W18)/2*(EOMONTH(W$8,0)-$C18+1)/DAY(EOMONTH(W$8,0)),(V18+W18)/2)),"N/D") -> 16144.903
C60: =C19 -> 46706 | L60: =IF(COUNT($C19,$D19,$E19,L19,0)=5,IF($C19>EOMONTH(L$8,0),0,IF($C19>=L$8,($D19*$E19+L19)/2*(EOMONTH(L$8,0)-$C19+1)/DAY(EOMONTH(L$8,0)),(0+L19)/2)),"N/D") -> 0 | M60: =IF(COUNT($C19,$D19,$E19,M19,L19)=5,IF($C19>EOMONTH(M$8,0),0,IF($C19>=M$8,($D19*$E19+M19)/2*(EOMONTH(M$8,0)-$C19+1)/DAY(EOMONTH(M$8,0)),(L19+M19)/2)),"N/D") -> 0 | N60: =IF(COUNT($C19,$D19,$E19,N19,M19)=5,IF($C19>EOMONTH(N$8,0),0,IF($C19>=N$8,($D19*$E19+N19)/2*(EOMONTH(N$8,0)-$C19+1)/DAY(EOMONTH(N$8,0)),(M19+N19)/2)),"N/D") -> 0 | O60: =IF(COUNT($C19,$D19,$E19,O19,N19)=5,IF($C19>EOMONTH(O$8,0),0,IF($C19>=O$8,($D19*$E19+O19)/2*(EOMONTH(O$8,0)-$C19+1)/DAY(EOMONTH(O$8,0)),(N19+O19)/2)),"N/D") -> 0 | P60: =IF(COUNT($C19,$D19,$E19,P19,O19)=5,IF($C19>EOMONTH(P$8,0),0,IF($C19>=P$8,($D19*$E19+P19)/2*(EOMONTH(P$8,0)-$C19+1)/DAY(EOMONTH(P$8,0)),(O19+P19)/2)),"N/D") -> 0 | Q60: =IF(COUNT($C19,$D19,$E19,Q19,P19)=5,IF($C19>EOMONTH(Q$8,0),0,IF($C19>=Q$8,($D19*$E19+Q19)/2*(EOMONTH(Q$8,0)-$C19+1)/DAY(EOMONTH(Q$8,0)),(P19+Q19)/2)),"N/D") -> 0 | R60: =IF(COUNT($C19,$D19,$E19,R19,Q19)=5,IF($C19>EOMONTH(R$8,0),0,IF($C19>=R$8,($D19*$E19+R19)/2*(EOMONTH(R$8,0)-$C19+1)/DAY(EOMONTH(R$8,0)),(Q19+R19)/2)),"N/D") -> 0 | S60: =IF(COUNT($C19,$D19,$E19,S19,R19)=5,IF($C19>EOMONTH(S$8,0),0,IF($C19>=S$8,($D19*$E19+S19)/2*(EOMONTH(S$8,0)-$C19+1)/DAY(EOMONTH(S$8,0)),(R19+S19)/2)),"N/D") -> 0 | T60: =IF(COUNT($C19,$D19,$E19,T19,S19)=5,IF($C19>EOMONTH(T$8,0),0,IF($C19>=T$8,($D19*$E19+T19)/2*(EOMONTH(T$8,0)-$C19+1)/DAY(EOMONTH(T$8,0)),(S19+T19)/2)),"N/D") -> 0 | ... W60: =IF(COUNT($C19,$D19,$E19,W19,V19)=5,IF($C19>EOMONTH(W$8,0),0,IF($C19>=W$8,($D19*$E19+W19)/2*(EOMONTH(W$8,0)-$C19+1)/DAY(EOMONTH(W$8,0)),(V19+W19)/2)),"N/D") -> 19208.612
C61: =C20 -> 46736 | L61: =IF(COUNT($C20,$D20,$E20,L20,0)=5,IF($C20>EOMONTH(L$8,0),0,IF($C20>=L$8,($D20*$E20+L20)/2*(EOMONTH(L$8,0)-$C20+1)/DAY(EOMONTH(L$8,0)),(0+L20)/2)),"N/D") -> 0 | M61: =IF(COUNT($C20,$D20,$E20,M20,L20)=5,IF($C20>EOMONTH(M$8,0),0,IF($C20>=M$8,($D20*$E20+M20)/2*(EOMONTH(M$8,0)-$C20+1)/DAY(EOMONTH(M$8,0)),(L20+M20)/2)),"N/D") -> 0 | N61: =IF(COUNT($C20,$D20,$E20,N20,M20)=5,IF($C20>EOMONTH(N$8,0),0,IF($C20>=N$8,($D20*$E20+N20)/2*(EOMONTH(N$8,0)-$C20+1)/DAY(EOMONTH(N$8,0)),(M20+N20)/2)),"N/D") -> 0 | O61: =IF(COUNT($C20,$D20,$E20,O20,N20)=5,IF($C20>EOMONTH(O$8,0),0,IF($C20>=O$8,($D20*$E20+O20)/2*(EOMONTH(O$8,0)-$C20+1)/DAY(EOMONTH(O$8,0)),(N20+O20)/2)),"N/D") -> 0 | P61: =IF(COUNT($C20,$D20,$E20,P20,O20)=5,IF($C20>EOMONTH(P$8,0),0,IF($C20>=P$8,($D20*$E20+P20)/2*(EOMONTH(P$8,0)-$C20+1)/DAY(EOMONTH(P$8,0)),(O20+P20)/2)),"N/D") -> 0 | Q61: =IF(COUNT($C20,$D20,$E20,Q20,P20)=5,IF($C20>EOMONTH(Q$8,0),0,IF($C20>=Q$8,($D20*$E20+Q20)/2*(EOMONTH(Q$8,0)-$C20+1)/DAY(EOMONTH(Q$8,0)),(P20+Q20)/2)),"N/D") -> 0 | R61: =IF(COUNT($C20,$D20,$E20,R20,Q20)=5,IF($C20>EOMONTH(R$8,0),0,IF($C20>=R$8,($D20*$E20+R20)/2*(EOMONTH(R$8,0)-$C20+1)/DAY(EOMONTH(R$8,0)),(Q20+R20)/2)),"N/D") -> 0 | S61: =IF(COUNT($C20,$D20,$E20,S20,R20)=5,IF($C20>EOMONTH(S$8,0),0,IF($C20>=S$8,($D20*$E20+S20)/2*(EOMONTH(S$8,0)-$C20+1)/DAY(EOMONTH(S$8,0)),(R20+S20)/2)),"N/D") -> 0 | T61: =IF(COUNT($C20,$D20,$E20,T20,S20)=5,IF($C20>EOMONTH(T$8,0),0,IF($C20>=T$8,($D20*$E20+T20)/2*(EOMONTH(T$8,0)-$C20+1)/DAY(EOMONTH(T$8,0)),(S20+T20)/2)),"N/D") -> 0 | ... W61: =IF(COUNT($C20,$D20,$E20,W20,V20)=5,IF($C20>EOMONTH(W$8,0),0,IF($C20>=W$8,($D20*$E20+W20)/2*(EOMONTH(W$8,0)-$C20+1)/DAY(EOMONTH(W$8,0)),(V20+W20)/2)),"N/D") -> 12166.585
C63: Saldo medio mensual | L63: =IF(COUNT(L50:L61)=12,SUM(L50:L61),"N/D") -> 243.33169 | M63: =IF(COUNT(M50:M61)=12,SUM(M50:M61),"N/D") -> 1094.503 | N63: =IF(COUNT(N50:N61)=12,SUM(N50:N61),"N/D") -> 3150.1831 | O63: =IF(COUNT(O50:O61)=12,SUM(O50:O61),"N/D") -> 6529.9163 | P63: =IF(COUNT(P50:P61)=12,SUM(P50:P61),"N/D") -> 11874.082 | Q63: =IF(COUNT(Q50:Q61)=12,SUM(Q50:Q61),"N/D") -> 18975.633 | R63: =IF(COUNT(R50:R61)=12,SUM(R50:R61),"N/D") -> 28235.405 | S63: =IF(COUNT(S50:S61)=12,SUM(S50:S61),"N/D") -> 39175.462 | ... W63: =IF(COUNT(W50:W61)=12,SUM(W50:W61),"N/D") -> 100912.43
C68: Saldo medio externo mensual, por cohorte | L68: M 1 | M68: M 2 | N68: M 3 | O68: M 4 | P68: M 5 | Q68: M 6 | R68: M 7 | S68: M 8 | T68: M 9 | U68: M 10 | V68: M 11 | W68: M 12
C70: =C9 -> 46402 | L70: =IF(COUNT(L50,$F9)=2,L50*$F9,"N/D") -> 170.33219 | M70: =IF(COUNT(M50,$F9)=2,M50*$F9,"N/D") -> 299.06297 | N70: =IF(COUNT(N50,$F9)=2,N50*$F9,"N/D") -> 283.58515 | O70: =IF(COUNT(O50,$F9)=2,O50*$F9,"N/D") -> 270.20602 | P70: =IF(COUNT(P50,$F9)=2,P50*$F9,"N/D") -> 262.24849 | Q70: =IF(COUNT(Q50,$F9)=2,Q50*$F9,"N/D") -> 256.91433 | R70: =IF(COUNT(R50,$F9)=2,R50*$F9,"N/D") -> 252.34354 | S70: =IF(COUNT(S50,$F9)=2,S50*$F9,"N/D") -> 249.07734 | ... W70: =IF(COUNT(W50,$F9)=2,W50*$F9,"N/D") -> 238.69734
C71: =C10 -> 46433 | L71: =IF(COUNT(L51,$F10)=2,L51*$F10,"N/D") -> 0 | M71: =IF(COUNT(M51,$F10)=2,M51*$F10,"N/D") -> 467.08914 | N71: =IF(COUNT(N51,$F10)=2,N51*$F10,"N/D") -> 899.54993 | O71: =IF(COUNT(O51,$F10)=2,O51*$F10,"N/D") -> 851.54245 | P71: =IF(COUNT(P51,$F10)=2,P51*$F10,"N/D") -> 811.40505 | Q71: =IF(COUNT(Q51,$F10)=2,Q51*$F10,"N/D") -> 787.00781 | R71: =IF(COUNT(R51,$F10)=2,R51*$F10,"N/D") -> 771.00532 | S71: =IF(COUNT(S51,$F10)=2,S51*$F10,"N/D") -> 757.03061 | ... W71: =IF(COUNT(W51,$F10)=2,W51*$F10,"N/D") -> 724.00465
C72: =C11 -> 46461 | L72: =IF(COUNT(L52,$F11)=2,L52*$F11,"N/D") -> 0 | M72: =IF(COUNT(M52,$F11)=2,M52*$F11,"N/D") -> 0 | N72: =IF(COUNT(N52,$F11)=2,N52*$F11,"N/D") -> 1021.9931 | O72: =IF(COUNT(O52,$F11)=2,O52*$F11,"N/D") -> 1791.2298 | P72: =IF(COUNT(P52,$F11)=2,P52*$F11,"N/D") -> 1695.2148 | Q72: =IF(COUNT(Q52,$F11)=2,Q52*$F11,"N/D") -> 1617.0387 | R72: =IF(COUNT(R52,$F11)=2,R52*$F11,"N/D") -> 1571.3923 | S72: =IF(COUNT(S52,$F11)=2,S52*$F11,"N/D") -> 1538.8626 | ... W72: =IF(COUNT(W52,$F11)=2,W52*$F11,"N/D") -> 1462.3031
C73: =C12 -> 46492 | L73: =IF(COUNT(L53,$F12)=2,L53*$F12,"N/D") -> 0 | M73: =IF(COUNT(M53,$F12)=2,M53*$F12,"N/D") -> 0 | N73: =IF(COUNT(N53,$F12)=2,N53*$F12,"N/D") -> 0 | O73: =IF(COUNT(O53,$F12)=2,O53*$F12,"N/D") -> 1657.9631 | P73: =IF(COUNT(P53,$F12)=2,P53*$F12,"N/D") -> 2988.0063 | Q73: =IF(COUNT(Q53,$F12)=2,Q53*$F12,"N/D") -> 2827.9814 | R73: =IF(COUNT(R53,$F12)=2,R53*$F12,"N/D") -> 2697.6879 | S73: =IF(COUNT(S53,$F12)=2,S53*$F12,"N/D") -> 2618.9871 | ... W73: =IF(COUNT(W53,$F12)=2,W53*$F12,"N/D") -> 2463.5472
C74: =C13 -> 46522 | L74: =IF(COUNT(L54,$F13)=2,L54*$F13,"N/D") -> 0 | M74: =IF(COUNT(M54,$F13)=2,M54*$F13,"N/D") -> 0 | N74: =IF(COUNT(N54,$F13)=2,N54*$F13,"N/D") -> 0 | O74: =IF(COUNT(O54,$F13)=2,O54*$F13,"N/D") -> 0 | P74: =IF(COUNT(P54,$F13)=2,P54*$F13,"N/D") -> 2554.9828 | Q74: =IF(COUNT(Q54,$F13)=2,Q54*$F13,"N/D") -> 4478.0745 | R74: =IF(COUNT(R54,$F13)=2,R54*$F13,"N/D") -> 4238.0371 | S74: =IF(COUNT(S54,$F13)=2,S54*$F13,"N/D") -> 4041.2851 | ... W74: =IF(COUNT(W54,$F13)=2,W54*$F13,"N/D") -> 3733.6076
C75: =C14 -> 46553 | L75: =IF(COUNT(L55,$F14)=2,L55*$F14,"N/D") -> 0 | M75: =IF(COUNT(M55,$F14)=2,M55*$F14,"N/D") -> 0 | N75: =IF(COUNT(N55,$F14)=2,N55*$F14,"N/D") -> 0 | O75: =IF(COUNT(O55,$F14)=2,O55*$F14,"N/D") -> 0 | P75: =IF(COUNT(P55,$F14)=2,P55*$F14,"N/D") -> 0 | Q75: =IF(COUNT(Q55,$F14)=2,Q55*$F14,"N/D") -> 3315.9262 | R75: =IF(COUNT(R55,$F14)=2,R55*$F14,"N/D") -> 5976.0127 | S75: =IF(COUNT(S55,$F14)=2,S55*$F14,"N/D") -> 5650.7161 | ... W75: =IF(COUNT(W55,$F14)=2,W55*$F14,"N/D") -> 5041.6713
C76: =C15 -> 46583 | L76: =IF(COUNT(L56,$F15)=2,L56*$F15,"N/D") -> 0 | M76: =IF(COUNT(M56,$F15)=2,M56*$F15,"N/D") -> 0 | N76: =IF(COUNT(N56,$F15)=2,N56*$F15,"N/D") -> 0 | O76: =IF(COUNT(O56,$F15)=2,O56*$F15,"N/D") -> 0 | P76: =IF(COUNT(P56,$F15)=2,P56*$F15,"N/D") -> 0 | Q76: =IF(COUNT(Q56,$F15)=2,Q56*$F15,"N/D") -> 0 | R76: =IF(COUNT(R56,$F15)=2,R56*$F15,"N/D") -> 4258.3046 | S76: =IF(COUNT(S56,$F15)=2,S56*$F15,"N/D") -> 7456.899 | ... W76: =IF(COUNT(W56,$F15)=2,W56*$F15,"N/D") -> 6411.9275
C77: =C16 -> 46614 | L77: =IF(COUNT(L57,$F16)=2,L57*$F16,"N/D") -> 0 | M77: =IF(COUNT(M57,$F16)=2,M57*$F16,"N/D") -> 0 | N77: =IF(COUNT(N57,$F16)=2,N57*$F16,"N/D") -> 0 | O77: =IF(COUNT(O57,$F16)=2,O57*$F16,"N/D") -> 0 | P77: =IF(COUNT(P57,$F16)=2,P57*$F16,"N/D") -> 0 | Q77: =IF(COUNT(Q57,$F16)=2,Q57*$F16,"N/D") -> 0 | R77: =IF(COUNT(R57,$F16)=2,R57*$F16,"N/D") -> 0 | S77: =IF(COUNT(S57,$F16)=2,S57*$F16,"N/D") -> 5109.9656 | ... W77: =IF(COUNT(W57,$F16)=2,W57*$F16,"N/D") -> 7856.9613
C78: =C17 -> 46645 | L78: =IF(COUNT(L58,$F17)=2,L58*$F17,"N/D") -> 0 | M78: =IF(COUNT(M58,$F17)=2,M58*$F17,"N/D") -> 0 | N78: =IF(COUNT(N58,$F17)=2,N58*$F17,"N/D") -> 0 | O78: =IF(COUNT(O58,$F17)=2,O58*$F17,"N/D") -> 0 | P78: =IF(COUNT(P58,$F17)=2,P58*$F17,"N/D") -> 0 | Q78: =IF(COUNT(Q58,$F17)=2,Q58*$F17,"N/D") -> 0 | R78: =IF(COUNT(R58,$F17)=2,R58*$F17,"N/D") -> 0 | S78: =IF(COUNT(S58,$F17)=2,S58*$F17,"N/D") -> 0 | ... W78: =IF(COUNT(W58,$F17)=2,W58*$F17,"N/D") -> 9441.9076
C79: =C18 -> 46675 | L79: =IF(COUNT(L59,$F18)=2,L59*$F18,"N/D") -> 0 | M79: =IF(COUNT(M59,$F18)=2,M59*$F18,"N/D") -> 0 | N79: =IF(COUNT(N59,$F18)=2,N59*$F18,"N/D") -> 0 | O79: =IF(COUNT(O59,$F18)=2,O59*$F18,"N/D") -> 0 | P79: =IF(COUNT(P59,$F18)=2,P59*$F18,"N/D") -> 0 | Q79: =IF(COUNT(Q59,$F18)=2,Q59*$F18,"N/D") -> 0 | R79: =IF(COUNT(R59,$F18)=2,R59*$F18,"N/D") -> 0 | S79: =IF(COUNT(S59,$F18)=2,S59*$F18,"N/D") -> 0 | ... W79: =IF(COUNT(W59,$F18)=2,W59*$F18,"N/D") -> 11301.432
C80: =C19 -> 46706 | L80: =IF(COUNT(L60,$F19)=2,L60*$F19,"N/D") -> 0 | M80: =IF(COUNT(M60,$F19)=2,M60*$F19,"N/D") -> 0 | N80: =IF(COUNT(N60,$F19)=2,N60*$F19,"N/D") -> 0 | O80: =IF(COUNT(O60,$F19)=2,O60*$F19,"N/D") -> 0 | P80: =IF(COUNT(P60,$F19)=2,P60*$F19,"N/D") -> 0 | Q80: =IF(COUNT(Q60,$F19)=2,Q60*$F19,"N/D") -> 0 | R80: =IF(COUNT(R60,$F19)=2,R60*$F19,"N/D") -> 0 | S80: =IF(COUNT(S60,$F19)=2,S60*$F19,"N/D") -> 0 | ... W80: =IF(COUNT(W60,$F19)=2,W60*$F19,"N/D") -> 13446.028
C81: =C20 -> 46736 | L81: =IF(COUNT(L61,$F20)=2,L61*$F20,"N/D") -> 0 | M81: =IF(COUNT(M61,$F20)=2,M61*$F20,"N/D") -> 0 | N81: =IF(COUNT(N61,$F20)=2,N61*$F20,"N/D") -> 0 | O81: =IF(COUNT(O61,$F20)=2,O61*$F20,"N/D") -> 0 | P81: =IF(COUNT(P61,$F20)=2,P61*$F20,"N/D") -> 0 | Q81: =IF(COUNT(Q61,$F20)=2,Q61*$F20,"N/D") -> 0 | R81: =IF(COUNT(R61,$F20)=2,R61*$F20,"N/D") -> 0 | S81: =IF(COUNT(S61,$F20)=2,S61*$F20,"N/D") -> 0 | ... W81: =IF(COUNT(W61,$F20)=2,W61*$F20,"N/D") -> 8516.6093
C83: Saldo medio externo mensual | L83: =IF(COUNT(L70:L81)=12,SUM(L70:L81),"N/D") -> 170.33219 | M83: =IF(COUNT(M70:M81)=12,SUM(M70:M81),"N/D") -> 766.15211 | N83: =IF(COUNT(N70:N81)=12,SUM(N70:N81),"N/D") -> 2205.1282 | O83: =IF(COUNT(O70:O81)=12,SUM(O70:O81),"N/D") -> 4570.9414 | P83: =IF(COUNT(P70:P81)=12,SUM(P70:P81),"N/D") -> 8311.8575 | Q83: =IF(COUNT(Q70:Q81)=12,SUM(Q70:Q81),"N/D") -> 13282.943 | R83: =IF(COUNT(R70:R81)=12,SUM(R70:R81),"N/D") -> 19764.783 | S83: =IF(COUNT(S70:S81)=12,SUM(S70:S81),"N/D") -> 27422.823 | ... W83: =IF(COUNT(W70:W81)=12,SUM(W70:W81),"N/D") -> 70638.698
C87: Primer fondeo | D87: Cuentas potenciales | E87: Saldo 30 d | F87: Saldo 60 d | G87: Saldo 90 d | H87: Saldo 180 d | I87: Saldo 365 d
C88: =C9 -> 46402 | D88: =D9 -> 0.1798875 | E88: =IF(COUNT($C9)=1,IF($C9+30>EOMONTH(Supuestos!$Q$21,0),"Fuera2027",IF(COUNT($D9,$E9,$G9)=3,$D9*$E9*$G9,"N/D")),"N/D") -> 427.23281 | F88: =IF(COUNT($C9)=1,IF($C9+60>EOMONTH(Supuestos!$Q$21,0),"Fuera2027",IF(COUNT($D9,$E9,$H9)=3,$D9*$E9*$H9,"N/D")),"N/D") -> 404.74687 | G88: =IF(COUNT($C9)=1,IF($C9+90>EOMONTH(Supuestos!$Q$21,0),"Fuera2027",IF(COUNT($D9,$E9,$I9)=3,$D9*$E9*$I9,"N/D")),"N/D") -> 382.26094 | H88: =IF(COUNT($C9)=1,IF($C9+180>EOMONTH(Supuestos!$Q$21,0),"Fuera2027",IF(COUNT($D9,$E9,$J9)=3,$D9*$E9*$J9,"N/D")),"N/D") -> 359.775 | I88: =IF(COUNT($C9)=1,IF($C9+365>EOMONTH(Supuestos!$Q$21,0),"Fuera2027",IF(COUNT($D9,$E9,$K9)=3,$D9*$E9*$K9,"N/D")),"N/D") -> Fuera2027
C89: =C10 -> 46433 | D89: =D10 -> 0.5396625 | E89: =IF(COUNT($C10)=1,IF($C10+30>EOMONTH(Supuestos!$Q$21,0),"Fuera2027",IF(COUNT($D10,$E10,$G10)=3,$D10*$E10*$G10,"N/D")),"N/D") -> 1281.6984 | F89: =IF(COUNT($C10)=1,IF($C10+60>EOMONTH(Supuestos!$Q$21,0),"Fuera2027",IF(COUNT($D10,$E10,$H10)=3,$D10*$E10*$H10,"N/D")),"N/D") -> 1214.2406 | G89: =IF(COUNT($C10)=1,IF($C10+90>EOMONTH(Supuestos!$Q$21,0),"Fuera2027",IF(COUNT($D10,$E10,$I10)=3,$D10*$E10*$I10,"N/D")),"N/D") -> 1146.7828 | H89: =IF(COUNT($C10)=1,IF($C10+180>EOMONTH(Supuestos!$Q$21,0),"Fuera2027",IF(COUNT($D10,$E10,$J10)=3,$D10*$E10*$J10,"N/D")),"N/D") -> 1079.325 | I89: =IF(COUNT($C10)=1,IF($C10+365>EOMONTH(Supuestos!$Q$21,0),"Fuera2027",IF(COUNT($D10,$E10,$K10)=3,$D10*$E10*$K10,"N/D")),"N/D") -> Fuera2027
C90: =C11 -> 46461 | D90: =D11 -> 1.079325 | E90: =IF(COUNT($C11)=1,IF($C11+30>EOMONTH(Supuestos!$Q$21,0),"Fuera2027",IF(COUNT($D11,$E11,$G11)=3,$D11*$E11*$G11,"N/D")),"N/D") -> 2563.3969 | F90: =IF(COUNT($C11)=1,IF($C11+60>EOMONTH(Supuestos!$Q$21,0),"Fuera2027",IF(COUNT($D11,$E11,$H11)=3,$D11*$E11*$H11,"N/D")),"N/D") -> 2428.4812 | G90: =IF(COUNT($C11)=1,IF($C11+90>EOMONTH(Supuestos!$Q$21,0),"Fuera2027",IF(COUNT($D11,$E11,$I11)=3,$D11*$E11*$I11,"N/D")),"N/D") -> 2293.5656 | H90: =IF(COUNT($C11)=1,IF($C11+180>EOMONTH(Supuestos!$Q$21,0),"Fuera2027",IF(COUNT($D11,$E11,$J11)=3,$D11*$E11*$J11,"N/D")),"N/D") -> 2158.65 | I90: =IF(COUNT($C11)=1,IF($C11+365>EOMONTH(Supuestos!$Q$21,0),"Fuera2027",IF(COUNT($D11,$E11,$K11)=3,$D11*$E11*$K11,"N/D")),"N/D") -> Fuera2027
C91: =C12 -> 46492 | D91: =D12 -> 1.798875 | E91: =IF(COUNT($C12)=1,IF($C12+30>EOMONTH(Supuestos!$Q$21,0),"Fuera2027",IF(COUNT($D12,$E12,$G12)=3,$D12*$E12*$G12,"N/D")),"N/D") -> 4272.3281 | F91: =IF(COUNT($C12)=1,IF($C12+60>EOMONTH(Supuestos!$Q$21,0),"Fuera2027",IF(COUNT($D12,$E12,$H12)=3,$D12*$E12*$H12,"N/D")),"N/D") -> 4047.4688 | G91: =IF(COUNT($C12)=1,IF($C12+90>EOMONTH(Supuestos!$Q$21,0),"Fuera2027",IF(COUNT($D12,$E12,$I12)=3,$D12*$E12*$I12,"N/D")),"N/D") -> 3822.6094 | H91: =IF(COUNT($C12)=1,IF($C12+180>EOMONTH(Supuestos!$Q$21,0),"Fuera2027",IF(COUNT($D12,$E12,$J12)=3,$D12*$E12*$J12,"N/D")),"N/D") -> 3597.75 | I91: =IF(COUNT($C12)=1,IF($C12+365>EOMONTH(Supuestos!$Q$21,0),"Fuera2027",IF(COUNT($D12,$E12,$K12)=3,$D12*$E12*$K12,"N/D")),"N/D") -> Fuera2027
C92: =C13 -> 46522 | D92: =D13 -> 2.6983125 | E92: =IF(COUNT($C13)=1,IF($C13+30>EOMONTH(Supuestos!$Q$21,0),"Fuera2027",IF(COUNT($D13,$E13,$G13)=3,$D13*$E13*$G13,"N/D")),"N/D") -> 6408.4922 | F92: =IF(COUNT($C13)=1,IF($C13+60>EOMONTH(Supuestos!$Q$21,0),"Fuera2027",IF(COUNT($D13,$E13,$H13)=3,$D13*$E13*$H13,"N/D")),"N/D") -> 6071.2031 | G92: =IF(COUNT($C13)=1,IF($C13+90>EOMONTH(Supuestos!$Q$21,0),"Fuera2027",IF(COUNT($D13,$E13,$I13)=3,$D13*$E13*$I13,"N/D")),"N/D") -> 5733.9141 | H92: =IF(COUNT($C13)=1,IF($C13+180>EOMONTH(Supuestos!$Q$21,0),"Fuera2027",IF(COUNT($D13,$E13,$J13)=3,$D13*$E13*$J13,"N/D")),"N/D") -> 5396.625 | I92: =IF(COUNT($C13)=1,IF($C13+365>EOMONTH(Supuestos!$Q$21,0),"Fuera2027",IF(COUNT($D13,$E13,$K13)=3,$D13*$E13*$K13,"N/D")),"N/D") -> Fuera2027
C93: =C14 -> 46553 | D93: =D14 -> 3.59775 | E93: =IF(COUNT($C14)=1,IF($C14+30>EOMONTH(Supuestos!$Q$21,0),"Fuera2027",IF(COUNT($D14,$E14,$G14)=3,$D14*$E14*$G14,"N/D")),"N/D") -> 8544.6562 | F93: =IF(COUNT($C14)=1,IF($C14+60>EOMONTH(Supuestos!$Q$21,0),"Fuera2027",IF(COUNT($D14,$E14,$H14)=3,$D14*$E14*$H14,"N/D")),"N/D") -> 8094.9375 | G93: =IF(COUNT($C14)=1,IF($C14+90>EOMONTH(Supuestos!$Q$21,0),"Fuera2027",IF(COUNT($D14,$E14,$I14)=3,$D14*$E14*$I14,"N/D")),"N/D") -> 7645.2188 | H93: =IF(COUNT($C14)=1,IF($C14+180>EOMONTH(Supuestos!$Q$21,0),"Fuera2027",IF(COUNT($D14,$E14,$J14)=3,$D14*$E14*$J14,"N/D")),"N/D") -> 7195.5 | I93: =IF(COUNT($C14)=1,IF($C14+365>EOMONTH(Supuestos!$Q$21,0),"Fuera2027",IF(COUNT($D14,$E14,$K14)=3,$D14*$E14*$K14,"N/D")),"N/D") -> Fuera2027
C94: =C15 -> 46583 | D94: =D15 -> 4.4971875 | E94: =IF(COUNT($C15)=1,IF($C15+30>EOMONTH(Supuestos!$Q$21,0),"Fuera2027",IF(COUNT($D15,$E15,$G15)=3,$D15*$E15*$G15,"N/D")),"N/D") -> 10680.82 | F94: =IF(COUNT($C15)=1,IF($C15+60>EOMONTH(Supuestos!$Q$21,0),"Fuera2027",IF(COUNT($D15,$E15,$H15)=3,$D15*$E15*$H15,"N/D")),"N/D") -> 10118.672 | G94: =IF(COUNT($C15)=1,IF($C15+90>EOMONTH(Supuestos!$Q$21,0),"Fuera2027",IF(COUNT($D15,$E15,$I15)=3,$D15*$E15*$I15,"N/D")),"N/D") -> 9556.5234 | H94: =IF(COUNT($C15)=1,IF($C15+180>EOMONTH(Supuestos!$Q$21,0),"Fuera2027",IF(COUNT($D15,$E15,$J15)=3,$D15*$E15*$J15,"N/D")),"N/D") -> Fuera2027 | I94: =IF(COUNT($C15)=1,IF($C15+365>EOMONTH(Supuestos!$Q$21,0),"Fuera2027",IF(COUNT($D15,$E15,$K15)=3,$D15*$E15*$K15,"N/D")),"N/D") -> Fuera2027
C95: =C16 -> 46614 | D95: =D16 -> 5.396625 | E95: =IF(COUNT($C16)=1,IF($C16+30>EOMONTH(Supuestos!$Q$21,0),"Fuera2027",IF(COUNT($D16,$E16,$G16)=3,$D16*$E16*$G16,"N/D")),"N/D") -> 12816.984 | F95: =IF(COUNT($C16)=1,IF($C16+60>EOMONTH(Supuestos!$Q$21,0),"Fuera2027",IF(COUNT($D16,$E16,$H16)=3,$D16*$E16*$H16,"N/D")),"N/D") -> 12142.406 | G95: =IF(COUNT($C16)=1,IF($C16+90>EOMONTH(Supuestos!$Q$21,0),"Fuera2027",IF(COUNT($D16,$E16,$I16)=3,$D16*$E16*$I16,"N/D")),"N/D") -> 11467.828 | H95: =IF(COUNT($C16)=1,IF($C16+180>EOMONTH(Supuestos!$Q$21,0),"Fuera2027",IF(COUNT($D16,$E16,$J16)=3,$D16*$E16*$J16,"N/D")),"N/D") -> Fuera2027 | I95: =IF(COUNT($C16)=1,IF($C16+365>EOMONTH(Supuestos!$Q$21,0),"Fuera2027",IF(COUNT($D16,$E16,$K16)=3,$D16*$E16*$K16,"N/D")),"N/D") -> Fuera2027
C96: =C17 -> 46645 | D96: =D17 -> 6.2960625 | E96: =IF(COUNT($C17)=1,IF($C17+30>EOMONTH(Supuestos!$Q$21,0),"Fuera2027",IF(COUNT($D17,$E17,$G17)=3,$D17*$E17*$G17,"N/D")),"N/D") -> 14953.148 | F96: =IF(COUNT($C17)=1,IF($C17+60>EOMONTH(Supuestos!$Q$21,0),"Fuera2027",IF(COUNT($D17,$E17,$H17)=3,$D17*$E17*$H17,"N/D")),"N/D") -> 14166.141 | G96: =IF(COUNT($C17)=1,IF($C17+90>EOMONTH(Supuestos!$Q$21,0),"Fuera2027",IF(COUNT($D17,$E17,$I17)=3,$D17*$E17*$I17,"N/D")),"N/D") -> 13379.133 | H96: =IF(COUNT($C17)=1,IF($C17+180>EOMONTH(Supuestos!$Q$21,0),"Fuera2027",IF(COUNT($D17,$E17,$J17)=3,$D17*$E17*$J17,"N/D")),"N/D") -> Fuera2027 | I96: =IF(COUNT($C17)=1,IF($C17+365>EOMONTH(Supuestos!$Q$21,0),"Fuera2027",IF(COUNT($D17,$E17,$K17)=3,$D17*$E17*$K17,"N/D")),"N/D") -> Fuera2027
C97: =C18 -> 46675 | D97: =D18 -> 7.1955 | E97: =IF(COUNT($C18)=1,IF($C18+30>EOMONTH(Supuestos!$Q$21,0),"Fuera2027",IF(COUNT($D18,$E18,$G18)=3,$D18*$E18*$G18,"N/D")),"N/D") -> 17089.312 | F97: =IF(COUNT($C18)=1,IF($C18+60>EOMONTH(Supuestos!$Q$21,0),"Fuera2027",IF(COUNT($D18,$E18,$H18)=3,$D18*$E18*$H18,"N/D")),"N/D") -> 16189.875 | G97: =IF(COUNT($C18)=1,IF($C18+90>EOMONTH(Supuestos!$Q$21,0),"Fuera2027",IF(COUNT($D18,$E18,$I18)=3,$D18*$E18*$I18,"N/D")),"N/D") -> Fuera2027 | H97: =IF(COUNT($C18)=1,IF($C18+180>EOMONTH(Supuestos!$Q$21,0),"Fuera2027",IF(COUNT($D18,$E18,$J18)=3,$D18*$E18*$J18,"N/D")),"N/D") -> Fuera2027 | I97: =IF(COUNT($C18)=1,IF($C18+365>EOMONTH(Supuestos!$Q$21,0),"Fuera2027",IF(COUNT($D18,$E18,$K18)=3,$D18*$E18*$K18,"N/D")),"N/D") -> Fuera2027
C98: =C19 -> 46706 | D98: =D19 -> 8.0949375 | E98: =IF(COUNT($C19)=1,IF($C19+30>EOMONTH(Supuestos!$Q$21,0),"Fuera2027",IF(COUNT($D19,$E19,$G19)=3,$D19*$E19*$G19,"N/D")),"N/D") -> 19225.477 | F98: =IF(COUNT($C19)=1,IF($C19+60>EOMONTH(Supuestos!$Q$21,0),"Fuera2027",IF(COUNT($D19,$E19,$H19)=3,$D19*$E19*$H19,"N/D")),"N/D") -> Fuera2027 | G98: =IF(COUNT($C19)=1,IF($C19+90>EOMONTH(Supuestos!$Q$21,0),"Fuera2027",IF(COUNT($D19,$E19,$I19)=3,$D19*$E19*$I19,"N/D")),"N/D") -> Fuera2027 | H98: =IF(COUNT($C19)=1,IF($C19+180>EOMONTH(Supuestos!$Q$21,0),"Fuera2027",IF(COUNT($D19,$E19,$J19)=3,$D19*$E19*$J19,"N/D")),"N/D") -> Fuera2027 | I98: =IF(COUNT($C19)=1,IF($C19+365>EOMONTH(Supuestos!$Q$21,0),"Fuera2027",IF(COUNT($D19,$E19,$K19)=3,$D19*$E19*$K19,"N/D")),"N/D") -> Fuera2027
C99: =C20 -> 46736 | D99: =D20 -> 8.994375 | E99: =IF(COUNT($C20)=1,IF($C20+30>EOMONTH(Supuestos!$Q$21,0),"Fuera2027",IF(COUNT($D20,$E20,$G20)=3,$D20*$E20*$G20,"N/D")),"N/D") -> Fuera2027 | F99: =IF(COUNT($C20)=1,IF($C20+60>EOMONTH(Supuestos!$Q$21,0),"Fuera2027",IF(COUNT($D20,$E20,$H20)=3,$D20*$E20*$H20,"N/D")),"N/D") -> Fuera2027 | G99: =IF(COUNT($C20)=1,IF($C20+90>EOMONTH(Supuestos!$Q$21,0),"Fuera2027",IF(COUNT($D20,$E20,$I20)=3,$D20*$E20*$I20,"N/D")),"N/D") -> Fuera2027 | H99: =IF(COUNT($C20)=1,IF($C20+180>EOMONTH(Supuestos!$Q$21,0),"Fuera2027",IF(COUNT($D20,$E20,$J20)=3,$D20*$E20*$J20,"N/D")),"N/D") -> Fuera2027 | I99: =IF(COUNT($C20)=1,IF($C20+365>EOMONTH(Supuestos!$Q$21,0),"Fuera2027",IF(COUNT($D20,$E20,$K20)=3,$D20*$E20*$K20,"N/D")),"N/D") -> Fuera2027
C102: 365 d se muestra Fuera 2027 si el aniversario cae en 2028. El knot 365 d sólo ayuda a interpolar la curva hipotética dentro del año.
C103: Día 15 y lag son supuestos de calendario. Saldo medio usa media de extremos con ponderación de días del primer mes; no dato bancario.
C104: La proporción externa de cada fila se conserva en toda su vida. Cambiar el driver de diciembre no repondera cohortes anteriores.
C108: Edad de cohorte en días al cierre | L108: M 1 | M108: M 2 | N108: M 3 | O108: M 4 | P108: M 5 | Q108: M 6 | R108: M 7 | S108: M 8 | T108: M 9 | U108: M 10 | V108: M 11 | W108: M 12
C110: =C9 -> 46402 | L110: =IF(COUNT($C9)=1,EOMONTH(L$8,0)-$C9,"N/D") -> 16 | M110: =IF(COUNT($C9)=1,EOMONTH(M$8,0)-$C9,"N/D") -> 44 | N110: =IF(COUNT($C9)=1,EOMONTH(N$8,0)-$C9,"N/D") -> 75 | O110: =IF(COUNT($C9)=1,EOMONTH(O$8,0)-$C9,"N/D") -> 105 | P110: =IF(COUNT($C9)=1,EOMONTH(P$8,0)-$C9,"N/D") -> 136 | Q110: =IF(COUNT($C9)=1,EOMONTH(Q$8,0)-$C9,"N/D") -> 166 | R110: =IF(COUNT($C9)=1,EOMONTH(R$8,0)-$C9,"N/D") -> 197 | S110: =IF(COUNT($C9)=1,EOMONTH(S$8,0)-$C9,"N/D") -> 228 | ... W110: =IF(COUNT($C9)=1,EOMONTH(W$8,0)-$C9,"N/D") -> 350
C111: =C10 -> 46433 | L111: =IF(COUNT($C10)=1,EOMONTH(L$8,0)-$C10,"N/D") -> -15 | M111: =IF(COUNT($C10)=1,EOMONTH(M$8,0)-$C10,"N/D") -> 13 | N111: =IF(COUNT($C10)=1,EOMONTH(N$8,0)-$C10,"N/D") -> 44 | O111: =IF(COUNT($C10)=1,EOMONTH(O$8,0)-$C10,"N/D") -> 74 | P111: =IF(COUNT($C10)=1,EOMONTH(P$8,0)-$C10,"N/D") -> 105 | Q111: =IF(COUNT($C10)=1,EOMONTH(Q$8,0)-$C10,"N/D") -> 135 | R111: =IF(COUNT($C10)=1,EOMONTH(R$8,0)-$C10,"N/D") -> 166 | S111: =IF(COUNT($C10)=1,EOMONTH(S$8,0)-$C10,"N/D") -> 197 | ... W111: =IF(COUNT($C10)=1,EOMONTH(W$8,0)-$C10,"N/D") -> 319
C112: =C11 -> 46461 | L112: =IF(COUNT($C11)=1,EOMONTH(L$8,0)-$C11,"N/D") -> -43 | M112: =IF(COUNT($C11)=1,EOMONTH(M$8,0)-$C11,"N/D") -> -15 | N112: =IF(COUNT($C11)=1,EOMONTH(N$8,0)-$C11,"N/D") -> 16 | O112: =IF(COUNT($C11)=1,EOMONTH(O$8,0)-$C11,"N/D") -> 46 | P112: =IF(COUNT($C11)=1,EOMONTH(P$8,0)-$C11,"N/D") -> 77 | Q112: =IF(COUNT($C11)=1,EOMONTH(Q$8,0)-$C11,"N/D") -> 107 | R112: =IF(COUNT($C11)=1,EOMONTH(R$8,0)-$C11,"N/D") -> 138 | S112: =IF(COUNT($C11)=1,EOMONTH(S$8,0)-$C11,"N/D") -> 169 | ... W112: =IF(COUNT($C11)=1,EOMONTH(W$8,0)-$C11,"N/D") -> 291
C113: =C12 -> 46492 | L113: =IF(COUNT($C12)=1,EOMONTH(L$8,0)-$C12,"N/D") -> -74 | M113: =IF(COUNT($C12)=1,EOMONTH(M$8,0)-$C12,"N/D") -> -46 | N113: =IF(COUNT($C12)=1,EOMONTH(N$8,0)-$C12,"N/D") -> -15 | O113: =IF(COUNT($C12)=1,EOMONTH(O$8,0)-$C12,"N/D") -> 15 | P113: =IF(COUNT($C12)=1,EOMONTH(P$8,0)-$C12,"N/D") -> 46 | Q113: =IF(COUNT($C12)=1,EOMONTH(Q$8,0)-$C12,"N/D") -> 76 | R113: =IF(COUNT($C12)=1,EOMONTH(R$8,0)-$C12,"N/D") -> 107 | S113: =IF(COUNT($C12)=1,EOMONTH(S$8,0)-$C12,"N/D") -> 138 | ... W113: =IF(COUNT($C12)=1,EOMONTH(W$8,0)-$C12,"N/D") -> 260
C114: =C13 -> 46522 | L114: =IF(COUNT($C13)=1,EOMONTH(L$8,0)-$C13,"N/D") -> -104 | M114: =IF(COUNT($C13)=1,EOMONTH(M$8,0)-$C13,"N/D") -> -76 | N114: =IF(COUNT($C13)=1,EOMONTH(N$8,0)-$C13,"N/D") -> -45 | O114: =IF(COUNT($C13)=1,EOMONTH(O$8,0)-$C13,"N/D") -> -15 | P114: =IF(COUNT($C13)=1,EOMONTH(P$8,0)-$C13,"N/D") -> 16 | Q114: =IF(COUNT($C13)=1,EOMONTH(Q$8,0)-$C13,"N/D") -> 46 | R114: =IF(COUNT($C13)=1,EOMONTH(R$8,0)-$C13,"N/D") -> 77 | S114: =IF(COUNT($C13)=1,EOMONTH(S$8,0)-$C13,"N/D") -> 108 | ... W114: =IF(COUNT($C13)=1,EOMONTH(W$8,0)-$C13,"N/D") -> 230
C115: =C14 -> 46553 | L115: =IF(COUNT($C14)=1,EOMONTH(L$8,0)-$C14,"N/D") -> -135 | M115: =IF(COUNT($C14)=1,EOMONTH(M$8,0)-$C14,"N/D") -> -107 | N115: =IF(COUNT($C14)=1,EOMONTH(N$8,0)-$C14,"N/D") -> -76 | O115: =IF(COUNT($C14)=1,EOMONTH(O$8,0)-$C14,"N/D") -> -46 | P115: =IF(COUNT($C14)=1,EOMONTH(P$8,0)-$C14,"N/D") -> -15 | Q115: =IF(COUNT($C14)=1,EOMONTH(Q$8,0)-$C14,"N/D") -> 15 | R115: =IF(COUNT($C14)=1,EOMONTH(R$8,0)-$C14,"N/D") -> 46 | S115: =IF(COUNT($C14)=1,EOMONTH(S$8,0)-$C14,"N/D") -> 77 | ... W115: =IF(COUNT($C14)=1,EOMONTH(W$8,0)-$C14,"N/D") -> 199
C116: =C15 -> 46583 | L116: =IF(COUNT($C15)=1,EOMONTH(L$8,0)-$C15,"N/D") -> -165 | M116: =IF(COUNT($C15)=1,EOMONTH(M$8,0)-$C15,"N/D") -> -137 | N116: =IF(COUNT($C15)=1,EOMONTH(N$8,0)-$C15,"N/D") -> -106 | O116: =IF(COUNT($C15)=1,EOMONTH(O$8,0)-$C15,"N/D") -> -76 | P116: =IF(COUNT($C15)=1,EOMONTH(P$8,0)-$C15,"N/D") -> -45 | Q116: =IF(COUNT($C15)=1,EOMONTH(Q$8,0)-$C15,"N/D") -> -15 | R116: =IF(COUNT($C15)=1,EOMONTH(R$8,0)-$C15,"N/D") -> 16 | S116: =IF(COUNT($C15)=1,EOMONTH(S$8,0)-$C15,"N/D") -> 47 | ... W116: =IF(COUNT($C15)=1,EOMONTH(W$8,0)-$C15,"N/D") -> 169
C117: =C16 -> 46614 | L117: =IF(COUNT($C16)=1,EOMONTH(L$8,0)-$C16,"N/D") -> -196 | M117: =IF(COUNT($C16)=1,EOMONTH(M$8,0)-$C16,"N/D") -> -168 | N117: =IF(COUNT($C16)=1,EOMONTH(N$8,0)-$C16,"N/D") -> -137 | O117: =IF(COUNT($C16)=1,EOMONTH(O$8,0)-$C16,"N/D") -> -107 | P117: =IF(COUNT($C16)=1,EOMONTH(P$8,0)-$C16,"N/D") -> -76 | Q117: =IF(COUNT($C16)=1,EOMONTH(Q$8,0)-$C16,"N/D") -> -46 | R117: =IF(COUNT($C16)=1,EOMONTH(R$8,0)-$C16,"N/D") -> -15 | S117: =IF(COUNT($C16)=1,EOMONTH(S$8,0)-$C16,"N/D") -> 16 | ... W117: =IF(COUNT($C16)=1,EOMONTH(W$8,0)-$C16,"N/D") -> 138
C118: =C17 -> 46645 | L118: =IF(COUNT($C17)=1,EOMONTH(L$8,0)-$C17,"N/D") -> -227 | M118: =IF(COUNT($C17)=1,EOMONTH(M$8,0)-$C17,"N/D") -> -199 | N118: =IF(COUNT($C17)=1,EOMONTH(N$8,0)-$C17,"N/D") -> -168 | O118: =IF(COUNT($C17)=1,EOMONTH(O$8,0)-$C17,"N/D") -> -138 | P118: =IF(COUNT($C17)=1,EOMONTH(P$8,0)-$C17,"N/D") -> -107 | Q118: =IF(COUNT($C17)=1,EOMONTH(Q$8,0)-$C17,"N/D") -> -77 | R118: =IF(COUNT($C17)=1,EOMONTH(R$8,0)-$C17,"N/D") -> -46 | S118: =IF(COUNT($C17)=1,EOMONTH(S$8,0)-$C17,"N/D") -> -15 | ... W118: =IF(COUNT($C17)=1,EOMONTH(W$8,0)-$C17,"N/D") -> 107
C119: =C18 -> 46675 | L119: =IF(COUNT($C18)=1,EOMONTH(L$8,0)-$C18,"N/D") -> -257 | M119: =IF(COUNT($C18)=1,EOMONTH(M$8,0)-$C18,"N/D") -> -229 | N119: =IF(COUNT($C18)=1,EOMONTH(N$8,0)-$C18,"N/D") -> -198 | O119: =IF(COUNT($C18)=1,EOMONTH(O$8,0)-$C18,"N/D") -> -168 | P119: =IF(COUNT($C18)=1,EOMONTH(P$8,0)-$C18,"N/D") -> -137 | Q119: =IF(COUNT($C18)=1,EOMONTH(Q$8,0)-$C18,"N/D") -> -107 | R119: =IF(COUNT($C18)=1,EOMONTH(R$8,0)-$C18,"N/D") -> -76 | S119: =IF(COUNT($C18)=1,EOMONTH(S$8,0)-$C18,"N/D") -> -45 | ... W119: =IF(COUNT($C18)=1,EOMONTH(W$8,0)-$C18,"N/D") -> 77
C120: =C19 -> 46706 | L120: =IF(COUNT($C19)=1,EOMONTH(L$8,0)-$C19,"N/D") -> -288 | M120: =IF(COUNT($C19)=1,EOMONTH(M$8,0)-$C19,"N/D") -> -260 | N120: =IF(COUNT($C19)=1,EOMONTH(N$8,0)-$C19,"N/D") -> -229 | O120: =IF(COUNT($C19)=1,EOMONTH(O$8,0)-$C19,"N/D") -> -199 | P120: =IF(COUNT($C19)=1,EOMONTH(P$8,0)-$C19,"N/D") -> -168 | Q120: =IF(COUNT($C19)=1,EOMONTH(Q$8,0)-$C19,"N/D") -> -138 | R120: =IF(COUNT($C19)=1,EOMONTH(R$8,0)-$C19,"N/D") -> -107 | S120: =IF(COUNT($C19)=1,EOMONTH(S$8,0)-$C19,"N/D") -> -76 | ... W120: =IF(COUNT($C19)=1,EOMONTH(W$8,0)-$C19,"N/D") -> 46
C121: =C20 -> 46736 | L121: =IF(COUNT($C20)=1,EOMONTH(L$8,0)-$C20,"N/D") -> -318 | M121: =IF(COUNT($C20)=1,EOMONTH(M$8,0)-$C20,"N/D") -> -290 | N121: =IF(COUNT($C20)=1,EOMONTH(N$8,0)-$C20,"N/D") -> -259 | O121: =IF(COUNT($C20)=1,EOMONTH(O$8,0)-$C20,"N/D") -> -229 | P121: =IF(COUNT($C20)=1,EOMONTH(P$8,0)-$C20,"N/D") -> -198 | Q121: =IF(COUNT($C20)=1,EOMONTH(Q$8,0)-$C20,"N/D") -> -168 | R121: =IF(COUNT($C20)=1,EOMONTH(R$8,0)-$C20,"N/D") -> -137 | S121: =IF(COUNT($C20)=1,EOMONTH(S$8,0)-$C20,"N/D") -> -106 | ... W121: =IF(COUNT($C20)=1,EOMONTH(W$8,0)-$C20,"N/D") -> 16
C127: Saldo relativo interpolado, por cohorte | L127: M 1 | M127: M 2 | N127: M 3 | O127: M 4 | P127: M 5 | Q127: M 6 | R127: M 7 | S127: M 8 | T127: M 9 | U127: M 10 | V127: M 11 | W127: M 12
C129: =C9 -> 46402 | L129: =IF(COUNT(L110,$G9:$K9)=6,IF(L110<0,0,IF(L110<30,1+($G9-1)*L110/30,IF(L110<60,$G9+($H9-$G9)*(L110-30)/30,IF(L110<90,$H9+($I9-$H9)*(L110-60)/30,IF(L110<180,$I9+($J9-$I9)*(L110-90)/90,IF(L110<=365,$J9+($K9-$J9)*(L110-180)/185,$K9)))))),"N/D") -> 0.97333333 | M129: =IF(COUNT(M110,$G9:$K9)=6,IF(M110<0,0,IF(M110<30,1+($G9-1)*M110/30,IF(M110<60,$G9+($H9-$G9)*(M110-30)/30,IF(M110<90,$H9+($I9-$H9)*(M110-60)/30,IF(M110<180,$I9+($J9-$I9)*(M110-90)/90,IF(M110<=365,$J9+($K9-$J9)*(M110-180)/185,$K9)))))),"N/D") -> 0.92666667 | N129: =IF(COUNT(N110,$G9:$K9)=6,IF(N110<0,0,IF(N110<30,1+($G9-1)*N110/30,IF(N110<60,$G9+($H9-$G9)*(N110-30)/30,IF(N110<90,$H9+($I9-$H9)*(N110-60)/30,IF(N110<180,$I9+($J9-$I9)*(N110-90)/90,IF(N110<=365,$J9+($K9-$J9)*(N110-180)/185,$K9)))))),"N/D") -> 0.875 | O129: =IF(COUNT(O110,$G9:$K9)=6,IF(O110<0,0,IF(O110<30,1+($G9-1)*O110/30,IF(O110<60,$G9+($H9-$G9)*(O110-30)/30,IF(O110<90,$H9+($I9-$H9)*(O110-60)/30,IF(O110<180,$I9+($J9-$I9)*(O110-90)/90,IF(O110<=365,$J9+($K9-$J9)*(O110-180)/185,$K9)))))),"N/D") -> 0.84166667 | P129: =IF(COUNT(P110,$G9:$K9)=6,IF(P110<0,0,IF(P110<30,1+($G9-1)*P110/30,IF(P110<60,$G9+($H9-$G9)*(P110-30)/30,IF(P110<90,$H9+($I9-$H9)*(P110-60)/30,IF(P110<180,$I9+($J9-$I9)*(P110-90)/90,IF(P110<=365,$J9+($K9-$J9)*(P110-180)/185,$K9)))))),"N/D") -> 0.82444444 | Q129: =IF(COUNT(Q110,$G9:$K9)=6,IF(Q110<0,0,IF(Q110<30,1+($G9-1)*Q110/30,IF(Q110<60,$G9+($H9-$G9)*(Q110-30)/30,IF(Q110<90,$H9+($I9-$H9)*(Q110-60)/30,IF(Q110<180,$I9+($J9-$I9)*(Q110-90)/90,IF(Q110<=365,$J9+($K9-$J9)*(Q110-180)/185,$K9)))))),"N/D") -> 0.80777778 | R129: =IF(COUNT(R110,$G9:$K9)=6,IF(R110<0,0,IF(R110<30,1+($G9-1)*R110/30,IF(R110<60,$G9+($H9-$G9)*(R110-30)/30,IF(R110<90,$H9+($I9-$H9)*(R110-60)/30,IF(R110<180,$I9+($J9-$I9)*(R110-90)/90,IF(R110<=365,$J9+($K9-$J9)*(R110-180)/185,$K9)))))),"N/D") -> 0.79540541 | S129: =IF(COUNT(S110,$G9:$K9)=6,IF(S110<0,0,IF(S110<30,1+($G9-1)*S110/30,IF(S110<60,$G9+($H9-$G9)*(S110-30)/30,IF(S110<90,$H9+($I9-$H9)*(S110-60)/30,IF(S110<180,$I9+($J9-$I9)*(S110-90)/90,IF(S110<=365,$J9+($K9-$J9)*(S110-180)/185,$K9)))))),"N/D") -> 0.78702703 | ... W129: =IF(COUNT(W110,$G9:$K9)=6,IF(W110<0,0,IF(W110<30,1+($G9-1)*W110/30,IF(W110<60,$G9+($H9-$G9)*(W110-30)/30,IF(W110<90,$H9+($I9-$H9)*(W110-60)/30,IF(W110<180,$I9+($J9-$I9)*(W110-90)/90,IF(W110<=365,$J9+($K9-$J9)*(W110-180)/185,$K9)))))),"N/D") -> 0.75405405
C130: =C10 -> 46433 | L130: =IF(COUNT(L111,$G10:$K10)=6,IF(L111<0,0,IF(L111<30,1+($G10-1)*L111/30,IF(L111<60,$G10+($H10-$G10)*(L111-30)/30,IF(L111<90,$H10+($I10-$H10)*(L111-60)/30,IF(L111<180,$I10+($J10-$I10)*(L111-90)/90,IF(L111<=365,$J10+($K10-$J10)*(L111-180)/185,$K10)))))),"N/D") -> 0 | M130: =IF(COUNT(M111,$G10:$K10)=6,IF(M111<0,0,IF(M111<30,1+($G10-1)*M111/30,IF(M111<60,$G10+($H10-$G10)*(M111-30)/30,IF(M111<90,$H10+($I10-$H10)*(M111-60)/30,IF(M111<180,$I10+($J10-$I10)*(M111-90)/90,IF(M111<=365,$J10+($K10-$J10)*(M111-180)/185,$K10)))))),"N/D") -> 0.97833333 | N130: =IF(COUNT(N111,$G10:$K10)=6,IF(N111<0,0,IF(N111<30,1+($G10-1)*N111/30,IF(N111<60,$G10+($H10-$G10)*(N111-30)/30,IF(N111<90,$H10+($I10-$H10)*(N111-60)/30,IF(N111<180,$I10+($J10-$I10)*(N111-90)/90,IF(N111<=365,$J10+($K10-$J10)*(N111-180)/185,$K10)))))),"N/D") -> 0.92666667 | O130: =IF(COUNT(O111,$G10:$K10)=6,IF(O111<0,0,IF(O111<30,1+($G10-1)*O111/30,IF(O111<60,$G10+($H10-$G10)*(O111-30)/30,IF(O111<90,$H10+($I10-$H10)*(O111-60)/30,IF(O111<180,$I10+($J10-$I10)*(O111-90)/90,IF(O111<=365,$J10+($K10-$J10)*(O111-180)/185,$K10)))))),"N/D") -> 0.87666667 | P130: =IF(COUNT(P111,$G10:$K10)=6,IF(P111<0,0,IF(P111<30,1+($G10-1)*P111/30,IF(P111<60,$G10+($H10-$G10)*(P111-30)/30,IF(P111<90,$H10+($I10-$H10)*(P111-60)/30,IF(P111<180,$I10+($J10-$I10)*(P111-90)/90,IF(P111<=365,$J10+($K10-$J10)*(P111-180)/185,$K10)))))),"N/D") -> 0.84166667 | Q130: =IF(COUNT(Q111,$G10:$K10)=6,IF(Q111<0,0,IF(Q111<30,1+($G10-1)*Q111/30,IF(Q111<60,$G10+($H10-$G10)*(Q111-30)/30,IF(Q111<90,$H10+($I10-$H10)*(Q111-60)/30,IF(Q111<180,$I10+($J10-$I10)*(Q111-90)/90,IF(Q111<=365,$J10+($K10-$J10)*(Q111-180)/185,$K10)))))),"N/D") -> 0.825 | R130: =IF(COUNT(R111,$G10:$K10)=6,IF(R111<0,0,IF(R111<30,1+($G10-1)*R111/30,IF(R111<60,$G10+($H10-$G10)*(R111-30)/30,IF(R111<90,$H10+($I10-$H10)*(R111-60)/30,IF(R111<180,$I10+($J10-$I10)*(R111-90)/90,IF(R111<=365,$J10+($K10-$J10)*(R111-180)/185,$K10)))))),"N/D") -> 0.80777778 | S130: =IF(COUNT(S111,$G10:$K10)=6,IF(S111<0,0,IF(S111<30,1+($G10-1)*S111/30,IF(S111<60,$G10+($H10-$G10)*(S111-30)/30,IF(S111<90,$H10+($I10-$H10)*(S111-60)/30,IF(S111<180,$I10+($J10-$I10)*(S111-90)/90,IF(S111<=365,$J10+($K10-$J10)*(S111-180)/185,$K10)))))),"N/D") -> 0.79540541 | ... W130: =IF(COUNT(W111,$G10:$K10)=6,IF(W111<0,0,IF(W111<30,1+($G10-1)*W111/30,IF(W111<60,$G10+($H10-$G10)*(W111-30)/30,IF(W111<90,$H10+($I10-$H10)*(W111-60)/30,IF(W111<180,$I10+($J10-$I10)*(W111-90)/90,IF(W111<=365,$J10+($K10-$J10)*(W111-180)/185,$K10)))))),"N/D") -> 0.76243243
C131: =C11 -> 46461 | L131: =IF(COUNT(L112,$G11:$K11)=6,IF(L112<0,0,IF(L112<30,1+($G11-1)*L112/30,IF(L112<60,$G11+($H11-$G11)*(L112-30)/30,IF(L112<90,$H11+($I11-$H11)*(L112-60)/30,IF(L112<180,$I11+($J11-$I11)*(L112-90)/90,IF(L112<=365,$J11+($K11-$J11)*(L112-180)/185,$K11)))))),"N/D") -> 0 | M131: =IF(COUNT(M112,$G11:$K11)=6,IF(M112<0,0,IF(M112<30,1+($G11-1)*M112/30,IF(M112<60,$G11+($H11-$G11)*(M112-30)/30,IF(M112<90,$H11+($I11-$H11)*(M112-60)/30,IF(M112<180,$I11+($J11-$I11)*(M112-90)/90,IF(M112<=365,$J11+($K11-$J11)*(M112-180)/185,$K11)))))),"N/D") -> 0 | N131: =IF(COUNT(N112,$G11:$K11)=6,IF(N112<0,0,IF(N112<30,1+($G11-1)*N112/30,IF(N112<60,$G11+($H11-$G11)*(N112-30)/30,IF(N112<90,$H11+($I11-$H11)*(N112-60)/30,IF(N112<180,$I11+($J11-$I11)*(N112-90)/90,IF(N112<=365,$J11+($K11-$J11)*(N112-180)/185,$K11)))))),"N/D") -> 0.97333333 | O131: =IF(COUNT(O112,$G11:$K11)=6,IF(O112<0,0,IF(O112<30,1+($G11-1)*O112/30,IF(O112<60,$G11+($H11-$G11)*(O112-30)/30,IF(O112<90,$H11+($I11-$H11)*(O112-60)/30,IF(O112<180,$I11+($J11-$I11)*(O112-90)/90,IF(O112<=365,$J11+($K11-$J11)*(O112-180)/185,$K11)))))),"N/D") -> 0.92333333 | P131: =IF(COUNT(P112,$G11:$K11)=6,IF(P112<0,0,IF(P112<30,1+($G11-1)*P112/30,IF(P112<60,$G11+($H11-$G11)*(P112-30)/30,IF(P112<90,$H11+($I11-$H11)*(P112-60)/30,IF(P112<180,$I11+($J11-$I11)*(P112-90)/90,IF(P112<=365,$J11+($K11-$J11)*(P112-180)/185,$K11)))))),"N/D") -> 0.87166667 | Q131: =IF(COUNT(Q112,$G11:$K11)=6,IF(Q112<0,0,IF(Q112<30,1+($G11-1)*Q112/30,IF(Q112<60,$G11+($H11-$G11)*(Q112-30)/30,IF(Q112<90,$H11+($I11-$H11)*(Q112-60)/30,IF(Q112<180,$I11+($J11-$I11)*(Q112-90)/90,IF(Q112<=365,$J11+($K11-$J11)*(Q112-180)/185,$K11)))))),"N/D") -> 0.84055556 | R131: =IF(COUNT(R112,$G11:$K11)=6,IF(R112<0,0,IF(R112<30,1+($G11-1)*R112/30,IF(R112<60,$G11+($H11-$G11)*(R112-30)/30,IF(R112<90,$H11+($I11-$H11)*(R112-60)/30,IF(R112<180,$I11+($J11-$I11)*(R112-90)/90,IF(R112<=365,$J11+($K11-$J11)*(R112-180)/185,$K11)))))),"N/D") -> 0.82333333 | S131: =IF(COUNT(S112,$G11:$K11)=6,IF(S112<0,0,IF(S112<30,1+($G11-1)*S112/30,IF(S112<60,$G11+($H11-$G11)*(S112-30)/30,IF(S112<90,$H11+($I11-$H11)*(S112-60)/30,IF(S112<180,$I11+($J11-$I11)*(S112-90)/90,IF(S112<=365,$J11+($K11-$J11)*(S112-180)/185,$K11)))))),"N/D") -> 0.80611111 | ... W131: =IF(COUNT(W112,$G11:$K11)=6,IF(W112<0,0,IF(W112<30,1+($G11-1)*W112/30,IF(W112<60,$G11+($H11-$G11)*(W112-30)/30,IF(W112<90,$H11+($I11-$H11)*(W112-60)/30,IF(W112<180,$I11+($J11-$I11)*(W112-90)/90,IF(W112<=365,$J11+($K11-$J11)*(W112-180)/185,$K11)))))),"N/D") -> 0.77
C132: =C12 -> 46492 | L132: =IF(COUNT(L113,$G12:$K12)=6,IF(L113<0,0,IF(L113<30,1+($G12-1)*L113/30,IF(L113<60,$G12+($H12-$G12)*(L113-30)/30,IF(L113<90,$H12+($I12-$H12)*(L113-60)/30,IF(L113<180,$I12+($J12-$I12)*(L113-90)/90,IF(L113<=365,$J12+($K12-$J12)*(L113-180)/185,$K12)))))),"N/D") -> 0 | M132: =IF(COUNT(M113,$G12:$K12)=6,IF(M113<0,0,IF(M113<30,1+($G12-1)*M113/30,IF(M113<60,$G12+($H12-$G12)*(M113-30)/30,IF(M113<90,$H12+($I12-$H12)*(M113-60)/30,IF(M113<180,$I12+($J12-$I12)*(M113-90)/90,IF(M113<=365,$J12+($K12-$J12)*(M113-180)/185,$K12)))))),"N/D") -> 0 | N132: =IF(COUNT(N113,$G12:$K12)=6,IF(N113<0,0,IF(N113<30,1+($G12-1)*N113/30,IF(N113<60,$G12+($H12-$G12)*(N113-30)/30,IF(N113<90,$H12+($I12-$H12)*(N113-60)/30,IF(N113<180,$I12+($J12-$I12)*(N113-90)/90,IF(N113<=365,$J12+($K12-$J12)*(N113-180)/185,$K12)))))),"N/D") -> 0 | O132: =IF(COUNT(O113,$G12:$K12)=6,IF(O113<0,0,IF(O113<30,1+($G12-1)*O113/30,IF(O113<60,$G12+($H12-$G12)*(O113-30)/30,IF(O113<90,$H12+($I12-$H12)*(O113-60)/30,IF(O113<180,$I12+($J12-$I12)*(O113-90)/90,IF(O113<=365,$J12+($K12-$J12)*(O113-180)/185,$K12)))))),"N/D") -> 0.975 | P132: =IF(COUNT(P113,$G12:$K12)=6,IF(P113<0,0,IF(P113<30,1+($G12-1)*P113/30,IF(P113<60,$G12+($H12-$G12)*(P113-30)/30,IF(P113<90,$H12+($I12-$H12)*(P113-60)/30,IF(P113<180,$I12+($J12-$I12)*(P113-90)/90,IF(P113<=365,$J12+($K12-$J12)*(P113-180)/185,$K12)))))),"N/D") -> 0.92333333 | Q132: =IF(COUNT(Q113,$G12:$K12)=6,IF(Q113<0,0,IF(Q113<30,1+($G12-1)*Q113/30,IF(Q113<60,$G12+($H12-$G12)*(Q113-30)/30,IF(Q113<90,$H12+($I12-$H12)*(Q113-60)/30,IF(Q113<180,$I12+($J12-$I12)*(Q113-90)/90,IF(Q113<=365,$J12+($K12-$J12)*(Q113-180)/185,$K12)))))),"N/D") -> 0.87333333 | R132: =IF(COUNT(R113,$G12:$K12)=6,IF(R113<0,0,IF(R113<30,1+($G12-1)*R113/30,IF(R113<60,$G12+($H12-$G12)*(R113-30)/30,IF(R113<90,$H12+($I12-$H12)*(R113-60)/30,IF(R113<180,$I12+($J12-$I12)*(R113-90)/90,IF(R113<=365,$J12+($K12-$J12)*(R113-180)/185,$K12)))))),"N/D") -> 0.84055556 | S132: =IF(COUNT(S113,$G12:$K12)=6,IF(S113<0,0,IF(S113<30,1+($G12-1)*S113/30,IF(S113<60,$G12+($H12-$G12)*(S113-30)/30,IF(S113<90,$H12+($I12-$H12)*(S113-60)/30,IF(S113<180,$I12+($J12-$I12)*(S113-90)/90,IF(S113<=365,$J12+($K12-$J12)*(S113-180)/185,$K12)))))),"N/D") -> 0.82333333 | ... W132: =IF(COUNT(W113,$G12:$K12)=6,IF(W113<0,0,IF(W113<30,1+($G12-1)*W113/30,IF(W113<60,$G12+($H12-$G12)*(W113-30)/30,IF(W113<90,$H12+($I12-$H12)*(W113-60)/30,IF(W113<180,$I12+($J12-$I12)*(W113-90)/90,IF(W113<=365,$J12+($K12-$J12)*(W113-180)/185,$K12)))))),"N/D") -> 0.77837838
C133: =C13 -> 46522 | L133: =IF(COUNT(L114,$G13:$K13)=6,IF(L114<0,0,IF(L114<30,1+($G13-1)*L114/30,IF(L114<60,$G13+($H13-$G13)*(L114-30)/30,IF(L114<90,$H13+($I13-$H13)*(L114-60)/30,IF(L114<180,$I13+($J13-$I13)*(L114-90)/90,IF(L114<=365,$J13+($K13-$J13)*(L114-180)/185,$K13)))))),"N/D") -> 0 | M133: =IF(COUNT(M114,$G13:$K13)=6,IF(M114<0,0,IF(M114<30,1+($G13-1)*M114/30,IF(M114<60,$G13+($H13-$G13)*(M114-30)/30,IF(M114<90,$H13+($I13-$H13)*(M114-60)/30,IF(M114<180,$I13+($J13-$I13)*(M114-90)/90,IF(M114<=365,$J13+($K13-$J13)*(M114-180)/185,$K13)))))),"N/D") -> 0 | N133: =IF(COUNT(N114,$G13:$K13)=6,IF(N114<0,0,IF(N114<30,1+($G13-1)*N114/30,IF(N114<60,$G13+($H13-$G13)*(N114-30)/30,IF(N114<90,$H13+($I13-$H13)*(N114-60)/30,IF(N114<180,$I13+($J13-$I13)*(N114-90)/90,IF(N114<=365,$J13+($K13-$J13)*(N114-180)/185,$K13)))))),"N/D") -> 0 | O133: =IF(COUNT(O114,$G13:$K13)=6,IF(O114<0,0,IF(O114<30,1+($G13-1)*O114/30,IF(O114<60,$G13+($H13-$G13)*(O114-30)/30,IF(O114<90,$H13+($I13-$H13)*(O114-60)/30,IF(O114<180,$I13+($J13-$I13)*(O114-90)/90,IF(O114<=365,$J13+($K13-$J13)*(O114-180)/185,$K13)))))),"N/D") -> 0 | P133: =IF(COUNT(P114,$G13:$K13)=6,IF(P114<0,0,IF(P114<30,1+($G13-1)*P114/30,IF(P114<60,$G13+($H13-$G13)*(P114-30)/30,IF(P114<90,$H13+($I13-$H13)*(P114-60)/30,IF(P114<180,$I13+($J13-$I13)*(P114-90)/90,IF(P114<=365,$J13+($K13-$J13)*(P114-180)/185,$K13)))))),"N/D") -> 0.97333333 | Q133: =IF(COUNT(Q114,$G13:$K13)=6,IF(Q114<0,0,IF(Q114<30,1+($G13-1)*Q114/30,IF(Q114<60,$G13+($H13-$G13)*(Q114-30)/30,IF(Q114<90,$H13+($I13-$H13)*(Q114-60)/30,IF(Q114<180,$I13+($J13-$I13)*(Q114-90)/90,IF(Q114<=365,$J13+($K13-$J13)*(Q114-180)/185,$K13)))))),"N/D") -> 0.92333333 | R133: =IF(COUNT(R114,$G13:$K13)=6,IF(R114<0,0,IF(R114<30,1+($G13-1)*R114/30,IF(R114<60,$G13+($H13-$G13)*(R114-30)/30,IF(R114<90,$H13+($I13-$H13)*(R114-60)/30,IF(R114<180,$I13+($J13-$I13)*(R114-90)/90,IF(R114<=365,$J13+($K13-$J13)*(R114-180)/185,$K13)))))),"N/D") -> 0.87166667 | S133: =IF(COUNT(S114,$G13:$K13)=6,IF(S114<0,0,IF(S114<30,1+($G13-1)*S114/30,IF(S114<60,$G13+($H13-$G13)*(S114-30)/30,IF(S114<90,$H13+($I13-$H13)*(S114-60)/30,IF(S114<180,$I13+($J13-$I13)*(S114-90)/90,IF(S114<=365,$J13+($K13-$J13)*(S114-180)/185,$K13)))))),"N/D") -> 0.84 | ... W133: =IF(COUNT(W114,$G13:$K13)=6,IF(W114<0,0,IF(W114<30,1+($G13-1)*W114/30,IF(W114<60,$G13+($H13-$G13)*(W114-30)/30,IF(W114<90,$H13+($I13-$H13)*(W114-60)/30,IF(W114<180,$I13+($J13-$I13)*(W114-90)/90,IF(W114<=365,$J13+($K13-$J13)*(W114-180)/185,$K13)))))),"N/D") -> 0.78648649
C134: =C14 -> 46553 | L134: =IF(COUNT(L115,$G14:$K14)=6,IF(L115<0,0,IF(L115<30,1+($G14-1)*L115/30,IF(L115<60,$G14+($H14-$G14)*(L115-30)/30,IF(L115<90,$H14+($I14-$H14)*(L115-60)/30,IF(L115<180,$I14+($J14-$I14)*(L115-90)/90,IF(L115<=365,$J14+($K14-$J14)*(L115-180)/185,$K14)))))),"N/D") -> 0 | M134: =IF(COUNT(M115,$G14:$K14)=6,IF(M115<0,0,IF(M115<30,1+($G14-1)*M115/30,IF(M115<60,$G14+($H14-$G14)*(M115-30)/30,IF(M115<90,$H14+($I14-$H14)*(M115-60)/30,IF(M115<180,$I14+($J14-$I14)*(M115-90)/90,IF(M115<=365,$J14+($K14-$J14)*(M115-180)/185,$K14)))))),"N/D") -> 0 | N134: =IF(COUNT(N115,$G14:$K14)=6,IF(N115<0,0,IF(N115<30,1+($G14-1)*N115/30,IF(N115<60,$G14+($H14-$G14)*(N115-30)/30,IF(N115<90,$H14+($I14-$H14)*(N115-60)/30,IF(N115<180,$I14+($J14-$I14)*(N115-90)/90,IF(N115<=365,$J14+($K14-$J14)*(N115-180)/185,$K14)))))),"N/D") -> 0 | O134: =IF(COUNT(O115,$G14:$K14)=6,IF(O115<0,0,IF(O115<30,1+($G14-1)*O115/30,IF(O115<60,$G14+($H14-$G14)*(O115-30)/30,IF(O115<90,$H14+($I14-$H14)*(O115-60)/30,IF(O115<180,$I14+($J14-$I14)*(O115-90)/90,IF(O115<=365,$J14+($K14-$J14)*(O115-180)/185,$K14)))))),"N/D") -> 0 | P134: =IF(COUNT(P115,$G14:$K14)=6,IF(P115<0,0,IF(P115<30,1+($G14-1)*P115/30,IF(P115<60,$G14+($H14-$G14)*(P115-30)/30,IF(P115<90,$H14+($I14-$H14)*(P115-60)/30,IF(P115<180,$I14+($J14-$I14)*(P115-90)/90,IF(P115<=365,$J14+($K14-$J14)*(P115-180)/185,$K14)))))),"N/D") -> 0 | Q134: =IF(COUNT(Q115,$G14:$K14)=6,IF(Q115<0,0,IF(Q115<30,1+($G14-1)*Q115/30,IF(Q115<60,$G14+($H14-$G14)*(Q115-30)/30,IF(Q115<90,$H14+($I14-$H14)*(Q115-60)/30,IF(Q115<180,$I14+($J14-$I14)*(Q115-90)/90,IF(Q115<=365,$J14+($K14-$J14)*(Q115-180)/185,$K14)))))),"N/D") -> 0.975 | R134: =IF(COUNT(R115,$G14:$K14)=6,IF(R115<0,0,IF(R115<30,1+($G14-1)*R115/30,IF(R115<60,$G14+($H14-$G14)*(R115-30)/30,IF(R115<90,$H14+($I14-$H14)*(R115-60)/30,IF(R115<180,$I14+($J14-$I14)*(R115-90)/90,IF(R115<=365,$J14+($K14-$J14)*(R115-180)/185,$K14)))))),"N/D") -> 0.92333333 | S134: =IF(COUNT(S115,$G14:$K14)=6,IF(S115<0,0,IF(S115<30,1+($G14-1)*S115/30,IF(S115<60,$G14+($H14-$G14)*(S115-30)/30,IF(S115<90,$H14+($I14-$H14)*(S115-60)/30,IF(S115<180,$I14+($J14-$I14)*(S115-90)/90,IF(S115<=365,$J14+($K14-$J14)*(S115-180)/185,$K14)))))),"N/D") -> 0.87166667 | ... W134: =IF(COUNT(W115,$G14:$K14)=6,IF(W115<0,0,IF(W115<30,1+($G14-1)*W115/30,IF(W115<60,$G14+($H14-$G14)*(W115-30)/30,IF(W115<90,$H14+($I14-$H14)*(W115-60)/30,IF(W115<180,$I14+($J14-$I14)*(W115-90)/90,IF(W115<=365,$J14+($K14-$J14)*(W115-180)/185,$K14)))))),"N/D") -> 0.79486486
C135: =C15 -> 46583 | L135: =IF(COUNT(L116,$G15:$K15)=6,IF(L116<0,0,IF(L116<30,1+($G15-1)*L116/30,IF(L116<60,$G15+($H15-$G15)*(L116-30)/30,IF(L116<90,$H15+($I15-$H15)*(L116-60)/30,IF(L116<180,$I15+($J15-$I15)*(L116-90)/90,IF(L116<=365,$J15+($K15-$J15)*(L116-180)/185,$K15)))))),"N/D") -> 0 | M135: =IF(COUNT(M116,$G15:$K15)=6,IF(M116<0,0,IF(M116<30,1+($G15-1)*M116/30,IF(M116<60,$G15+($H15-$G15)*(M116-30)/30,IF(M116<90,$H15+($I15-$H15)*(M116-60)/30,IF(M116<180,$I15+($J15-$I15)*(M116-90)/90,IF(M116<=365,$J15+($K15-$J15)*(M116-180)/185,$K15)))))),"N/D") -> 0 | N135: =IF(COUNT(N116,$G15:$K15)=6,IF(N116<0,0,IF(N116<30,1+($G15-1)*N116/30,IF(N116<60,$G15+($H15-$G15)*(N116-30)/30,IF(N116<90,$H15+($I15-$H15)*(N116-60)/30,IF(N116<180,$I15+($J15-$I15)*(N116-90)/90,IF(N116<=365,$J15+($K15-$J15)*(N116-180)/185,$K15)))))),"N/D") -> 0 | O135: =IF(COUNT(O116,$G15:$K15)=6,IF(O116<0,0,IF(O116<30,1+($G15-1)*O116/30,IF(O116<60,$G15+($H15-$G15)*(O116-30)/30,IF(O116<90,$H15+($I15-$H15)*(O116-60)/30,IF(O116<180,$I15+($J15-$I15)*(O116-90)/90,IF(O116<=365,$J15+($K15-$J15)*(O116-180)/185,$K15)))))),"N/D") -> 0 | P135: =IF(COUNT(P116,$G15:$K15)=6,IF(P116<0,0,IF(P116<30,1+($G15-1)*P116/30,IF(P116<60,$G15+($H15-$G15)*(P116-30)/30,IF(P116<90,$H15+($I15-$H15)*(P116-60)/30,IF(P116<180,$I15+($J15-$I15)*(P116-90)/90,IF(P116<=365,$J15+($K15-$J15)*(P116-180)/185,$K15)))))),"N/D") -> 0 | Q135: =IF(COUNT(Q116,$G15:$K15)=6,IF(Q116<0,0,IF(Q116<30,1+($G15-1)*Q116/30,IF(Q116<60,$G15+($H15-$G15)*(Q116-30)/30,IF(Q116<90,$H15+($I15-$H15)*(Q116-60)/30,IF(Q116<180,$I15+($J15-$I15)*(Q116-90)/90,IF(Q116<=365,$J15+($K15-$J15)*(Q116-180)/185,$K15)))))),"N/D") -> 0 | R135: =IF(COUNT(R116,$G15:$K15)=6,IF(R116<0,0,IF(R116<30,1+($G15-1)*R116/30,IF(R116<60,$G15+($H15-$G15)*(R116-30)/30,IF(R116<90,$H15+($I15-$H15)*(R116-60)/30,IF(R116<180,$I15+($J15-$I15)*(R116-90)/90,IF(R116<=365,$J15+($K15-$J15)*(R116-180)/185,$K15)))))),"N/D") -> 0.97333333 | S135: =IF(COUNT(S116,$G15:$K15)=6,IF(S116<0,0,IF(S116<30,1+($G15-1)*S116/30,IF(S116<60,$G15+($H15-$G15)*(S116-30)/30,IF(S116<90,$H15+($I15-$H15)*(S116-60)/30,IF(S116<180,$I15+($J15-$I15)*(S116-90)/90,IF(S116<=365,$J15+($K15-$J15)*(S116-180)/185,$K15)))))),"N/D") -> 0.92166667 | ... W135: =IF(COUNT(W116,$G15:$K15)=6,IF(W116<0,0,IF(W116<30,1+($G15-1)*W116/30,IF(W116<60,$G15+($H15-$G15)*(W116-30)/30,IF(W116<90,$H15+($I15-$H15)*(W116-60)/30,IF(W116<180,$I15+($J15-$I15)*(W116-90)/90,IF(W116<=365,$J15+($K15-$J15)*(W116-180)/185,$K15)))))),"N/D") -> 0.80611111
C136: =C16 -> 46614 | L136: =IF(COUNT(L117,$G16:$K16)=6,IF(L117<0,0,IF(L117<30,1+($G16-1)*L117/30,IF(L117<60,$G16+($H16-$G16)*(L117-30)/30,IF(L117<90,$H16+($I16-$H16)*(L117-60)/30,IF(L117<180,$I16+($J16-$I16)*(L117-90)/90,IF(L117<=365,$J16+($K16-$J16)*(L117-180)/185,$K16)))))),"N/D") -> 0 | M136: =IF(COUNT(M117,$G16:$K16)=6,IF(M117<0,0,IF(M117<30,1+($G16-1)*M117/30,IF(M117<60,$G16+($H16-$G16)*(M117-30)/30,IF(M117<90,$H16+($I16-$H16)*(M117-60)/30,IF(M117<180,$I16+($J16-$I16)*(M117-90)/90,IF(M117<=365,$J16+($K16-$J16)*(M117-180)/185,$K16)))))),"N/D") -> 0 | N136: =IF(COUNT(N117,$G16:$K16)=6,IF(N117<0,0,IF(N117<30,1+($G16-1)*N117/30,IF(N117<60,$G16+($H16-$G16)*(N117-30)/30,IF(N117<90,$H16+($I16-$H16)*(N117-60)/30,IF(N117<180,$I16+($J16-$I16)*(N117-90)/90,IF(N117<=365,$J16+($K16-$J16)*(N117-180)/185,$K16)))))),"N/D") -> 0 | O136: =IF(COUNT(O117,$G16:$K16)=6,IF(O117<0,0,IF(O117<30,1+($G16-1)*O117/30,IF(O117<60,$G16+($H16-$G16)*(O117-30)/30,IF(O117<90,$H16+($I16-$H16)*(O117-60)/30,IF(O117<180,$I16+($J16-$I16)*(O117-90)/90,IF(O117<=365,$J16+($K16-$J16)*(O117-180)/185,$K16)))))),"N/D") -> 0 | P136: =IF(COUNT(P117,$G16:$K16)=6,IF(P117<0,0,IF(P117<30,1+($G16-1)*P117/30,IF(P117<60,$G16+($H16-$G16)*(P117-30)/30,IF(P117<90,$H16+($I16-$H16)*(P117-60)/30,IF(P117<180,$I16+($J16-$I16)*(P117-90)/90,IF(P117<=365,$J16+($K16-$J16)*(P117-180)/185,$K16)))))),"N/D") -> 0 | Q136: =IF(COUNT(Q117,$G16:$K16)=6,IF(Q117<0,0,IF(Q117<30,1+($G16-1)*Q117/30,IF(Q117<60,$G16+($H16-$G16)*(Q117-30)/30,IF(Q117<90,$H16+($I16-$H16)*(Q117-60)/30,IF(Q117<180,$I16+($J16-$I16)*(Q117-90)/90,IF(Q117<=365,$J16+($K16-$J16)*(Q117-180)/185,$K16)))))),"N/D") -> 0 | R136: =IF(COUNT(R117,$G16:$K16)=6,IF(R117<0,0,IF(R117<30,1+($G16-1)*R117/30,IF(R117<60,$G16+($H16-$G16)*(R117-30)/30,IF(R117<90,$H16+($I16-$H16)*(R117-60)/30,IF(R117<180,$I16+($J16-$I16)*(R117-90)/90,IF(R117<=365,$J16+($K16-$J16)*(R117-180)/185,$K16)))))),"N/D") -> 0 | S136: =IF(COUNT(S117,$G16:$K16)=6,IF(S117<0,0,IF(S117<30,1+($G16-1)*S117/30,IF(S117<60,$G16+($H16-$G16)*(S117-30)/30,IF(S117<90,$H16+($I16-$H16)*(S117-60)/30,IF(S117<180,$I16+($J16-$I16)*(S117-90)/90,IF(S117<=365,$J16+($K16-$J16)*(S117-180)/185,$K16)))))),"N/D") -> 0.97333333 | ... W136: =IF(COUNT(W117,$G16:$K16)=6,IF(W117<0,0,IF(W117<30,1+($G16-1)*W117/30,IF(W117<60,$G16+($H16-$G16)*(W117-30)/30,IF(W117<90,$H16+($I16-$H16)*(W117-60)/30,IF(W117<180,$I16+($J16-$I16)*(W117-90)/90,IF(W117<=365,$J16+($K16-$J16)*(W117-180)/185,$K16)))))),"N/D") -> 0.82333333
C137: =C17 -> 46645 | L137: =IF(COUNT(L118,$G17:$K17)=6,IF(L118<0,0,IF(L118<30,1+($G17-1)*L118/30,IF(L118<60,$G17+($H17-$G17)*(L118-30)/30,IF(L118<90,$H17+($I17-$H17)*(L118-60)/30,IF(L118<180,$I17+($J17-$I17)*(L118-90)/90,IF(L118<=365,$J17+($K17-$J17)*(L118-180)/185,$K17)))))),"N/D") -> 0 | M137: =IF(COUNT(M118,$G17:$K17)=6,IF(M118<0,0,IF(M118<30,1+($G17-1)*M118/30,IF(M118<60,$G17+($H17-$G17)*(M118-30)/30,IF(M118<90,$H17+($I17-$H17)*(M118-60)/30,IF(M118<180,$I17+($J17-$I17)*(M118-90)/90,IF(M118<=365,$J17+($K17-$J17)*(M118-180)/185,$K17)))))),"N/D") -> 0 | N137: =IF(COUNT(N118,$G17:$K17)=6,IF(N118<0,0,IF(N118<30,1+($G17-1)*N118/30,IF(N118<60,$G17+($H17-$G17)*(N118-30)/30,IF(N118<90,$H17+($I17-$H17)*(N118-60)/30,IF(N118<180,$I17+($J17-$I17)*(N118-90)/90,IF(N118<=365,$J17+($K17-$J17)*(N118-180)/185,$K17)))))),"N/D") -> 0 | O137: =IF(COUNT(O118,$G17:$K17)=6,IF(O118<0,0,IF(O118<30,1+($G17-1)*O118/30,IF(O118<60,$G17+($H17-$G17)*(O118-30)/30,IF(O118<90,$H17+($I17-$H17)*(O118-60)/30,IF(O118<180,$I17+($J17-$I17)*(O118-90)/90,IF(O118<=365,$J17+($K17-$J17)*(O118-180)/185,$K17)))))),"N/D") -> 0 | P137: =IF(COUNT(P118,$G17:$K17)=6,IF(P118<0,0,IF(P118<30,1+($G17-1)*P118/30,IF(P118<60,$G17+($H17-$G17)*(P118-30)/30,IF(P118<90,$H17+($I17-$H17)*(P118-60)/30,IF(P118<180,$I17+($J17-$I17)*(P118-90)/90,IF(P118<=365,$J17+($K17-$J17)*(P118-180)/185,$K17)))))),"N/D") -> 0 | Q137: =IF(COUNT(Q118,$G17:$K17)=6,IF(Q118<0,0,IF(Q118<30,1+($G17-1)*Q118/30,IF(Q118<60,$G17+($H17-$G17)*(Q118-30)/30,IF(Q118<90,$H17+($I17-$H17)*(Q118-60)/30,IF(Q118<180,$I17+($J17-$I17)*(Q118-90)/90,IF(Q118<=365,$J17+($K17-$J17)*(Q118-180)/185,$K17)))))),"N/D") -> 0 | R137: =IF(COUNT(R118,$G17:$K17)=6,IF(R118<0,0,IF(R118<30,1+($G17-1)*R118/30,IF(R118<60,$G17+($H17-$G17)*(R118-30)/30,IF(R118<90,$H17+($I17-$H17)*(R118-60)/30,IF(R118<180,$I17+($J17-$I17)*(R118-90)/90,IF(R118<=365,$J17+($K17-$J17)*(R118-180)/185,$K17)))))),"N/D") -> 0 | S137: =IF(COUNT(S118,$G17:$K17)=6,IF(S118<0,0,IF(S118<30,1+($G17-1)*S118/30,IF(S118<60,$G17+($H17-$G17)*(S118-30)/30,IF(S118<90,$H17+($I17-$H17)*(S118-60)/30,IF(S118<180,$I17+($J17-$I17)*(S118-90)/90,IF(S118<=365,$J17+($K17-$J17)*(S118-180)/185,$K17)))))),"N/D") -> 0 | ... W137: =IF(COUNT(W118,$G17:$K17)=6,IF(W118<0,0,IF(W118<30,1+($G17-1)*W118/30,IF(W118<60,$G17+($H17-$G17)*(W118-30)/30,IF(W118<90,$H17+($I17-$H17)*(W118-60)/30,IF(W118<180,$I17+($J17-$I17)*(W118-90)/90,IF(W118<=365,$J17+($K17-$J17)*(W118-180)/185,$K17)))))),"N/D") -> 0.84055556
C138: =C18 -> 46675 | L138: =IF(COUNT(L119,$G18:$K18)=6,IF(L119<0,0,IF(L119<30,1+($G18-1)*L119/30,IF(L119<60,$G18+($H18-$G18)*(L119-30)/30,IF(L119<90,$H18+($I18-$H18)*(L119-60)/30,IF(L119<180,$I18+($J18-$I18)*(L119-90)/90,IF(L119<=365,$J18+($K18-$J18)*(L119-180)/185,$K18)))))),"N/D") -> 0 | M138: =IF(COUNT(M119,$G18:$K18)=6,IF(M119<0,0,IF(M119<30,1+($G18-1)*M119/30,IF(M119<60,$G18+($H18-$G18)*(M119-30)/30,IF(M119<90,$H18+($I18-$H18)*(M119-60)/30,IF(M119<180,$I18+($J18-$I18)*(M119-90)/90,IF(M119<=365,$J18+($K18-$J18)*(M119-180)/185,$K18)))))),"N/D") -> 0 | N138: =IF(COUNT(N119,$G18:$K18)=6,IF(N119<0,0,IF(N119<30,1+($G18-1)*N119/30,IF(N119<60,$G18+($H18-$G18)*(N119-30)/30,IF(N119<90,$H18+($I18-$H18)*(N119-60)/30,IF(N119<180,$I18+($J18-$I18)*(N119-90)/90,IF(N119<=365,$J18+($K18-$J18)*(N119-180)/185,$K18)))))),"N/D") -> 0 | O138: =IF(COUNT(O119,$G18:$K18)=6,IF(O119<0,0,IF(O119<30,1+($G18-1)*O119/30,IF(O119<60,$G18+($H18-$G18)*(O119-30)/30,IF(O119<90,$H18+($I18-$H18)*(O119-60)/30,IF(O119<180,$I18+($J18-$I18)*(O119-90)/90,IF(O119<=365,$J18+($K18-$J18)*(O119-180)/185,$K18)))))),"N/D") -> 0 | P138: =IF(COUNT(P119,$G18:$K18)=6,IF(P119<0,0,IF(P119<30,1+($G18-1)*P119/30,IF(P119<60,$G18+($H18-$G18)*(P119-30)/30,IF(P119<90,$H18+($I18-$H18)*(P119-60)/30,IF(P119<180,$I18+($J18-$I18)*(P119-90)/90,IF(P119<=365,$J18+($K18-$J18)*(P119-180)/185,$K18)))))),"N/D") -> 0 | Q138: =IF(COUNT(Q119,$G18:$K18)=6,IF(Q119<0,0,IF(Q119<30,1+($G18-1)*Q119/30,IF(Q119<60,$G18+($H18-$G18)*(Q119-30)/30,IF(Q119<90,$H18+($I18-$H18)*(Q119-60)/30,IF(Q119<180,$I18+($J18-$I18)*(Q119-90)/90,IF(Q119<=365,$J18+($K18-$J18)*(Q119-180)/185,$K18)))))),"N/D") -> 0 | R138: =IF(COUNT(R119,$G18:$K18)=6,IF(R119<0,0,IF(R119<30,1+($G18-1)*R119/30,IF(R119<60,$G18+($H18-$G18)*(R119-30)/30,IF(R119<90,$H18+($I18-$H18)*(R119-60)/30,IF(R119<180,$I18+($J18-$I18)*(R119-90)/90,IF(R119<=365,$J18+($K18-$J18)*(R119-180)/185,$K18)))))),"N/D") -> 0 | S138: =IF(COUNT(S119,$G18:$K18)=6,IF(S119<0,0,IF(S119<30,1+($G18-1)*S119/30,IF(S119<60,$G18+($H18-$G18)*(S119-30)/30,IF(S119<90,$H18+($I18-$H18)*(S119-60)/30,IF(S119<180,$I18+($J18-$I18)*(S119-90)/90,IF(S119<=365,$J18+($K18-$J18)*(S119-180)/185,$K18)))))),"N/D") -> 0 | ... W138: =IF(COUNT(W119,$G18:$K18)=6,IF(W119<0,0,IF(W119<30,1+($G18-1)*W119/30,IF(W119<60,$G18+($H18-$G18)*(W119-30)/30,IF(W119<90,$H18+($I18-$H18)*(W119-60)/30,IF(W119<180,$I18+($J18-$I18)*(W119-90)/90,IF(W119<=365,$J18+($K18-$J18)*(W119-180)/185,$K18)))))),"N/D") -> 0.87166667
C139: =C19 -> 46706 | L139: =IF(COUNT(L120,$G19:$K19)=6,IF(L120<0,0,IF(L120<30,1+($G19-1)*L120/30,IF(L120<60,$G19+($H19-$G19)*(L120-30)/30,IF(L120<90,$H19+($I19-$H19)*(L120-60)/30,IF(L120<180,$I19+($J19-$I19)*(L120-90)/90,IF(L120<=365,$J19+($K19-$J19)*(L120-180)/185,$K19)))))),"N/D") -> 0 | M139: =IF(COUNT(M120,$G19:$K19)=6,IF(M120<0,0,IF(M120<30,1+($G19-1)*M120/30,IF(M120<60,$G19+($H19-$G19)*(M120-30)/30,IF(M120<90,$H19+($I19-$H19)*(M120-60)/30,IF(M120<180,$I19+($J19-$I19)*(M120-90)/90,IF(M120<=365,$J19+($K19-$J19)*(M120-180)/185,$K19)))))),"N/D") -> 0 | N139: =IF(COUNT(N120,$G19:$K19)=6,IF(N120<0,0,IF(N120<30,1+($G19-1)*N120/30,IF(N120<60,$G19+($H19-$G19)*(N120-30)/30,IF(N120<90,$H19+($I19-$H19)*(N120-60)/30,IF(N120<180,$I19+($J19-$I19)*(N120-90)/90,IF(N120<=365,$J19+($K19-$J19)*(N120-180)/185,$K19)))))),"N/D") -> 0 | O139: =IF(COUNT(O120,$G19:$K19)=6,IF(O120<0,0,IF(O120<30,1+($G19-1)*O120/30,IF(O120<60,$G19+($H19-$G19)*(O120-30)/30,IF(O120<90,$H19+($I19-$H19)*(O120-60)/30,IF(O120<180,$I19+($J19-$I19)*(O120-90)/90,IF(O120<=365,$J19+($K19-$J19)*(O120-180)/185,$K19)))))),"N/D") -> 0 | P139: =IF(COUNT(P120,$G19:$K19)=6,IF(P120<0,0,IF(P120<30,1+($G19-1)*P120/30,IF(P120<60,$G19+($H19-$G19)*(P120-30)/30,IF(P120<90,$H19+($I19-$H19)*(P120-60)/30,IF(P120<180,$I19+($J19-$I19)*(P120-90)/90,IF(P120<=365,$J19+($K19-$J19)*(P120-180)/185,$K19)))))),"N/D") -> 0 | Q139: =IF(COUNT(Q120,$G19:$K19)=6,IF(Q120<0,0,IF(Q120<30,1+($G19-1)*Q120/30,IF(Q120<60,$G19+($H19-$G19)*(Q120-30)/30,IF(Q120<90,$H19+($I19-$H19)*(Q120-60)/30,IF(Q120<180,$I19+($J19-$I19)*(Q120-90)/90,IF(Q120<=365,$J19+($K19-$J19)*(Q120-180)/185,$K19)))))),"N/D") -> 0 | R139: =IF(COUNT(R120,$G19:$K19)=6,IF(R120<0,0,IF(R120<30,1+($G19-1)*R120/30,IF(R120<60,$G19+($H19-$G19)*(R120-30)/30,IF(R120<90,$H19+($I19-$H19)*(R120-60)/30,IF(R120<180,$I19+($J19-$I19)*(R120-90)/90,IF(R120<=365,$J19+($K19-$J19)*(R120-180)/185,$K19)))))),"N/D") -> 0 | S139: =IF(COUNT(S120,$G19:$K19)=6,IF(S120<0,0,IF(S120<30,1+($G19-1)*S120/30,IF(S120<60,$G19+($H19-$G19)*(S120-30)/30,IF(S120<90,$H19+($I19-$H19)*(S120-60)/30,IF(S120<180,$I19+($J19-$I19)*(S120-90)/90,IF(S120<=365,$J19+($K19-$J19)*(S120-180)/185,$K19)))))),"N/D") -> 0 | ... W139: =IF(COUNT(W120,$G19:$K19)=6,IF(W120<0,0,IF(W120<30,1+($G19-1)*W120/30,IF(W120<60,$G19+($H19-$G19)*(W120-30)/30,IF(W120<90,$H19+($I19-$H19)*(W120-60)/30,IF(W120<180,$I19+($J19-$I19)*(W120-90)/90,IF(W120<=365,$J19+($K19-$J19)*(W120-180)/185,$K19)))))),"N/D") -> 0.92333333
...

Sheet Sensibilidad
C2: Escala y sensibilidad anual
C4: Escenario seleccionado | D4: =Supuestos!D5 -> Base
C7: Banda meta provisional | D7: Cuentas requeridas | E7: Visitas requeridas | F7: Depósito inicial USD eq.
C8: 0.01 | D8: =C8*Supuestos!D8 -> 152 | E8: =IF(COUNT(Supuestos!F40,Supuestos!F45)=2,IF(Supuestos!F40*Supuestos!F45>0,D8/(Supuestos!F40*Supuestos!F45),"N/D"),"N/D") -> 11692.308 | F8: =D8*Supuestos!D10 -> 380000
C9: 0.05 | D9: =C9*Supuestos!D8 -> 760 | E9: =IF(COUNT(Supuestos!F40,Supuestos!F45)=2,IF(Supuestos!F40*Supuestos!F45>0,D9/(Supuestos!F40*Supuestos!F45),"N/D"),"N/D") -> 58461.538 | F9: =D9*Supuestos!D10 -> 1900000
C10: 0.1 | D10: =C10*Supuestos!D8 -> 1520 | E10: =IF(COUNT(Supuestos!F40,Supuestos!F45)=2,IF(Supuestos!F40*Supuestos!F45>0,D10/(Supuestos!F40*Supuestos!F45),"N/D"),"N/D") -> 116923.08 | F10: =D10*Supuestos!D10 -> 3800000
C12: Bandas son escala aritmética, no compromiso. Usa tasasM 1 constantes; lag y variaciones posteriores se revisan en build anual.
C15: Apertura / Fondeo | F15: 0.4 | G15: 0.5 | H15: 0.65 | I15: 0.75 | J15: 0.85
C16: 0.01 | F16: =IF(COUNT(Mensual!$F$16:$Q$16)=12,SUM(Mensual!$F$16:$Q$16)*$C16*F$15,"N/D") -> 15.498 | G16: =IF(COUNT(Mensual!$F$16:$Q$16)=12,SUM(Mensual!$F$16:$Q$16)*$C16*G$15,"N/D") -> 19.3725 | H16: =IF(COUNT(Mensual!$F$16:$Q$16)=12,SUM(Mensual!$F$16:$Q$16)*$C16*H$15,"N/D") -> 25.18425 | I16: =IF(COUNT(Mensual!$F$16:$Q$16)=12,SUM(Mensual!$F$16:$Q$16)*$C16*I$15,"N/D") -> 29.05875 | J16: =IF(COUNT(Mensual!$F$16:$Q$16)=12,SUM(Mensual!$F$16:$Q$16)*$C16*J$15,"N/D") -> 32.93325
C17: 0.015 | F17: =IF(COUNT(Mensual!$F$16:$Q$16)=12,SUM(Mensual!$F$16:$Q$16)*$C17*F$15,"N/D") -> 23.247 | G17: =IF(COUNT(Mensual!$F$16:$Q$16)=12,SUM(Mensual!$F$16:$Q$16)*$C17*G$15,"N/D") -> 29.05875 | H17: =IF(COUNT(Mensual!$F$16:$Q$16)=12,SUM(Mensual!$F$16:$Q$16)*$C17*H$15,"N/D") -> 37.776375 | I17: =IF(COUNT(Mensual!$F$16:$Q$16)=12,SUM(Mensual!$F$16:$Q$16)*$C17*I$15,"N/D") -> 43.588125 | J17: =IF(COUNT(Mensual!$F$16:$Q$16)=12,SUM(Mensual!$F$16:$Q$16)*$C17*J$15,"N/D") -> 49.399875
C18: 0.02 | F18: =IF(COUNT(Mensual!$F$16:$Q$16)=12,SUM(Mensual!$F$16:$Q$16)*$C18*F$15,"N/D") -> 30.996 | G18: =IF(COUNT(Mensual!$F$16:$Q$16)=12,SUM(Mensual!$F$16:$Q$16)*$C18*G$15,"N/D") -> 38.745 | H18: =IF(COUNT(Mensual!$F$16:$Q$16)=12,SUM(Mensual!$F$16:$Q$16)*$C18*H$15,"N/D") -> 50.3685 | I18: =IF(COUNT(Mensual!$F$16:$Q$16)=12,SUM(Mensual!$F$16:$Q$16)*$C18*I$15,"N/D") -> 58.1175 | J18: =IF(COUNT(Mensual!$F$16:$Q$16)=12,SUM(Mensual!$F$16:$Q$16)*$C18*J$15,"N/D") -> 65.8665
C19: 0.025 | F19: =IF(COUNT(Mensual!$F$16:$Q$16)=12,SUM(Mensual!$F$16:$Q$16)*$C19*F$15,"N/D") -> 38.745 | G19: =IF(COUNT(Mensual!$F$16:$Q$16)=12,SUM(Mensual!$F$16:$Q$16)*$C19*G$15,"N/D") -> 48.43125 | H19: =IF(COUNT(Mensual!$F$16:$Q$16)=12,SUM(Mensual!$F$16:$Q$16)*$C19*H$15,"N/D") -> 62.960625 | I19: =IF(COUNT(Mensual!$F$16:$Q$16)=12,SUM(Mensual!$F$16:$Q$16)*$C19*I$15,"N/D") -> 72.646875 | J19: =IF(COUNT(Mensual!$F$16:$Q$16)=12,SUM(Mensual!$F$16:$Q$16)*$C19*J$15,"N/D") -> 82.333125
C20: 0.03 | F20: =IF(COUNT(Mensual!$F$16:$Q$16)=12,SUM(Mensual!$F$16:$Q$16)*$C20*F$15,"N/D") -> 46.494 | G20: =IF(COUNT(Mensual!$F$16:$Q$16)=12,SUM(Mensual!$F$16:$Q$16)*$C20*G$15,"N/D") -> 58.1175 | H20: =IF(COUNT(Mensual!$F$16:$Q$16)=12,SUM(Mensual!$F$16:$Q$16)*$C20*H$15,"N/D") -> 75.55275 | I20: =IF(COUNT(Mensual!$F$16:$Q$16)=12,SUM(Mensual!$F$16:$Q$16)*$C20*I$15,"N/D") -> 87.17625 | J20: =IF(COUNT(Mensual!$F$16:$Q$16)=12,SUM(Mensual!$F$16:$Q$16)*$C20*J$15,"N/D") -> 98.79975
C23: Lag a primer fondeo (meses) | D23: Fondeadas dentro de 2027 | E23: Fondeadas después de 2027
C24: 0 | D24: =IF(AND(COUNT(Mensual!$F$25:$Q$25)=12,C24>=0,C24<12),SUM(Mensual!$F$25:INDEX(Mensual!$F$25:$Q$25,1,12-C24)),"N/D") -> 50.3685 | E24: =IF(COUNT(D24)=1,SUM(Mensual!$F$25:$Q$25)-D24,"N/D") -> 0
C25: 1 | D25: =IF(AND(COUNT(Mensual!$F$25:$Q$25)=12,C25>=0,C25<12),SUM(Mensual!$F$25:INDEX(Mensual!$F$25:$Q$25,1,12-C25)),"N/D") -> 41.374125 | E25: =IF(COUNT(D25)=1,SUM(Mensual!$F$25:$Q$25)-D25,"N/D") -> 8.994375
C26: 2 | D26: =IF(AND(COUNT(Mensual!$F$25:$Q$25)=12,C26>=0,C26<12),SUM(Mensual!$F$25:INDEX(Mensual!$F$25:$Q$25,1,12-C26)),"N/D") -> 33.279187 | E26: =IF(COUNT(D26)=1,SUM(Mensual!$F$25:$Q$25)-D26,"N/D") -> 17.089312
C29: Inversión hipotética anual USD | D29: Valor/cuenta mínimo para equilibrio | E29: Naturaleza
C30: 10000 | D30: =IF(AND(COUNT(Resumen!$D$10)=1,Resumen!$D$10>0),C30/Resumen!$D$10,"N/D") -> 198.53678 | E30: Sensibilidad; no fee
C31: 25000 | D31: =IF(AND(COUNT(Resumen!$D$10)=1,Resumen!$D$10>0),C31/Resumen!$D$10,"N/D") -> 496.34196 | E31: Sensibilidad; no fee
C32: 50000 | D32: =IF(AND(COUNT(Resumen!$D$10)=1,Resumen!$D$10>0),C32/Resumen!$D$10,"N/D") -> 992.68392 | E32: Sensibilidad; no fee
C34: Inversión 10 k/25 k/50 k es sensibilidad hipotética. No es oferta ni costo Efeonce. ROI sigue N/D hasta inversión y Finance validados.
C37: Todas cohortes con origen externo | D37: Saldo externo cierre hipotético
C38: 0.4 | D38: =IF(COUNT(Mensual!$Q$35)=1,Mensual!$Q$35*C38,"N/D") -> 43621.871
C39: 0.7 | D39: =IF(COUNT(Mensual!$Q$35)=1,Mensual!$Q$35*C39,"N/D") -> 76338.274
C40: 1 | D40: =IF(COUNT(Mensual!$Q$35)=1,Mensual!$Q$35*C40,"N/D") -> 109054.68
C43: Sensibilidad uniforme externa es prueba aparte. El build real conserva proporción de origen de cada cohorte.
C44: Retención y ticket se editan en Supuestos y recalculan todos los cierres/valores. Datos ausentes se propaganN/D.

Sheet Demanda
C2: Demanda de mercado: fuente y cobertura
C4: Escenario seleccionado | D4: =Supuestos!D5 -> Base
I5: Proxy directo | J5: =G21 -> 3690
C7: Grupo | D7: Consulta / territorio | E7: Proxy por mes | F7: Carril | G7: Incluido directo
C8: D 01 | D8: cuenta de ahorros | E8: 2900 | F8: Directa | G8: 2900
C9: D 02 | D9: mejores cuentas de ahorro peru | E9: 320 | F9: Directa | G9: 320
C10: D 03 | D10: abrir cuenta de ahorros | E10: 210 | F10: Directa | G10: 210
C11: D 04 | D11: interés de cuenta de ahorro | E11: 210 | F11: Directa | G11: 210
C12: D 05 | D12: cuenta de ahorros sin mantenimiento | E12: 50 | F12: Directa | G12: 50
C13: C 01 | D13: cuenta digital | E13: 1300 | F13: Condicional | G13: 0
C14: C 02 | D14: cuentas de alto rendimiento peru | E14: 390 | F14: Condicional | G14: 0
C15: E 01 | D15: fondo de seguro de depositos | E15: 1600 | F15: Educación asistida | G15: 0
C16: E 02 | D16: que es trea | E16: 880 | F16: Educación asistida | G16: 0
C17: E 03 | D17: transferencia bancaria | E17: 1000 | F17: Educación asistida | G17: 0
C18: E 04 | D18: como ahorrar dinero | E18: 590 | F18: Educación asistida | G18: 0
C19: F 01 | D19: cuenta en dolares | E19: 480 | F19: USD futuro | G19: 0
C21: Proxy adquisición directa mensual | G21: =SUM(G8:G19) -> 3690
C24: Market estimates historical; no GSC. Model panel chosen for intent and product fit, not maximal volume; additional clusters remain research backlog.
C25: Exact-query dedup plus provider core families and manual model representatives. Panel subtotal is a working proxy with residual cross-intent overlap; not unique people, total market or actual traffic. No blanket MAX universe.
C26: Historical last 12 months per row; mapping shape to 2027 is illustrative, no trend/growth projection. Prefer flat sensitivity plus observed historical shape, not automatic repeated-growth curve.
C27: Panel directo 3690/mes; media histórica 4015. Condicional 1690 y educación 4070 separados; no sumados a adquisición.
C28: No demanda total, personas únicas ni forecast 2027. Baseline marca actual, conversiones y AEO: ausentes.
C39: M 1 son controles de acceso/medición/delivery. El servicio propuesto dura todo 2027; no es piloto de 3/6 meses.

Sheet Historia
C2: Serie histórica separada de hipótesis 2027
C4: Escenario seleccionado | D4: =Supuestos!D5 -> Base
C7: Observación histórica | D7: Unidad | F7: Jan | G7: Feb | H7: Mar | I7: Apr | J7: May | K7: Jun | L7: Jul | M7: Aug | N7: Sep | O7: Oct | P7: Nov | Q7: Dec
C9: Demanda observada por mes calendario | D9: búsquedas | F9: 4370 | G9: 3690 | H9: 4860 | I9: 4440 | J9: 3710 | K9: 2960 | L9: 3530 | M9: 3490 | N9: 4630 | O9: 4550 | P9: 4330 | Q9: 3620
C10: Periodo representativo de la muestra | D10: sep 2025–ago 2026
C11: Factor / media histórica disponible | D11: factor | F11: =IF(COUNT(F9:Q9)=12,IF(AVERAGE(F9:Q9)>0,F9/AVERAGE(F9:Q9),"N/D"),"N/D") -> 1.0884184 | G11: =IF(COUNT(F9:Q9)=12,IF(AVERAGE(F9:Q9)>0,G9/AVERAGE(F9:Q9),"N/D"),"N/D") -> 0.91905355 | H11: =IF(COUNT(F9:Q9)=12,IF(AVERAGE(F9:Q9)>0,H9/AVERAGE(F9:Q9),"N/D"),"N/D") -> 1.2104608 | I11: =IF(COUNT(F9:Q9)=12,IF(AVERAGE(F9:Q9)>0,I9/AVERAGE(F9:Q9),"N/D"),"N/D") -> 1.1058531 | J11: =IF(COUNT(F9:Q9)=12,IF(AVERAGE(F9:Q9)>0,J9/AVERAGE(F9:Q9),"N/D"),"N/D") -> 0.92403487 | K11: =IF(COUNT(F9:Q9)=12,IF(AVERAGE(F9:Q9)>0,K9/AVERAGE(F9:Q9),"N/D"),"N/D") -> 0.73723537 | L11: =IF(COUNT(F9:Q9)=12,IF(AVERAGE(F9:Q9)>0,L9/AVERAGE(F9:Q9),"N/D"),"N/D") -> 0.87920299 | M11: =IF(COUNT(F9:Q9)=12,IF(AVERAGE(F9:Q9)>0,M9/AVERAGE(F9:Q9),"N/D"),"N/D") -> 0.86924035 | N11: =IF(COUNT(F9:Q9)=12,IF(AVERAGE(F9:Q9)>0,N9/AVERAGE(F9:Q9),"N/D"),"N/D") -> 1.1531756 | O11: =IF(COUNT(F9:Q9)=12,IF(AVERAGE(F9:Q9)>0,O9/AVERAGE(F9:Q9),"N/D"),"N/D") -> 1.1332503 | P11: =IF(COUNT(F9:Q9)=12,IF(AVERAGE(F9:Q9)>0,P9/AVERAGE(F9:Q9),"N/D"),"N/D") -> 1.0784558 | Q11: =IF(COUNT(F9:Q9)=12,IF(AVERAGE(F9:Q9)>0,Q9/AVERAGE(F9:Q9),"N/D"),"N/D") -> 0.90161893
C14: Historia conserva serie de mercado; no es demanda Pibank post-lanzamiento ni forecast 2027. Plano=1 es hipótesis neutral.
C15: Sólo se habilita Historia cuando los 12 meses de la misma canasta tienen evidencia. No rellenar meses ausentes con cero.
C16: La selección de representantes manuales, variantes y cobertura están en source-demand.json. Queda solapamiento entre grupos.

Sheet Fuentes
C2: Ledger de evidencia y supuestos
C4: Escenario seleccionado | D4: =Supuestos!D5 -> Base
C7: ID | D7: Naturaleza | E7: Fuente | F7: Alcance / condición | G7: Estado
C8: META | D8: Inferencia provisional | E8: Reunión 06/10 + operador | F8: 15200×2500=US 38 m. Año exacto/meta cuenta fondeada no confirmados | G8: Provisional
C9: DEMANDA | D9: Estimación de mercado | E9: source-demand.json; DataForSEO | F9: País/idioma, cobertura y periodo en metadata. NoTAM ni usuarios únicos | G9: Observado con límites
C10: HISTORIA | D10: Serie histórica de mercado | E10: source-demand.json | F10: No 2027 ni Pibank analytics. No crecimiento 2 x automático | G10: Historia separada
C11: SIM | D11: Hipótesis aritméticas | E11: inputs.json | F11: Captura, referencia, apertura, fondeo, relevancia y retención no medidos | G11: Ilustrativo
C12: CALENDARIO | D12: Hipótesis de ejecución | E12: inputs.json | F12: Enero 2027,12 meses,día 15+lag. Inicio y fondeo se validan al implementar | G12: Ilustrativo
C13: ORIGEN | D13: Hipótesis por cohorte | E13: Supuestos filas 80-83 | F13: Dinero externo se fija por cohorte; traslado interno no fondeo nuevo grupo | G13: Pendiente banco
C14: FINANCE | D14: Autoridad banco | E14: Método neto por definir | F14: Tasa anual neta por USD de saldo medio externo. Un único método, sin dobleFTP | G14: N/D
C15: INVERSIÓN | D15: Propuesta no aprobada | E15: Supuestos filas 22-24 | F15: Inversión cliente vacía. CosteEfeonce vacío. Matriz inversión separada | G15: N/D
C16: CAPACIDAD | D16: Estimación planificación | E16: ../propuesta-anual/CAPACIDAD-Y-COSTEO-INTERNO.md | F16: 2560 h+336 hreserva=2896 h. No fee, roster ni capacidad comprometida | G16: Operations/Finance pendiente
C17: GOOGLE | D17: Fuente técnica primaria | E17: https://developers.google.com/search/docs/appearance/ai-features | F17: FundamentosSEO, sin requisitos extra ni garantía; sóloGoogle | G17: Consultada 06/10
C18: PIBANK | D18: Fuente producto primaria | E18: https://pibank.pe/cuenta-soles-pibank/ | F18: CuentaSoles pública. USD eq.modelado no confirma cuentaUSD | G18: Consultada 06/10
C22: M 1 revisa accesos/datos/delivery; no valida fracaso o éxitoSEO. Programa 2027 anual con optimización trimestral.
C23: El contrafactual no demuestra pérdidas históricas. CitasIA no se multiplican para fabricar conversiones.
