Workbook
Name TipoCambio: 'Tipos de Cambio'!$C$1

Sheet Datos
A1: Categoría | B1: Tipo | C1: Tier | E1: Área de Servicio | F1: Frecuencia | G1: Tipo Herramienta | H1: Unidad Prorrateo | I1: Facturación | J1: Activo | K1: Tipo de Ítem | L1: Tipo de Servicio
A2: Creativo | B2: Staff | C2: Tier 1: Commoditizado | E2: Creatividad | F2: Mes | G2: SaaS / Licencia | H2: Proyectos/mes | I2: Mensual | J2: ✅ | K2: Rol | L2: Proyecto / Implementación | N2: Parámetro | O2: Valor
A3: Consultoria | B3: Servicio | C3: Tier 2: Especializado | E3: Social / Medios | F3: Año | G3: Recurso / Banco | H3: Proyectos | I3: Anual | J3: ❌ | K3: Herramienta | L3: Retainer | N3: Horas/mes | O3: 180
A4: Performance | C4: Tier 3: Estratégico | E4: Analítica / Performance | F4: Mes | G4: SaaS | H4: Meses | I4: Créditos | L4: Consultoría Estratégica
A5: Tech | C5: Tier 4: IP Propietaria | E5: MarTech / HubSpot | F5: Usuario | G5: Plataforma | H5: Usuarios/mes | I5: Bolsa | L5: Proyecto / Servicio Técnico
A6: PR | E6: Automatización / Integraciones | F6: Bolsa | G6: Plugin | H6: Clientes activos | L6: Retainer
E7: IA / Contenido | F7: Créditos | G7: Infraestructura | H7: Automatizaciones
E8: Hosting
E9: Plugins / CMS
E10: Infraestructura / Data
E11: Gestión Interna
E12: Gestión Financiera

Sheet Tier Datos
A1: Tier | B1: Margen (%)
A2: Tier 1: Commoditizado | B2: 0.25
A3: Tier 2: Especializado | B3: 0.3
A4: Tier 3: Estratégico | B4: 0.5
A5: Tier 4: Ip Propietaria | B5: 0.6

Sheet Tiers
A1: Rol | B1: Tier | C1: Margen MIN | D1: Margen OPT | E1: Margen MAX
A2: TIER 1: COMMODITIZADO
A3: Community Manager | B3: 1 | C3: 0.2 | D3: 0.3 | E3: 0.35
A4: Social Media Manager | B4: 1 | C4: 0.2 | D4: 0.3 | E4: 0.35
A5: Content Creator | B5: 1 | C5: 0.2 | D5: 0.3 | E5: 0.35
A6: UGC Creator | B6: 1 | C6: 0.2 | D6: 0.3 | E6: 0.35
A7: Creative Designer (Jr/Mid) | B7: 1 | C7: 0.2 | D7: 0.3 | E7: 0.35
A8: TIER 2: ESPECIALIZADO
A9: Copywriter | B9: 2 | C9: 0.3 | D9: 0.4 | E9: 0.45
A10: Senior Visual Designer | B10: 2 | C10: 0.3 | D10: 0.4 | E10: 0.45
A11: Video Editor/Motion Graphics | B11: 2 | C11: 0.3 | D11: 0.4 | E11: 0.45
A12: UX/UI Designer | B12: 2 | C12: 0.3 | D12: 0.4 | E12: 0.45
A13: Desarrollador WordPress | B13: 2 | C13: 0.3 | D13: 0.4 | E13: 0.45
A14: Desarrollador Full Stack Jr/Mid | B14: 2 | C14: 0.3 | D14: 0.4 | E14: 0.45
A15: Paid Media Specialist | B15: 2 | C15: 0.3 | D15: 0.4 | E15: 0.45
A16: Media Buyer | B16: 2 | C16: 0.3 | D16: 0.4 | E16: 0.45
A17: SEO Specialist | B17: 2 | C17: 0.3 | D17: 0.4 | E17: 0.45
A18: Influencer Manager | B18: 2 | C18: 0.3 | D18: 0.4 | E18: 0.45
A19: PR Analyst | B19: 2 | C19: 0.3 | D19: 0.4 | E19: 0.45
A20: Content Manager | B20: 2 | C20: 0.3 | D20: 0.4 | E20: 0.45
A21: TIER 3: ESTRATÉGICO
A22: Creative Operations Lead | B22: 3 | C22: 0.4 | D22: 0.5 | E22: 0.6
A23: Director de Arte | B23: 3 | C23: 0.4 | D23: 0.5 | E23: 0.6
A24: Project Manager | B24: 3 | C24: 0.4 | D24: 0.5 | E24: 0.6
A25: Data Analyst | B25: 3 | C25: 0.4 | D25: 0.5 | E25: 0.6
A26: CRO Specialist | B26: 3 | C26: 0.4 | D26: 0.5 | E26: 0.6
A27: Growth Hacker | B27: 3 | C27: 0.4 | D27: 0.5 | E27: 0.6
A28: Marketing Automation Specialist | B28: 3 | C28: 0.4 | D28: 0.5 | E28: 0.6
A29: Analista GA4/GTM/Looker | B29: 3 | C29: 0.4 | D29: 0.5 | E29: 0.6
A30: Desarrollador Full Stack Senior | B30: 3 | C30: 0.4 | D30: 0.5 | E30: 0.6
A31: Implementador HubSpot | B31: 3 | C31: 0.4 | D31: 0.5 | E31: 0.6
A32: Desarrollador HubSpot | B32: 3 | C32: 0.4 | D32: 0.5 | E32: 0.6
A33: Periodista PR Digital | B33: 3 | C33: 0.4 | D33: 0.5 | E33: 0.6
A34: TIER 4: IP PROPIETARIA
A35: Consultor HubSpot | B35: 4 | C35: 0.6 | D35: 0.7 | E35: 0.8
A36: Estrategia AEO | B36: 4 | C36: 0.6 | D36: 0.7 | E36: 0.8
A37: Globe OS (futuro) | B37: 4 | C37: 0.6 | D37: 0.7 | E37: 0.8

Sheet Tipos de Cambio
A1: Moneda | B1: Código | C1: Tipo de cambio | D1: Última actualización | E1: Notas
A2: Peso Chileno | B2: CLP | C2: 1000 | D2: 45970 | E2: Valor base interno Efeonce
A3: Peso Colombiano | B3: COP | C3: 4200 | D3: 45970 | E3: Promedio mercado LATAM
A4: Peso Mexicano | B4: MXN | C4: 18.5 | D4: 45970 | E4: SAT + XE promedio
A5: Sol Peruano | B5: PEN | C5: 3.8 | D5: 45970 | E5: Promedio BCRP
A6: Unidad de Fomento (Chile) | B6: CLF | C6: 0.024 | D6: 45971 | E6: 1 UF ≈ 41,64 USD
A7: Dólar estadounidense | B7: USD | C7: 1 | D7: 45971 | E7: Referencia principal

Sheet Factor País
A1: 🌎 TABLA FACTOR PAÍS
A3: Tipo de Cliente | B3: Factor | C3: Cuándo Usar
A4: Chile Corporate | B4: 1.0 | C4: Mid-market o enterprise estándar
A5: Chile PYME | B5: 0.9 | C5: Startup, PYME budget limitado
A6: Colombia / PYME LATAM | B6: 0.85-0.9 | C6: Mercado precio-sensible
A7: Internacional USD | B7: 1.1-1.2 | C7: USA, Europa con budget
A8: Licitación Pública | B8: 0.85-0.95 | C8: Gobierno, concurso
A9: Cliente Estratégico | B9: 0.95 | C9: Futuro valor > margen actual

Sheet Tier Servicios
A1: Tier | B1: Margen Base (%) | C1: Descripción
A2: Tier 1 | B2: 0.4 | C2: Servicios básicos o de entrada
A3: Tier 2 | B3: 0.45 | C3: Servicios estándar recurrentes
A4: Tier 3 | B4: 0.5 | C4: Servicios de consultoría o implementación media
A5: Tier 4 | B5: 0.55 | C5: Servicios estratégicos o premium

Sheet Modelo comercial
A1: Modelo Comercial | B1: Multiplicador (%) | C1: Descripción
A2: On-Going | B2: 0 | C2: Retainers o contratos estables
A3: On-Demand | B3: 0.1 | C3: Proyectos o implementaciones puntuales
A4: Híbrido | B4: 0.05 | C4: Combina setup + retainer
A5: Licencia / Consultoría | B5: 0.15 | C5: Servicios especializados o de licenciamiento

Sheet Tabla Guía FTE
A1: % Dedicación | B1: Equivalente en FTE | C1: Horas mensuales | D1: Descripción recomendada
A2: 0.1 | B2: 0,1 FTE | C2: 18 h/mes | D2: Soporte mínimo o participación táctica puntual
A3: 0.2 | B3: 0,2 FTE | C3: 36 h/mes | D3: Rol parcial, apoyo en una cuenta o subproyecto
A4: 0.25 | B4: 0,25 FTE | C4: 45 h/mes | D4: Involucramiento semanal (1 día aprox.)
A5: 0.3 | B5: 0,3 FTE | C5: 54 h/mes | D5: Participación frecuente en un frente de trabajo
A6: 0.4 | B6: 0,4 FTE | C6: 72 h/mes | D6: Dedicación parcial sostenida
A7: 0.5 | B7: 0,5 FTE | C7: 90 h/mes | D7: Mitad de jornada mensual
A8: 0.6 | B8: 0,6 FTE | C8: 108 h/mes | D8: Presencia importante en dos proyectos o marcas
A9: 0.7 | B9: 0,7 FTE | C9: 126 h/mes | D9: Casi tiempo completo, comparte carga con otro frente
A10: 0.8 | B10: 0,8 FTE | C10: 144 h/mes | D10: Alta dedicación (por ejemplo, PM o Creative Lead)
A11: 0.9 | B11: 0,9 FTE | C11: 162 h/mes | D11: Prácticamente dedicado, con mínima flexibilidad
A12: 1 | B12: 1,0 FTE | C12: 180 h/mes | D12: Dedicación completa mensual (full-time)

Sheet Estructura de Servicios
A1: SKU Servicio | B1: Nombre del servicio | C1: Tipo de ítem | D1: Rol | E1: Horas | F1: Herramienta | G1: Cantidad | H1: Costo unitario (USD) | I1: Subtotal (USD) | J1: Comentario
A2: =IF(B2="","",INDEX('Precios Servicios'!$A:$A,MATCH(B2,'Precios Servicios'!$C:$C,0))) -> EFG-001 | B2: Onboarding HubSpot Marketing Pro | C2: Rol | D2: Consultor HubSpot | E2: 4 | H2: =IF(C2="Rol", VLOOKUP(D2,'Precios personal'!$C:$N,12,FALSE), IF(C2="Herramienta", VLOOKUP(F2,Herramientas!$C:$K,8,FALSE), "")) -> 62.355556 | I2: =IF(C2="Rol",E2*H2,IF(C2="Herramienta",G2*H2,"")) -> 249.42222
A3: =IF(B3="","",INDEX('Precios Servicios'!$A:$A,MATCH(B3,'Precios Servicios'!$C:$C,0))) -> EFG-001 | B3: Onboarding HubSpot Marketing Pro | C3: Herramienta | F3: Notion | G3: 1 | H3: =IF(C3="Rol", VLOOKUP(D3,'Precios personal'!$C:$N,12,FALSE), IF(C3="Herramienta", VLOOKUP(F3,Herramientas!$C:$K,8,FALSE), "")) -> 24 | I3: =IF(C3="Rol",E3*H3,IF(C3="Herramienta",G3*H3,"")) -> 24
A4: =IF(B4="","",INDEX('Precios Servicios'!$A:$A,MATCH(B4,'Precios Servicios'!$C:$C,0))) -> EFG-001 | B4: Onboarding HubSpot Marketing Pro | C4: Herramienta | F4: Microsoft 365 | G4: 1 | H4: =IF(C4="Rol", VLOOKUP(D4,'Precios personal'!$C:$N,12,FALSE), IF(C4="Herramienta", VLOOKUP(F4,Herramientas!$C:$K,8,FALSE), "")) -> 16 | I4: =IF(C4="Rol",E4*H4,IF(C4="Herramienta",G4*H4,"")) -> 16
A5: =IF(B5="","",INDEX('Precios Servicios'!$A:$A,MATCH(B5,'Precios Servicios'!$C:$C,0))) -> EFG-001 | B5: Onboarding HubSpot Marketing Pro | C5: Herramienta | F5: ChatGPT Plus | G5: 1 | H5: =IF(C5="Rol", VLOOKUP(D5,'Precios personal'!$C:$N,12,FALSE), IF(C5="Herramienta", VLOOKUP(F5,Herramientas!$C:$K,8,FALSE), "")) -> 5 | I5: =IF(C5="Rol",E5*H5,IF(C5="Herramienta",G5*H5,"")) -> 5
A6: =IF(B6="","",INDEX('Precios Servicios'!$A:$A,MATCH(B6,'Precios Servicios'!$C:$C,0))) -> EFG-001 | B6: Onboarding HubSpot Marketing Pro | C6: Rol | D6: Implementador HubSpot | E6: 18 | H6: =IF(C6="Rol", VLOOKUP(D6,'Precios personal'!$C:$N,12,FALSE), IF(C6="Herramienta", VLOOKUP(F6,Herramientas!$C:$K,8,FALSE), "")) -> 43.605556 | I6: =IF(C6="Rol",E6*H6,IF(C6="Herramienta",G6*H6,"")) -> 784.9
A7: =IF(B7="","",INDEX('Precios Servicios'!$A:$A,MATCH(B7,'Precios Servicios'!$C:$C,0))) -> EFG-001 | B7: Onboarding HubSpot Marketing Pro | C7: Herramienta | F7: Microsoft 365 | G7: 1 | H7: =IF(C7="Rol", VLOOKUP(D7,'Precios personal'!$C:$N,12,FALSE), IF(C7="Herramienta", VLOOKUP(F7,Herramientas!$C:$K,8,FALSE), "")) -> 16 | I7: =IF(C7="Rol",E7*H7,IF(C7="Herramienta",G7*H7,"")) -> 16
A8: =IF(B8="","",INDEX('Precios Servicios'!$A:$A,MATCH(B8,'Precios Servicios'!$C:$C,0))) -> EFG-001 | B8: Onboarding HubSpot Marketing Pro | C8: Herramienta | F8: Notion | G8: 1 | H8: =IF(C8="Rol", VLOOKUP(D8,'Precios personal'!$C:$N,12,FALSE), IF(C8="Herramienta", VLOOKUP(F8,Herramientas!$C:$K,8,FALSE), "")) -> 24 | I8: =IF(C8="Rol",E8*H8,IF(C8="Herramienta",G8*H8,"")) -> 24
A9: TOTAL | B9: TOTAL — Onboarding HubSpot Marketing Pro | I9: =SUM(I2:I8) -> 1119.3222
A10: =IF(B10="","",INDEX('Precios Servicios'!$A:$A,MATCH(B10,'Precios Servicios'!$C:$C,0))) -> EFG-002 | B10: Servicio de Diseño Digital Full Funnel | C10: Rol | D10: Creative Operations Lead | E10: 180 | H10: =IF(C10="Rol", VLOOKUP(D10,'Precios personal'!$C:$N,12,FALSE), IF(C10="Herramienta", VLOOKUP(F10,Herramientas!$C:$K,8,FALSE), "")) -> 10.827778 | I10: =IF(C10="Rol",E10*H10,IF(C10="Herramienta",G10*H10,"")) -> 1949
A11: =IF(B11="","",INDEX('Precios Servicios'!$A:$A,MATCH(B11,'Precios Servicios'!$C:$C,0))) -> EFG-002 | B11: Servicio de Diseño Digital Full Funnel | C11: Rol | D11: Senior Visual Designer | E11: 180 | H11: =IF(C11="Rol", VLOOKUP(D11,'Precios personal'!$C:$N,12,FALSE), IF(C11="Herramienta", VLOOKUP(F11,Herramientas!$C:$K,8,FALSE), "")) -> 7.55 | I11: =IF(C11="Rol",E11*H11,IF(C11="Herramienta",G11*H11,"")) -> 1359
A12: =IF(B12="","",INDEX('Precios Servicios'!$A:$A,MATCH(B12,'Precios Servicios'!$C:$C,0))) -> EFG-002 | B12: Servicio de Diseño Digital Full Funnel | C12: Rol | D12: Senior Visual Designer | E12: 180 | H12: =IF(C12="Rol", VLOOKUP(D12,'Precios personal'!$C:$N,12,FALSE), IF(C12="Herramienta", VLOOKUP(F12,Herramientas!$C:$K,8,FALSE), "")) -> 7.55 | I12: =IF(C12="Rol",E12*H12,IF(C12="Herramienta",G12*H12,"")) -> 1359
A13: =IF(B13="","",INDEX('Precios Servicios'!$A:$A,MATCH(B13,'Precios Servicios'!$C:$C,0))) -> EFG-002 | B13: Servicio de Diseño Digital Full Funnel | C13: Herramienta | F13: Envato Elements | G13: 1 | H13: =IF(C13="Rol", VLOOKUP(D13,'Precios personal'!$C:$N,12,FALSE), IF(C13="Herramienta", VLOOKUP(F13,Herramientas!$C:$K,8,FALSE), "")) -> 8.25 | I13: =IF(C13="Rol",E13*H13,IF(C13="Herramienta",G13*H13,"")) -> 8.25
A14: =IF(B14="","",INDEX('Precios Servicios'!$A:$A,MATCH(B14,'Precios Servicios'!$C:$C,0))) -> EFG-002 | B14: Servicio de Diseño Digital Full Funnel | C14: Herramienta | F14: Adobe Creative Cloud | G14: 3 | H14: =IF(C14="Rol", VLOOKUP(D14,'Precios personal'!$C:$N,12,FALSE), IF(C14="Herramienta", VLOOKUP(F14,Herramientas!$C:$K,8,FALSE), "")) -> 20 | I14: =IF(C14="Rol",E14*H14,IF(C14="Herramienta",G14*H14,"")) -> 60
A15: =IF(B15="","",INDEX('Precios Servicios'!$A:$A,MATCH(B15,'Precios Servicios'!$C:$C,0))) -> EFG-002 | B15: Servicio de Diseño Digital Full Funnel | C15: Herramienta | F15: Freepik | G15: 1 | H15: =IF(C15="Rol", VLOOKUP(D15,'Precios personal'!$C:$N,12,FALSE), IF(C15="Herramienta", VLOOKUP(F15,Herramientas!$C:$K,8,FALSE), "")) -> 8.25 | I15: =IF(C15="Rol",E15*H15,IF(C15="Herramienta",G15*H15,"")) -> 8.25
A16: =IF(B16="","",INDEX('Precios Servicios'!$A:$A,MATCH(B16,'Precios Servicios'!$C:$C,0))) -> EFG-002 | B16: Servicio de Diseño Digital Full Funnel | C16: Herramienta | F16: Notion | G16: 3 | H16: =IF(C16="Rol", VLOOKUP(D16,'Precios personal'!$C:$N,12,FALSE), IF(C16="Herramienta", VLOOKUP(F16,Herramientas!$C:$K,8,FALSE), "")) -> 24 | I16: =IF(C16="Rol",E16*H16,IF(C16="Herramienta",G16*H16,"")) -> 72
A17: =IF(B17="","",INDEX('Precios Servicios'!$A:$A,MATCH(B17,'Precios Servicios'!$C:$C,0))) -> EFG-002 | B17: Servicio de Diseño Digital Full Funnel | C17: Herramienta | F17: Microsoft 365 | G17: 3 | H17: =IF(C17="Rol", VLOOKUP(D17,'Precios personal'!$C:$N,12,FALSE), IF(C17="Herramienta", VLOOKUP(F17,Herramientas!$C:$K,8,FALSE), "")) -> 16 | I17: =IF(C17="Rol",E17*H17,IF(C17="Herramienta",G17*H17,"")) -> 48
A18: =IF(B18="","",INDEX('Precios Servicios'!$A:$A,MATCH(B18,'Precios Servicios'!$C:$C,0))) -> EFG-002 | B18: Servicio de Diseño Digital Full Funnel | C18: Herramienta | F18: Deel | G18: 3 | H18: =IF(C18="Rol", VLOOKUP(D18,'Precios personal'!$C:$N,12,FALSE), IF(C18="Herramienta", VLOOKUP(F18,Herramientas!$C:$K,8,FALSE), "")) -> 12.25 | I18: =IF(C18="Rol",E18*H18,IF(C18="Herramienta",G18*H18,"")) -> 36.75
A19: TOTAL | B19: TOTAL — Servicio de Diseño Digital Full Funnel | I19: =SUM(I10:I18) -> 4900.25
A20: =IF(B20="","",INDEX('Precios Servicios'!$A:$A,MATCH(B20,'Precios Servicios'!$C:$C,0))) -> EFG-003 | B20: Servicio de Performance y Paid Ads | C20: Rol | D20: Paid Media Manager | E20: 54 | H20: =IF(C20="Rol", VLOOKUP(D20,'Precios personal'!$C:$N,12,FALSE), IF(C20="Herramienta", VLOOKUP(F20,Herramientas!$C:$K,8,FALSE), "")) -> 17.494444 | I20: =IF(C20="Rol",E20*H20,IF(C20="Herramienta",G20*H20,"")) -> 944.7
A21: =IF(B21="","",INDEX('Precios Servicios'!$A:$A,MATCH(B21,'Precios Servicios'!$C:$C,0))) -> EFG-003 | B21: Servicio de Performance y Paid Ads | C21: Rol | D21: Creative Designer | E21: 36 | H21: =IF(C21="Rol", VLOOKUP(D21,'Precios personal'!$C:$N,12,FALSE), IF(C21="Herramienta", VLOOKUP(F21,Herramientas!$C:$K,8,FALSE), "")) -> 5.7444444 | I21: =IF(C21="Rol",E21*H21,IF(C21="Herramienta",G21*H21,"")) -> 206.8
A22: =IF(B22="","",INDEX('Precios Servicios'!$A:$A,MATCH(B22,'Precios Servicios'!$C:$C,0))) -> EFG-003 | B22: Servicio de Performance y Paid Ads | C22: Herramienta | F22: Notion | G22: 2 | H22: =IF(C22="Rol", VLOOKUP(D22,'Precios personal'!$C:$N,12,FALSE), IF(C22="Herramienta", VLOOKUP(F22,Herramientas!$C:$K,8,FALSE), "")) -> 24 | I22: =IF(C22="Rol",E22*H22,IF(C22="Herramienta",G22*H22,"")) -> 48
A23: =IF(B23="","",INDEX('Precios Servicios'!$A:$A,MATCH(B23,'Precios Servicios'!$C:$C,0))) -> EFG-003 | B23: Servicio de Performance y Paid Ads | C23: Herramienta | F23: Microsoft 365 | G23: 2 | H23: =IF(C23="Rol", VLOOKUP(D23,'Precios personal'!$C:$N,12,FALSE), IF(C23="Herramienta", VLOOKUP(F23,Herramientas!$C:$K,8,FALSE), "")) -> 16 | I23: =IF(C23="Rol",E23*H23,IF(C23="Herramienta",G23*H23,"")) -> 32
A24: =IF(B24="","",INDEX('Precios Servicios'!$A:$A,MATCH(B24,'Precios Servicios'!$C:$C,0))) -> EFG-003 | B24: Servicio de Performance y Paid Ads | C24: Herramienta | F24: Adobe Creative Cloud | G24: 1 | H24: =IF(C24="Rol", VLOOKUP(D24,'Precios personal'!$C:$N,12,FALSE), IF(C24="Herramienta", VLOOKUP(F24,Herramientas!$C:$K,8,FALSE), "")) -> 20 | I24: =IF(C24="Rol",E24*H24,IF(C24="Herramienta",G24*H24,"")) -> 20
A25: TOTAL | B25: TOTAL — Servicio de Performance y Paid Ads | I25: =SUM(I20:I24) -> 1251.5
A26: =IF(B26="","",INDEX('Precios Servicios'!$A:$A,MATCH(B26,'Precios Servicios'!$C:$C,0))) | H26: =IF(C26="Rol", VLOOKUP(D26,'Precios personal'!$C:$N,12,FALSE), IF(C26="Herramienta", VLOOKUP(F26,Herramientas!$C:$K,8,FALSE), "")) | I26: =IF(C26="Rol",E26*H26,IF(C26="Herramienta",G26*H26,""))
A27: =IF(B27="","",INDEX('Precios Servicios'!$A:$A,MATCH(B27,'Precios Servicios'!$C:$C,0))) | H27: =IF(C27="Rol", VLOOKUP(D27,'Precios personal'!$C:$N,12,FALSE), IF(C27="Herramienta", VLOOKUP(F27,Herramientas!$C:$K,8,FALSE), "")) | I27: =IF(C27="Rol",E27*H27,IF(C27="Herramienta",G27*H27,""))
A28: =IF(B28="","",INDEX('Precios Servicios'!$A:$A,MATCH(B28,'Precios Servicios'!$C:$C,0))) | H28: =IF(C28="Rol", VLOOKUP(D28,'Precios personal'!$C:$N,12,FALSE), IF(C28="Herramienta", VLOOKUP(F28,Herramientas!$C:$K,8,FALSE), "")) | I28: =IF(C28="Rol",E28*H28,IF(C28="Herramienta",G28*H28,""))
A29: =IF(B29="","",INDEX('Precios Servicios'!$A:$A,MATCH(B29,'Precios Servicios'!$C:$C,0))) | H29: =IF(C29="Rol", VLOOKUP(D29,'Precios personal'!$C:$N,12,FALSE), IF(C29="Herramienta", VLOOKUP(F29,Herramientas!$C:$K,8,FALSE), "")) | I29: =IF(C29="Rol",E29*H29,IF(C29="Herramienta",G29*H29,""))
A30: =IF(B30="","",INDEX('Precios Servicios'!$A:$A,MATCH(B30,'Precios Servicios'!$C:$C,0))) | H30: =IF(C30="Rol", VLOOKUP(D30,'Precios personal'!$C:$N,12,FALSE), IF(C30="Herramienta", VLOOKUP(F30,Herramientas!$C:$K,8,FALSE), "")) | I30: =IF(C30="Rol",E30*H30,IF(C30="Herramienta",G30*H30,""))
A31: =IF(B31="","",INDEX('Precios Servicios'!$A:$A,MATCH(B31,'Precios Servicios'!$C:$C,0))) | H31: =IF(C31="Rol", VLOOKUP(D31,'Precios personal'!$C:$N,12,FALSE), IF(C31="Herramienta", VLOOKUP(F31,Herramientas!$C:$K,8,FALSE), "")) | I31: =IF(C31="Rol",E31*H31,IF(C31="Herramienta",G31*H31,""))
A32: =IF(B32="","",INDEX('Precios Servicios'!$A:$A,MATCH(B32,'Precios Servicios'!$C:$C,0))) | I32: =IF(C32="Rol",E32*H32,IF(C32="Herramienta",G32*H32,""))
A33: =IF(B33="","",INDEX('Precios Servicios'!$A:$A,MATCH(B33,'Precios Servicios'!$C:$C,0))) | I33: =IF(C33="Rol",E33*H33,IF(C33="Herramienta",G33*H33,""))
A34: =IF(B34="","",INDEX('Precios Servicios'!$A:$A,MATCH(B34,'Precios Servicios'!$C:$C,0))) | I34: =IF(C34="Rol",E34*H34,IF(C34="Herramienta",G34*H34,""))
A35: =IF(B35="","",INDEX('Precios Servicios'!$A:$A,MATCH(B35,'Precios Servicios'!$C:$C,0))) | I35: =IF(C35="Rol",E35*H35,IF(C35="Herramienta",G35*H35,""))
A36: =IF(B36="","",INDEX('Precios Servicios'!$A:$A,MATCH(B36,'Precios Servicios'!$C:$C,0))) | I36: =IF(C36="Rol",E36*H36,IF(C36="Herramienta",G36*H36,""))
A37: =IF(B37="","",INDEX('Precios Servicios'!$A:$A,MATCH(B37,'Precios Servicios'!$C:$C,0))) | I37: =IF(C37="Rol",E37*H37,IF(C37="Herramienta",G37*H37,""))
A38: =IF(B38="","",INDEX('Precios Servicios'!$A:$A,MATCH(B38,'Precios Servicios'!$C:$C,0))) | I38: =IF(C38="Rol",E38*H38,IF(C38="Herramienta",G38*H38,""))
A39: =IF(B39="","",INDEX('Precios Servicios'!$A:$A,MATCH(B39,'Precios Servicios'!$C:$C,0))) | I39: =IF(C39="Rol",E39*H39,IF(C39="Herramienta",G39*H39,""))
A40: =IF(B40="","",INDEX('Precios Servicios'!$A:$A,MATCH(B40,'Precios Servicios'!$C:$C,0))) | I40: =IF(C40="Rol",E40*H40,IF(C40="Herramienta",G40*H40,""))
A41: =IF(B41="","",INDEX('Precios Servicios'!$A:$A,MATCH(B41,'Precios Servicios'!$C:$C,0))) | I41: =IF(C41="Rol",E41*H41,IF(C41="Herramienta",G41*H41,""))
A42: =IF(B42="","",INDEX('Precios Servicios'!$A:$A,MATCH(B42,'Precios Servicios'!$C:$C,0))) | I42: =IF(C42="Rol",E42*H42,IF(C42="Herramienta",G42*H42,""))
A43: =IF(B43="","",INDEX('Precios Servicios'!$A:$A,MATCH(B43,'Precios Servicios'!$C:$C,0))) | I43: =IF(C43="Rol",E43*H43,IF(C43="Herramienta",G43*H43,""))
... A51: =IF(B51="","",INDEX('Precios Servicios'!$A:$A,MATCH(B51,'Precios Servicios'!$C:$C,0))) | I51: =IF(C51="Rol",E51*H51,IF(C51="Herramienta",G51*H51,""))

Sheet Precios personal
A1: SKU | B1: Categoría | C1: Rol | D1: Tipo (Staff/Servicio) | E1: Tier | F1: Salario Base (USD) | G1: Bonificación JiT | H1: Bonificación RpA | I1: Bonificación AR | J1: Bonificación Sobrecumplimiento | K1: Gastos Previsionales | L1: Fee Deel | M1: Costo total | N1: Costo Interno (USD/h) | O1: Costo Interno (FTE) | P1: Precio Hora Agencia (USD) | Q1: Margen en % | R1: Precio Hora (CLP) | S1: Precio Hora (CLF) | T1: Precio Hora (COP) | U1: Precio Hora (MXN) | V1: Precio Hora (PEN) | W1: Precio FTE (USD) | X1: Precio FTE (CLP) | Y1: Precio FTE (CLF) | Z1: Precio FTE (COP) | AA1: Precio FTE (MXN) | AB1: Precio FTE (PEN)
A2: ECG-001 | B2: Creativo | C2: Creative Operations Lead | D2: Staff | E2: Tier 3: Estratégico | F2: 1400 | G2: 200 | H2: 100 | I2: 50 | J2: 150 | K2: 0 | L2: 49 | M2: =(F2 + G2 + H2 + I2 + J2 + K2 + L2) -> 1949 | N2: =M2/Datos!$O$3 -> 10.827778 | O2: =N2*Datos!$O$3 -> 1949 | P2: =N2*(1+VLOOKUP(E2,'Tier Datos'!$A$2:$B$5,2,FALSE)) -> 16.241667 | Q2: =IFERROR(VLOOKUP(E2,'Tier Datos'!$A$2:$B$5,2,FALSE),"") -> 0.5 | R2: =P2*VLOOKUP("CLP",'Tipos de Cambio'!$B:$C,2,FALSE) -> 16241.667 | S2: =P2*VLOOKUP("CLF",'Tipos de Cambio'!$B:$C,2,FALSE) -> 0.3898 | T2: =P2*VLOOKUP("COP",'Tipos de Cambio'!$B:$C,2,FALSE) -> 68215 | U2: =P2*VLOOKUP("MXN",'Tipos de Cambio'!$B:$C,2,FALSE) -> 300.47083 | V2: =P2*VLOOKUP("PEN",'Tipos de Cambio'!$B:$C,2,FALSE) -> 61.718333 | W2: =P2*Datos!$O$3 -> 2923.5 | X2: =W2*VLOOKUP("CLP",'Tipos de Cambio'!$B:$C,2,FALSE) -> 2923500 | Y2: =W2*VLOOKUP("CLF",'Tipos de Cambio'!$B:$C,2,FALSE) -> 70.164 | Z2: =W2*VLOOKUP("COP",'Tipos de Cambio'!$B:$C,2,FALSE) -> 12278700 | AA2: =W2*VLOOKUP("MXN",'Tipos de Cambio'!$B:$C,2,FALSE) -> 54084.75 | AB2: =W2*VLOOKUP("PEN",'Tipos de Cambio'!$B:$C,2,FALSE) -> 11109.3
A3: ECG-002 | B3: Creativo | C3: Senior Visual Designer | D3: Staff | E3: Tier 2: Especializado | F3: 950 | G3: 150 | H3: 75 | I3: 35 | J3: 100 | K3: 0 | L3: 49 | M3: =(F3 + G3 + H3 + I3 + J3 + K3 + L3) -> 1359 | N3: =M3/Datos!$O$3 -> 7.55 | O3: =N3*Datos!$O$3 -> 1359 | P3: =N3*(1+VLOOKUP(E3,'Tier Datos'!$A$2:$B$5,2,FALSE)) -> 9.815 | Q3: =IFERROR(VLOOKUP(E3,'Tier Datos'!$A$2:$B$5,2,FALSE),"") -> 0.3 | R3: =P3*VLOOKUP("CLP",'Tipos de Cambio'!$B:$C,2,FALSE) -> 9815 | S3: =P3*VLOOKUP("CLF",'Tipos de Cambio'!$B:$C,2,FALSE) -> 0.23556 | T3: =P3*VLOOKUP("COP",'Tipos de Cambio'!$B:$C,2,FALSE) -> 41223 | U3: =P3*VLOOKUP("MXN",'Tipos de Cambio'!$B:$C,2,FALSE) -> 181.5775 | V3: =P3*VLOOKUP("PEN",'Tipos de Cambio'!$B:$C,2,FALSE) -> 37.297 | W3: =P3*Datos!$O$3 -> 1766.7 | X3: =W3*VLOOKUP("CLP",'Tipos de Cambio'!$B:$C,2,FALSE) -> 1766700 | Y3: =W3*VLOOKUP("CLF",'Tipos de Cambio'!$B:$C,2,FALSE) -> 42.4008 | Z3: =W3*VLOOKUP("COP",'Tipos de Cambio'!$B:$C,2,FALSE) -> 7420140 | AA3: =W3*VLOOKUP("MXN",'Tipos de Cambio'!$B:$C,2,FALSE) -> 32683.95 | AB3: =W3*VLOOKUP("PEN",'Tipos de Cambio'!$B:$C,2,FALSE) -> 6713.46
A4: ECG-003 | B4: Creativo | C4: Creative Designer | D4: Staff | E4: Tier 1: Commoditizado | F4: 675 | G4: 150 | H4: 50 | I4: 35 | J4: 75 | K4: 0 | L4: 49 | M4: =(F4 + G4 + H4 + I4 + J4 + K4 + L4) -> 1034 | N4: =M4/Datos!$O$3 -> 5.7444444 | O4: =N4*Datos!$O$3 -> 1034 | P4: =N4*(1+VLOOKUP(E4,'Tier Datos'!$A$2:$B$5,2,FALSE)) -> 7.1805556 | Q4: =IFERROR(VLOOKUP(E4,'Tier Datos'!$A$2:$B$5,2,FALSE),"") -> 0.25 | R4: =P4*VLOOKUP("CLP",'Tipos de Cambio'!$B:$C,2,FALSE) -> 7180.5556 | S4: =P4*VLOOKUP("CLF",'Tipos de Cambio'!$B:$C,2,FALSE) -> 0.17233333 | T4: =P4*VLOOKUP("COP",'Tipos de Cambio'!$B:$C,2,FALSE) -> 30158.333 | U4: =P4*VLOOKUP("MXN",'Tipos de Cambio'!$B:$C,2,FALSE) -> 132.84028 | V4: =P4*VLOOKUP("PEN",'Tipos de Cambio'!$B:$C,2,FALSE) -> 27.286111 | W4: =P4*Datos!$O$3 -> 1292.5 | X4: =W4*VLOOKUP("CLP",'Tipos de Cambio'!$B:$C,2,FALSE) -> 1292500 | Y4: =W4*VLOOKUP("CLF",'Tipos de Cambio'!$B:$C,2,FALSE) -> 31.02 | Z4: =W4*VLOOKUP("COP",'Tipos de Cambio'!$B:$C,2,FALSE) -> 5428500 | AA4: =W4*VLOOKUP("MXN",'Tipos de Cambio'!$B:$C,2,FALSE) -> 23911.25 | AB4: =W4*VLOOKUP("PEN",'Tipos de Cambio'!$B:$C,2,FALSE) -> 4911.5
A5: ECG-004 | B5: PR | C5: PR Analyst | D5: Staff | E5: Tier 3: Estratégico | F5: 550 | G5: 0 | H5: 0 | I5: 150 | J5: 100 | K5: 150 | L5: 49 | M5: =(F5 + G5 + H5 + I5 + J5 + K5 + L5) -> 999 | N5: =M5/Datos!$O$3 -> 5.55 | O5: =N5*Datos!$O$3 -> 999 | P5: =N5*(1+VLOOKUP(E5,'Tier Datos'!$A$2:$B$5,2,FALSE)) -> 8.325 | Q5: =IFERROR(VLOOKUP(E5,'Tier Datos'!$A$2:$B$5,2,FALSE),"") -> 0.5 | R5: =P5*VLOOKUP("CLP",'Tipos de Cambio'!$B:$C,2,FALSE) -> 8325 | S5: =P5*VLOOKUP("CLF",'Tipos de Cambio'!$B:$C,2,FALSE) -> 0.1998 | T5: =P5*VLOOKUP("COP",'Tipos de Cambio'!$B:$C,2,FALSE) -> 34965 | U5: =P5*VLOOKUP("MXN",'Tipos de Cambio'!$B:$C,2,FALSE) -> 154.0125 | V5: =P5*VLOOKUP("PEN",'Tipos de Cambio'!$B:$C,2,FALSE) -> 31.635 | W5: =P5*Datos!$O$3 -> 1498.5 | X5: =W5*VLOOKUP("CLP",'Tipos de Cambio'!$B:$C,2,FALSE) -> 1498500 | Y5: =W5*VLOOKUP("CLF",'Tipos de Cambio'!$B:$C,2,FALSE) -> 35.964 | Z5: =W5*VLOOKUP("COP",'Tipos de Cambio'!$B:$C,2,FALSE) -> 6293700 | AA5: =W5*VLOOKUP("MXN",'Tipos de Cambio'!$B:$C,2,FALSE) -> 27722.25 | AB5: =W5*VLOOKUP("PEN",'Tipos de Cambio'!$B:$C,2,FALSE) -> 5694.3
A6: ECG-005 | B6: Creativo | C6: Director de Arte | D6: Servicio | E6: Tier 3: Estratégico | F6: 1300 | G6: 250 | H6: 150 | I6: 50 | J6: 150 | K6: 0 | L6: 49 | M6: =(F6 + G6 + H6 + I6 + J6 + K6 + L6) -> 1949 | N6: =M6/Datos!$O$3 -> 10.827778 | O6: =N6*Datos!$O$3 -> 1949 | P6: =N6*(1+VLOOKUP(E6,'Tier Datos'!$A$2:$B$5,2,FALSE)) -> 16.241667 | Q6: =IFERROR(VLOOKUP(E6,'Tier Datos'!$A$2:$B$5,2,FALSE),"") -> 0.5 | R6: =P6*VLOOKUP("CLP",'Tipos de Cambio'!$B:$C,2,FALSE) -> 16241.667 | S6: =P6*VLOOKUP("CLF",'Tipos de Cambio'!$B:$C,2,FALSE) -> 0.3898 | T6: =P6*VLOOKUP("COP",'Tipos de Cambio'!$B:$C,2,FALSE) -> 68215 | U6: =P6*VLOOKUP("MXN",'Tipos de Cambio'!$B:$C,2,FALSE) -> 300.47083 | V6: =P6*VLOOKUP("PEN",'Tipos de Cambio'!$B:$C,2,FALSE) -> 61.718333 | W6: =P6*Datos!$O$3 -> 2923.5 | X6: =W6*VLOOKUP("CLP",'Tipos de Cambio'!$B:$C,2,FALSE) -> 2923500 | Y6: =W6*VLOOKUP("CLF",'Tipos de Cambio'!$B:$C,2,FALSE) -> 70.164 | Z6: =W6*VLOOKUP("COP",'Tipos de Cambio'!$B:$C,2,FALSE) -> 12278700 | AA6: =W6*VLOOKUP("MXN",'Tipos de Cambio'!$B:$C,2,FALSE) -> 54084.75 | AB6: =W6*VLOOKUP("PEN",'Tipos de Cambio'!$B:$C,2,FALSE) -> 11109.3
A7: ECG-006 | B7: Creativo | C7: Social Media Manager | D7: Servicio | E7: Tier 1: Commoditizado | F7: 1000 | G7: 200 | H7: 100 | I7: 50 | J7: 150 | K7: 0 | L7: 49 | M7: =(F7 + G7 + H7 + I7 + J7 + K7 + L7) -> 1549 | N7: =M7/Datos!$O$3 -> 8.6055556 | O7: =N7*Datos!$O$3 -> 1549 | P7: =N7*(1+VLOOKUP(E7,'Tier Datos'!$A$2:$B$5,2,FALSE)) -> 10.756944 | Q7: =IFERROR(VLOOKUP(E7,'Tier Datos'!$A$2:$B$5,2,FALSE),"") -> 0.25 | R7: =P7*VLOOKUP("CLP",'Tipos de Cambio'!$B:$C,2,FALSE) -> 10756.944 | S7: =P7*VLOOKUP("CLF",'Tipos de Cambio'!$B:$C,2,FALSE) -> 0.25816667 | T7: =P7*VLOOKUP("COP",'Tipos de Cambio'!$B:$C,2,FALSE) -> 45179.167 | U7: =P7*VLOOKUP("MXN",'Tipos de Cambio'!$B:$C,2,FALSE) -> 199.00347 | V7: =P7*VLOOKUP("PEN",'Tipos de Cambio'!$B:$C,2,FALSE) -> 40.876389 | W7: =P7*Datos!$O$3 -> 1936.25 | X7: =W7*VLOOKUP("CLP",'Tipos de Cambio'!$B:$C,2,FALSE) -> 1936250 | Y7: =W7*VLOOKUP("CLF",'Tipos de Cambio'!$B:$C,2,FALSE) -> 46.47 | Z7: =W7*VLOOKUP("COP",'Tipos de Cambio'!$B:$C,2,FALSE) -> 8132250 | AA7: =W7*VLOOKUP("MXN",'Tipos de Cambio'!$B:$C,2,FALSE) -> 35820.625 | AB7: =W7*VLOOKUP("PEN",'Tipos de Cambio'!$B:$C,2,FALSE) -> 7357.75
A8: ECG-007 | B8: Performance | C8: Community Manager | D8: Servicio | E8: Tier 1: Commoditizado | F8: 900 | G8: 200 | H8: 100 | I8: 50 | J8: 150 | K8: 0 | L8: 49 | M8: =(F8 + G8 + H8 + I8 + J8 + K8 + L8) -> 1449 | N8: =M8/Datos!$O$3 -> 8.05 | O8: =N8*Datos!$O$3 -> 1449 | P8: =N8*(1+VLOOKUP(E8,'Tier Datos'!$A$2:$B$5,2,FALSE)) -> 10.0625 | Q8: =IFERROR(VLOOKUP(E8,'Tier Datos'!$A$2:$B$5,2,FALSE),"") -> 0.25 | R8: =P8*VLOOKUP("CLP",'Tipos de Cambio'!$B:$C,2,FALSE) -> 10062.5 | S8: =P8*VLOOKUP("CLF",'Tipos de Cambio'!$B:$C,2,FALSE) -> 0.2415 | T8: =P8*VLOOKUP("COP",'Tipos de Cambio'!$B:$C,2,FALSE) -> 42262.5 | U8: =P8*VLOOKUP("MXN",'Tipos de Cambio'!$B:$C,2,FALSE) -> 186.15625 | V8: =P8*VLOOKUP("PEN",'Tipos de Cambio'!$B:$C,2,FALSE) -> 38.2375 | W8: =P8*Datos!$O$3 -> 1811.25 | X8: =W8*VLOOKUP("CLP",'Tipos de Cambio'!$B:$C,2,FALSE) -> 1811250 | Y8: =W8*VLOOKUP("CLF",'Tipos de Cambio'!$B:$C,2,FALSE) -> 43.47 | Z8: =W8*VLOOKUP("COP",'Tipos de Cambio'!$B:$C,2,FALSE) -> 7607250 | AA8: =W8*VLOOKUP("MXN",'Tipos de Cambio'!$B:$C,2,FALSE) -> 33508.125 | AB8: =W8*VLOOKUP("PEN",'Tipos de Cambio'!$B:$C,2,FALSE) -> 6882.75
A9: ECG-008 | B9: Performance | C9: Paid Media Manager | D9: Servicio | E9: Tier 2: Especializado | F9: 2500 | G9: 250 | H9: 150 | I9: 50 | J9: 150 | K9: 0 | L9: 49 | M9: =(F9 + G9 + H9 + I9 + J9 + K9 + L9) -> 3149 | N9: =M9/Datos!$O$3 -> 17.494444 | O9: =N9*Datos!$O$3 -> 3149 | P9: =N9*(1+VLOOKUP(E9,'Tier Datos'!$A$2:$B$5,2,FALSE)) -> 22.742778 | Q9: =IFERROR(VLOOKUP(E9,'Tier Datos'!$A$2:$B$5,2,FALSE),"") -> 0.3 | R9: =P9*VLOOKUP("CLP",'Tipos de Cambio'!$B:$C,2,FALSE) -> 22742.778 | S9: =P9*VLOOKUP("CLF",'Tipos de Cambio'!$B:$C,2,FALSE) -> 0.54582667 | T9: =P9*VLOOKUP("COP",'Tipos de Cambio'!$B:$C,2,FALSE) -> 95519.667 | U9: =P9*VLOOKUP("MXN",'Tipos de Cambio'!$B:$C,2,FALSE) -> 420.74139 | V9: =P9*VLOOKUP("PEN",'Tipos de Cambio'!$B:$C,2,FALSE) -> 86.422556 | W9: =P9*Datos!$O$3 -> 4093.7 | X9: =W9*VLOOKUP("CLP",'Tipos de Cambio'!$B:$C,2,FALSE) -> 4093700 | Y9: =W9*VLOOKUP("CLF",'Tipos de Cambio'!$B:$C,2,FALSE) -> 98.2488 | Z9: =W9*VLOOKUP("COP",'Tipos de Cambio'!$B:$C,2,FALSE) -> 17193540 | AA9: =W9*VLOOKUP("MXN",'Tipos de Cambio'!$B:$C,2,FALSE) -> 75733.45 | AB9: =W9*VLOOKUP("PEN",'Tipos de Cambio'!$B:$C,2,FALSE) -> 15556.06
A10: ECG-009 | B10: Performance | C10: Media Buyer | D10: Servicio | E10: Tier 1: Commoditizado | F10: 1300 | G10: 200 | H10: 100 | I10: 50 | J10: 150 | K10: 0 | L10: 49 | M10: =(F10 + G10 + H10 + I10 + J10 + K10 + L10) -> 1849 | N10: =M10/Datos!$O$3 -> 10.272222 | O10: =N10*Datos!$O$3 -> 1849 | P10: =N10*(1+VLOOKUP(E10,'Tier Datos'!$A$2:$B$5,2,FALSE)) -> 12.840278 | Q10: =IFERROR(VLOOKUP(E10,'Tier Datos'!$A$2:$B$5,2,FALSE),"") -> 0.25 | R10: =P10*VLOOKUP("CLP",'Tipos de Cambio'!$B:$C,2,FALSE) -> 12840.278 | S10: =P10*VLOOKUP("CLF",'Tipos de Cambio'!$B:$C,2,FALSE) -> 0.30816667 | T10: =P10*VLOOKUP("COP",'Tipos de Cambio'!$B:$C,2,FALSE) -> 53929.167 | U10: =P10*VLOOKUP("MXN",'Tipos de Cambio'!$B:$C,2,FALSE) -> 237.54514 | V10: =P10*VLOOKUP("PEN",'Tipos de Cambio'!$B:$C,2,FALSE) -> 48.793056 | W10: =P10*Datos!$O$3 -> 2311.25 | X10: =W10*VLOOKUP("CLP",'Tipos de Cambio'!$B:$C,2,FALSE) -> 2311250 | Y10: =W10*VLOOKUP("CLF",'Tipos de Cambio'!$B:$C,2,FALSE) -> 55.47 | Z10: =W10*VLOOKUP("COP",'Tipos de Cambio'!$B:$C,2,FALSE) -> 9707250 | AA10: =W10*VLOOKUP("MXN",'Tipos de Cambio'!$B:$C,2,FALSE) -> 42758.125 | AB10: =W10*VLOOKUP("PEN",'Tipos de Cambio'!$B:$C,2,FALSE) -> 8782.75
A11: ECG-010 | B11: Creativo | C11: Content Manager | D11: Servicio | E11: Tier 1: Commoditizado | F11: 1200 | G11: 200 | H11: 100 | I11: 50 | J11: 150 | K11: 0 | L11: 49 | M11: =(F11 + G11 + H11 + I11 + J11 + K11 + L11) -> 1749 | N11: =M11/Datos!$O$3 -> 9.7166667 | O11: =N11*Datos!$O$3 -> 1749 | P11: =N11*(1+VLOOKUP(E11,'Tier Datos'!$A$2:$B$5,2,FALSE)) -> 12.145833 | Q11: =IFERROR(VLOOKUP(E11,'Tier Datos'!$A$2:$B$5,2,FALSE),"") -> 0.25 | R11: =P11*VLOOKUP("CLP",'Tipos de Cambio'!$B:$C,2,FALSE) -> 12145.833 | S11: =P11*VLOOKUP("CLF",'Tipos de Cambio'!$B:$C,2,FALSE) -> 0.2915 | T11: =P11*VLOOKUP("COP",'Tipos de Cambio'!$B:$C,2,FALSE) -> 51012.5 | U11: =P11*VLOOKUP("MXN",'Tipos de Cambio'!$B:$C,2,FALSE) -> 224.69792 | V11: =P11*VLOOKUP("PEN",'Tipos de Cambio'!$B:$C,2,FALSE) -> 46.154167 | W11: =P11*Datos!$O$3 -> 2186.25 | X11: =W11*VLOOKUP("CLP",'Tipos de Cambio'!$B:$C,2,FALSE) -> 2186250 | Y11: =W11*VLOOKUP("CLF",'Tipos de Cambio'!$B:$C,2,FALSE) -> 52.47 | Z11: =W11*VLOOKUP("COP",'Tipos de Cambio'!$B:$C,2,FALSE) -> 9182250 | AA11: =W11*VLOOKUP("MXN",'Tipos de Cambio'!$B:$C,2,FALSE) -> 40445.625 | AB11: =W11*VLOOKUP("PEN",'Tipos de Cambio'!$B:$C,2,FALSE) -> 8307.75
A12: ECG-011 | B12: Creativo | C12: Copywriter | D12: Servicio | E12: Tier 1: Commoditizado | F12: 1000 | G12: 200 | H12: 100 | I12: 50 | J12: 150 | K12: 0 | L12: 49 | M12: =(F12 + G12 + H12 + I12 + J12 + K12 + L12) -> 1549 | N12: =M12/Datos!$O$3 -> 8.6055556 | O12: =N12*Datos!$O$3 -> 1549 | P12: =N12*(1+VLOOKUP(E12,'Tier Datos'!$A$2:$B$5,2,FALSE)) -> 10.756944 | Q12: =IFERROR(VLOOKUP(E12,'Tier Datos'!$A$2:$B$5,2,FALSE),"") -> 0.25 | R12: =P12*VLOOKUP("CLP",'Tipos de Cambio'!$B:$C,2,FALSE) -> 10756.944 | S12: =P12*VLOOKUP("CLF",'Tipos de Cambio'!$B:$C,2,FALSE) -> 0.25816667 | T12: =P12*VLOOKUP("COP",'Tipos de Cambio'!$B:$C,2,FALSE) -> 45179.167 | U12: =P12*VLOOKUP("MXN",'Tipos de Cambio'!$B:$C,2,FALSE) -> 199.00347 | V12: =P12*VLOOKUP("PEN",'Tipos de Cambio'!$B:$C,2,FALSE) -> 40.876389 | W12: =P12*Datos!$O$3 -> 1936.25 | X12: =W12*VLOOKUP("CLP",'Tipos de Cambio'!$B:$C,2,FALSE) -> 1936250 | Y12: =W12*VLOOKUP("CLF",'Tipos de Cambio'!$B:$C,2,FALSE) -> 46.47 | Z12: =W12*VLOOKUP("COP",'Tipos de Cambio'!$B:$C,2,FALSE) -> 8132250 | AA12: =W12*VLOOKUP("MXN",'Tipos de Cambio'!$B:$C,2,FALSE) -> 35820.625 | AB12: =W12*VLOOKUP("PEN",'Tipos de Cambio'!$B:$C,2,FALSE) -> 7357.75
A13: ECG-012 | B13: Tech | C13: Desarrollador WordPress | D13: Staff | E13: Tier 3: Estratégico | F13: 1100 | G13: 200 | H13: 100 | I13: 50 | J13: 150 | K13: 0 | L13: 49 | M13: =(F13 + G13 + H13 + I13 + J13 + K13 + L13) -> 1649 | N13: =M13/Datos!$O$3 -> 9.1611111 | O13: =N13*Datos!$O$3 -> 1649 | P13: =N13*(1+VLOOKUP(E13,'Tier Datos'!$A$2:$B$5,2,FALSE)) -> 13.741667 | Q13: =IFERROR(VLOOKUP(E13,'Tier Datos'!$A$2:$B$5,2,FALSE),"") -> 0.5 | R13: =P13*VLOOKUP("CLP",'Tipos de Cambio'!$B:$C,2,FALSE) -> 13741.667 | S13: =P13*VLOOKUP("CLF",'Tipos de Cambio'!$B:$C,2,FALSE) -> 0.3298 | T13: =P13*VLOOKUP("COP",'Tipos de Cambio'!$B:$C,2,FALSE) -> 57715 | U13: =P13*VLOOKUP("MXN",'Tipos de Cambio'!$B:$C,2,FALSE) -> 254.22083 | V13: =P13*VLOOKUP("PEN",'Tipos de Cambio'!$B:$C,2,FALSE) -> 52.218333 | W13: =P13*Datos!$O$3 -> 2473.5 | X13: =W13*VLOOKUP("CLP",'Tipos de Cambio'!$B:$C,2,FALSE) -> 2473500 | Y13: =W13*VLOOKUP("CLF",'Tipos de Cambio'!$B:$C,2,FALSE) -> 59.364 | Z13: =W13*VLOOKUP("COP",'Tipos de Cambio'!$B:$C,2,FALSE) -> 10388700 | AA13: =W13*VLOOKUP("MXN",'Tipos de Cambio'!$B:$C,2,FALSE) -> 45759.75 | AB13: =W13*VLOOKUP("PEN",'Tipos de Cambio'!$B:$C,2,FALSE) -> 9399.3
... A32: ECG-031 | B32: Performance | C32: Analista de Implementación GA4/GTM/Looker | D32: Servicio | E32: Tier 2: Especializado | F32: 1300 | G32: 200 | H32: 100 | I32: 50 | J32: 150 | K32: 0 | L32: 49 | M32: =(F32 + G32 + H32 + I32 + J32 + K32 + L32) -> 1849 | N32: =M32/Datos!$O$3 -> 10.272222 | O32: =N32*Datos!$O$3 -> 1849 | P32: =N32*(1+VLOOKUP(E32,'Tier Datos'!$A$2:$B$5,2,FALSE)) -> 13.353889 | Q32: =IFERROR(VLOOKUP(E32,'Tier Datos'!$A$2:$B$5,2,FALSE),"") -> 0.3 | R32: =P32*VLOOKUP("CLP",'Tipos de Cambio'!$B:$C,2,FALSE) -> 13353.889 | S32: =P32*VLOOKUP("CLF",'Tipos de Cambio'!$B:$C,2,FALSE) -> 0.32049333 | T32: =P32*VLOOKUP("COP",'Tipos de Cambio'!$B:$C,2,FALSE) -> 56086.333 | U32: =P32*VLOOKUP("MXN",'Tipos de Cambio'!$B:$C,2,FALSE) -> 247.04694 | V32: =P32*VLOOKUP("PEN",'Tipos de Cambio'!$B:$C,2,FALSE) -> 50.744778 | W32: =P32*Datos!$O$3 -> 2403.7 | X32: =W32*VLOOKUP("CLP",'Tipos de Cambio'!$B:$C,2,FALSE) -> 2403700 | Y32: =W32*VLOOKUP("CLF",'Tipos de Cambio'!$B:$C,2,FALSE) -> 57.6888 | Z32: =W32*VLOOKUP("COP",'Tipos de Cambio'!$B:$C,2,FALSE) -> 10095540 | AA32: =W32*VLOOKUP("MXN",'Tipos de Cambio'!$B:$C,2,FALSE) -> 44468.45 | AB32: =W32*VLOOKUP("PEN",'Tipos de Cambio'!$B:$C,2,FALSE) -> 9134.06
A33: ECG-032 | B33: Consultoria | C33: Consultor HubSpot Premium | D33: Servicio | E33: Tier 4: IP Propietaria | F33: 23140 | G33: 0 | H33: 0 | I33: 0 | J33: 0 | K33: 0 | M33: =(F33 + G33 + H33 + I33 + J33 + K33 + L33) -> 23140 | N33: =M33/Datos!$O$3 -> 128.55556 | O33: =N33*Datos!$O$3 -> 23140 | P33: =N33*(1+VLOOKUP(E33,'Tier Datos'!$A$2:$B$5,2,FALSE)) -> 205.68889 | Q33: =IFERROR(VLOOKUP(E33,'Tier Datos'!$A$2:$B$5,2,FALSE),"") -> 0.6 | R33: =P33*VLOOKUP("CLP",'Tipos de Cambio'!$B:$C,2,FALSE) -> 205688.89 | S33: =P33*VLOOKUP("CLF",'Tipos de Cambio'!$B:$C,2,FALSE) -> 4.9365333 | T33: =P33*VLOOKUP("COP",'Tipos de Cambio'!$B:$C,2,FALSE) -> 863893.33 | U33: =P33*VLOOKUP("MXN",'Tipos de Cambio'!$B:$C,2,FALSE) -> 3805.2444 | V33: =P33*VLOOKUP("PEN",'Tipos de Cambio'!$B:$C,2,FALSE) -> 781.61778 | W33: =P33*Datos!$O$3 -> 37024 | X33: =W33*VLOOKUP("CLP",'Tipos de Cambio'!$B:$C,2,FALSE) -> 37024000 | Y33: =W33*VLOOKUP("CLF",'Tipos de Cambio'!$B:$C,2,FALSE) -> 888.576 | Z33: =W33*VLOOKUP("COP",'Tipos de Cambio'!$B:$C,2,FALSE) -> 155500800 | AA33: =W33*VLOOKUP("MXN",'Tipos de Cambio'!$B:$C,2,FALSE) -> 684944 | AB33: =W33*VLOOKUP("PEN",'Tipos de Cambio'!$B:$C,2,FALSE) -> 140691.2
A34: ECG-033 | B34: Consultoria | D34: Servicio | O34: =N34*Datos!$O$3 -> 0 | Q34: =IFERROR(VLOOKUP(E34,'Tier Datos'!$A$2:$B$5,2,FALSE),"") | R34: =P34*VLOOKUP("CLP",'Tipos de Cambio'!$B:$C,2,FALSE) -> 0 | S34: =P34*VLOOKUP("CLF",'Tipos de Cambio'!$B:$C,2,FALSE) -> 0 | T34: =P34*VLOOKUP("COP",'Tipos de Cambio'!$B:$C,2,FALSE) -> 0 | U34: =P34*VLOOKUP("MXN",'Tipos de Cambio'!$B:$C,2,FALSE) -> 0 | V34: =P34*VLOOKUP("PEN",'Tipos de Cambio'!$B:$C,2,FALSE) -> 0 | W34: =P34*Datos!$O$3 -> 0 | X34: =W34*VLOOKUP("CLP",'Tipos de Cambio'!$B:$C,2,FALSE) -> 0 | Y34: =W34*VLOOKUP("CLF",'Tipos de Cambio'!$B:$C,2,FALSE) -> 0 | Z34: =W34*VLOOKUP("COP",'Tipos de Cambio'!$B:$C,2,FALSE) -> 0 | AA34: =W34*VLOOKUP("MXN",'Tipos de Cambio'!$B:$C,2,FALSE) -> 0 | AB34: =W34*VLOOKUP("PEN",'Tipos de Cambio'!$B:$C,2,FALSE) -> 0
A35: ECG-034 | B35: Performance | D35: Servicio | O35: =N35*Datos!$O$3 -> 0 | Q35: =IFERROR(VLOOKUP(E35,'Tier Datos'!$A$2:$B$5,2,FALSE),"") | R35: =P35*VLOOKUP("CLP",'Tipos de Cambio'!$B:$C,2,FALSE) -> 0 | S35: =P35*VLOOKUP("CLF",'Tipos de Cambio'!$B:$C,2,FALSE) -> 0 | T35: =P35*VLOOKUP("COP",'Tipos de Cambio'!$B:$C,2,FALSE) -> 0 | U35: =P35*VLOOKUP("MXN",'Tipos de Cambio'!$B:$C,2,FALSE) -> 0 | V35: =P35*VLOOKUP("PEN",'Tipos de Cambio'!$B:$C,2,FALSE) -> 0 | W35: =P35*Datos!$O$3 -> 0 | X35: =W35*VLOOKUP("CLP",'Tipos de Cambio'!$B:$C,2,FALSE) -> 0 | Y35: =W35*VLOOKUP("CLF",'Tipos de Cambio'!$B:$C,2,FALSE) -> 0 | Z35: =W35*VLOOKUP("COP",'Tipos de Cambio'!$B:$C,2,FALSE) -> 0 | AA35: =W35*VLOOKUP("MXN",'Tipos de Cambio'!$B:$C,2,FALSE) -> 0 | AB35: =W35*VLOOKUP("PEN",'Tipos de Cambio'!$B:$C,2,FALSE) -> 0
A36: ECG-035 | B36: Performance | D36: Servicio | O36: =N36*Datos!$O$3 -> 0 | Q36: =IFERROR(VLOOKUP(E36,'Tier Datos'!$A$2:$B$5,2,FALSE),"") | R36: =P36*VLOOKUP("CLP",'Tipos de Cambio'!$B:$C,2,FALSE) -> 0 | S36: =P36*VLOOKUP("CLF",'Tipos de Cambio'!$B:$C,2,FALSE) -> 0 | T36: =P36*VLOOKUP("COP",'Tipos de Cambio'!$B:$C,2,FALSE) -> 0 | U36: =P36*VLOOKUP("MXN",'Tipos de Cambio'!$B:$C,2,FALSE) -> 0 | V36: =P36*VLOOKUP("PEN",'Tipos de Cambio'!$B:$C,2,FALSE) -> 0 | W36: =P36*Datos!$O$3 -> 0 | X36: =W36*VLOOKUP("CLP",'Tipos de Cambio'!$B:$C,2,FALSE) -> 0 | Y36: =W36*VLOOKUP("CLF",'Tipos de Cambio'!$B:$C,2,FALSE) -> 0 | Z36: =W36*VLOOKUP("COP",'Tipos de Cambio'!$B:$C,2,FALSE) -> 0 | AA36: =W36*VLOOKUP("MXN",'Tipos de Cambio'!$B:$C,2,FALSE) -> 0 | AB36: =W36*VLOOKUP("PEN",'Tipos de Cambio'!$B:$C,2,FALSE) -> 0
A37: ECG-036 | B37: Performance | D37: Servicio | O37: =N37*Datos!$O$3 -> 0 | Q37: =IFERROR(VLOOKUP(E37,'Tier Datos'!$A$2:$B$5,2,FALSE),"") | R37: =P37*VLOOKUP("CLP",'Tipos de Cambio'!$B:$C,2,FALSE) -> 0 | S37: =P37*VLOOKUP("CLF",'Tipos de Cambio'!$B:$C,2,FALSE) -> 0 | T37: =P37*VLOOKUP("COP",'Tipos de Cambio'!$B:$C,2,FALSE) -> 0 | U37: =P37*VLOOKUP("MXN",'Tipos de Cambio'!$B:$C,2,FALSE) -> 0 | V37: =P37*VLOOKUP("PEN",'Tipos de Cambio'!$B:$C,2,FALSE) -> 0 | W37: =P37*Datos!$O$3 -> 0 | X37: =W37*VLOOKUP("CLP",'Tipos de Cambio'!$B:$C,2,FALSE) -> 0 | Y37: =W37*VLOOKUP("CLF",'Tipos de Cambio'!$B:$C,2,FALSE) -> 0 | Z37: =W37*VLOOKUP("COP",'Tipos de Cambio'!$B:$C,2,FALSE) -> 0 | AA37: =W37*VLOOKUP("MXN",'Tipos de Cambio'!$B:$C,2,FALSE) -> 0 | AB37: =W37*VLOOKUP("PEN",'Tipos de Cambio'!$B:$C,2,FALSE) -> 0
A38: ECG-037 | B38: Performance | D38: Servicio | O38: =N38*Datos!$O$3 -> 0 | Q38: =IFERROR(VLOOKUP(E38,'Tier Datos'!$A$2:$B$5,2,FALSE),"") | R38: =P38*VLOOKUP("CLP",'Tipos de Cambio'!$B:$C,2,FALSE) -> 0 | S38: =P38*VLOOKUP("CLF",'Tipos de Cambio'!$B:$C,2,FALSE) -> 0 | T38: =P38*VLOOKUP("COP",'Tipos de Cambio'!$B:$C,2,FALSE) -> 0 | U38: =P38*VLOOKUP("MXN",'Tipos de Cambio'!$B:$C,2,FALSE) -> 0 | V38: =P38*VLOOKUP("PEN",'Tipos de Cambio'!$B:$C,2,FALSE) -> 0 | X38: =W38*VLOOKUP("CLP",'Tipos de Cambio'!$B:$C,2,FALSE) -> 0 | Y38: =W38*VLOOKUP("CLF",'Tipos de Cambio'!$B:$C,2,FALSE) -> 0 | Z38: =W38*VLOOKUP("COP",'Tipos de Cambio'!$B:$C,2,FALSE) -> 0 | AA38: =W38*VLOOKUP("MXN",'Tipos de Cambio'!$B:$C,2,FALSE) -> 0 | AB38: =W38*VLOOKUP("PEN",'Tipos de Cambio'!$B:$C,2,FALSE) -> 0
A39: ECG-038 | B39: Performance | D39: Servicio | O39: =N39*Datos!$O$3 -> 0 | Q39: =IFERROR(VLOOKUP(E39,'Tier Datos'!$A$2:$B$5,2,FALSE),"") | R39: =P39*VLOOKUP("CLP",'Tipos de Cambio'!$B:$C,2,FALSE) -> 0 | S39: =P39*VLOOKUP("CLF",'Tipos de Cambio'!$B:$C,2,FALSE) -> 0 | T39: =P39*VLOOKUP("COP",'Tipos de Cambio'!$B:$C,2,FALSE) -> 0 | U39: =P39*VLOOKUP("MXN",'Tipos de Cambio'!$B:$C,2,FALSE) -> 0 | V39: =P39*VLOOKUP("PEN",'Tipos de Cambio'!$B:$C,2,FALSE) -> 0 | X39: =W39*VLOOKUP("CLP",'Tipos de Cambio'!$B:$C,2,FALSE) -> 0 | Y39: =W39*VLOOKUP("CLF",'Tipos de Cambio'!$B:$C,2,FALSE) -> 0 | Z39: =W39*VLOOKUP("COP",'Tipos de Cambio'!$B:$C,2,FALSE) -> 0 | AA39: =W39*VLOOKUP("MXN",'Tipos de Cambio'!$B:$C,2,FALSE) -> 0 | AB39: =W39*VLOOKUP("PEN",'Tipos de Cambio'!$B:$C,2,FALSE) -> 0
A40: ECG-039 | B40: Performance | D40: Servicio | O40: =N40*Datos!$O$3 -> 0 | Q40: =IFERROR(VLOOKUP(E40,'Tier Datos'!$A$2:$B$5,2,FALSE),"") | R40: =P40*VLOOKUP("CLP",'Tipos de Cambio'!$B:$C,2,FALSE) -> 0 | S40: =P40*VLOOKUP("CLF",'Tipos de Cambio'!$B:$C,2,FALSE) -> 0 | T40: =P40*VLOOKUP("COP",'Tipos de Cambio'!$B:$C,2,FALSE) -> 0 | U40: =P40*VLOOKUP("MXN",'Tipos de Cambio'!$B:$C,2,FALSE) -> 0 | V40: =P40*VLOOKUP("PEN",'Tipos de Cambio'!$B:$C,2,FALSE) -> 0 | X40: =W40*VLOOKUP("CLP",'Tipos de Cambio'!$B:$C,2,FALSE) -> 0 | Y40: =W40*VLOOKUP("CLF",'Tipos de Cambio'!$B:$C,2,FALSE) -> 0 | Z40: =W40*VLOOKUP("COP",'Tipos de Cambio'!$B:$C,2,FALSE) -> 0 | AA40: =W40*VLOOKUP("MXN",'Tipos de Cambio'!$B:$C,2,FALSE) -> 0 | AB40: =W40*VLOOKUP("PEN",'Tipos de Cambio'!$B:$C,2,FALSE) -> 0
A41: ECG-040 | B41: Performance | D41: Servicio | O41: =N41*Datos!$O$3 -> 0 | Q41: =IFERROR(VLOOKUP(E41,'Tier Datos'!$A$2:$B$5,2,FALSE),"") | R41: =P41*VLOOKUP("CLP",'Tipos de Cambio'!$B:$C,2,FALSE) -> 0 | S41: =P41*VLOOKUP("CLF",'Tipos de Cambio'!$B:$C,2,FALSE) -> 0 | T41: =P41*VLOOKUP("COP",'Tipos de Cambio'!$B:$C,2,FALSE) -> 0 | U41: =P41*VLOOKUP("MXN",'Tipos de Cambio'!$B:$C,2,FALSE) -> 0 | V41: =P41*VLOOKUP("PEN",'Tipos de Cambio'!$B:$C,2,FALSE) -> 0 | X41: =W41*VLOOKUP("CLP",'Tipos de Cambio'!$B:$C,2,FALSE) -> 0 | Y41: =W41*VLOOKUP("CLF",'Tipos de Cambio'!$B:$C,2,FALSE) -> 0 | Z41: =W41*VLOOKUP("COP",'Tipos de Cambio'!$B:$C,2,FALSE) -> 0 | AA41: =W41*VLOOKUP("MXN",'Tipos de Cambio'!$B:$C,2,FALSE) -> 0 | AB41: =W41*VLOOKUP("PEN",'Tipos de Cambio'!$B:$C,2,FALSE) -> 0
A42: ECG-041 | B42: Performance | D42: Servicio | O42: =N42*Datos!$O$3 -> 0 | Q42: =IFERROR(VLOOKUP(E42,'Tier Datos'!$A$2:$B$5,2,FALSE),"") | R42: =P42*VLOOKUP("CLP",'Tipos de Cambio'!$B:$C,2,FALSE) -> 0 | S42: =P42*VLOOKUP("CLF",'Tipos de Cambio'!$B:$C,2,FALSE) -> 0 | T42: =P42*VLOOKUP("COP",'Tipos de Cambio'!$B:$C,2,FALSE) -> 0 | U42: =P42*VLOOKUP("MXN",'Tipos de Cambio'!$B:$C,2,FALSE) -> 0 | V42: =P42*VLOOKUP("PEN",'Tipos de Cambio'!$B:$C,2,FALSE) -> 0 | X42: =W42*VLOOKUP("CLP",'Tipos de Cambio'!$B:$C,2,FALSE) -> 0 | Y42: =W42*VLOOKUP("CLF",'Tipos de Cambio'!$B:$C,2,FALSE) -> 0 | Z42: =W42*VLOOKUP("COP",'Tipos de Cambio'!$B:$C,2,FALSE) -> 0 | AA42: =W42*VLOOKUP("MXN",'Tipos de Cambio'!$B:$C,2,FALSE) -> 0 | AB42: =W42*VLOOKUP("PEN",'Tipos de Cambio'!$B:$C,2,FALSE) -> 0
A43: ECG-042 | B43: Performance | D43: Servicio | O43: =N43*Datos!$O$3 -> 0 | Q43: =IFERROR(VLOOKUP(E43,'Tier Datos'!$A$2:$B$5,2,FALSE),"") | R43: =P43*VLOOKUP("CLP",'Tipos de Cambio'!$B:$C,2,FALSE) -> 0 | S43: =P43*VLOOKUP("CLF",'Tipos de Cambio'!$B:$C,2,FALSE) -> 0 | T43: =P43*VLOOKUP("COP",'Tipos de Cambio'!$B:$C,2,FALSE) -> 0 | U43: =P43*VLOOKUP("MXN",'Tipos de Cambio'!$B:$C,2,FALSE) -> 0 | V43: =P43*VLOOKUP("PEN",'Tipos de Cambio'!$B:$C,2,FALSE) -> 0 | X43: =W43*VLOOKUP("CLP",'Tipos de Cambio'!$B:$C,2,FALSE) -> 0 | Y43: =W43*VLOOKUP("CLF",'Tipos de Cambio'!$B:$C,2,FALSE) -> 0 | Z43: =W43*VLOOKUP("COP",'Tipos de Cambio'!$B:$C,2,FALSE) -> 0 | AA43: =W43*VLOOKUP("MXN",'Tipos de Cambio'!$B:$C,2,FALSE) -> 0 | AB43: =W43*VLOOKUP("PEN",'Tipos de Cambio'!$B:$C,2,FALSE) -> 0
A44: ECG-043 | B44: Performance | D44: Servicio | O44: =N44*Datos!$O$3 -> 0 | Q44: =IFERROR(VLOOKUP(E44,'Tier Datos'!$A$2:$B$5,2,FALSE),"") | R44: =P44*VLOOKUP("CLP",'Tipos de Cambio'!$B:$C,2,FALSE) -> 0 | S44: =P44*VLOOKUP("CLF",'Tipos de Cambio'!$B:$C,2,FALSE) -> 0 | T44: =P44*VLOOKUP("COP",'Tipos de Cambio'!$B:$C,2,FALSE) -> 0 | U44: =P44*VLOOKUP("MXN",'Tipos de Cambio'!$B:$C,2,FALSE) -> 0 | V44: =P44*VLOOKUP("PEN",'Tipos de Cambio'!$B:$C,2,FALSE) -> 0 | X44: =W44*VLOOKUP("CLP",'Tipos de Cambio'!$B:$C,2,FALSE) -> 0 | Y44: =W44*VLOOKUP("CLF",'Tipos de Cambio'!$B:$C,2,FALSE) -> 0 | Z44: =W44*VLOOKUP("COP",'Tipos de Cambio'!$B:$C,2,FALSE) -> 0 | AA44: =W44*VLOOKUP("MXN",'Tipos de Cambio'!$B:$C,2,FALSE) -> 0 | AB44: =W44*VLOOKUP("PEN",'Tipos de Cambio'!$B:$C,2,FALSE) -> 0
A45: ECG-044 | B45: Performance | D45: Servicio | O45: =N45*Datos!$O$3 -> 0 | Q45: =IFERROR(VLOOKUP(E45,'Tier Datos'!$A$2:$B$5,2,FALSE),"") | R45: =P45*VLOOKUP("CLP",'Tipos de Cambio'!$B:$C,2,FALSE) -> 0 | S45: =P45*VLOOKUP("CLF",'Tipos de Cambio'!$B:$C,2,FALSE) -> 0 | T45: =P45*VLOOKUP("COP",'Tipos de Cambio'!$B:$C,2,FALSE) -> 0 | U45: =P45*VLOOKUP("MXN",'Tipos de Cambio'!$B:$C,2,FALSE) -> 0 | V45: =P45*VLOOKUP("PEN",'Tipos de Cambio'!$B:$C,2,FALSE) -> 0 | X45: =W45*VLOOKUP("CLP",'Tipos de Cambio'!$B:$C,2,FALSE) -> 0 | Y45: =W45*VLOOKUP("CLF",'Tipos de Cambio'!$B:$C,2,FALSE) -> 0 | Z45: =W45*VLOOKUP("COP",'Tipos de Cambio'!$B:$C,2,FALSE) -> 0 | AA45: =W45*VLOOKUP("MXN",'Tipos de Cambio'!$B:$C,2,FALSE) -> 0 | AB45: =W45*VLOOKUP("PEN",'Tipos de Cambio'!$B:$C,2,FALSE) -> 0
A46: ECG-045 | B46: Performance | D46: Servicio | O46: =N46*Datos!$O$3 -> 0 | Q46: =IFERROR(VLOOKUP(E46,'Tier Datos'!$A$2:$B$5,2,FALSE),"") | R46: =P46*VLOOKUP("CLP",'Tipos de Cambio'!$B:$C,2,FALSE) -> 0 | S46: =P46*VLOOKUP("CLF",'Tipos de Cambio'!$B:$C,2,FALSE) -> 0 | T46: =P46*VLOOKUP("COP",'Tipos de Cambio'!$B:$C,2,FALSE) -> 0 | U46: =P46*VLOOKUP("MXN",'Tipos de Cambio'!$B:$C,2,FALSE) -> 0 | V46: =P46*VLOOKUP("PEN",'Tipos de Cambio'!$B:$C,2,FALSE) -> 0 | X46: =W46*VLOOKUP("CLP",'Tipos de Cambio'!$B:$C,2,FALSE) -> 0 | Y46: =W46*VLOOKUP("CLF",'Tipos de Cambio'!$B:$C,2,FALSE) -> 0 | Z46: =W46*VLOOKUP("COP",'Tipos de Cambio'!$B:$C,2,FALSE) -> 0 | AA46: =W46*VLOOKUP("MXN",'Tipos de Cambio'!$B:$C,2,FALSE) -> 0 | AB46: =W46*VLOOKUP("PEN",'Tipos de Cambio'!$B:$C,2,FALSE) -> 0
A47: ECG-046 | B47: Performance | D47: Servicio | O47: =N47*Datos!$O$3 -> 0 | Q47: =IFERROR(VLOOKUP(E47,'Tier Datos'!$A$2:$B$5,2,FALSE),"") | R47: =P47*VLOOKUP("CLP",'Tipos de Cambio'!$B:$C,2,FALSE) -> 0 | S47: =P47*VLOOKUP("CLF",'Tipos de Cambio'!$B:$C,2,FALSE) -> 0 | T47: =P47*VLOOKUP("COP",'Tipos de Cambio'!$B:$C,2,FALSE) -> 0 | U47: =P47*VLOOKUP("MXN",'Tipos de Cambio'!$B:$C,2,FALSE) -> 0 | V47: =P47*VLOOKUP("PEN",'Tipos de Cambio'!$B:$C,2,FALSE) -> 0 | X47: =W47*VLOOKUP("CLP",'Tipos de Cambio'!$B:$C,2,FALSE) -> 0 | Y47: =W47*VLOOKUP("CLF",'Tipos de Cambio'!$B:$C,2,FALSE) -> 0 | Z47: =W47*VLOOKUP("COP",'Tipos de Cambio'!$B:$C,2,FALSE) -> 0 | AA47: =W47*VLOOKUP("MXN",'Tipos de Cambio'!$B:$C,2,FALSE) -> 0 | AB47: =W47*VLOOKUP("PEN",'Tipos de Cambio'!$B:$C,2,FALSE) -> 0
A48: ECG-047 | B48: Performance | D48: Servicio | O48: =N48*Datos!$O$3 -> 0 | Q48: =IFERROR(VLOOKUP(E48,'Tier Datos'!$A$2:$B$5,2,FALSE),"") | R48: =P48*VLOOKUP("CLP",'Tipos de Cambio'!$B:$C,2,FALSE) -> 0 | S48: =P48*VLOOKUP("CLF",'Tipos de Cambio'!$B:$C,2,FALSE) -> 0 | T48: =P48*VLOOKUP("COP",'Tipos de Cambio'!$B:$C,2,FALSE) -> 0 | U48: =P48*VLOOKUP("MXN",'Tipos de Cambio'!$B:$C,2,FALSE) -> 0 | V48: =P48*VLOOKUP("PEN",'Tipos de Cambio'!$B:$C,2,FALSE) -> 0 | X48: =W48*VLOOKUP("CLP",'Tipos de Cambio'!$B:$C,2,FALSE) -> 0 | Y48: =W48*VLOOKUP("CLF",'Tipos de Cambio'!$B:$C,2,FALSE) -> 0 | Z48: =W48*VLOOKUP("COP",'Tipos de Cambio'!$B:$C,2,FALSE) -> 0 | AA48: =W48*VLOOKUP("MXN",'Tipos de Cambio'!$B:$C,2,FALSE) -> 0 | AB48: =W48*VLOOKUP("PEN",'Tipos de Cambio'!$B:$C,2,FALSE) -> 0
A49: ECG-048 | B49: Performance | D49: Servicio | O49: =N49*Datos!$O$3 -> 0 | Q49: =IFERROR(VLOOKUP(E49,'Tier Datos'!$A$2:$B$5,2,FALSE),"") | R49: =P49*VLOOKUP("CLP",'Tipos de Cambio'!$B:$C,2,FALSE) -> 0 | S49: =P49*VLOOKUP("CLF",'Tipos de Cambio'!$B:$C,2,FALSE) -> 0 | T49: =P49*VLOOKUP("COP",'Tipos de Cambio'!$B:$C,2,FALSE) -> 0 | U49: =P49*VLOOKUP("MXN",'Tipos de Cambio'!$B:$C,2,FALSE) -> 0 | V49: =P49*VLOOKUP("PEN",'Tipos de Cambio'!$B:$C,2,FALSE) -> 0 | X49: =W49*VLOOKUP("CLP",'Tipos de Cambio'!$B:$C,2,FALSE) -> 0 | Y49: =W49*VLOOKUP("CLF",'Tipos de Cambio'!$B:$C,2,FALSE) -> 0 | Z49: =W49*VLOOKUP("COP",'Tipos de Cambio'!$B:$C,2,FALSE) -> 0 | AA49: =W49*VLOOKUP("MXN",'Tipos de Cambio'!$B:$C,2,FALSE) -> 0 | AB49: =W49*VLOOKUP("PEN",'Tipos de Cambio'!$B:$C,2,FALSE) -> 0
... A57: ECG-056 | B57: Performance | D57: Servicio | O57: =N57*Datos!$O$3 -> 0 | Q57: =IFERROR(VLOOKUP(E57,'Tier Datos'!$A$2:$B$5,2,FALSE),"") | R57: =P57*VLOOKUP("CLP",'Tipos de Cambio'!$B:$C,2,FALSE) -> 0 | S57: =P57*VLOOKUP("CLF",'Tipos de Cambio'!$B:$C,2,FALSE) -> 0 | T57: =P57*VLOOKUP("COP",'Tipos de Cambio'!$B:$C,2,FALSE) -> 0 | U57: =P57*VLOOKUP("MXN",'Tipos de Cambio'!$B:$C,2,FALSE) -> 0 | V57: =P57*VLOOKUP("PEN",'Tipos de Cambio'!$B:$C,2,FALSE) -> 0 | X57: =W57*VLOOKUP("CLP",'Tipos de Cambio'!$B:$C,2,FALSE) -> 0 | Y57: =W57*VLOOKUP("CLF",'Tipos de Cambio'!$B:$C,2,FALSE) -> 0 | Z57: =W57*VLOOKUP("COP",'Tipos de Cambio'!$B:$C,2,FALSE) -> 0 | AA57: =W57*VLOOKUP("MXN",'Tipos de Cambio'!$B:$C,2,FALSE) -> 0 | AB57: =W57*VLOOKUP("PEN",'Tipos de Cambio'!$B:$C,2,FALSE) -> 0
A58: ECG-057 | B58: Performance | D58: Servicio | O58: =N58*Datos!$O$3 -> 0 | Q58: =IFERROR(VLOOKUP(E58,'Tier Datos'!$A$2:$B$5,2,FALSE),"") | R58: =P58*VLOOKUP("CLP",'Tipos de Cambio'!$B:$C,2,FALSE) -> 0 | S58: =P58*VLOOKUP("CLF",'Tipos de Cambio'!$B:$C,2,FALSE) -> 0 | T58: =P58*VLOOKUP("COP",'Tipos de Cambio'!$B:$C,2,FALSE) -> 0 | U58: =P58*VLOOKUP("MXN",'Tipos de Cambio'!$B:$C,2,FALSE) -> 0 | V58: =P58*VLOOKUP("PEN",'Tipos de Cambio'!$B:$C,2,FALSE) -> 0 | Z58: =W58*VLOOKUP("COP",'Tipos de Cambio'!$B:$C,2,FALSE) -> 0 | AA58: =W58*VLOOKUP("MXN",'Tipos de Cambio'!$B:$C,2,FALSE) -> 0 | AB58: =W58*VLOOKUP("PEN",'Tipos de Cambio'!$B:$C,2,FALSE) -> 0
A59: ECG-058 | B59: Performance | D59: Servicio | O59: =N59*Datos!$O$3 -> 0 | Q59: =IFERROR(VLOOKUP(E59,'Tier Datos'!$A$2:$B$5,2,FALSE),"") | R59: =P59*VLOOKUP("CLP",'Tipos de Cambio'!$B:$C,2,FALSE) -> 0 | S59: =P59*VLOOKUP("CLF",'Tipos de Cambio'!$B:$C,2,FALSE) -> 0 | T59: =P59*VLOOKUP("COP",'Tipos de Cambio'!$B:$C,2,FALSE) -> 0 | U59: =P59*VLOOKUP("MXN",'Tipos de Cambio'!$B:$C,2,FALSE) -> 0 | V59: =P59*VLOOKUP("PEN",'Tipos de Cambio'!$B:$C,2,FALSE) -> 0 | Z59: =W59*VLOOKUP("COP",'Tipos de Cambio'!$B:$C,2,FALSE) -> 0 | AA59: =W59*VLOOKUP("MXN",'Tipos de Cambio'!$B:$C,2,FALSE) -> 0 | AB59: =W59*VLOOKUP("PEN",'Tipos de Cambio'!$B:$C,2,FALSE) -> 0
A60: ECG-059 | B60: Performance | D60: Servicio | O60: =N60*Datos!$O$3 -> 0 | Q60: =IFERROR(VLOOKUP(E60,'Tier Datos'!$A$2:$B$5,2,FALSE),"") | R60: =P60*VLOOKUP("CLP",'Tipos de Cambio'!$B:$C,2,FALSE) -> 0 | S60: =P60*VLOOKUP("CLF",'Tipos de Cambio'!$B:$C,2,FALSE) -> 0 | T60: =P60*VLOOKUP("COP",'Tipos de Cambio'!$B:$C,2,FALSE) -> 0 | U60: =P60*VLOOKUP("MXN",'Tipos de Cambio'!$B:$C,2,FALSE) -> 0 | V60: =P60*VLOOKUP("PEN",'Tipos de Cambio'!$B:$C,2,FALSE) -> 0 | Z60: =W60*VLOOKUP("COP",'Tipos de Cambio'!$B:$C,2,FALSE) -> 0 | AA60: =W60*VLOOKUP("MXN",'Tipos de Cambio'!$B:$C,2,FALSE) -> 0 | AB60: =W60*VLOOKUP("PEN",'Tipos de Cambio'!$B:$C,2,FALSE) -> 0
A61: ECG-060 | B61: Performance | D61: Servicio | O61: =N61*Datos!$O$3 -> 0 | Q61: =IFERROR(VLOOKUP(E61,'Tier Datos'!$A$2:$B$5,2,FALSE),"") | R61: =P61*VLOOKUP("CLP",'Tipos de Cambio'!$B:$C,2,FALSE) -> 0 | S61: =P61*VLOOKUP("CLF",'Tipos de Cambio'!$B:$C,2,FALSE) -> 0 | T61: =P61*VLOOKUP("COP",'Tipos de Cambio'!$B:$C,2,FALSE) -> 0 | U61: =P61*VLOOKUP("MXN",'Tipos de Cambio'!$B:$C,2,FALSE) -> 0 | V61: =P61*VLOOKUP("PEN",'Tipos de Cambio'!$B:$C,2,FALSE) -> 0 | Z61: =W61*VLOOKUP("COP",'Tipos de Cambio'!$B:$C,2,FALSE) -> 0 | AA61: =W61*VLOOKUP("MXN",'Tipos de Cambio'!$B:$C,2,FALSE) -> 0 | AB61: =W61*VLOOKUP("PEN",'Tipos de Cambio'!$B:$C,2,FALSE) -> 0
A62: ECG-061 | B62: Performance | D62: Servicio | O62: =N62*Datos!$O$3 -> 0 | Q62: =IFERROR(VLOOKUP(E62,'Tier Datos'!$A$2:$B$5,2,FALSE),"") | R62: =P62*VLOOKUP("CLP",'Tipos de Cambio'!$B:$C,2,FALSE) -> 0 | S62: =P62*VLOOKUP("CLF",'Tipos de Cambio'!$B:$C,2,FALSE) -> 0 | T62: =P62*VLOOKUP("COP",'Tipos de Cambio'!$B:$C,2,FALSE) -> 0 | U62: =P62*VLOOKUP("MXN",'Tipos de Cambio'!$B:$C,2,FALSE) -> 0 | V62: =P62*VLOOKUP("PEN",'Tipos de Cambio'!$B:$C,2,FALSE) -> 0 | Z62: =W62*VLOOKUP("COP",'Tipos de Cambio'!$B:$C,2,FALSE) -> 0 | AA62: =W62*VLOOKUP("MXN",'Tipos de Cambio'!$B:$C,2,FALSE) -> 0 | AB62: =W62*VLOOKUP("PEN",'Tipos de Cambio'!$B:$C,2,FALSE) -> 0
A63: ECG-062 | B63: Performance | D63: Servicio | O63: =N63*Datos!$O$3 -> 0 | Q63: =IFERROR(VLOOKUP(E63,'Tier Datos'!$A$2:$B$5,2,FALSE),"") | R63: =P63*VLOOKUP("CLP",'Tipos de Cambio'!$B:$C,2,FALSE) -> 0 | S63: =P63*VLOOKUP("CLF",'Tipos de Cambio'!$B:$C,2,FALSE) -> 0 | T63: =P63*VLOOKUP("COP",'Tipos de Cambio'!$B:$C,2,FALSE) -> 0 | U63: =P63*VLOOKUP("MXN",'Tipos de Cambio'!$B:$C,2,FALSE) -> 0 | V63: =P63*VLOOKUP("PEN",'Tipos de Cambio'!$B:$C,2,FALSE) -> 0 | Z63: =W63*VLOOKUP("COP",'Tipos de Cambio'!$B:$C,2,FALSE) -> 0 | AA63: =W63*VLOOKUP("MXN",'Tipos de Cambio'!$B:$C,2,FALSE) -> 0 | AB63: =W63*VLOOKUP("PEN",'Tipos de Cambio'!$B:$C,2,FALSE) -> 0
A64: ECG-063 | B64: Performance | D64: Servicio | O64: =N64*Datos!$O$3 -> 0 | Q64: =IFERROR(VLOOKUP(E64,'Tier Datos'!$A$2:$B$5,2,FALSE),"") | R64: =P64*VLOOKUP("CLP",'Tipos de Cambio'!$B:$C,2,FALSE) -> 0 | S64: =P64*VLOOKUP("CLF",'Tipos de Cambio'!$B:$C,2,FALSE) -> 0 | T64: =P64*VLOOKUP("COP",'Tipos de Cambio'!$B:$C,2,FALSE) -> 0 | U64: =P64*VLOOKUP("MXN",'Tipos de Cambio'!$B:$C,2,FALSE) -> 0 | V64: =P64*VLOOKUP("PEN",'Tipos de Cambio'!$B:$C,2,FALSE) -> 0 | Z64: =W64*VLOOKUP("COP",'Tipos de Cambio'!$B:$C,2,FALSE) -> 0 | AB64: =W64*VLOOKUP("PEN",'Tipos de Cambio'!$B:$C,2,FALSE) -> 0
A65: ECG-064 | B65: Performance | D65: Servicio | Q65: =IFERROR(VLOOKUP(E65,'Tier Datos'!$A$2:$B$5,2,FALSE),"") | R65: =P65*VLOOKUP("CLP",'Tipos de Cambio'!$B:$C,2,FALSE) -> 0 | S65: =P65*VLOOKUP("CLF",'Tipos de Cambio'!$B:$C,2,FALSE) -> 0 | T65: =P65*VLOOKUP("COP",'Tipos de Cambio'!$B:$C,2,FALSE) -> 0 | U65: =P65*VLOOKUP("MXN",'Tipos de Cambio'!$B:$C,2,FALSE) -> 0 | V65: =P65*VLOOKUP("PEN",'Tipos de Cambio'!$B:$C,2,FALSE) -> 0 | Z65: =W65*VLOOKUP("COP",'Tipos de Cambio'!$B:$C,2,FALSE) -> 0 | AB65: =W65*VLOOKUP("PEN",'Tipos de Cambio'!$B:$C,2,FALSE) -> 0
A66: ECG-065 | B66: Performance | D66: Servicio | Q66: =IFERROR(VLOOKUP(E66,'Tier Datos'!$A$2:$B$5,2,FALSE),"") | Z66: =W66*VLOOKUP("COP",'Tipos de Cambio'!$B:$C,2,FALSE) -> 0 | AB66: =W66*VLOOKUP("PEN",'Tipos de Cambio'!$B:$C,2,FALSE) -> 0
A67: ECG-066 | B67: Performance | D67: Servicio | Q67: =IFERROR(VLOOKUP(E67,'Tier Datos'!$A$2:$B$5,2,FALSE),"") | Z67: =W67*VLOOKUP("COP",'Tipos de Cambio'!$B:$C,2,FALSE) -> 0 | AB67: =W67*VLOOKUP("PEN",'Tipos de Cambio'!$B:$C,2,FALSE) -> 0
A68: ECG-067 | B68: Performance | D68: Servicio | Q68: =IFERROR(VLOOKUP(E68,'Tier Datos'!$A$2:$B$5,2,FALSE),"") | Z68: =W68*VLOOKUP("COP",'Tipos de Cambio'!$B:$C,2,FALSE) -> 0 | AB68: =W68*VLOOKUP("PEN",'Tipos de Cambio'!$B:$C,2,FALSE) -> 0
A69: ECG-068 | B69: Performance | D69: Servicio | Q69: =IFERROR(VLOOKUP(E69,'Tier Datos'!$A$2:$B$5,2,FALSE),"") | Z69: =W69*VLOOKUP("COP",'Tipos de Cambio'!$B:$C,2,FALSE) -> 0 | AB69: =W69*VLOOKUP("PEN",'Tipos de Cambio'!$B:$C,2,FALSE) -> 0
A70: ECG-069 | B70: Performance | D70: Servicio | Q70: =IFERROR(VLOOKUP(E70,'Tier Datos'!$A$2:$B$5,2,FALSE),"")
A71: ECG-070 | B71: Performance | D71: Servicio | Q71: =IFERROR(VLOOKUP(E71,'Tier Datos'!$A$2:$B$5,2,FALSE),"")
A72: ECG-071 | B72: Performance | D72: Servicio | Q72: =IFERROR(VLOOKUP(E72,'Tier Datos'!$A$2:$B$5,2,FALSE),"")
A73: ECG-072 | B73: Performance | D73: Servicio | Q73: =IFERROR(VLOOKUP(E73,'Tier Datos'!$A$2:$B$5,2,FALSE),"")
A74: ECG-073 | B74: Performance | D74: Servicio | Q74: =IFERROR(VLOOKUP(E74,'Tier Datos'!$A$2:$B$5,2,FALSE),"")
A75: ECG-074 | B75: Performance | D75: Servicio | Q75: =IFERROR(VLOOKUP(E75,'Tier Datos'!$A$2:$B$5,2,FALSE),"")
A76: ECG-075 | B76: Performance | D76: Servicio | Q76: =IFERROR(VLOOKUP(E76,'Tier Datos'!$A$2:$B$5,2,FALSE),"")
A77: ECG-076 | B77: Performance | D77: Servicio | Q77: =IFERROR(VLOOKUP(E77,'Tier Datos'!$A$2:$B$5,2,FALSE),"")
A78: ECG-077 | B78: Performance | D78: Servicio | Q78: =IFERROR(VLOOKUP(E78,'Tier Datos'!$A$2:$B$5,2,FALSE),"")
A79: ECG-078 | B79: Performance | D79: Servicio | Q79: =IFERROR(VLOOKUP(E79,'Tier Datos'!$A$2:$B$5,2,FALSE),"")
A80: ECG-079 | B80: Performance | D80: Servicio | Q80: =IFERROR(VLOOKUP(E80,'Tier Datos'!$A$2:$B$5,2,FALSE),"")
A81: ECG-080 | B81: Performance | D81: Servicio | Q81: =IFERROR(VLOOKUP(E81,'Tier Datos'!$A$2:$B$5,2,FALSE),"")
A82: ECG-081 | D82: Servicio | Q82: =IFERROR(VLOOKUP(E82,'Tier Datos'!$A$2:$B$5,2,FALSE),"")
A83: ECG-082 | Q83: =IFERROR(VLOOKUP(E83,'Tier Datos'!$A$2:$B$5,2,FALSE),"")
A84: ECG-083 | Q84: =IFERROR(VLOOKUP(E84,'Tier Datos'!$A$2:$B$5,2,FALSE),"")
A85: ECG-084 | Q85: =IFERROR(VLOOKUP(E85,'Tier Datos'!$A$2:$B$5,2,FALSE),"")
A86: ECG-085 | Q86: =IFERROR(VLOOKUP(E86,'Tier Datos'!$A$2:$B$5,2,FALSE),"")
A87: ECG-086 | Q87: =IFERROR(VLOOKUP(E87,'Tier Datos'!$A$2:$B$5,2,FALSE),"")

Sheet Precios Servicios
A1: SKU | B1: Categoría | C1: Nombre del Servicio | D1: Unidad | E1: Tipo de Servicio | F1: Modelo Comercial | G1: Tier | H1: Costo Interno (USD) | I1: Margen Agencia (%) | J1: Precio Final (USD) | K1: Precio Final (CLP) | L1: Precio Final (CLF) | M1: Precio Final (COP) | N1: Precio Final (MXN) | O1: Precio Final (PEN) | P1: Descripción breve / Alcance | Q1: Duración estimada | R1: Unidad / Brand | S1: Comentarios
A2: EFG-001 | B2: Implementaciones MarTech | C2: Onboarding HubSpot Marketing Pro | D2: Proyecto | E2: Proyecto / Implementación | F2: On-Demand | G2: Tier 4 | H2: ='Estructura de Servicios'!I9 -> 1119.3222 | I2: =IFERROR( VLOOKUP(G2,'Tier Servicios'!$A:$C,2,FALSE), "" ) -> 0.55 | J2: =IFERROR( ROUNDUP( H2 * ( 1 + VLOOKUP(G2,'Tier Servicios'!$A:$C,2,FALSE) + VLOOKUP(F2,'Modelo comercial'!$A:$C,2,FALSE) ), -1), "Verificar tier/modelo") -> 1850 | K2: =IFERROR(J2*VLOOKUP("CLP",'Tipos de Cambio'!$B:$C,2,FALSE),"") -> 1850000 | L2: =IFERROR(J2*VLOOKUP("CLF",'Tipos de Cambio'!$B:$C,2,FALSE),"") -> 44.4 | M2: =IFERROR(J2*VLOOKUP("COP",'Tipos de Cambio'!$B:$C,2,FALSE),"") -> 7770000 | N2: =IFERROR(J2*VLOOKUP("MXN",'Tipos de Cambio'!$B:$C,2,FALSE),"") -> 34225 | O2: =IFERROR(J2*VLOOKUP("PEN",'Tipos de Cambio'!$B:$C,2,FALSE),"") -> 7030 | P2: Setup completo del portal Marketing Pro: automatizaciones, dashboards y training. | Q2: 4–6 semanas | R2: Wave | S2: Incluye 1 capacitación y 1 QA final
A3: EFG-002 | B3: Creatividad y Contenido | C3: Servicio de Diseño Digital Full Funnel | D3: Proyecto | E3: Retainer | F3: On-Demand | G3: Tier 2 | H3: ='Estructura de Servicios'!I19 -> 4900.25 | I3: =IFERROR( VLOOKUP(G3,'Tier Servicios'!$A:$C,2,FALSE), "" ) -> 0.45 | J3: =IFERROR( ROUNDUP( H3 * ( 1 + VLOOKUP(G3,'Tier Servicios'!$A:$C,2,FALSE) + VLOOKUP(F3,'Modelo comercial'!$A:$C,2,FALSE) ), -1), "Verificar tier/modelo") -> 7600 | K3: =IFERROR(J3*VLOOKUP("CLP",'Tipos de Cambio'!$B:$C,2,FALSE),"") -> 7600000 | L3: =IFERROR(J3*VLOOKUP("CLF",'Tipos de Cambio'!$B:$C,2,FALSE),"") -> 182.4 | M3: =IFERROR(J3*VLOOKUP("COP",'Tipos de Cambio'!$B:$C,2,FALSE),"") -> 31920000 | N3: =IFERROR(J3*VLOOKUP("MXN",'Tipos de Cambio'!$B:$C,2,FALSE),"") -> 140600 | O3: =IFERROR(J3*VLOOKUP("PEN",'Tipos de Cambio'!$B:$C,2,FALSE),"") -> 28880 | P3: Servicio de Diseño Full-time para empresas | Q3: Mensual | R3: Globe | S3: Incluye 3 ronda de ajustes
A4: EFG-003 | B4: Performance y Paid Media | C4: Servicio de Performance y Paid Ads | D4: Mes | E4: Retainer | F4: On-Going | G4: Tier 2 | H4: ='Estructura de Servicios'!I25 -> 1251.5 | I4: =IFERROR( VLOOKUP(G4,'Tier Servicios'!$A:$C,2,FALSE), "" ) -> 0.45 | J4: =IFERROR( ROUNDUP( H4 * ( 1 + VLOOKUP(G4,'Tier Servicios'!$A:$C,2,FALSE) + VLOOKUP(F4,'Modelo comercial'!$A:$C,2,FALSE) ), -1), "Verificar tier/modelo") -> 1820 | K4: =IFERROR(J4*VLOOKUP("CLP",'Tipos de Cambio'!$B:$C,2,FALSE),"") -> 1820000 | L4: =IFERROR(J4*VLOOKUP("CLF",'Tipos de Cambio'!$B:$C,2,FALSE),"") -> 43.68 | M4: =IFERROR(J4*VLOOKUP("COP",'Tipos de Cambio'!$B:$C,2,FALSE),"") -> 7644000 | N4: =IFERROR(J4*VLOOKUP("MXN",'Tipos de Cambio'!$B:$C,2,FALSE),"") -> 33670 | O4: =IFERROR(J4*VLOOKUP("PEN",'Tipos de Cambio'!$B:$C,2,FALSE),"") -> 6916 | P4: Gestión integral de campañas + reporting mensual. | Q4: Mensual | R4: Wave | S4: Incluye optimización y dashboard
A5: EFG-004 | B5: Consultoría Estratégica | C5: Consultoría Go-To-Market Efeonce | D5: Proyecto | E5: Consultoría Estratégica | F5: On-Demand | G5: Tier 3 | H5: =SUMIF('Estructura de Servicios'!$A:$A,A5,'Estructura de Servicios'!$I:$I) -> 0 | I5: =IFERROR( VLOOKUP(G5,'Tier Servicios'!$A:$C,2,FALSE), "" ) -> 0.5 | J5: =IFERROR( ROUNDUP( H5 * ( 1 + VLOOKUP(G5,'Tier Servicios'!$A:$C,2,FALSE) + VLOOKUP(F5,'Modelo comercial'!$A:$C,2,FALSE) ), -1), "Verificar tier/modelo") -> 0 | K5: =IFERROR(J5*VLOOKUP("CLP",'Tipos de Cambio'!$B:$C,2,FALSE),"") -> 0 | L5: =IFERROR(J5*VLOOKUP("CLF",'Tipos de Cambio'!$B:$C,2,FALSE),"") -> 0 | M5: =IFERROR(J5*VLOOKUP("COP",'Tipos de Cambio'!$B:$C,2,FALSE),"") -> 0 | N5: =IFERROR(J5*VLOOKUP("MXN",'Tipos de Cambio'!$B:$C,2,FALSE),"") -> 0 | O5: =IFERROR(J5*VLOOKUP("PEN",'Tipos de Cambio'!$B:$C,2,FALSE),"") -> 0 | P5: Análisis, roadmap GTM y estructura comercial. | Q5: 2 semanas | R5: Efeonce | S5: Workshop remoto + entrega ejecutiva
A6: EFG-005 | B6: Automatización y CRM | C6: Implementación CRM Sales Hub | D6: Proyecto | E6: Proyecto / Implementación | F6: On-Demand | G6: Tier 3 | H6: =SUMIF('Estructura de Servicios'!$A:$A,A6,'Estructura de Servicios'!$I:$I) -> 0 | I6: =IFERROR( VLOOKUP(G6,'Tier Servicios'!$A:$C,2,FALSE), "" ) -> 0.5 | J6: =IFERROR( ROUNDUP( H6 * ( 1 + VLOOKUP(G6,'Tier Servicios'!$A:$C,2,FALSE) + VLOOKUP(F6,'Modelo comercial'!$A:$C,2,FALSE) ), -1), "Verificar tier/modelo") -> 0 | K6: =IFERROR(J6*VLOOKUP("CLP",'Tipos de Cambio'!$B:$C,2,FALSE),"") -> 0 | L6: =IFERROR(J6*VLOOKUP("CLF",'Tipos de Cambio'!$B:$C,2,FALSE),"") -> 0 | M6: =IFERROR(J6*VLOOKUP("COP",'Tipos de Cambio'!$B:$C,2,FALSE),"") -> 0 | N6: =IFERROR(J6*VLOOKUP("MXN",'Tipos de Cambio'!$B:$C,2,FALSE),"") -> 0 | O6: =IFERROR(J6*VLOOKUP("PEN",'Tipos de Cambio'!$B:$C,2,FALSE),"") -> 0 | P6: Implementación completa de Sales Hub Pro con pipelines y dashboards. | Q6: 4 semanas | R6: Wave | S6: Incluye capacitación de equipos
A7: EFG-006 | B7: AEO / SEO Técnico | C7: Auditoría Técnica AEO | D7: Proyecto | E7: Proyecto / Servicio Técnico | F7: On-Demand | G7: Tier 2 | H7: =SUMIF('Estructura de Servicios'!$A:$A,A7,'Estructura de Servicios'!$I:$I) -> 0 | I7: =IFERROR( VLOOKUP(G7,'Tier Servicios'!$A:$C,2,FALSE), "" ) -> 0.45 | J7: =IFERROR( ROUNDUP( H7 * ( 1 + VLOOKUP(G7,'Tier Servicios'!$A:$C,2,FALSE) + VLOOKUP(F7,'Modelo comercial'!$A:$C,2,FALSE) ), -1), "Verificar tier/modelo") -> 0 | K7: =IFERROR(J7*VLOOKUP("CLP",'Tipos de Cambio'!$B:$C,2,FALSE),"") -> 0 | L7: =IFERROR(J7*VLOOKUP("CLF",'Tipos de Cambio'!$B:$C,2,FALSE),"") -> 0 | M7: =IFERROR(J7*VLOOKUP("COP",'Tipos de Cambio'!$B:$C,2,FALSE),"") -> 0 | N7: =IFERROR(J7*VLOOKUP("MXN",'Tipos de Cambio'!$B:$C,2,FALSE),"") -> 0 | O7: =IFERROR(J7*VLOOKUP("PEN",'Tipos de Cambio'!$B:$C,2,FALSE),"") -> 0 | P7: Diagnóstico completo AEO + plan de acción técnico. | Q7: 2 semanas | R7: Wave | S7: Ideal previo a optimización
A8: EFG-007 | B8: Retainers Integrales | C8: Retainer Loop Marketing | D8: Mes | E8: Retainer | F8: On-Going | G8: Tier 3 | H8: =SUMIF('Estructura de Servicios'!$A:$A,A8,'Estructura de Servicios'!$I:$I) -> 0 | I8: =IFERROR( VLOOKUP(G8,'Tier Servicios'!$A:$C,2,FALSE), "" ) -> 0.5 | J8: =IFERROR( ROUNDUP( H8 * ( 1 + VLOOKUP(G8,'Tier Servicios'!$A:$C,2,FALSE) + VLOOKUP(F8,'Modelo comercial'!$A:$C,2,FALSE) ), -1), "Verificar tier/modelo") -> 0 | K8: =IFERROR(J8*VLOOKUP("CLP",'Tipos de Cambio'!$B:$C,2,FALSE),"") -> 0 | L8: =IFERROR(J8*VLOOKUP("CLF",'Tipos de Cambio'!$B:$C,2,FALSE),"") -> 0 | M8: =IFERROR(J8*VLOOKUP("COP",'Tipos de Cambio'!$B:$C,2,FALSE),"") -> 0 | N8: =IFERROR(J8*VLOOKUP("MXN",'Tipos de Cambio'!$B:$C,2,FALSE),"") -> 0 | O8: =IFERROR(J8*VLOOKUP("PEN",'Tipos de Cambio'!$B:$C,2,FALSE),"") -> 0 | P8: Retainer mensual de estrategia, contenido y performance. | Q8: Mensual | R8: Efeonce / Globe / Wave / Reach | S8: Full funnel con reporting mensual
A9: EFG-008 | H9: =SUMIF('Estructura de Servicios'!$A:$A,A9,'Estructura de Servicios'!$I:$I) -> 0 | I9: =IFERROR( VLOOKUP(G9,'Tier Servicios'!$A:$C,2,FALSE), "" ) | J9: =IFERROR( ROUNDUP( H9 * ( 1 + VLOOKUP(G9,'Tier Servicios'!$A:$C,2,FALSE) + VLOOKUP(F9,'Modelo comercial'!$A:$C,2,FALSE) ), -1), "Verificar tier/modelo") -> Verificar tier/modelo | K9: =IFERROR(J9*VLOOKUP("CLP",'Tipos de Cambio'!$B:$C,2,FALSE),"") | L9: =IFERROR(J9*VLOOKUP("CLF",'Tipos de Cambio'!$B:$C,2,FALSE),"") | M9: =IFERROR(J9*VLOOKUP("COP",'Tipos de Cambio'!$B:$C,2,FALSE),"") | N9: =IFERROR(J9*VLOOKUP("MXN",'Tipos de Cambio'!$B:$C,2,FALSE),"") | O9: =IFERROR(J9*VLOOKUP("PEN",'Tipos de Cambio'!$B:$C,2,FALSE),"")
A10: EFG-009 | H10: =SUMIF('Estructura de Servicios'!$A:$A,A10,'Estructura de Servicios'!$I:$I) -> 0 | I10: =IFERROR( VLOOKUP(G10,'Tier Servicios'!$A:$C,2,FALSE), "" ) | J10: =IFERROR( ROUNDUP( H10 * ( 1 + VLOOKUP(G10,'Tier Servicios'!$A:$C,2,FALSE) + VLOOKUP(F10,'Modelo comercial'!$A:$C,2,FALSE) ), -1), "Verificar tier/modelo") -> Verificar tier/modelo | K10: =IFERROR(J10*VLOOKUP("CLP",'Tipos de Cambio'!$B:$C,2,FALSE),"") | L10: =IFERROR(J10*VLOOKUP("CLF",'Tipos de Cambio'!$B:$C,2,FALSE),"") | M10: =IFERROR(J10*VLOOKUP("COP",'Tipos de Cambio'!$B:$C,2,FALSE),"") | N10: =IFERROR(J10*VLOOKUP("MXN",'Tipos de Cambio'!$B:$C,2,FALSE),"") | O10: =IFERROR(J10*VLOOKUP("PEN",'Tipos de Cambio'!$B:$C,2,FALSE),"")
A11: EFG-010 | H11: =SUMIF('Estructura de Servicios'!$A:$A,A11,'Estructura de Servicios'!$I:$I) -> 0 | I11: =IFERROR( VLOOKUP(G11,'Tier Servicios'!$A:$C,2,FALSE), "" ) | J11: =IFERROR( ROUNDUP( H11 * ( 1 + VLOOKUP(G11,'Tier Servicios'!$A:$C,2,FALSE) + VLOOKUP(F11,'Modelo comercial'!$A:$C,2,FALSE) ), -1), "Verificar tier/modelo") -> Verificar tier/modelo | K11: =IFERROR(J11*VLOOKUP("CLP",'Tipos de Cambio'!$B:$C,2,FALSE),"") | L11: =IFERROR(J11*VLOOKUP("CLF",'Tipos de Cambio'!$B:$C,2,FALSE),"") | M11: =IFERROR(J11*VLOOKUP("COP",'Tipos de Cambio'!$B:$C,2,FALSE),"") | N11: =IFERROR(J11*VLOOKUP("MXN",'Tipos de Cambio'!$B:$C,2,FALSE),"") | O11: =IFERROR(J11*VLOOKUP("PEN",'Tipos de Cambio'!$B:$C,2,FALSE),"")
A12: EFG-011 | H12: =SUMIF('Estructura de Servicios'!$A:$A,A12,'Estructura de Servicios'!$I:$I) -> 0 | I12: =IFERROR( VLOOKUP(G12,'Tier Servicios'!$A:$C,2,FALSE), "" ) | J12: =IFERROR( ROUNDUP( H12 * ( 1 + VLOOKUP(G12,'Tier Servicios'!$A:$C,2,FALSE) + VLOOKUP(F12,'Modelo comercial'!$A:$C,2,FALSE) ), -1), "Verificar tier/modelo") -> Verificar tier/modelo | K12: =IFERROR(J12*VLOOKUP("CLP",'Tipos de Cambio'!$B:$C,2,FALSE),"") | L12: =IFERROR(J12*VLOOKUP("CLF",'Tipos de Cambio'!$B:$C,2,FALSE),"") | M12: =IFERROR(J12*VLOOKUP("COP",'Tipos de Cambio'!$B:$C,2,FALSE),"") | N12: =IFERROR(J12*VLOOKUP("MXN",'Tipos de Cambio'!$B:$C,2,FALSE),"") | O12: =IFERROR(J12*VLOOKUP("PEN",'Tipos de Cambio'!$B:$C,2,FALSE),"")
A13: EFG-012 | H13: =SUMIF('Estructura de Servicios'!$A:$A,A13,'Estructura de Servicios'!$I:$I) -> 0 | I13: =IFERROR( VLOOKUP(G13,'Tier Servicios'!$A:$C,2,FALSE), "" ) | J13: =IFERROR( ROUNDUP( H13 * ( 1 + VLOOKUP(G13,'Tier Servicios'!$A:$C,2,FALSE) + VLOOKUP(F13,'Modelo comercial'!$A:$C,2,FALSE) ), -1), "Verificar tier/modelo") -> Verificar tier/modelo | K13: =IFERROR(J13*VLOOKUP("CLP",'Tipos de Cambio'!$B:$C,2,FALSE),"") | L13: =IFERROR(J13*VLOOKUP("CLF",'Tipos de Cambio'!$B:$C,2,FALSE),"") | M13: =IFERROR(J13*VLOOKUP("COP",'Tipos de Cambio'!$B:$C,2,FALSE),"") | N13: =IFERROR(J13*VLOOKUP("MXN",'Tipos de Cambio'!$B:$C,2,FALSE),"") | O13: =IFERROR(J13*VLOOKUP("PEN",'Tipos de Cambio'!$B:$C,2,FALSE),"")
A14: EFG-013 | H14: =SUMIF('Estructura de Servicios'!$A:$A,A14,'Estructura de Servicios'!$I:$I) -> 0 | I14: =IFERROR( VLOOKUP(G14,'Tier Servicios'!$A:$C,2,FALSE), "" ) | J14: =IFERROR( ROUNDUP( H14 * ( 1 + VLOOKUP(G14,'Tier Servicios'!$A:$C,2,FALSE) + VLOOKUP(F14,'Modelo comercial'!$A:$C,2,FALSE) ), -1), "Verificar tier/modelo") -> Verificar tier/modelo | K14: =IFERROR(J14*VLOOKUP("CLP",'Tipos de Cambio'!$B:$C,2,FALSE),"") | L14: =IFERROR(J14*VLOOKUP("CLF",'Tipos de Cambio'!$B:$C,2,FALSE),"") | M14: =IFERROR(J14*VLOOKUP("COP",'Tipos de Cambio'!$B:$C,2,FALSE),"") | N14: =IFERROR(J14*VLOOKUP("MXN",'Tipos de Cambio'!$B:$C,2,FALSE),"") | O14: =IFERROR(J14*VLOOKUP("PEN",'Tipos de Cambio'!$B:$C,2,FALSE),"")
A15: EFG-014 | H15: =SUMIF('Estructura de Servicios'!$A:$A,A15,'Estructura de Servicios'!$I:$I) -> 0 | I15: =IFERROR( VLOOKUP(G15,'Tier Servicios'!$A:$C,2,FALSE), "" ) | J15: =IFERROR( ROUNDUP( H15 * ( 1 + VLOOKUP(G15,'Tier Servicios'!$A:$C,2,FALSE) + VLOOKUP(F15,'Modelo comercial'!$A:$C,2,FALSE) ), -1), "Verificar tier/modelo") -> Verificar tier/modelo | K15: =IFERROR(J15*VLOOKUP("CLP",'Tipos de Cambio'!$B:$C,2,FALSE),"") | L15: =IFERROR(J15*VLOOKUP("CLF",'Tipos de Cambio'!$B:$C,2,FALSE),"") | M15: =IFERROR(J15*VLOOKUP("COP",'Tipos de Cambio'!$B:$C,2,FALSE),"") | N15: =IFERROR(J15*VLOOKUP("MXN",'Tipos de Cambio'!$B:$C,2,FALSE),"") | O15: =IFERROR(J15*VLOOKUP("PEN",'Tipos de Cambio'!$B:$C,2,FALSE),"")
A16: EFG-015 | H16: =SUMIF('Estructura de Servicios'!$A:$A,A16,'Estructura de Servicios'!$I:$I) -> 0 | I16: =IFERROR( VLOOKUP(G16,'Tier Servicios'!$A:$C,2,FALSE), "" ) | J16: =IFERROR( ROUNDUP( H16 * ( 1 + VLOOKUP(G16,'Tier Servicios'!$A:$C,2,FALSE) + VLOOKUP(F16,'Modelo comercial'!$A:$C,2,FALSE) ), -1), "Verificar tier/modelo") -> Verificar tier/modelo | K16: =IFERROR(J16*VLOOKUP("CLP",'Tipos de Cambio'!$B:$C,2,FALSE),"") | L16: =IFERROR(J16*VLOOKUP("CLF",'Tipos de Cambio'!$B:$C,2,FALSE),"") | M16: =IFERROR(J16*VLOOKUP("COP",'Tipos de Cambio'!$B:$C,2,FALSE),"") | N16: =IFERROR(J16*VLOOKUP("MXN",'Tipos de Cambio'!$B:$C,2,FALSE),"") | O16: =IFERROR(J16*VLOOKUP("PEN",'Tipos de Cambio'!$B:$C,2,FALSE),"")
A17: EFG-016 | H17: =SUMIF('Estructura de Servicios'!$A:$A,A17,'Estructura de Servicios'!$I:$I) -> 0 | I17: =IFERROR( VLOOKUP(G17,'Tier Servicios'!$A:$C,2,FALSE), "" ) | J17: =IFERROR( ROUNDUP( H17 * ( 1 + VLOOKUP(G17,'Tier Servicios'!$A:$C,2,FALSE) + VLOOKUP(F17,'Modelo comercial'!$A:$C,2,FALSE) ), -1), "Verificar tier/modelo") -> Verificar tier/modelo | K17: =IFERROR(J17*VLOOKUP("CLP",'Tipos de Cambio'!$B:$C,2,FALSE),"") | L17: =IFERROR(J17*VLOOKUP("CLF",'Tipos de Cambio'!$B:$C,2,FALSE),"") | M17: =IFERROR(J17*VLOOKUP("COP",'Tipos de Cambio'!$B:$C,2,FALSE),"") | N17: =IFERROR(J17*VLOOKUP("MXN",'Tipos de Cambio'!$B:$C,2,FALSE),"") | O17: =IFERROR(J17*VLOOKUP("PEN",'Tipos de Cambio'!$B:$C,2,FALSE),"")
A18: EFG-017 | H18: =SUMIF('Estructura de Servicios'!$A:$A,A18,'Estructura de Servicios'!$I:$I) -> 0 | I18: =IFERROR( VLOOKUP(G18,'Tier Servicios'!$A:$C,2,FALSE), "" ) | J18: =IFERROR( ROUNDUP( H18 * ( 1 + VLOOKUP(G18,'Tier Servicios'!$A:$C,2,FALSE) + VLOOKUP(F18,'Modelo comercial'!$A:$C,2,FALSE) ), -1), "Verificar tier/modelo") -> Verificar tier/modelo | K18: =IFERROR(J18*VLOOKUP("CLP",'Tipos de Cambio'!$B:$C,2,FALSE),"") | L18: =IFERROR(J18*VLOOKUP("CLF",'Tipos de Cambio'!$B:$C,2,FALSE),"") | M18: =IFERROR(J18*VLOOKUP("COP",'Tipos de Cambio'!$B:$C,2,FALSE),"") | N18: =IFERROR(J18*VLOOKUP("MXN",'Tipos de Cambio'!$B:$C,2,FALSE),"") | O18: =IFERROR(J18*VLOOKUP("PEN",'Tipos de Cambio'!$B:$C,2,FALSE),"")
A19: EFG-018 | H19: =SUMIF('Estructura de Servicios'!$A:$A,A19,'Estructura de Servicios'!$I:$I) -> 0 | I19: =IFERROR( VLOOKUP(G19,'Tier Servicios'!$A:$C,2,FALSE), "" ) | J19: =IFERROR( ROUNDUP( H19 * ( 1 + VLOOKUP(G19,'Tier Servicios'!$A:$C,2,FALSE) + VLOOKUP(F19,'Modelo comercial'!$A:$C,2,FALSE) ), -1), "Verificar tier/modelo") -> Verificar tier/modelo | K19: =IFERROR(J19*VLOOKUP("CLP",'Tipos de Cambio'!$B:$C,2,FALSE),"") | L19: =IFERROR(J19*VLOOKUP("CLF",'Tipos de Cambio'!$B:$C,2,FALSE),"") | M19: =IFERROR(J19*VLOOKUP("COP",'Tipos de Cambio'!$B:$C,2,FALSE),"") | N19: =IFERROR(J19*VLOOKUP("MXN",'Tipos de Cambio'!$B:$C,2,FALSE),"") | O19: =IFERROR(J19*VLOOKUP("PEN",'Tipos de Cambio'!$B:$C,2,FALSE),"")
A20: EFG-019 | H20: =SUMIF('Estructura de Servicios'!$A:$A,A20,'Estructura de Servicios'!$I:$I) -> 0 | I20: =IFERROR( VLOOKUP(G20,'Tier Servicios'!$A:$C,2,FALSE), "" ) | J20: =IFERROR( ROUNDUP( H20 * ( 1 + VLOOKUP(G20,'Tier Servicios'!$A:$C,2,FALSE) + VLOOKUP(F20,'Modelo comercial'!$A:$C,2,FALSE) ), -1), "Verificar tier/modelo") -> Verificar tier/modelo | K20: =IFERROR(J20*VLOOKUP("CLP",'Tipos de Cambio'!$B:$C,2,FALSE),"") | L20: =IFERROR(J20*VLOOKUP("CLF",'Tipos de Cambio'!$B:$C,2,FALSE),"") | M20: =IFERROR(J20*VLOOKUP("COP",'Tipos de Cambio'!$B:$C,2,FALSE),"") | N20: =IFERROR(J20*VLOOKUP("MXN",'Tipos de Cambio'!$B:$C,2,FALSE),"") | O20: =IFERROR(J20*VLOOKUP("PEN",'Tipos de Cambio'!$B:$C,2,FALSE),"")
... A35: EFG-034 | H35: =SUMIF('Estructura de Servicios'!$A:$A,A35,'Estructura de Servicios'!$I:$I) -> 0 | I35: =IFERROR( VLOOKUP(G35,'Tier Servicios'!$A:$C,2,FALSE), "" ) | J35: =IFERROR( ROUNDUP( H35 * ( 1 + VLOOKUP(G35,'Tier Servicios'!$A:$C,2,FALSE) + VLOOKUP(F35,'Modelo comercial'!$A:$C,2,FALSE) ), -1), "Verificar tier/modelo") -> Verificar tier/modelo | K35: =IFERROR(J35*VLOOKUP("CLP",'Tipos de Cambio'!$B:$C,2,FALSE),"") | L35: =IFERROR(J35*VLOOKUP("CLF",'Tipos de Cambio'!$B:$C,2,FALSE),"") | M35: =IFERROR(J35*VLOOKUP("COP",'Tipos de Cambio'!$B:$C,2,FALSE),"") | N35: =IFERROR(J35*VLOOKUP("MXN",'Tipos de Cambio'!$B:$C,2,FALSE),"") | O35: =IFERROR(J35*VLOOKUP("PEN",'Tipos de Cambio'!$B:$C,2,FALSE),"")
A36: EFG-035 | H36: =SUMIF('Estructura de Servicios'!$A:$A,A36,'Estructura de Servicios'!$I:$I) -> 0 | I36: =IFERROR( VLOOKUP(G36,'Tier Servicios'!$A:$C,2,FALSE), "" ) | K36: =IFERROR(J36*VLOOKUP("CLP",'Tipos de Cambio'!$B:$C,2,FALSE),"") -> 0 | L36: =IFERROR(J36*VLOOKUP("CLF",'Tipos de Cambio'!$B:$C,2,FALSE),"") -> 0 | M36: =IFERROR(J36*VLOOKUP("COP",'Tipos de Cambio'!$B:$C,2,FALSE),"") -> 0 | N36: =IFERROR(J36*VLOOKUP("MXN",'Tipos de Cambio'!$B:$C,2,FALSE),"") -> 0 | O36: =IFERROR(J36*VLOOKUP("PEN",'Tipos de Cambio'!$B:$C,2,FALSE),"") -> 0
A37: EFG-036 | H37: =SUMIF('Estructura de Servicios'!$A:$A,A37,'Estructura de Servicios'!$I:$I) -> 0 | I37: =IFERROR( VLOOKUP(G37,'Tier Servicios'!$A:$C,2,FALSE), "" ) | K37: =IFERROR(J37*VLOOKUP("CLP",'Tipos de Cambio'!$B:$C,2,FALSE),"") -> 0 | L37: =IFERROR(J37*VLOOKUP("CLF",'Tipos de Cambio'!$B:$C,2,FALSE),"") -> 0 | M37: =IFERROR(J37*VLOOKUP("COP",'Tipos de Cambio'!$B:$C,2,FALSE),"") -> 0 | N37: =IFERROR(J37*VLOOKUP("MXN",'Tipos de Cambio'!$B:$C,2,FALSE),"") -> 0 | O37: =IFERROR(J37*VLOOKUP("PEN",'Tipos de Cambio'!$B:$C,2,FALSE),"") -> 0
A38: EFG-037 | H38: =SUMIF('Estructura de Servicios'!$A:$A,A38,'Estructura de Servicios'!$I:$I) -> 0 | I38: =IFERROR( VLOOKUP(G38,'Tier Servicios'!$A:$C,2,FALSE), "" ) | K38: =IFERROR(J38*VLOOKUP("CLP",'Tipos de Cambio'!$B:$C,2,FALSE),"") -> 0 | L38: =IFERROR(J38*VLOOKUP("CLF",'Tipos de Cambio'!$B:$C,2,FALSE),"") -> 0 | M38: =IFERROR(J38*VLOOKUP("COP",'Tipos de Cambio'!$B:$C,2,FALSE),"") -> 0 | N38: =IFERROR(J38*VLOOKUP("MXN",'Tipos de Cambio'!$B:$C,2,FALSE),"") -> 0 | O38: =IFERROR(J38*VLOOKUP("PEN",'Tipos de Cambio'!$B:$C,2,FALSE),"") -> 0
A39: EFG-038 | H39: =SUMIF('Estructura de Servicios'!$A:$A,A39,'Estructura de Servicios'!$I:$I) -> 0 | I39: =IFERROR( VLOOKUP(G39,'Tier Servicios'!$A:$C,2,FALSE), "" ) | K39: =IFERROR(J39*VLOOKUP("CLP",'Tipos de Cambio'!$B:$C,2,FALSE),"") -> 0 | L39: =IFERROR(J39*VLOOKUP("CLF",'Tipos de Cambio'!$B:$C,2,FALSE),"") -> 0 | M39: =IFERROR(J39*VLOOKUP("COP",'Tipos de Cambio'!$B:$C,2,FALSE),"") -> 0 | N39: =IFERROR(J39*VLOOKUP("MXN",'Tipos de Cambio'!$B:$C,2,FALSE),"") -> 0 | O39: =IFERROR(J39*VLOOKUP("PEN",'Tipos de Cambio'!$B:$C,2,FALSE),"") -> 0
A40: EFG-039 | H40: =SUMIF('Estructura de Servicios'!$A:$A,A40,'Estructura de Servicios'!$I:$I) -> 0 | I40: =IFERROR( VLOOKUP(G40,'Tier Servicios'!$A:$C,2,FALSE), "" ) | K40: =IFERROR(J40*VLOOKUP("CLP",'Tipos de Cambio'!$B:$C,2,FALSE),"") -> 0 | L40: =IFERROR(J40*VLOOKUP("CLF",'Tipos de Cambio'!$B:$C,2,FALSE),"") -> 0 | M40: =IFERROR(J40*VLOOKUP("COP",'Tipos de Cambio'!$B:$C,2,FALSE),"") -> 0 | N40: =IFERROR(J40*VLOOKUP("MXN",'Tipos de Cambio'!$B:$C,2,FALSE),"") -> 0 | O40: =IFERROR(J40*VLOOKUP("PEN",'Tipos de Cambio'!$B:$C,2,FALSE),"") -> 0
A41: EFG-040 | H41: =SUMIF('Estructura de Servicios'!$A:$A,A41,'Estructura de Servicios'!$I:$I) -> 0 | I41: =IFERROR( VLOOKUP(G41,'Tier Servicios'!$A:$C,2,FALSE), "" ) | K41: =IFERROR(J41*VLOOKUP("CLP",'Tipos de Cambio'!$B:$C,2,FALSE),"") -> 0 | L41: =IFERROR(J41*VLOOKUP("CLF",'Tipos de Cambio'!$B:$C,2,FALSE),"") -> 0 | M41: =IFERROR(J41*VLOOKUP("COP",'Tipos de Cambio'!$B:$C,2,FALSE),"") -> 0 | N41: =IFERROR(J41*VLOOKUP("MXN",'Tipos de Cambio'!$B:$C,2,FALSE),"") -> 0 | O41: =IFERROR(J41*VLOOKUP("PEN",'Tipos de Cambio'!$B:$C,2,FALSE),"") -> 0
A42: EFG-041 | H42: =SUMIF('Estructura de Servicios'!$A:$A,A42,'Estructura de Servicios'!$I:$I) -> 0 | I42: =IFERROR( VLOOKUP(G42,'Tier Servicios'!$A:$C,2,FALSE), "" ) | K42: =IFERROR(J42*VLOOKUP("CLP",'Tipos de Cambio'!$B:$C,2,FALSE),"") -> 0 | L42: =IFERROR(J42*VLOOKUP("CLF",'Tipos de Cambio'!$B:$C,2,FALSE),"") -> 0 | M42: =IFERROR(J42*VLOOKUP("COP",'Tipos de Cambio'!$B:$C,2,FALSE),"") -> 0 | N42: =IFERROR(J42*VLOOKUP("MXN",'Tipos de Cambio'!$B:$C,2,FALSE),"") -> 0 | O42: =IFERROR(J42*VLOOKUP("PEN",'Tipos de Cambio'!$B:$C,2,FALSE),"") -> 0
A43: EFG-042 | H43: =SUMIF('Estructura de Servicios'!$A:$A,A43,'Estructura de Servicios'!$I:$I) -> 0 | I43: =IFERROR( VLOOKUP(G43,'Tier Servicios'!$A:$C,2,FALSE), "" ) | K43: =IFERROR(J43*VLOOKUP("CLP",'Tipos de Cambio'!$B:$C,2,FALSE),"") -> 0 | L43: =IFERROR(J43*VLOOKUP("CLF",'Tipos de Cambio'!$B:$C,2,FALSE),"") -> 0 | M43: =IFERROR(J43*VLOOKUP("COP",'Tipos de Cambio'!$B:$C,2,FALSE),"") -> 0 | N43: =IFERROR(J43*VLOOKUP("MXN",'Tipos de Cambio'!$B:$C,2,FALSE),"") -> 0 | O43: =IFERROR(J43*VLOOKUP("PEN",'Tipos de Cambio'!$B:$C,2,FALSE),"") -> 0
A44: EFG-043 | H44: =SUMIF('Estructura de Servicios'!$A:$A,A44,'Estructura de Servicios'!$I:$I) -> 0 | I44: =IFERROR( VLOOKUP(G44,'Tier Servicios'!$A:$C,2,FALSE), "" ) | K44: =IFERROR(J44*VLOOKUP("CLP",'Tipos de Cambio'!$B:$C,2,FALSE),"") -> 0 | L44: =IFERROR(J44*VLOOKUP("CLF",'Tipos de Cambio'!$B:$C,2,FALSE),"") -> 0 | M44: =IFERROR(J44*VLOOKUP("COP",'Tipos de Cambio'!$B:$C,2,FALSE),"") -> 0 | N44: =IFERROR(J44*VLOOKUP("MXN",'Tipos de Cambio'!$B:$C,2,FALSE),"") -> 0 | O44: =IFERROR(J44*VLOOKUP("PEN",'Tipos de Cambio'!$B:$C,2,FALSE),"") -> 0
A45: EFG-044 | H45: =SUMIF('Estructura de Servicios'!$A:$A,A45,'Estructura de Servicios'!$I:$I) -> 0 | I45: =IFERROR( VLOOKUP(G45,'Tier Servicios'!$A:$C,2,FALSE), "" ) | K45: =IFERROR(J45*VLOOKUP("CLP",'Tipos de Cambio'!$B:$C,2,FALSE),"") -> 0 | L45: =IFERROR(J45*VLOOKUP("CLF",'Tipos de Cambio'!$B:$C,2,FALSE),"") -> 0 | M45: =IFERROR(J45*VLOOKUP("COP",'Tipos de Cambio'!$B:$C,2,FALSE),"") -> 0 | N45: =IFERROR(J45*VLOOKUP("MXN",'Tipos de Cambio'!$B:$C,2,FALSE),"") -> 0 | O45: =IFERROR(J45*VLOOKUP("PEN",'Tipos de Cambio'!$B:$C,2,FALSE),"") -> 0
A46: EFG-045 | H46: =SUMIF('Estructura de Servicios'!$A:$A,A46,'Estructura de Servicios'!$I:$I) -> 0 | K46: =IFERROR(J46*VLOOKUP("CLP",'Tipos de Cambio'!$B:$C,2,FALSE),"") -> 0 | L46: =IFERROR(J46*VLOOKUP("CLF",'Tipos de Cambio'!$B:$C,2,FALSE),"") -> 0 | M46: =IFERROR(J46*VLOOKUP("COP",'Tipos de Cambio'!$B:$C,2,FALSE),"") -> 0 | N46: =IFERROR(J46*VLOOKUP("MXN",'Tipos de Cambio'!$B:$C,2,FALSE),"") -> 0 | O46: =IFERROR(J46*VLOOKUP("PEN",'Tipos de Cambio'!$B:$C,2,FALSE),"") -> 0
A47: EFG-046 | K47: =IFERROR(J47*VLOOKUP("CLP",'Tipos de Cambio'!$B:$C,2,FALSE),"") -> 0 | L47: =IFERROR(J47*VLOOKUP("CLF",'Tipos de Cambio'!$B:$C,2,FALSE),"") -> 0 | M47: =IFERROR(J47*VLOOKUP("COP",'Tipos de Cambio'!$B:$C,2,FALSE),"") -> 0 | N47: =IFERROR(J47*VLOOKUP("MXN",'Tipos de Cambio'!$B:$C,2,FALSE),"") -> 0 | O47: =IFERROR(J47*VLOOKUP("PEN",'Tipos de Cambio'!$B:$C,2,FALSE),"") -> 0
A48: EFG-047 | K48: =IFERROR(J48*VLOOKUP("CLP",'Tipos de Cambio'!$B:$C,2,FALSE),"") -> 0 | L48: =IFERROR(J48*VLOOKUP("CLF",'Tipos de Cambio'!$B:$C,2,FALSE),"") -> 0 | M48: =IFERROR(J48*VLOOKUP("COP",'Tipos de Cambio'!$B:$C,2,FALSE),"") -> 0 | N48: =IFERROR(J48*VLOOKUP("MXN",'Tipos de Cambio'!$B:$C,2,FALSE),"") -> 0 | O48: =IFERROR(J48*VLOOKUP("PEN",'Tipos de Cambio'!$B:$C,2,FALSE),"") -> 0
A49: EFG-048 | K49: =IFERROR(J49*VLOOKUP("CLP",'Tipos de Cambio'!$B:$C,2,FALSE),"") -> 0 | L49: =IFERROR(J49*VLOOKUP("CLF",'Tipos de Cambio'!$B:$C,2,FALSE),"") -> 0 | M49: =IFERROR(J49*VLOOKUP("COP",'Tipos de Cambio'!$B:$C,2,FALSE),"") -> 0 | N49: =IFERROR(J49*VLOOKUP("MXN",'Tipos de Cambio'!$B:$C,2,FALSE),"") -> 0 | O49: =IFERROR(J49*VLOOKUP("PEN",'Tipos de Cambio'!$B:$C,2,FALSE),"") -> 0
A50: EFG-049 | K50: =IFERROR(J50*VLOOKUP("CLP",'Tipos de Cambio'!$B:$C,2,FALSE),"") -> 0 | L50: =IFERROR(J50*VLOOKUP("CLF",'Tipos de Cambio'!$B:$C,2,FALSE),"") -> 0 | M50: =IFERROR(J50*VLOOKUP("COP",'Tipos de Cambio'!$B:$C,2,FALSE),"") -> 0 | N50: =IFERROR(J50*VLOOKUP("MXN",'Tipos de Cambio'!$B:$C,2,FALSE),"") -> 0 | O50: =IFERROR(J50*VLOOKUP("PEN",'Tipos de Cambio'!$B:$C,2,FALSE),"") -> 0
A51: EFG-050 | K51: =IFERROR(J51*VLOOKUP("CLP",'Tipos de Cambio'!$B:$C,2,FALSE),"") -> 0 | L51: =IFERROR(J51*VLOOKUP("CLF",'Tipos de Cambio'!$B:$C,2,FALSE),"") -> 0 | M51: =IFERROR(J51*VLOOKUP("COP",'Tipos de Cambio'!$B:$C,2,FALSE),"") -> 0 | N51: =IFERROR(J51*VLOOKUP("MXN",'Tipos de Cambio'!$B:$C,2,FALSE),"") -> 0 | O51: =IFERROR(J51*VLOOKUP("PEN",'Tipos de Cambio'!$B:$C,2,FALSE),"") -> 0

Sheet Herramientas
A1: SKU | B1: Categoría | C1: Nombre de la Herramienta | D1: Tipo | E1: Unidad | F1: Costo Total (USD) | G1: Frecuencia | H1: Prorrateo Estimado | I1: Tipo de prorrateo | J1: Costo Prorrateado (USD) | K1: Precio Prorrateado | L1: Aplicable a | M1: Incluye en Add-on | N1: Comentarios
A2: ETG-001 | B2: Creatividad | C2: Adobe Creative Cloud | D2: SaaS / Licencia | E2: Mes | F2: 80 | G2: Mensual | H2: 4 | I2: Proyectos/mes | J2: =IF(OR(H2="",H2=0),F2,F2/VALUE(H2)) -> 20 | K2: =IF(OR(J2="",J2="N/A"),"",J2*(1+'Addons - Overheads'!$G$2)) -> 23 | L2: Globe | M2: ✅ | N2: Incluye Photoshop, Illustrator, After Effects
A3: ETG-002 | B3: Creatividad | C3: Envato Elements | D3: Recurso / Banco | E3: Mes | F3: 33 | G3: Mensual | H3: 4 | I3: Proyectos/mes | J3: =IF(OR(H3="",H3=0),F3,F3/VALUE(H3)) -> 8.25 | K3: =IF(OR(J3="",J3="N/A"),"",J3*(1+'Addons - Overheads'!$G$2)) -> 9.4875 | L3: Globe | M3: ✅ | N3: Stock, plantillas, fuentes
A4: ETG-003 | B4: Social / Medios | C4: Metricool | D4: SaaS / Licencia | E4: Mes | F4: 54 | G4: Mensual | H4: 15 | I4: Clientes activos | J4: =IF(OR(H4="",H4=0),F4,F4/VALUE(H4)) -> 3.6 | K4: =IF(OR(J4="",J4="N/A"),"",J4*(1+'Addons - Overheads'!$G$2)) -> 4.14 | L4: Reach / Globe | M4: ✅ | N4: Licencia Multiaccount
A5: ETG-004 | B5: Analítica / Performance | C5: SEMrush | D5: SaaS | E5: Mes | F5: 120 | G5: Mensual | H5: 3 | I5: Proyectos | J5: =IF(OR(H5="",H5=0),F5,F5/VALUE(H5)) -> 40 | K5: =IF(OR(J5="",J5="N/A"),"",J5*(1+'Addons - Overheads'!$G$2)) -> 46 | L5: Wave | M5: ✅ | N5: Auditoría SEO, Keywords
A6: ETG-005 | B6: MarTech / HubSpot | C6: HubSpot | D6: Plataforma | E6: Mes | F6: N/A | G6: Mensual | J6: =IF(OR(H6="",H6=0),F6,F6/VALUE(H6)) -> N/A | K6: =IF(OR(J6="",J6="N/A"),"",J6*(1+'Addons - Overheads'!$G$2)) | L6: Efeonce / Wave | M6: ❌ | N6: Incluido como partner
A7: ETG-006 | B7: Automatización / Integraciones | C7: Zapier | D7: SaaS | E7: Mes | F7: 49 | G7: Mensual | H7: 5 | I7: Automatizaciones | J7: =IF(OR(H7="",H7=0),F7,F7/VALUE(H7)) -> 9.8 | K7: =IF(OR(J7="",J7="N/A"),"",J7*(1+'Addons - Overheads'!$G$2)) -> 11.27 | L7: Wave / Efeonce | M7: ✅ | N7: Costo compartido
A8: ETG-007 | B8: IA / Contenido | C8: ChatGPT Plus | D8: SaaS | E8: Mes | F8: 20 | G8: Mensual | H8: 4 | I8: Proyectos | J8: =IF(OR(H8="",H8=0),F8,F8/VALUE(H8)) -> 5 | K8: =IF(OR(J8="",J8="N/A"),"",J8*(1+'Addons - Overheads'!$G$2)) -> 5.75 | L8: Globe / Efeonce | M8: ✅ | N8: Incluye uso Promptcraft
A9: ETG-008 | B9: IA / Diseño | C9: Midjourney | D9: SaaS | E9: Mes | F9: 30 | G9: Mensual | H9: 6 | I9: Proyectos | J9: =IF(OR(H9="",H9=0),F9,F9/VALUE(H9)) -> 5 | K9: =IF(OR(J9="",J9="N/A"),"",J9*(1+'Addons - Overheads'!$G$2)) -> 5.75 | L9: Globe | M9: ✅ | N9: Uso en renders creativos
A10: ETG-009 | B10: Hosting | C10: Cloudways VPS | D10: Hosting | E10: Año | F10: 240 | G10: Anual | H10: 1 | I10: Clientes activos | J10: =IF(OR(H10="",H10=0),F10,F10/VALUE(H10)) -> 240 | K10: =IF(OR(J10="",J10="N/A"),"",J10*(1+'Addons - Overheads'!$G$2)) -> 276 | L10: Wave | M10: ✅ | N10: Hosting cliente / sitio web
A11: ETG-010 | B11: Plugins / CMS | C11: Elementor Pro | D11: Plugin | E11: Año | F11: 100 | G11: Anual | H11: 3 | I11: Clientes activos | J11: =IF(OR(H11="",H11=0),F11,F11/VALUE(H11)) -> 33.333333 | K11: =IF(OR(J11="",J11="N/A"),"",J11*(1+'Addons - Overheads'!$G$2)) -> 38.333333 | L11: Wave | M11: ✅ | N11: Webs WordPress
A12: ETG-011 | B12: Plugins / CMS | C12: WP Rocket | D12: Plugin | E12: Año | F12: 59 | G12: Anual | H12: 3 | I12: Clientes activos | J12: =IF(OR(H12="",H12=0),F12,F12/VALUE(H12)) -> 19.666667 | K12: =IF(OR(J12="",J12="N/A"),"",J12*(1+'Addons - Overheads'!$G$2)) -> 22.616667 | L12: Wave | M12: ✅ | N12: Optimización de velocidad
A13: ETG-012 | B13: Plugins / CMS | C13: Crocoblock Suite | D13: Plugin | E13: Año | F13: 130 | G13: Anual | H13: 12 | I13: Usuarios/mes | J13: =IF(OR(H13="",H13=0),F13,F13/VALUE(H13)) -> 10.833333 | K13: =IF(OR(J13="",J13="N/A"),"",J13*(1+'Addons - Overheads'!$G$2)) -> 12.458333 | L13: Wave | M13: ✅ | N13: Webs dinámicas
A14: ETG-013 | B14: Infraestructura / Data | C14: GTM Server-side | D14: Infraestructura | E14: Mes | F14: 60 | G14: Mensual | H14: 3 | I14: Proyectos | J14: =IF(OR(H14="",H14=0),F14,F14/VALUE(H14)) -> 20 | K14: =IF(OR(J14="",J14="N/A"),"",J14*(1+'Addons - Overheads'!$G$2)) -> 23 | L14: Wave | M14: ✅ | N14: Tracking avanzado
A15: ETG-014 | B15: Infraestructura / Data | C15: BigQuery | D15: Plataforma | E15: Mes | F15: 50 | G15: Mensual | H15: 5 | I15: Proyectos | J15: =IF(OR(H15="",H15=0),F15,F15/VALUE(H15)) -> 10 | K15: =IF(OR(J15="",J15="N/A"),"",J15*(1+'Addons - Overheads'!$G$2)) -> 11.5 | L15: Wave / Efeonce | M15: ✅ | N15: Análisis de datos
A16: ETG-015 | B16: Gestión Interna | C16: Notion | D16: SaaS | E16: Mes | F16: 144 | G16: Mensual | H16: 6 | I16: Usuarios/mes | J16: =IF(OR(H16="",H16=0),F16,F16/VALUE(H16)) -> 24 | K16: =IF(OR(J16="",J16="N/A"),"",J16*1.15) -> 27.6 | L16: Todos | M16: ❌ | N16: Costo operativo
A17: ETG-016 | B17: Gestión Interna | C17: Microsoft 365 | D17: SaaS | E17: Mes | F17: 80 | G17: Mensual | H17: 5 | I17: Clientes activos | J17: =IF(OR(H17="",H17=0),F17,F17/VALUE(H17)) -> 16 | K17: =IF(OR(J17="",J17="N/A"),"",J17*1.15) -> 18.4 | L17: Todos | M17: ❌ | N17: Cuentas corporativas
A18: ETG-017 | B18: Gestión Financiera | C18: Deel | D18: Plataforma | E18: Usuario | F18: 49 | G18: Mensual | H18: 4 | I18: Clientes activos | J18: =IF(OR(H18="",H18=0),F18,F18/VALUE(H18)) -> 12.25 | K18: =IF(OR(J18="",J18="N/A"),"",J18*1.15) -> 14.0875 | L18: Staff Augmentation | M18: ✅ | N18: Fee por colaborador externo (gestión global de pagos y contratos internacionales).
A19: ETG-018 | B19: IA / Contenido | C19: Gemini | D19: SaaS | E19: Mes | F19: 23 | G19: Mensual | H19: 4 | I19: Proyectos/mes | J19: =IF(OR(H19="",H19=0),F19,F19/VALUE(H19)) -> 5.75 | K19: =IF(OR(J19="",J19="N/A"),"",J19*1.15) -> 6.6125 | L19: Globe | M19: ✅ | N19: Asistente de IA generativa para prompts, textos y soporte creativo (IA generativa Google).
A20: ETG-019 | B20: IA / Contenido | C20: Figma | D20: SaaS | E20: Mes | F20: 60 | G20: Mensual | H20: 3 | I20: Proyectos/mes | J20: =IF(OR(H20="",H20=0),F20,F20/VALUE(H20)) -> 20 | K20: =IF(OR(J20="",J20="N/A"),"",J20*1.15) -> 23 | L20: Wave | M20: ✅ | N20: Plataforma de diseño colaborativo UI/UX y prototipado para Globe y Wave.
A21: ETG-020 | B21: Social / Medios | C21: Shutterstock | D21: Recurso / Banco | E21: Mes | F21: 29 | G21: Mensual | H21: 6 | I21: Proyectos/mes | J21: =IF(OR(H21="",H21=0),F21,F21/VALUE(H21)) -> 4.8333333 | K21: =IF(OR(J21="",J21="N/A"),"",J21*1.15) -> 5.5583333 | L21: Globe | M21: ✅ | N21: Banco de imágenes y videos premium con licencia comercial.
A22: ETG-021 | B22: Social / Medios | C22: Freepik | D22: Recurso / Banco | E22: Mes | F22: 33 | G22: Mensual | H22: 4 | I22: Proyectos/mes | J22: =IF(OR(H22="",H22=0),F22,F22/VALUE(H22)) -> 8.25 | K22: =IF(OR(J22="",J22="N/A"),"",J22*1.15) -> 9.4875 | L22: Globe | M22: ✅ | N22: Recurso gráfico complementario (vectores, íconos, plantillas).
A23: ETG-022 | B23: Social / Medios | C23: Frame.io | D23: Plataforma | E23: Mes | F23: 75 | G23: Mensual | H23: 5 | I23: Proyectos/mes | J23: =IF(OR(H23="",H23=0),F23,F23/VALUE(H23)) -> 15 | K23: =IF(OR(J23="",J23="N/A"),"",J23*1.15) -> 17.25 | L23: Globe | M23: ✅ | N23: Plataforma de revisión colaborativa de video y control de versiones.
A24: ETG-023 | B24: IA / Contenido | C24: Eleven Labs | D24: SaaS / Licencia | E24: Mes | F24: 5 | G24: Mensual | H24: 3 | I24: Proyectos/mes | J24: =IF(OR(H24="",H24=0),F24,F24/VALUE(H24)) -> 1.6666667 | K24: =IF(OR(J24="",J24="N/A"),"",J24*1.15) -> 1.9166667 | L24: Globe | M24: ✅ | N24: Generación de voz con IA para contenidos multimedia o campañas.
A25: ETG-024 | B25: IA / Contenido | C25: Github Copilot | D25: SaaS / Licencia | E25: Mes | F25: 36 | G25: Mensual | H25: 6 | I25: Proyectos/mes | J25: =IF(OR(H25="",H25=0),F25,F25/VALUE(H25)) -> 6 | K25: =IF(OR(J25="",J25="N/A"),"",J25*1.15) -> 6.9 | L25: Wave | M25: ✅ | N25: Asistente de codificación IA para automatización de desarrollo (Wave).
A26: ETG-025 | B26: Social / Medios | C26: Adobe Express | D26: SaaS / Licencia | E26: Mes | F26: 24 | G26: Mensual | H26: 4 | I26: Proyectos/mes | J26: =IF(OR(H26="",H26=0),F26,F26/VALUE(H26)) -> 6 | K26: =IF(OR(J26="",J26="N/A"),"",J26*1.15) -> 6.9 | L26: Globe | M26: ✅ | N26: Herramienta de diseño rápido para social media y piezas simples.
A27: ETG-026 | B27: Social / Medios | C27: Favikon | D27: SaaS | E27: Mes | F27: 199 | G27: Mensual | H27: 5 | I27: Proyectos/mes | J27: =IF(OR(H27="",H27=0),F27,F27/VALUE(H27)) -> 39.8 | K27: =IF(OR(J27="",J27="N/A"),"",J27*1.15) -> 45.77 | L27: Globe | M27: ✅
A28: ETG-027 | J28: =IF(OR(H28="",H28=0),F28,F28/VALUE(H28)) -> 0 | K28: =IF(OR(J28="",J28="N/A"),"",J28*1.15) -> 0
A29: ETG-028 | J29: =IF(OR(H29="",H29=0),F29,F29/VALUE(H29)) -> 0 | K29: =IF(OR(J29="",J29="N/A"),"",J29*1.15) -> 0
A30: ETG-029 | J30: =IF(OR(H30="",H30=0),F30,F30/VALUE(H30)) -> 0 | K30: =IF(OR(J30="",J30="N/A"),"",J30*1.15) -> 0
A31: ETG-030 | J31: =IF(OR(H31="",H31=0),F31,F31/VALUE(H31)) -> 0 | K31: =IF(OR(J31="",J31="N/A"),"",J31*1.15) -> 0
A32: ETG-031 | J32: =IF(OR(H32="",H32=0),F32,F32/VALUE(H32)) -> 0 | K32: =IF(OR(J32="",J32="N/A"),"",J32*1.15) -> 0
A33: ETG-032 | J33: =IF(OR(H33="",H33=0),F33,F33/VALUE(H33)) -> 0 | K33: =IF(OR(J33="",J33="N/A"),"",J33*1.15) -> 0
A34: ETG-033 | J34: =IF(OR(H34="",H34=0),F34,F34/VALUE(H34)) -> 0 | K34: =IF(OR(J34="",J34="N/A"),"",J34*1.15) -> 0
J35: =IF(OR(H35="",H35=0),F35,F35/VALUE(H35)) -> 0 | K35: =IF(OR(J35="",J35="N/A"),"",J35*1.15) -> 0
J36: =IF(OR(H36="",H36=0),F36,F36/VALUE(H36)) -> 0 | K36: =IF(OR(J36="",J36="N/A"),"",J36*1.15) -> 0
J37: =IF(OR(H37="",H37=0),F37,F37/VALUE(H37)) -> 0 | K37: =IF(OR(J37="",J37="N/A"),"",J37*1.15) -> 0

Sheet Addons - Overheads
A1: SKU | B1: Categoría | C1: Nombre del Add-On | D1: Tipo | E1: Unidad | F1: Costo Interno (USD) | G1: Margen Agencia (%) | H1: Precio Final (USD) | I1: Descripción / Cuándo aplicar | J1: Aplicable a | K1: Comentarios
A2: EFO-001 | B2: Overhead Operativo | C2: Costo de Herramientas Creativas | D2: Overhead | E2: Mes | F2: 50 | G2: 0.15 | H2: 50 | I2: Prorrateo de Adobe CC, Envato, Frame.io, Metricool, Notion, etc. | J2: Staff & Servicios Creativos (Globe) | K2: Puede incluir IA (ChatGPT, Gemini)
A3: EFO-002 | B3: Overhead Operativo | C3: Costo de Herramientas MarTech / HubSpot | D3: Overhead | E3: Mes | F3: 80 | G3: 0.15 | H3: 80 | I3: Uso compartido de HubSpot sandbox, Zapier, Make, GA4, GTM server-side. | J3: Wave, Efeonce | K3: Aplicar si el cliente no tiene su propia licencia
A4: EFO-003 | B4: Fee de Gestión Efeonce | C4: Project Management Fee | D4: Fee | E4: Proyecto / Mes | F4: 0 | G4: 0.15 | H4: 10 % del subtotal | I4: Cobertura de coordinación interna, QA, comunicación y reporting. | J4: Todos los proyectos y retainers | K4: Puede automatizarse en CPQ como “surcharge %”
A5: EFO-004 | B5: Fee Administrativo | C5: Recruiting & Onboarding Fee (Staff Aug) | D5: Fee | E5: Único (setup) | F5: 0 | G5: 0.15 | H5: 1 mes del costo del recurso | I5: Se cobra una sola vez al inicio de cada recurso dedicado. | J5: Staff Augmentation | K5: Incluye scouting, entrevistas, validación técnica
A6: EFO-005 | B6: Fee Administrativo | C6: Renovación / Continuidad Staff Aug | D6: Fee | E6: Mensual | F6: 0 | G6: 0.15 | H6: 5 % del valor mensual del recurso | I6: Se aplica cuando se renueva un FTE ya existente. | J6: Staff Augmentation | K6: Opcional o negociable según duración
A7: EFO-006 | B7: Fee Financiero | C7: Costos Transaccionales (Comisiones / Deel / Global66) | D7: Overhead | E7: % del monto | F7: 0 | G7: 0.15 | H7: 4–7 % variable | I7: Cobertura de fees por pago internacional, tarjeta, conversión, etc. | J7: Staff & Servicios Internacionales | K7: Ajustable por método de pago
A8: EFO-007 | B8: Overhead Estratégico | C8: AI & Data Infrastructure Fee | D8: Overhead | E8: Mes | F8: 0 | G8: 0.15 | H8: 3 % del proyecto o USD 30 mínimo | I8: Uso de infraestructura IA, BigQuery, Breeze, Promptcraft. | J8: Wave, Efeonce | K8: Integrar en propuestas tech
A9: EFO-008 | B9: Overhead General | C9: Efeonce Operational Overhead (base) | D9: Overhead | E9: % | F9: 0 | G9: 0.15 | H9: 8–10 % global | I9: Costos indirectos de operación (RRHH, marketing, administración). | J9: Todos los proyectos | K9: Incluir en pricing interno, no visible al cliente
A10: EFO-009 | B10: Descuento / Bono | C10: Fee de Retención / Descuento anual | D10: Ajuste | E10: % | F10: 0 | G10: 0.15 | H10: −10 % | I10: Aplicable a contratos On-Going > 12 meses. | J10: Retainers | K10: Negociable, aprobado por dirección
