Workbook

Sheet Decision
C2: Pibank 2027: decisión de inversión, no forecast
C4: La decisión parte de requisitos y valor bancario. Los escenarios previos 10/50/147 se retiran del uso con cliente; archivos históricos intactos.
C6: Pregunta de inversión | D6: Resultado activo | E6: Unidad
C8: Contribución contextual requerida | D8: =Supuestos!D12 -> 152 | E8: cuentas
C9: Visitas requeridas bajo tasas de prueba | D9: =IF(COUNT(Requisitos!F13:Q13)=12,SUM(Requisitos!F13:Q13),"N/D") -> 7600 | E9: visitas
C10: Ratio requisito / panel parcial elegible | D10: =IF(COUNT(Requisitos!F13:Q13,Requisitos!F16:Q16)=24,IF(SUM(Requisitos!F16:Q16)>0,SUM(Requisitos!F13:Q13)/SUM(Requisitos!F16:Q16),"N/D"),"N/D") -> 0.22884673 | E10: ratio panel
C11: Saldo medio externo en ventana activa | D11: =IF(COUNT(Requisitos!F19:Q19,Supuestos!D45)=13,SUM(Requisitos!F19:Q19)/Supuestos!D45,"N/D") -> 74916.492 | E11: USD eq.
C12: Saldo externo al cierre de ventana | D12: =IF(COUNT(Supuestos!D45)=1,INDEX(Requisitos!F20:Q20,1,Supuestos!D45),"N/D") -> 142419.88 | E12: USD eq.
C14: Valor neto banco según método/horizonte | D14: =Economia!D8 -> N/D | E14: USD
C15: Techo de inversión según retorno exigido | D15: =Economia!D9 -> N/D | E15: USD
C16: Piso operativo enfocado según costeo | D16: =Economia!D15 -> N/D | E16: USD
C17: Horas compatibles con el techo bancario | D17: =Economia!D17 -> N/D | E17: horas
C18: ROI condicionado dentro de ventana | D18: =Requisitos!Q26 -> N/D | E18: %
C19: Payback condicionado dentro de ventana | D19: =IF(COUNT(Requisitos!F27:Q27)=12,IFERROR(MATCH(1,Requisitos!F27:Q27,0),"No en ventana"),"N/D") -> N/D | E19: mes
C20: Fondeadas dentro de ventana, calidad | D20: =IF(COUNT(Requisitos!F11:Q11)=12,SUM(Requisitos!F11:Q11),"N/D") -> 98.8 | E20: cuentas
C21: N/D conserva inputs faltantes. El techo es condicional a alcanzar la contribución; no es precio, presupuesto aprobado ni beneficio garantizado.
C22: Fondeo potencial posterior (excluido) | D22: =IF(COUNT(Requisitos!F12:Q12,Supuestos!D10,D20)=14,SUM(Requisitos!F12:Q12)*Supuestos!D10-D20,"N/D") -> 0
C24: Banda contextual | D24: Cuentas según definición | E24: Visitas necesarias | F24: Saldo medio externo condicionado | G24: Techo inversión condicionado
C25: 0.01 | D25: =C25*Supuestos!D6 -> 152 | E25: =IF(COUNT($D$8,$D$9)=2,IF($D$8>0,$D$9*D25/$D$8,"N/D"),"N/D") -> 7600 | F25: =IF(COUNT($D$8,$D$11)=2,IF($D$8>0,$D$11*D25/$D$8,"N/D"),"N/D") -> 74916.492 | G25: =IF(COUNT($D$8,$D$15)=2,IF($D$8>0,$D$15*D25/$D$8,"N/D"),"N/D") -> N/D
C26: 0.05 | D26: =C26*Supuestos!D6 -> 760 | E26: =IF(COUNT($D$8,$D$9)=2,IF($D$8>0,$D$9*D26/$D$8,"N/D"),"N/D") -> 38000 | F26: =IF(COUNT($D$8,$D$11)=2,IF($D$8>0,$D$11*D26/$D$8,"N/D"),"N/D") -> 374582.46 | G26: =IF(COUNT($D$8,$D$15)=2,IF($D$8>0,$D$15*D26/$D$8,"N/D"),"N/D") -> N/D
C27: 0.1 | D27: =C27*Supuestos!D6 -> 1520 | E27: =IF(COUNT($D$8,$D$9)=2,IF($D$8>0,$D$9*D27/$D$8,"N/D"),"N/D") -> 76000 | F27: =IF(COUNT($D$8,$D$11)=2,IF($D$8>0,$D$11*D27/$D$8,"N/D"),"N/D") -> 749164.92 | G27: =IF(COUNT($D$8,$D$15)=2,IF($D$8>0,$D$15*D27/$D$8,"N/D"),"N/D") -> N/D
C29: Comparación matemática bajo iguales tasas, calendario y origen; no son tres forecasts paralelos ni objetivos comerciales acordados.
C31: Programa enfocado candidato: 814h base +110h reserva=924h. Operations revisa carga, dependencias y disponibilidad; no se vende por horas.
C32: Si piso operativo supera techo bancario condicionado: revisar contribución/canales/alcance y evidencia; no inventar demanda o conversión.
C34: Una intervención de conversión puede mejorar tráfico de otros canales; requiere baseline y contrafactual propios para valorar incrementalidad.
C35: Educación/confianza y retención son mecanismos posibles, no ingresos adicionales sumables sin cohortes y deduplicación.
C37: M1 revisa accesos, medición y delivery. Las optimizaciones M3/6/9/12 sostienen el programa anual; no son cortes por ROI a tres meses.
C39: Riesgo central: tamaño/captura elegible y valor neto por saldo no están medidos. Cotización se prepara; la evidencia privada refina, no bloquea.

Sheet Supuestos
C2: Inputs: metas contextuales, pruebas y validaciones
C3: Selector banda (1 / 2 / 3) | D3: 1
C4: Bandas 1/5/10% son decisiones de contribución contextual. No objetivos acordados ni previsiones del canal.
C5: Participación contextual elegida | D5: =CHOOSE(D3,1%,5%,10%) -> 0.01
C6: Meta cuentas provisional | D6: 15200 | F6: Definición de la banda | G6: Aperturas
C7: Meta USD inferida, sin periodo confirmado | D7: 38000000
C8: Ticket USD equivalente provisional | D8: 2500
C9: Visita→apertura, prueba aritmética | D9: 0.02
C10: Apertura→fondeo, prueba aritmética | D10: 0.65
C11: Elegibilidad del panel, prueba | D11: 0.75
C12: Cuentas requeridas según definición elegida | D12: =D5*D6 -> 152
C13: Lag apertura→primer fondeo (meses) | D13: 0
C14: Día de primer fondeo (1–28) | D14: 15
C15: Inicio ilustrativo programa | D15: 46388
C16: Finance valida método/valor neto | D16: No
C17: Valor neto anual por USD saldo medio externo
C18: ROI mínimo exigido, prueba 0=equilibrio | D18: 0
C19: Inversión cliente completa validada | D19: No
C20: Costeo/margen Efeonce validado | D20: No
C21: Costo real blended USD/h (pendiente)
C22: Margen bruto autorizado (pendiente)
C23: Horas candidato enfocado (base+reserva) | D23: 924
C25: Otros costos enfocado USD (pendiente)
C27: Conversión, elegibilidad, ticket, retención, origen y distribución son hipótesis. Se calculan requisitos; no se predicen resultados.
C28: US$38m = 15.200×2.500: inferencia provisional. Programa anual no confirma definición/anualidad de meta ni producto USD.
C29: Contexto del análisis | D29: Programa2027
C30: Fecha retrolanzamiento (desconocida)
F31: =IF(COUNT($D$36)=1,EDATE($D$36,0),"N/D") -> 46388 | G31: =IF(COUNT($D$36)=1,EDATE($D$36,1),"N/D") -> 46419 | H31: =IF(COUNT($D$36)=1,EDATE($D$36,2),"N/D") -> 46447 | I31: =IF(COUNT($D$36)=1,EDATE($D$36,3),"N/D") -> 46478 | J31: =IF(COUNT($D$36)=1,EDATE($D$36,4),"N/D") -> 46508 | K31: =IF(COUNT($D$36)=1,EDATE($D$36,5),"N/D") -> 46539 | L31: =IF(COUNT($D$36)=1,EDATE($D$36,6),"N/D") -> 46569 | M31: =IF(COUNT($D$36)=1,EDATE($D$36,7),"N/D") -> 46600 | N31: =IF(COUNT($D$36)=1,EDATE($D$36,8),"N/D") -> 46631 | O31: =IF(COUNT($D$36)=1,EDATE($D$36,9),"N/D") -> 46661 | P31: =IF(COUNT($D$36)=1,EDATE($D$36,10),"N/D") -> 46692 | Q31: =IF(COUNT($D$36)=1,EDATE($D$36,11),"N/D") -> 46722
C32: Inversión cliente USD mensual, pendiente
C34: Peso del objetivo de fondeo, prueba | F34: 1 | G34: 1 | H34: 1 | I34: 1 | J34: 1 | K34: 1 | L34: 1 | M34: 1 | N34: 1 | O34: 1 | P34: 1 | Q34: 1
C35: Meses ventana retrospectiva (desconocidos)
C36: Inicio del cálculo activo | D36: =IF(D29="Programa2027",D15,IF(COUNT(D30)=1,D30,"N/D")) -> 46388
C37: Saldo relativo 30 días (hipótesis) | D37: 0.95
C38: Saldo relativo 60 días (hipótesis) | D38: 0.9
C39: Saldo relativo 90 días (hipótesis) | D39: 0.85
C40: Saldo relativo 180 días (hipótesis) | D40: 0.8
C41: Saldo relativo 365 días (hipótesis) | D41: 0.75
C44: Origen externo por cohorte, prueba | F44: 0.7 | G44: 0.7 | H44: 0.7 | I44: 0.7 | J44: 0.7 | K44: 0.7 | L44: 0.7 | M44: 0.7 | N44: 0.7 | O44: 0.7 | P44: 0.7 | Q44: 0.7
C45: Meses activos del cálculo | D45: =IF(D29="Programa2027",12,IF(COUNT(D35)=1,IF(AND(D35>=1,D35<=12),D35,"N/D"),"N/D")) -> 12
C46: Los pesos distribuyen una meta requerida, no una rampa SEO. Lag excluye fondeos que necesitarían aperturas anteriores al programa.
C47: Origen externo se fija por cohorte. No sumar traslado interno como nuevo fondeo del grupo.
C48: M1: accesos/datos/delivery. Revisiones M3/6/9/12: optimización del programa anual, sin piloto ni gate de ROI temprano.
C49: Costo/h incluye sólo el método fully loaded validado; evitar duplicar overhead. Ningún fee o roster está aprobado.
C52: Método único de valor bancario | D52: Saldo medio externo
C53: Horizonte del valor, meses | D53: 12
C54: Valor neto por fondeada aprobado (ND)

Sheet Requisitos
C2: Requisitos mensuales para la contribución elegida
C6: Requisito | D6: Unidad | F6: M1 | G6: M2 | H6: M3 | I6: M4 | J6: M5 | K6: M6 | L6: M7 | M6: M8 | N6: M9 | O6: M10 | P6: M11 | Q6: M12
F7: =Supuestos!F31 -> 46388 | G7: =Supuestos!G31 -> 46419 | H7: =Supuestos!H31 -> 46447 | I7: =Supuestos!I31 -> 46478 | J7: =Supuestos!J31 -> 46508 | K7: =Supuestos!K31 -> 46539 | L7: =Supuestos!L31 -> 46569 | M7: =Supuestos!M31 -> 46600 | ... Q7: =Supuestos!Q31 -> 46722
C9: Peso de fondeo indicado | D9: peso | F9: =IF(COUNT(Supuestos!F34)=1,Supuestos!F34,"N/D") -> 1 | G9: =IF(COUNT(Supuestos!G34)=1,Supuestos!G34,"N/D") -> 1 | H9: =IF(COUNT(Supuestos!H34)=1,Supuestos!H34,"N/D") -> 1 | I9: =IF(COUNT(Supuestos!I34)=1,Supuestos!I34,"N/D") -> 1 | J9: =IF(COUNT(Supuestos!J34)=1,Supuestos!J34,"N/D") -> 1 | K9: =IF(COUNT(Supuestos!K34)=1,Supuestos!K34,"N/D") -> 1 | L9: =IF(COUNT(Supuestos!L34)=1,Supuestos!L34,"N/D") -> 1 | M9: =IF(COUNT(Supuestos!M34)=1,Supuestos!M34,"N/D") -> 1 | ... Q9: =IF(COUNT(Supuestos!Q34)=1,Supuestos!Q34,"N/D") -> 1
C10: Peso elegible por inicio/lag | D10: peso | F10: =IF(COUNT(Supuestos!$D$13,Supuestos!$D$45,F9)=3,IF(0<Supuestos!$D$45,IF(Supuestos!$G$6="Fondeadas",IF(0+Supuestos!$D$13<Supuestos!$D$45,F9,0),F9),0),"N/D") -> 1 | G10: =IF(COUNT(Supuestos!$D$13,Supuestos!$D$45,G9)=3,IF(1<Supuestos!$D$45,IF(Supuestos!$G$6="Fondeadas",IF(1+Supuestos!$D$13<Supuestos!$D$45,G9,0),G9),0),"N/D") -> 1 | H10: =IF(COUNT(Supuestos!$D$13,Supuestos!$D$45,H9)=3,IF(2<Supuestos!$D$45,IF(Supuestos!$G$6="Fondeadas",IF(2+Supuestos!$D$13<Supuestos!$D$45,H9,0),H9),0),"N/D") -> 1 | I10: =IF(COUNT(Supuestos!$D$13,Supuestos!$D$45,I9)=3,IF(3<Supuestos!$D$45,IF(Supuestos!$G$6="Fondeadas",IF(3+Supuestos!$D$13<Supuestos!$D$45,I9,0),I9),0),"N/D") -> 1 | J10: =IF(COUNT(Supuestos!$D$13,Supuestos!$D$45,J9)=3,IF(4<Supuestos!$D$45,IF(Supuestos!$G$6="Fondeadas",IF(4+Supuestos!$D$13<Supuestos!$D$45,J9,0),J9),0),"N/D") -> 1 | K10: =IF(COUNT(Supuestos!$D$13,Supuestos!$D$45,K9)=3,IF(5<Supuestos!$D$45,IF(Supuestos!$G$6="Fondeadas",IF(5+Supuestos!$D$13<Supuestos!$D$45,K9,0),K9),0),"N/D") -> 1 | L10: =IF(COUNT(Supuestos!$D$13,Supuestos!$D$45,L9)=3,IF(6<Supuestos!$D$45,IF(Supuestos!$G$6="Fondeadas",IF(6+Supuestos!$D$13<Supuestos!$D$45,L9,0),L9),0),"N/D") -> 1 | M10: =IF(COUNT(Supuestos!$D$13,Supuestos!$D$45,M9)=3,IF(7<Supuestos!$D$45,IF(Supuestos!$G$6="Fondeadas",IF(7+Supuestos!$D$13<Supuestos!$D$45,M9,0),M9),0),"N/D") -> 1 | N10: =IF(COUNT(Supuestos!$D$13,Supuestos!$D$45,N9)=3,IF(8<Supuestos!$D$45,IF(Supuestos!$G$6="Fondeadas",IF(8+Supuestos!$D$13<Supuestos!$D$45,N9,0),N9),0),"N/D") -> 1 | O10: =IF(COUNT(Supuestos!$D$13,Supuestos!$D$45,O9)=3,IF(9<Supuestos!$D$45,IF(Supuestos!$G$6="Fondeadas",IF(9+Supuestos!$D$13<Supuestos!$D$45,O9,0),O9),0),"N/D") -> 1 | P10: =IF(COUNT(Supuestos!$D$13,Supuestos!$D$45,P9)=3,IF(10<Supuestos!$D$45,IF(Supuestos!$G$6="Fondeadas",IF(10+Supuestos!$D$13<Supuestos!$D$45,P9,0),P9),0),"N/D") -> 1 | Q10: =IF(COUNT(Supuestos!$D$13,Supuestos!$D$45,Q9)=3,IF(11<Supuestos!$D$45,IF(Supuestos!$G$6="Fondeadas",IF(11+Supuestos!$D$13<Supuestos!$D$45,Q9,0),Q9),0),"N/D") -> 1
C11: Primeras cuentas fondeadas requeridas | D11: cuentas | F11: =IF(COUNT(Supuestos!$D$13,Supuestos!$D$45,Supuestos!$D$10)=3,IF(AND(0<Supuestos!$D$45,0>=Supuestos!$D$13),IF(COUNT(INDEX($F$12:$Q$12,1,1-Supuestos!$D$13))=1,INDEX($F$12:$Q$12,1,1-Supuestos!$D$13)*Supuestos!$D$10,"N/D"),0),"N/D") -> 8.2333333 | G11: =IF(COUNT(Supuestos!$D$13,Supuestos!$D$45,Supuestos!$D$10)=3,IF(AND(1<Supuestos!$D$45,1>=Supuestos!$D$13),IF(COUNT(INDEX($F$12:$Q$12,1,2-Supuestos!$D$13))=1,INDEX($F$12:$Q$12,1,2-Supuestos!$D$13)*Supuestos!$D$10,"N/D"),0),"N/D") -> 8.2333333 | H11: =IF(COUNT(Supuestos!$D$13,Supuestos!$D$45,Supuestos!$D$10)=3,IF(AND(2<Supuestos!$D$45,2>=Supuestos!$D$13),IF(COUNT(INDEX($F$12:$Q$12,1,3-Supuestos!$D$13))=1,INDEX($F$12:$Q$12,1,3-Supuestos!$D$13)*Supuestos!$D$10,"N/D"),0),"N/D") -> 8.2333333 | I11: =IF(COUNT(Supuestos!$D$13,Supuestos!$D$45,Supuestos!$D$10)=3,IF(AND(3<Supuestos!$D$45,3>=Supuestos!$D$13),IF(COUNT(INDEX($F$12:$Q$12,1,4-Supuestos!$D$13))=1,INDEX($F$12:$Q$12,1,4-Supuestos!$D$13)*Supuestos!$D$10,"N/D"),0),"N/D") -> 8.2333333 | J11: =IF(COUNT(Supuestos!$D$13,Supuestos!$D$45,Supuestos!$D$10)=3,IF(AND(4<Supuestos!$D$45,4>=Supuestos!$D$13),IF(COUNT(INDEX($F$12:$Q$12,1,5-Supuestos!$D$13))=1,INDEX($F$12:$Q$12,1,5-Supuestos!$D$13)*Supuestos!$D$10,"N/D"),0),"N/D") -> 8.2333333 | K11: =IF(COUNT(Supuestos!$D$13,Supuestos!$D$45,Supuestos!$D$10)=3,IF(AND(5<Supuestos!$D$45,5>=Supuestos!$D$13),IF(COUNT(INDEX($F$12:$Q$12,1,6-Supuestos!$D$13))=1,INDEX($F$12:$Q$12,1,6-Supuestos!$D$13)*Supuestos!$D$10,"N/D"),0),"N/D") -> 8.2333333 | L11: =IF(COUNT(Supuestos!$D$13,Supuestos!$D$45,Supuestos!$D$10)=3,IF(AND(6<Supuestos!$D$45,6>=Supuestos!$D$13),IF(COUNT(INDEX($F$12:$Q$12,1,7-Supuestos!$D$13))=1,INDEX($F$12:$Q$12,1,7-Supuestos!$D$13)*Supuestos!$D$10,"N/D"),0),"N/D") -> 8.2333333 | M11: =IF(COUNT(Supuestos!$D$13,Supuestos!$D$45,Supuestos!$D$10)=3,IF(AND(7<Supuestos!$D$45,7>=Supuestos!$D$13),IF(COUNT(INDEX($F$12:$Q$12,1,8-Supuestos!$D$13))=1,INDEX($F$12:$Q$12,1,8-Supuestos!$D$13)*Supuestos!$D$10,"N/D"),0),"N/D") -> 8.2333333 | N11: =IF(COUNT(Supuestos!$D$13,Supuestos!$D$45,Supuestos!$D$10)=3,IF(AND(8<Supuestos!$D$45,8>=Supuestos!$D$13),IF(COUNT(INDEX($F$12:$Q$12,1,9-Supuestos!$D$13))=1,INDEX($F$12:$Q$12,1,9-Supuestos!$D$13)*Supuestos!$D$10,"N/D"),0),"N/D") -> 8.2333333 | O11: =IF(COUNT(Supuestos!$D$13,Supuestos!$D$45,Supuestos!$D$10)=3,IF(AND(9<Supuestos!$D$45,9>=Supuestos!$D$13),IF(COUNT(INDEX($F$12:$Q$12,1,10-Supuestos!$D$13))=1,INDEX($F$12:$Q$12,1,10-Supuestos!$D$13)*Supuestos!$D$10,"N/D"),0),"N/D") -> 8.2333333 | P11: =IF(COUNT(Supuestos!$D$13,Supuestos!$D$45,Supuestos!$D$10)=3,IF(AND(10<Supuestos!$D$45,10>=Supuestos!$D$13),IF(COUNT(INDEX($F$12:$Q$12,1,11-Supuestos!$D$13))=1,INDEX($F$12:$Q$12,1,11-Supuestos!$D$13)*Supuestos!$D$10,"N/D"),0),"N/D") -> 8.2333333 | Q11: =IF(COUNT(Supuestos!$D$13,Supuestos!$D$45,Supuestos!$D$10)=3,IF(AND(11<Supuestos!$D$45,11>=Supuestos!$D$13),IF(COUNT(INDEX($F$12:$Q$12,1,12-Supuestos!$D$13))=1,INDEX($F$12:$Q$12,1,12-Supuestos!$D$13)*Supuestos!$D$10,"N/D"),0),"N/D") -> 8.2333333
C12: Aperturas necesarias desde este mes | D12: cuentas | F12: =IF(COUNT($F$10:$Q$10)=12,IF(SUM($F$10:$Q$10)>0,IF(Supuestos!$G$6="Aperturas",Supuestos!$D$12*F10/SUM($F$10:$Q$10),IF(COUNT(Supuestos!$D$10)=1,IF(Supuestos!$D$10>0,Supuestos!$D$12*F10/SUM($F$10:$Q$10)/Supuestos!$D$10,"N/D"),"N/D")),"N/D"),"N/D") -> 12.666667 | G12: =IF(COUNT($F$10:$Q$10)=12,IF(SUM($F$10:$Q$10)>0,IF(Supuestos!$G$6="Aperturas",Supuestos!$D$12*G10/SUM($F$10:$Q$10),IF(COUNT(Supuestos!$D$10)=1,IF(Supuestos!$D$10>0,Supuestos!$D$12*G10/SUM($F$10:$Q$10)/Supuestos!$D$10,"N/D"),"N/D")),"N/D"),"N/D") -> 12.666667 | H12: =IF(COUNT($F$10:$Q$10)=12,IF(SUM($F$10:$Q$10)>0,IF(Supuestos!$G$6="Aperturas",Supuestos!$D$12*H10/SUM($F$10:$Q$10),IF(COUNT(Supuestos!$D$10)=1,IF(Supuestos!$D$10>0,Supuestos!$D$12*H10/SUM($F$10:$Q$10)/Supuestos!$D$10,"N/D"),"N/D")),"N/D"),"N/D") -> 12.666667 | I12: =IF(COUNT($F$10:$Q$10)=12,IF(SUM($F$10:$Q$10)>0,IF(Supuestos!$G$6="Aperturas",Supuestos!$D$12*I10/SUM($F$10:$Q$10),IF(COUNT(Supuestos!$D$10)=1,IF(Supuestos!$D$10>0,Supuestos!$D$12*I10/SUM($F$10:$Q$10)/Supuestos!$D$10,"N/D"),"N/D")),"N/D"),"N/D") -> 12.666667 | J12: =IF(COUNT($F$10:$Q$10)=12,IF(SUM($F$10:$Q$10)>0,IF(Supuestos!$G$6="Aperturas",Supuestos!$D$12*J10/SUM($F$10:$Q$10),IF(COUNT(Supuestos!$D$10)=1,IF(Supuestos!$D$10>0,Supuestos!$D$12*J10/SUM($F$10:$Q$10)/Supuestos!$D$10,"N/D"),"N/D")),"N/D"),"N/D") -> 12.666667 | K12: =IF(COUNT($F$10:$Q$10)=12,IF(SUM($F$10:$Q$10)>0,IF(Supuestos!$G$6="Aperturas",Supuestos!$D$12*K10/SUM($F$10:$Q$10),IF(COUNT(Supuestos!$D$10)=1,IF(Supuestos!$D$10>0,Supuestos!$D$12*K10/SUM($F$10:$Q$10)/Supuestos!$D$10,"N/D"),"N/D")),"N/D"),"N/D") -> 12.666667 | L12: =IF(COUNT($F$10:$Q$10)=12,IF(SUM($F$10:$Q$10)>0,IF(Supuestos!$G$6="Aperturas",Supuestos!$D$12*L10/SUM($F$10:$Q$10),IF(COUNT(Supuestos!$D$10)=1,IF(Supuestos!$D$10>0,Supuestos!$D$12*L10/SUM($F$10:$Q$10)/Supuestos!$D$10,"N/D"),"N/D")),"N/D"),"N/D") -> 12.666667 | M12: =IF(COUNT($F$10:$Q$10)=12,IF(SUM($F$10:$Q$10)>0,IF(Supuestos!$G$6="Aperturas",Supuestos!$D$12*M10/SUM($F$10:$Q$10),IF(COUNT(Supuestos!$D$10)=1,IF(Supuestos!$D$10>0,Supuestos!$D$12*M10/SUM($F$10:$Q$10)/Supuestos!$D$10,"N/D"),"N/D")),"N/D"),"N/D") -> 12.666667 | ... Q12: =IF(COUNT($F$10:$Q$10)=12,IF(SUM($F$10:$Q$10)>0,IF(Supuestos!$G$6="Aperturas",Supuestos!$D$12*Q10/SUM($F$10:$Q$10),IF(COUNT(Supuestos!$D$10)=1,IF(Supuestos!$D$10>0,Supuestos!$D$12*Q10/SUM($F$10:$Q$10)/Supuestos!$D$10,"N/D"),"N/D")),"N/D"),"N/D") -> 12.666667
C13: Visitas necesarias desde este mes | D13: visitas | F13: =IF(COUNT(Supuestos!$D$9,F12)=2,IF(Supuestos!$D$9>0,F12/Supuestos!$D$9,"N/D"),"N/D") -> 633.33333 | G13: =IF(COUNT(Supuestos!$D$9,G12)=2,IF(Supuestos!$D$9>0,G12/Supuestos!$D$9,"N/D"),"N/D") -> 633.33333 | H13: =IF(COUNT(Supuestos!$D$9,H12)=2,IF(Supuestos!$D$9>0,H12/Supuestos!$D$9,"N/D"),"N/D") -> 633.33333 | I13: =IF(COUNT(Supuestos!$D$9,I12)=2,IF(Supuestos!$D$9>0,I12/Supuestos!$D$9,"N/D"),"N/D") -> 633.33333 | J13: =IF(COUNT(Supuestos!$D$9,J12)=2,IF(Supuestos!$D$9>0,J12/Supuestos!$D$9,"N/D"),"N/D") -> 633.33333 | K13: =IF(COUNT(Supuestos!$D$9,K12)=2,IF(Supuestos!$D$9>0,K12/Supuestos!$D$9,"N/D"),"N/D") -> 633.33333 | L13: =IF(COUNT(Supuestos!$D$9,L12)=2,IF(Supuestos!$D$9>0,L12/Supuestos!$D$9,"N/D"),"N/D") -> 633.33333 | M13: =IF(COUNT(Supuestos!$D$9,M12)=2,IF(Supuestos!$D$9>0,M12/Supuestos!$D$9,"N/D"),"N/D") -> 633.33333 | ... Q13: =IF(COUNT(Supuestos!$D$9,Q12)=2,IF(Supuestos!$D$9>0,Q12/Supuestos!$D$9,"N/D"),"N/D") -> 633.33333
C15: Panel directo observado, contexto parcial | D15: búsquedas/mes | F15: =Evidencia!J5 -> 3690 | G15: =Evidencia!J5 -> 3690 | H15: =Evidencia!J5 -> 3690 | I15: =Evidencia!J5 -> 3690 | J15: =Evidencia!J5 -> 3690 | K15: =Evidencia!J5 -> 3690 | L15: =Evidencia!J5 -> 3690 | M15: =Evidencia!J5 -> 3690 | N15: =Evidencia!J5 -> 3690 | O15: =Evidencia!J5 -> 3690 | P15: =Evidencia!J5 -> 3690 | Q15: =Evidencia!J5 -> 3690
C16: Panel tras elegibilidad hipotética | D16: búsquedas/mes | F16: =IF(COUNT(F15,Supuestos!$D$11,Supuestos!$D$45)=3,IF(0<Supuestos!$D$45,F15*Supuestos!$D$11,0),"N/D") -> 2767.5 | G16: =IF(COUNT(G15,Supuestos!$D$11,Supuestos!$D$45)=3,IF(1<Supuestos!$D$45,G15*Supuestos!$D$11,0),"N/D") -> 2767.5 | H16: =IF(COUNT(H15,Supuestos!$D$11,Supuestos!$D$45)=3,IF(2<Supuestos!$D$45,H15*Supuestos!$D$11,0),"N/D") -> 2767.5 | I16: =IF(COUNT(I15,Supuestos!$D$11,Supuestos!$D$45)=3,IF(3<Supuestos!$D$45,I15*Supuestos!$D$11,0),"N/D") -> 2767.5 | J16: =IF(COUNT(J15,Supuestos!$D$11,Supuestos!$D$45)=3,IF(4<Supuestos!$D$45,J15*Supuestos!$D$11,0),"N/D") -> 2767.5 | K16: =IF(COUNT(K15,Supuestos!$D$11,Supuestos!$D$45)=3,IF(5<Supuestos!$D$45,K15*Supuestos!$D$11,0),"N/D") -> 2767.5 | L16: =IF(COUNT(L15,Supuestos!$D$11,Supuestos!$D$45)=3,IF(6<Supuestos!$D$45,L15*Supuestos!$D$11,0),"N/D") -> 2767.5 | M16: =IF(COUNT(M15,Supuestos!$D$11,Supuestos!$D$45)=3,IF(7<Supuestos!$D$45,M15*Supuestos!$D$11,0),"N/D") -> 2767.5 | N16: =IF(COUNT(N15,Supuestos!$D$11,Supuestos!$D$45)=3,IF(8<Supuestos!$D$45,N15*Supuestos!$D$11,0),"N/D") -> 2767.5 | O16: =IF(COUNT(O15,Supuestos!$D$11,Supuestos!$D$45)=3,IF(9<Supuestos!$D$45,O15*Supuestos!$D$11,0),"N/D") -> 2767.5 | P16: =IF(COUNT(P15,Supuestos!$D$11,Supuestos!$D$45)=3,IF(10<Supuestos!$D$45,P15*Supuestos!$D$11,0),"N/D") -> 2767.5 | Q16: =IF(COUNT(Q15,Supuestos!$D$11,Supuestos!$D$45)=3,IF(11<Supuestos!$D$45,Q15*Supuestos!$D$11,0),"N/D") -> 2767.5
C17: Visitas requeridas / panel elegible | D17: ratio panel | F17: =IF(COUNT(F13,F16)=2,IF(F16>0,F13/F16,"N/D"),"N/D") -> 0.22884673 | G17: =IF(COUNT(G13,G16)=2,IF(G16>0,G13/G16,"N/D"),"N/D") -> 0.22884673 | H17: =IF(COUNT(H13,H16)=2,IF(H16>0,H13/H16,"N/D"),"N/D") -> 0.22884673 | I17: =IF(COUNT(I13,I16)=2,IF(I16>0,I13/I16,"N/D"),"N/D") -> 0.22884673 | J17: =IF(COUNT(J13,J16)=2,IF(J16>0,J13/J16,"N/D"),"N/D") -> 0.22884673 | K17: =IF(COUNT(K13,K16)=2,IF(K16>0,K13/K16,"N/D"),"N/D") -> 0.22884673 | L17: =IF(COUNT(L13,L16)=2,IF(L16>0,L13/L16,"N/D"),"N/D") -> 0.22884673 | M17: =IF(COUNT(M13,M16)=2,IF(M16>0,M13/M16,"N/D"),"N/D") -> 0.22884673 | ... Q17: =IF(COUNT(Q13,Q16)=2,IF(Q16>0,Q13/Q16,"N/D"),"N/D") -> 0.22884673
C19: Saldo externo medio requerido | D19: USD eq. | F19: =Cohortes!L63 -> 7795.9928 | G19: =Cohortes!M63 -> 20814.038 | H19: =Cohortes!N63 -> 34499.437 | I19: =Cohortes!O63 -> 46610.958 | J19: =Cohortes!P63 -> 58785.484 | K19: =Cohortes!Q63 -> 70296.657 | L19: =Cohortes!R63 -> 82049.858 | M19: =Cohortes!S63 -> 93385.928 | ... Q19: =Cohortes!W63 -> 137807.3
C20: Saldo externo al cierre requerido | D20: USD eq. | F20: =Cohortes!L43 -> 14024.111 | G20: =Cohortes!M43 -> 27447.875 | H20: =Cohortes!N43 -> 39983.125 | I20: =Cohortes!O43 -> 52110.139 | J20: =Cohortes!P43 -> 63892.954 | K20: =Cohortes!Q43 -> 75571.708 | L20: =Cohortes!R43 -> 86960.133 | M20: =Cohortes!S43 -> 98243.848 | ... Q20: =Cohortes!W43 -> 142419.88
C22: Valor neto bancario condicionado | D22: USD | F22: =IF(COUNT(Supuestos!$D$45)=1,IF(0>=Supuestos!$D$45,0,IF(AND(Supuestos!$D$16="Sí",Supuestos!$D$52="Saldo medio externo",COUNT(Supuestos!$D$17,F19)=2),F19*Supuestos!$D$17/12,"N/D")),"N/D") -> N/D | G22: =IF(COUNT(Supuestos!$D$45)=1,IF(1>=Supuestos!$D$45,0,IF(AND(Supuestos!$D$16="Sí",Supuestos!$D$52="Saldo medio externo",COUNT(Supuestos!$D$17,G19)=2),G19*Supuestos!$D$17/12,"N/D")),"N/D") -> N/D | H22: =IF(COUNT(Supuestos!$D$45)=1,IF(2>=Supuestos!$D$45,0,IF(AND(Supuestos!$D$16="Sí",Supuestos!$D$52="Saldo medio externo",COUNT(Supuestos!$D$17,H19)=2),H19*Supuestos!$D$17/12,"N/D")),"N/D") -> N/D | I22: =IF(COUNT(Supuestos!$D$45)=1,IF(3>=Supuestos!$D$45,0,IF(AND(Supuestos!$D$16="Sí",Supuestos!$D$52="Saldo medio externo",COUNT(Supuestos!$D$17,I19)=2),I19*Supuestos!$D$17/12,"N/D")),"N/D") -> N/D | J22: =IF(COUNT(Supuestos!$D$45)=1,IF(4>=Supuestos!$D$45,0,IF(AND(Supuestos!$D$16="Sí",Supuestos!$D$52="Saldo medio externo",COUNT(Supuestos!$D$17,J19)=2),J19*Supuestos!$D$17/12,"N/D")),"N/D") -> N/D | K22: =IF(COUNT(Supuestos!$D$45)=1,IF(5>=Supuestos!$D$45,0,IF(AND(Supuestos!$D$16="Sí",Supuestos!$D$52="Saldo medio externo",COUNT(Supuestos!$D$17,K19)=2),K19*Supuestos!$D$17/12,"N/D")),"N/D") -> N/D | L22: =IF(COUNT(Supuestos!$D$45)=1,IF(6>=Supuestos!$D$45,0,IF(AND(Supuestos!$D$16="Sí",Supuestos!$D$52="Saldo medio externo",COUNT(Supuestos!$D$17,L19)=2),L19*Supuestos!$D$17/12,"N/D")),"N/D") -> N/D | M22: =IF(COUNT(Supuestos!$D$45)=1,IF(7>=Supuestos!$D$45,0,IF(AND(Supuestos!$D$16="Sí",Supuestos!$D$52="Saldo medio externo",COUNT(Supuestos!$D$17,M19)=2),M19*Supuestos!$D$17/12,"N/D")),"N/D") -> N/D | N22: =IF(COUNT(Supuestos!$D$45)=1,IF(8>=Supuestos!$D$45,0,IF(AND(Supuestos!$D$16="Sí",Supuestos!$D$52="Saldo medio externo",COUNT(Supuestos!$D$17,N19)=2),N19*Supuestos!$D$17/12,"N/D")),"N/D") -> N/D | O22: =IF(COUNT(Supuestos!$D$45)=1,IF(9>=Supuestos!$D$45,0,IF(AND(Supuestos!$D$16="Sí",Supuestos!$D$52="Saldo medio externo",COUNT(Supuestos!$D$17,O19)=2),O19*Supuestos!$D$17/12,"N/D")),"N/D") -> N/D | P22: =IF(COUNT(Supuestos!$D$45)=1,IF(10>=Supuestos!$D$45,0,IF(AND(Supuestos!$D$16="Sí",Supuestos!$D$52="Saldo medio externo",COUNT(Supuestos!$D$17,P19)=2),P19*Supuestos!$D$17/12,"N/D")),"N/D") -> N/D | Q22: =IF(COUNT(Supuestos!$D$45)=1,IF(11>=Supuestos!$D$45,0,IF(AND(Supuestos!$D$16="Sí",Supuestos!$D$52="Saldo medio externo",COUNT(Supuestos!$D$17,Q19)=2),Q19*Supuestos!$D$17/12,"N/D")),"N/D") -> N/D
C23: Inversión cliente pendiente | D23: USD | F23: =IF(COUNT(Supuestos!$D$45)=1,IF(0>=Supuestos!$D$45,0,IF(COUNT(Supuestos!F32)=1,IF(Supuestos!F32>=0,Supuestos!F32,"N/D"),"N/D")),"N/D") -> N/D | G23: =IF(COUNT(Supuestos!$D$45)=1,IF(1>=Supuestos!$D$45,0,IF(COUNT(Supuestos!G32)=1,IF(Supuestos!G32>=0,Supuestos!G32,"N/D"),"N/D")),"N/D") -> N/D | H23: =IF(COUNT(Supuestos!$D$45)=1,IF(2>=Supuestos!$D$45,0,IF(COUNT(Supuestos!H32)=1,IF(Supuestos!H32>=0,Supuestos!H32,"N/D"),"N/D")),"N/D") -> N/D | I23: =IF(COUNT(Supuestos!$D$45)=1,IF(3>=Supuestos!$D$45,0,IF(COUNT(Supuestos!I32)=1,IF(Supuestos!I32>=0,Supuestos!I32,"N/D"),"N/D")),"N/D") -> N/D | J23: =IF(COUNT(Supuestos!$D$45)=1,IF(4>=Supuestos!$D$45,0,IF(COUNT(Supuestos!J32)=1,IF(Supuestos!J32>=0,Supuestos!J32,"N/D"),"N/D")),"N/D") -> N/D | K23: =IF(COUNT(Supuestos!$D$45)=1,IF(5>=Supuestos!$D$45,0,IF(COUNT(Supuestos!K32)=1,IF(Supuestos!K32>=0,Supuestos!K32,"N/D"),"N/D")),"N/D") -> N/D | L23: =IF(COUNT(Supuestos!$D$45)=1,IF(6>=Supuestos!$D$45,0,IF(COUNT(Supuestos!L32)=1,IF(Supuestos!L32>=0,Supuestos!L32,"N/D"),"N/D")),"N/D") -> N/D | M23: =IF(COUNT(Supuestos!$D$45)=1,IF(7>=Supuestos!$D$45,0,IF(COUNT(Supuestos!M32)=1,IF(Supuestos!M32>=0,Supuestos!M32,"N/D"),"N/D")),"N/D") -> N/D | N23: =IF(COUNT(Supuestos!$D$45)=1,IF(8>=Supuestos!$D$45,0,IF(COUNT(Supuestos!N32)=1,IF(Supuestos!N32>=0,Supuestos!N32,"N/D"),"N/D")),"N/D") -> N/D | O23: =IF(COUNT(Supuestos!$D$45)=1,IF(9>=Supuestos!$D$45,0,IF(COUNT(Supuestos!O32)=1,IF(Supuestos!O32>=0,Supuestos!O32,"N/D"),"N/D")),"N/D") -> N/D | P23: =IF(COUNT(Supuestos!$D$45)=1,IF(10>=Supuestos!$D$45,0,IF(COUNT(Supuestos!P32)=1,IF(Supuestos!P32>=0,Supuestos!P32,"N/D"),"N/D")),"N/D") -> N/D | Q23: =IF(COUNT(Supuestos!$D$45)=1,IF(11>=Supuestos!$D$45,0,IF(COUNT(Supuestos!Q32)=1,IF(Supuestos!Q32>=0,Supuestos!Q32,"N/D"),"N/D")),"N/D") -> N/D
C24: Valor acumulado condicionado | D24: USD | F24: =IF(COUNT($F$22:F22)=1,SUM($F$22:F22),"N/D") -> N/D | G24: =IF(COUNT($F$22:G22)=2,SUM($F$22:G22),"N/D") -> N/D | H24: =IF(COUNT($F$22:H22)=3,SUM($F$22:H22),"N/D") -> N/D | I24: =IF(COUNT($F$22:I22)=4,SUM($F$22:I22),"N/D") -> N/D | J24: =IF(COUNT($F$22:J22)=5,SUM($F$22:J22),"N/D") -> N/D | K24: =IF(COUNT($F$22:K22)=6,SUM($F$22:K22),"N/D") -> N/D | L24: =IF(COUNT($F$22:L22)=7,SUM($F$22:L22),"N/D") -> N/D | M24: =IF(COUNT($F$22:M22)=8,SUM($F$22:M22),"N/D") -> N/D | N24: =IF(COUNT($F$22:N22)=9,SUM($F$22:N22),"N/D") -> N/D | O24: =IF(COUNT($F$22:O22)=10,SUM($F$22:O22),"N/D") -> N/D | P24: =IF(COUNT($F$22:P22)=11,SUM($F$22:P22),"N/D") -> N/D | Q24: =IF(COUNT($F$22:Q22)=12,SUM($F$22:Q22),"N/D") -> N/D
C25: Inversión acumulada | D25: USD | F25: =IF(COUNT($F$23:F23)=1,SUM($F$23:F23),"N/D") -> N/D | G25: =IF(COUNT($F$23:G23)=2,SUM($F$23:G23),"N/D") -> N/D | H25: =IF(COUNT($F$23:H23)=3,SUM($F$23:H23),"N/D") -> N/D | I25: =IF(COUNT($F$23:I23)=4,SUM($F$23:I23),"N/D") -> N/D | J25: =IF(COUNT($F$23:J23)=5,SUM($F$23:J23),"N/D") -> N/D | K25: =IF(COUNT($F$23:K23)=6,SUM($F$23:K23),"N/D") -> N/D | L25: =IF(COUNT($F$23:L23)=7,SUM($F$23:L23),"N/D") -> N/D | M25: =IF(COUNT($F$23:M23)=8,SUM($F$23:M23),"N/D") -> N/D | N25: =IF(COUNT($F$23:N23)=9,SUM($F$23:N23),"N/D") -> N/D | O25: =IF(COUNT($F$23:O23)=10,SUM($F$23:O23),"N/D") -> N/D | P25: =IF(COUNT($F$23:P23)=11,SUM($F$23:P23),"N/D") -> N/D | Q25: =IF(COUNT($F$23:Q23)=12,SUM($F$23:Q23),"N/D") -> N/D
C26: ROI condicional a logro de la banda | D26: % | F26: =IF(AND(Supuestos!$D$16="Sí",Supuestos!$D$19="Sí",COUNT(F24,F25)=2,F25>0),(F24-F25)/F25,"N/D") -> N/D | G26: =IF(AND(Supuestos!$D$16="Sí",Supuestos!$D$19="Sí",COUNT(G24,G25)=2,G25>0),(G24-G25)/G25,"N/D") -> N/D | H26: =IF(AND(Supuestos!$D$16="Sí",Supuestos!$D$19="Sí",COUNT(H24,H25)=2,H25>0),(H24-H25)/H25,"N/D") -> N/D | I26: =IF(AND(Supuestos!$D$16="Sí",Supuestos!$D$19="Sí",COUNT(I24,I25)=2,I25>0),(I24-I25)/I25,"N/D") -> N/D | J26: =IF(AND(Supuestos!$D$16="Sí",Supuestos!$D$19="Sí",COUNT(J24,J25)=2,J25>0),(J24-J25)/J25,"N/D") -> N/D | K26: =IF(AND(Supuestos!$D$16="Sí",Supuestos!$D$19="Sí",COUNT(K24,K25)=2,K25>0),(K24-K25)/K25,"N/D") -> N/D | L26: =IF(AND(Supuestos!$D$16="Sí",Supuestos!$D$19="Sí",COUNT(L24,L25)=2,L25>0),(L24-L25)/L25,"N/D") -> N/D | M26: =IF(AND(Supuestos!$D$16="Sí",Supuestos!$D$19="Sí",COUNT(M24,M25)=2,M25>0),(M24-M25)/M25,"N/D") -> N/D | ... Q26: =IF(AND(Supuestos!$D$16="Sí",Supuestos!$D$19="Sí",COUNT(Q24,Q25)=2,Q25>0),(Q24-Q25)/Q25,"N/D") -> N/D
C27: Recuperación alcanzada (condicional) | D27: 0/1 | F27: =IF(COUNT(F26)=1,IF(F26>=0,1,0),"N/D") -> N/D | G27: =IF(COUNT(G26)=1,IF(G26>=0,1,0),"N/D") -> N/D | H27: =IF(COUNT(H26)=1,IF(H26>=0,1,0),"N/D") -> N/D | I27: =IF(COUNT(I26)=1,IF(I26>=0,1,0),"N/D") -> N/D | J27: =IF(COUNT(J26)=1,IF(J26>=0,1,0),"N/D") -> N/D | K27: =IF(COUNT(K26)=1,IF(K26>=0,1,0),"N/D") -> N/D | L27: =IF(COUNT(L26)=1,IF(L26>=0,1,0),"N/D") -> N/D | M27: =IF(COUNT(M26)=1,IF(M26>=0,1,0),"N/D") -> N/D | ... Q27: =IF(COUNT(Q26)=1,IF(Q26>=0,1,0),"N/D") -> N/D
C30: Un ratio >100% significa que este panel no alcanza para el requisito bajo esos supuestos; no demuestra inviabilidad del mercado.
C31: El denominador es una canasta parcial de consultas, con overlap residual. No son personas únicas, TAM ni visitas Pibank.
C32: Marca, educación, activación y retención tienen recorridos distintos; sus retornos permanecen N/D sin baseline y deduplicación.
C33: Toda valoración/ROI es condicional al logro de la banda. No transforma requisitos en forecast ni atribuye todo al SEO/AEO.

Sheet Cohortes
C2: Saldo externo y valor dentro del horizonte 2027
C6: Primer fondeo | D6: Cuentas requeridas | E6: Ticket USD eq. | F6: Origen externo | G6: Ret30 | H6: Ret60 | I6: Ret90 | J6: Ret180 | K6: Ret365 | L6: M1 | M6: M2 | N6: M3 | O6: M4 | P6: M5 | Q6: M6 | R6: M7 | S6: M8 | T6: M9 | U6: M10 | V6: M11 | W6: M12
L7: =Supuestos!F31 -> 46388 | M7: =Supuestos!G31 -> 46419 | N7: =Supuestos!H31 -> 46447 | O7: =Supuestos!I31 -> 46478 | P7: =Supuestos!J31 -> 46508 | Q7: =Supuestos!K31 -> 46539 | R7: =Supuestos!L31 -> 46569 | S7: =Supuestos!M31 -> 46600 | ... W7: =Supuestos!Q31 -> 46722
C9: =IF(COUNT(Supuestos!F31,Supuestos!$D$14,Supuestos!$D$36)=3,MAX(Supuestos!$D$36,DATE(YEAR(Supuestos!F31),MONTH(Supuestos!F31),Supuestos!$D$14)),"N/D") -> 46402 | D9: =Requisitos!F11 -> 8.2333333 | E9: =Supuestos!$D$8 -> 2500 | F9: =IF(COUNT(Supuestos!F44)=1,Supuestos!F44,"N/D") -> 0.7 | G9: =IF(COUNT(Supuestos!$D$37)=1,Supuestos!$D$37,"N/D") -> 0.95 | H9: =IF(COUNT(Supuestos!$D$38)=1,Supuestos!$D$38,"N/D") -> 0.9 | I9: =IF(COUNT(Supuestos!$D$39)=1,Supuestos!$D$39,"N/D") -> 0.85 | J9: =IF(COUNT(Supuestos!$D$40)=1,Supuestos!$D$40,"N/D") -> 0.8 | K9: =IF(COUNT(Supuestos!$D$41)=1,Supuestos!$D$41,"N/D") -> 0.75 | L9: =IF(COUNT($D9,$E9,L95)=3,$D9*$E9*L95,"N/D") -> 20034.444 | M9: =IF(COUNT($D9,$E9,M95)=3,$D9*$E9*M95,"N/D") -> 19073.889 | N9: =IF(COUNT($D9,$E9,N95)=3,$D9*$E9*N95,"N/D") -> 18010.417 | O9: =IF(COUNT($D9,$E9,O95)=3,$D9*$E9*O95,"N/D") -> 17324.306 | P9: =IF(COUNT($D9,$E9,P95)=3,$D9*$E9*P95,"N/D") -> 16969.815 | Q9: =IF(COUNT($D9,$E9,Q95)=3,$D9*$E9*Q95,"N/D") -> 16626.759 | R9: =IF(COUNT($D9,$E9,R95)=3,$D9*$E9*R95,"N/D") -> 16372.095 | S9: =IF(COUNT($D9,$E9,S95)=3,$D9*$E9*S95,"N/D") -> 16199.64 | ... W9: =IF(COUNT($D9,$E9,W95)=3,$D9*$E9*W95,"N/D") -> 15520.946
C10: =IF(COUNT(Supuestos!G31,Supuestos!$D$14,Supuestos!$D$36)=3,MAX(Supuestos!$D$36,DATE(YEAR(Supuestos!G31),MONTH(Supuestos!G31),Supuestos!$D$14)),"N/D") -> 46433 | D10: =Requisitos!G11 -> 8.2333333 | E10: =Supuestos!$D$8 -> 2500 | F10: =IF(COUNT(Supuestos!G44)=1,Supuestos!G44,"N/D") -> 0.7 | G10: =IF(COUNT(Supuestos!$D$37)=1,Supuestos!$D$37,"N/D") -> 0.95 | H10: =IF(COUNT(Supuestos!$D$38)=1,Supuestos!$D$38,"N/D") -> 0.9 | I10: =IF(COUNT(Supuestos!$D$39)=1,Supuestos!$D$39,"N/D") -> 0.85 | J10: =IF(COUNT(Supuestos!$D$40)=1,Supuestos!$D$40,"N/D") -> 0.8 | K10: =IF(COUNT(Supuestos!$D$41)=1,Supuestos!$D$41,"N/D") -> 0.75 | L10: =IF(COUNT($D10,$E10,L96)=3,$D10*$E10*L96,"N/D") -> 0 | M10: =IF(COUNT($D10,$E10,M96)=3,$D10*$E10*M96,"N/D") -> 20137.361 | N10: =IF(COUNT($D10,$E10,N96)=3,$D10*$E10*N96,"N/D") -> 19073.889 | O10: =IF(COUNT($D10,$E10,O96)=3,$D10*$E10*O96,"N/D") -> 18044.722 | P10: =IF(COUNT($D10,$E10,P96)=3,$D10*$E10*P96,"N/D") -> 17324.306 | Q10: =IF(COUNT($D10,$E10,Q96)=3,$D10*$E10*Q96,"N/D") -> 16981.25 | R10: =IF(COUNT($D10,$E10,R96)=3,$D10*$E10*R96,"N/D") -> 16626.759 | S10: =IF(COUNT($D10,$E10,S96)=3,$D10*$E10*S96,"N/D") -> 16372.095 | ... W10: =IF(COUNT($D10,$E10,W96)=3,$D10*$E10*W96,"N/D") -> 15693.401
C11: =IF(COUNT(Supuestos!H31,Supuestos!$D$14,Supuestos!$D$36)=3,MAX(Supuestos!$D$36,DATE(YEAR(Supuestos!H31),MONTH(Supuestos!H31),Supuestos!$D$14)),"N/D") -> 46461 | D11: =Requisitos!H11 -> 8.2333333 | E11: =Supuestos!$D$8 -> 2500 | F11: =IF(COUNT(Supuestos!H44)=1,Supuestos!H44,"N/D") -> 0.7 | G11: =IF(COUNT(Supuestos!$D$37)=1,Supuestos!$D$37,"N/D") -> 0.95 | H11: =IF(COUNT(Supuestos!$D$38)=1,Supuestos!$D$38,"N/D") -> 0.9 | I11: =IF(COUNT(Supuestos!$D$39)=1,Supuestos!$D$39,"N/D") -> 0.85 | J11: =IF(COUNT(Supuestos!$D$40)=1,Supuestos!$D$40,"N/D") -> 0.8 | K11: =IF(COUNT(Supuestos!$D$41)=1,Supuestos!$D$41,"N/D") -> 0.75 | L11: =IF(COUNT($D11,$E11,L97)=3,$D11*$E11*L97,"N/D") -> 0 | M11: =IF(COUNT($D11,$E11,M97)=3,$D11*$E11*M97,"N/D") -> 0 | N11: =IF(COUNT($D11,$E11,N97)=3,$D11*$E11*N97,"N/D") -> 20034.444 | O11: =IF(COUNT($D11,$E11,O97)=3,$D11*$E11*O97,"N/D") -> 19005.278 | P11: =IF(COUNT($D11,$E11,P97)=3,$D11*$E11*P97,"N/D") -> 17941.806 | Q11: =IF(COUNT($D11,$E11,Q97)=3,$D11*$E11*Q97,"N/D") -> 17301.435 | R11: =IF(COUNT($D11,$E11,R97)=3,$D11*$E11*R97,"N/D") -> 16946.944 | S11: =IF(COUNT($D11,$E11,S97)=3,$D11*$E11*S97,"N/D") -> 16592.454 | ... W11: =IF(COUNT($D11,$E11,W97)=3,$D11*$E11*W97,"N/D") -> 15849.167
C12: =IF(COUNT(Supuestos!I31,Supuestos!$D$14,Supuestos!$D$36)=3,MAX(Supuestos!$D$36,DATE(YEAR(Supuestos!I31),MONTH(Supuestos!I31),Supuestos!$D$14)),"N/D") -> 46492 | D12: =Requisitos!I11 -> 8.2333333 | E12: =Supuestos!$D$8 -> 2500 | F12: =IF(COUNT(Supuestos!I44)=1,Supuestos!I44,"N/D") -> 0.7 | G12: =IF(COUNT(Supuestos!$D$37)=1,Supuestos!$D$37,"N/D") -> 0.95 | H12: =IF(COUNT(Supuestos!$D$38)=1,Supuestos!$D$38,"N/D") -> 0.9 | I12: =IF(COUNT(Supuestos!$D$39)=1,Supuestos!$D$39,"N/D") -> 0.85 | J12: =IF(COUNT(Supuestos!$D$40)=1,Supuestos!$D$40,"N/D") -> 0.8 | K12: =IF(COUNT(Supuestos!$D$41)=1,Supuestos!$D$41,"N/D") -> 0.75 | L12: =IF(COUNT($D12,$E12,L98)=3,$D12*$E12*L98,"N/D") -> 0 | M12: =IF(COUNT($D12,$E12,M98)=3,$D12*$E12*M98,"N/D") -> 0 | N12: =IF(COUNT($D12,$E12,N98)=3,$D12*$E12*N98,"N/D") -> 0 | O12: =IF(COUNT($D12,$E12,O98)=3,$D12*$E12*O98,"N/D") -> 20068.75 | P12: =IF(COUNT($D12,$E12,P98)=3,$D12*$E12*P98,"N/D") -> 19005.278 | Q12: =IF(COUNT($D12,$E12,Q98)=3,$D12*$E12*Q98,"N/D") -> 17976.111 | R12: =IF(COUNT($D12,$E12,R98)=3,$D12*$E12*R98,"N/D") -> 17301.435 | S12: =IF(COUNT($D12,$E12,S98)=3,$D12*$E12*S98,"N/D") -> 16946.944 | ... W12: =IF(COUNT($D12,$E12,W98)=3,$D12*$E12*W98,"N/D") -> 16021.622
C13: =IF(COUNT(Supuestos!J31,Supuestos!$D$14,Supuestos!$D$36)=3,MAX(Supuestos!$D$36,DATE(YEAR(Supuestos!J31),MONTH(Supuestos!J31),Supuestos!$D$14)),"N/D") -> 46522 | D13: =Requisitos!J11 -> 8.2333333 | E13: =Supuestos!$D$8 -> 2500 | F13: =IF(COUNT(Supuestos!J44)=1,Supuestos!J44,"N/D") -> 0.7 | G13: =IF(COUNT(Supuestos!$D$37)=1,Supuestos!$D$37,"N/D") -> 0.95 | H13: =IF(COUNT(Supuestos!$D$38)=1,Supuestos!$D$38,"N/D") -> 0.9 | I13: =IF(COUNT(Supuestos!$D$39)=1,Supuestos!$D$39,"N/D") -> 0.85 | J13: =IF(COUNT(Supuestos!$D$40)=1,Supuestos!$D$40,"N/D") -> 0.8 | K13: =IF(COUNT(Supuestos!$D$41)=1,Supuestos!$D$41,"N/D") -> 0.75 | L13: =IF(COUNT($D13,$E13,L99)=3,$D13*$E13*L99,"N/D") -> 0 | M13: =IF(COUNT($D13,$E13,M99)=3,$D13*$E13*M99,"N/D") -> 0 | N13: =IF(COUNT($D13,$E13,N99)=3,$D13*$E13*N99,"N/D") -> 0 | O13: =IF(COUNT($D13,$E13,O99)=3,$D13*$E13*O99,"N/D") -> 0 | P13: =IF(COUNT($D13,$E13,P99)=3,$D13*$E13*P99,"N/D") -> 20034.444 | Q13: =IF(COUNT($D13,$E13,Q99)=3,$D13*$E13*Q99,"N/D") -> 19005.278 | R13: =IF(COUNT($D13,$E13,R99)=3,$D13*$E13*R99,"N/D") -> 17941.806 | S13: =IF(COUNT($D13,$E13,S99)=3,$D13*$E13*S99,"N/D") -> 17290 | ... W13: =IF(COUNT($D13,$E13,W99)=3,$D13*$E13*W99,"N/D") -> 16188.514
C14: =IF(COUNT(Supuestos!K31,Supuestos!$D$14,Supuestos!$D$36)=3,MAX(Supuestos!$D$36,DATE(YEAR(Supuestos!K31),MONTH(Supuestos!K31),Supuestos!$D$14)),"N/D") -> 46553 | D14: =Requisitos!K11 -> 8.2333333 | E14: =Supuestos!$D$8 -> 2500 | F14: =IF(COUNT(Supuestos!K44)=1,Supuestos!K44,"N/D") -> 0.7 | G14: =IF(COUNT(Supuestos!$D$37)=1,Supuestos!$D$37,"N/D") -> 0.95 | H14: =IF(COUNT(Supuestos!$D$38)=1,Supuestos!$D$38,"N/D") -> 0.9 | I14: =IF(COUNT(Supuestos!$D$39)=1,Supuestos!$D$39,"N/D") -> 0.85 | J14: =IF(COUNT(Supuestos!$D$40)=1,Supuestos!$D$40,"N/D") -> 0.8 | K14: =IF(COUNT(Supuestos!$D$41)=1,Supuestos!$D$41,"N/D") -> 0.75 | L14: =IF(COUNT($D14,$E14,L100)=3,$D14*$E14*L100,"N/D") -> 0 | M14: =IF(COUNT($D14,$E14,M100)=3,$D14*$E14*M100,"N/D") -> 0 | N14: =IF(COUNT($D14,$E14,N100)=3,$D14*$E14*N100,"N/D") -> 0 | O14: =IF(COUNT($D14,$E14,O100)=3,$D14*$E14*O100,"N/D") -> 0 | P14: =IF(COUNT($D14,$E14,P100)=3,$D14*$E14*P100,"N/D") -> 0 | Q14: =IF(COUNT($D14,$E14,Q100)=3,$D14*$E14*Q100,"N/D") -> 20068.75 | R14: =IF(COUNT($D14,$E14,R100)=3,$D14*$E14*R100,"N/D") -> 19005.278 | S14: =IF(COUNT($D14,$E14,S100)=3,$D14*$E14*S100,"N/D") -> 17941.806 | ... W14: =IF(COUNT($D14,$E14,W100)=3,$D14*$E14*W100,"N/D") -> 16360.968
C15: =IF(COUNT(Supuestos!L31,Supuestos!$D$14,Supuestos!$D$36)=3,MAX(Supuestos!$D$36,DATE(YEAR(Supuestos!L31),MONTH(Supuestos!L31),Supuestos!$D$14)),"N/D") -> 46583 | D15: =Requisitos!L11 -> 8.2333333 | E15: =Supuestos!$D$8 -> 2500 | F15: =IF(COUNT(Supuestos!L44)=1,Supuestos!L44,"N/D") -> 0.7 | G15: =IF(COUNT(Supuestos!$D$37)=1,Supuestos!$D$37,"N/D") -> 0.95 | H15: =IF(COUNT(Supuestos!$D$38)=1,Supuestos!$D$38,"N/D") -> 0.9 | I15: =IF(COUNT(Supuestos!$D$39)=1,Supuestos!$D$39,"N/D") -> 0.85 | J15: =IF(COUNT(Supuestos!$D$40)=1,Supuestos!$D$40,"N/D") -> 0.8 | K15: =IF(COUNT(Supuestos!$D$41)=1,Supuestos!$D$41,"N/D") -> 0.75 | L15: =IF(COUNT($D15,$E15,L101)=3,$D15*$E15*L101,"N/D") -> 0 | M15: =IF(COUNT($D15,$E15,M101)=3,$D15*$E15*M101,"N/D") -> 0 | N15: =IF(COUNT($D15,$E15,N101)=3,$D15*$E15*N101,"N/D") -> 0 | O15: =IF(COUNT($D15,$E15,O101)=3,$D15*$E15*O101,"N/D") -> 0 | P15: =IF(COUNT($D15,$E15,P101)=3,$D15*$E15*P101,"N/D") -> 0 | Q15: =IF(COUNT($D15,$E15,Q101)=3,$D15*$E15*Q101,"N/D") -> 0 | R15: =IF(COUNT($D15,$E15,R101)=3,$D15*$E15*R101,"N/D") -> 20034.444 | S15: =IF(COUNT($D15,$E15,S101)=3,$D15*$E15*S101,"N/D") -> 18970.972 | ... W15: =IF(COUNT($D15,$E15,W101)=3,$D15*$E15*W101,"N/D") -> 16592.454
C16: =IF(COUNT(Supuestos!M31,Supuestos!$D$14,Supuestos!$D$36)=3,MAX(Supuestos!$D$36,DATE(YEAR(Supuestos!M31),MONTH(Supuestos!M31),Supuestos!$D$14)),"N/D") -> 46614 | D16: =Requisitos!M11 -> 8.2333333 | E16: =Supuestos!$D$8 -> 2500 | F16: =IF(COUNT(Supuestos!M44)=1,Supuestos!M44,"N/D") -> 0.7 | G16: =IF(COUNT(Supuestos!$D$37)=1,Supuestos!$D$37,"N/D") -> 0.95 | H16: =IF(COUNT(Supuestos!$D$38)=1,Supuestos!$D$38,"N/D") -> 0.9 | I16: =IF(COUNT(Supuestos!$D$39)=1,Supuestos!$D$39,"N/D") -> 0.85 | J16: =IF(COUNT(Supuestos!$D$40)=1,Supuestos!$D$40,"N/D") -> 0.8 | K16: =IF(COUNT(Supuestos!$D$41)=1,Supuestos!$D$41,"N/D") -> 0.75 | L16: =IF(COUNT($D16,$E16,L102)=3,$D16*$E16*L102,"N/D") -> 0 | M16: =IF(COUNT($D16,$E16,M102)=3,$D16*$E16*M102,"N/D") -> 0 | N16: =IF(COUNT($D16,$E16,N102)=3,$D16*$E16*N102,"N/D") -> 0 | O16: =IF(COUNT($D16,$E16,O102)=3,$D16*$E16*O102,"N/D") -> 0 | P16: =IF(COUNT($D16,$E16,P102)=3,$D16*$E16*P102,"N/D") -> 0 | Q16: =IF(COUNT($D16,$E16,Q102)=3,$D16*$E16*Q102,"N/D") -> 0 | R16: =IF(COUNT($D16,$E16,R102)=3,$D16*$E16*R102,"N/D") -> 0 | S16: =IF(COUNT($D16,$E16,S102)=3,$D16*$E16*S102,"N/D") -> 20034.444 | ... W16: =IF(COUNT($D16,$E16,W102)=3,$D16*$E16*W102,"N/D") -> 16946.944
C17: =IF(COUNT(Supuestos!N31,Supuestos!$D$14,Supuestos!$D$36)=3,MAX(Supuestos!$D$36,DATE(YEAR(Supuestos!N31),MONTH(Supuestos!N31),Supuestos!$D$14)),"N/D") -> 46645 | D17: =Requisitos!N11 -> 8.2333333 | E17: =Supuestos!$D$8 -> 2500 | F17: =IF(COUNT(Supuestos!N44)=1,Supuestos!N44,"N/D") -> 0.7 | G17: =IF(COUNT(Supuestos!$D$37)=1,Supuestos!$D$37,"N/D") -> 0.95 | H17: =IF(COUNT(Supuestos!$D$38)=1,Supuestos!$D$38,"N/D") -> 0.9 | I17: =IF(COUNT(Supuestos!$D$39)=1,Supuestos!$D$39,"N/D") -> 0.85 | J17: =IF(COUNT(Supuestos!$D$40)=1,Supuestos!$D$40,"N/D") -> 0.8 | K17: =IF(COUNT(Supuestos!$D$41)=1,Supuestos!$D$41,"N/D") -> 0.75 | L17: =IF(COUNT($D17,$E17,L103)=3,$D17*$E17*L103,"N/D") -> 0 | M17: =IF(COUNT($D17,$E17,M103)=3,$D17*$E17*M103,"N/D") -> 0 | N17: =IF(COUNT($D17,$E17,N103)=3,$D17*$E17*N103,"N/D") -> 0 | O17: =IF(COUNT($D17,$E17,O103)=3,$D17*$E17*O103,"N/D") -> 0 | P17: =IF(COUNT($D17,$E17,P103)=3,$D17*$E17*P103,"N/D") -> 0 | Q17: =IF(COUNT($D17,$E17,Q103)=3,$D17*$E17*Q103,"N/D") -> 0 | R17: =IF(COUNT($D17,$E17,R103)=3,$D17*$E17*R103,"N/D") -> 0 | S17: =IF(COUNT($D17,$E17,S103)=3,$D17*$E17*S103,"N/D") -> 0 | ... W17: =IF(COUNT($D17,$E17,W103)=3,$D17*$E17*W103,"N/D") -> 17301.435
C18: =IF(COUNT(Supuestos!O31,Supuestos!$D$14,Supuestos!$D$36)=3,MAX(Supuestos!$D$36,DATE(YEAR(Supuestos!O31),MONTH(Supuestos!O31),Supuestos!$D$14)),"N/D") -> 46675 | D18: =Requisitos!O11 -> 8.2333333 | E18: =Supuestos!$D$8 -> 2500 | F18: =IF(COUNT(Supuestos!O44)=1,Supuestos!O44,"N/D") -> 0.7 | G18: =IF(COUNT(Supuestos!$D$37)=1,Supuestos!$D$37,"N/D") -> 0.95 | H18: =IF(COUNT(Supuestos!$D$38)=1,Supuestos!$D$38,"N/D") -> 0.9 | I18: =IF(COUNT(Supuestos!$D$39)=1,Supuestos!$D$39,"N/D") -> 0.85 | J18: =IF(COUNT(Supuestos!$D$40)=1,Supuestos!$D$40,"N/D") -> 0.8 | K18: =IF(COUNT(Supuestos!$D$41)=1,Supuestos!$D$41,"N/D") -> 0.75 | L18: =IF(COUNT($D18,$E18,L104)=3,$D18*$E18*L104,"N/D") -> 0 | M18: =IF(COUNT($D18,$E18,M104)=3,$D18*$E18*M104,"N/D") -> 0 | N18: =IF(COUNT($D18,$E18,N104)=3,$D18*$E18*N104,"N/D") -> 0 | O18: =IF(COUNT($D18,$E18,O104)=3,$D18*$E18*O104,"N/D") -> 0 | P18: =IF(COUNT($D18,$E18,P104)=3,$D18*$E18*P104,"N/D") -> 0 | Q18: =IF(COUNT($D18,$E18,Q104)=3,$D18*$E18*Q104,"N/D") -> 0 | R18: =IF(COUNT($D18,$E18,R104)=3,$D18*$E18*R104,"N/D") -> 0 | S18: =IF(COUNT($D18,$E18,S104)=3,$D18*$E18*S104,"N/D") -> 0 | ... W18: =IF(COUNT($D18,$E18,W104)=3,$D18*$E18*W104,"N/D") -> 17941.806
C19: =IF(COUNT(Supuestos!P31,Supuestos!$D$14,Supuestos!$D$36)=3,MAX(Supuestos!$D$36,DATE(YEAR(Supuestos!P31),MONTH(Supuestos!P31),Supuestos!$D$14)),"N/D") -> 46706 | D19: =Requisitos!P11 -> 8.2333333 | E19: =Supuestos!$D$8 -> 2500 | F19: =IF(COUNT(Supuestos!P44)=1,Supuestos!P44,"N/D") -> 0.7 | G19: =IF(COUNT(Supuestos!$D$37)=1,Supuestos!$D$37,"N/D") -> 0.95 | H19: =IF(COUNT(Supuestos!$D$38)=1,Supuestos!$D$38,"N/D") -> 0.9 | I19: =IF(COUNT(Supuestos!$D$39)=1,Supuestos!$D$39,"N/D") -> 0.85 | J19: =IF(COUNT(Supuestos!$D$40)=1,Supuestos!$D$40,"N/D") -> 0.8 | K19: =IF(COUNT(Supuestos!$D$41)=1,Supuestos!$D$41,"N/D") -> 0.75 | L19: =IF(COUNT($D19,$E19,L105)=3,$D19*$E19*L105,"N/D") -> 0 | M19: =IF(COUNT($D19,$E19,M105)=3,$D19*$E19*M105,"N/D") -> 0 | N19: =IF(COUNT($D19,$E19,N105)=3,$D19*$E19*N105,"N/D") -> 0 | O19: =IF(COUNT($D19,$E19,O105)=3,$D19*$E19*O105,"N/D") -> 0 | P19: =IF(COUNT($D19,$E19,P105)=3,$D19*$E19*P105,"N/D") -> 0 | Q19: =IF(COUNT($D19,$E19,Q105)=3,$D19*$E19*Q105,"N/D") -> 0 | R19: =IF(COUNT($D19,$E19,R105)=3,$D19*$E19*R105,"N/D") -> 0 | S19: =IF(COUNT($D19,$E19,S105)=3,$D19*$E19*S105,"N/D") -> 0 | ... W19: =IF(COUNT($D19,$E19,W105)=3,$D19*$E19*W105,"N/D") -> 19005.278
C20: =IF(COUNT(Supuestos!Q31,Supuestos!$D$14,Supuestos!$D$36)=3,MAX(Supuestos!$D$36,DATE(YEAR(Supuestos!Q31),MONTH(Supuestos!Q31),Supuestos!$D$14)),"N/D") -> 46736 | D20: =Requisitos!Q11 -> 8.2333333 | E20: =Supuestos!$D$8 -> 2500 | F20: =IF(COUNT(Supuestos!Q44)=1,Supuestos!Q44,"N/D") -> 0.7 | G20: =IF(COUNT(Supuestos!$D$37)=1,Supuestos!$D$37,"N/D") -> 0.95 | H20: =IF(COUNT(Supuestos!$D$38)=1,Supuestos!$D$38,"N/D") -> 0.9 | I20: =IF(COUNT(Supuestos!$D$39)=1,Supuestos!$D$39,"N/D") -> 0.85 | J20: =IF(COUNT(Supuestos!$D$40)=1,Supuestos!$D$40,"N/D") -> 0.8 | K20: =IF(COUNT(Supuestos!$D$41)=1,Supuestos!$D$41,"N/D") -> 0.75 | L20: =IF(COUNT($D20,$E20,L106)=3,$D20*$E20*L106,"N/D") -> 0 | M20: =IF(COUNT($D20,$E20,M106)=3,$D20*$E20*M106,"N/D") -> 0 | N20: =IF(COUNT($D20,$E20,N106)=3,$D20*$E20*N106,"N/D") -> 0 | O20: =IF(COUNT($D20,$E20,O106)=3,$D20*$E20*O106,"N/D") -> 0 | P20: =IF(COUNT($D20,$E20,P106)=3,$D20*$E20*P106,"N/D") -> 0 | Q20: =IF(COUNT($D20,$E20,Q106)=3,$D20*$E20*Q106,"N/D") -> 0 | R20: =IF(COUNT($D20,$E20,R106)=3,$D20*$E20*R106,"N/D") -> 0 | S20: =IF(COUNT($D20,$E20,S106)=3,$D20*$E20*S106,"N/D") -> 0 | ... W20: =IF(COUNT($D20,$E20,W106)=3,$D20*$E20*W106,"N/D") -> 20034.444
C22: Saldo total al cierre | L22: =IF(COUNT(L9:L20)=12,SUM(L9:L20),"N/D") -> 20034.444 | M22: =IF(COUNT(M9:M20)=12,SUM(M9:M20),"N/D") -> 39211.25 | N22: =IF(COUNT(N9:N20)=12,SUM(N9:N20),"N/D") -> 57118.75 | O22: =IF(COUNT(O9:O20)=12,SUM(O9:O20),"N/D") -> 74443.056 | P22: =IF(COUNT(P9:P20)=12,SUM(P9:P20),"N/D") -> 91275.648 | Q22: =IF(COUNT(Q9:Q20)=12,SUM(Q9:Q20),"N/D") -> 107959.58 | R22: =IF(COUNT(R9:R20)=12,SUM(R9:R20),"N/D") -> 124228.76 | S22: =IF(COUNT(S9:S20)=12,SUM(S9:S20),"N/D") -> 140348.35 | ... W22: =IF(COUNT(W9:W20)=12,SUM(W9:W20),"N/D") -> 203456.98
C24: USD equivalentes provisionales. Depósito bruto y saldo son stock, no beneficio. Finanzas valora el saldo medio externo dentro de 2027.
C28: Saldo externo al cierre por cohorte | L28: M1 | M28: M2 | N28: M3 | O28: M4 | P28: M5 | Q28: M6 | R28: M7 | S28: M8 | T28: M9 | U28: M10 | V28: M11 | W28: M12
C30: =C9 -> 46402 | L30: =IF(COUNT(L9,$F9)=2,L9*$F9,"N/D") -> 14024.111 | M30: =IF(COUNT(M9,$F9)=2,M9*$F9,"N/D") -> 13351.722 | N30: =IF(COUNT(N9,$F9)=2,N9*$F9,"N/D") -> 12607.292 | O30: =IF(COUNT(O9,$F9)=2,O9*$F9,"N/D") -> 12127.014 | P30: =IF(COUNT(P9,$F9)=2,P9*$F9,"N/D") -> 11878.87 | Q30: =IF(COUNT(Q9,$F9)=2,Q9*$F9,"N/D") -> 11638.731 | R30: =IF(COUNT(R9,$F9)=2,R9*$F9,"N/D") -> 11460.466 | S30: =IF(COUNT(S9,$F9)=2,S9*$F9,"N/D") -> 11339.748 | ... W30: =IF(COUNT(W9,$F9)=2,W9*$F9,"N/D") -> 10864.662
C31: =C10 -> 46433 | L31: =IF(COUNT(L10,$F10)=2,L10*$F10,"N/D") -> 0 | M31: =IF(COUNT(M10,$F10)=2,M10*$F10,"N/D") -> 14096.153 | N31: =IF(COUNT(N10,$F10)=2,N10*$F10,"N/D") -> 13351.722 | O31: =IF(COUNT(O10,$F10)=2,O10*$F10,"N/D") -> 12631.306 | P31: =IF(COUNT(P10,$F10)=2,P10*$F10,"N/D") -> 12127.014 | Q31: =IF(COUNT(Q10,$F10)=2,Q10*$F10,"N/D") -> 11886.875 | R31: =IF(COUNT(R10,$F10)=2,R10*$F10,"N/D") -> 11638.731 | S31: =IF(COUNT(S10,$F10)=2,S10*$F10,"N/D") -> 11460.466 | ... W31: =IF(COUNT(W10,$F10)=2,W10*$F10,"N/D") -> 10985.381
C32: =C11 -> 46461 | L32: =IF(COUNT(L11,$F11)=2,L11*$F11,"N/D") -> 0 | M32: =IF(COUNT(M11,$F11)=2,M11*$F11,"N/D") -> 0 | N32: =IF(COUNT(N11,$F11)=2,N11*$F11,"N/D") -> 14024.111 | O32: =IF(COUNT(O11,$F11)=2,O11*$F11,"N/D") -> 13303.694 | P32: =IF(COUNT(P11,$F11)=2,P11*$F11,"N/D") -> 12559.264 | Q32: =IF(COUNT(Q11,$F11)=2,Q11*$F11,"N/D") -> 12111.005 | R32: =IF(COUNT(R11,$F11)=2,R11*$F11,"N/D") -> 11862.861 | S32: =IF(COUNT(S11,$F11)=2,S11*$F11,"N/D") -> 11614.718 | ... W32: =IF(COUNT(W11,$F11)=2,W11*$F11,"N/D") -> 11094.417
C33: =C12 -> 46492 | L33: =IF(COUNT(L12,$F12)=2,L12*$F12,"N/D") -> 0 | M33: =IF(COUNT(M12,$F12)=2,M12*$F12,"N/D") -> 0 | N33: =IF(COUNT(N12,$F12)=2,N12*$F12,"N/D") -> 0 | O33: =IF(COUNT(O12,$F12)=2,O12*$F12,"N/D") -> 14048.125 | P33: =IF(COUNT(P12,$F12)=2,P12*$F12,"N/D") -> 13303.694 | Q33: =IF(COUNT(Q12,$F12)=2,Q12*$F12,"N/D") -> 12583.278 | R33: =IF(COUNT(R12,$F12)=2,R12*$F12,"N/D") -> 12111.005 | S33: =IF(COUNT(S12,$F12)=2,S12*$F12,"N/D") -> 11862.861 | ... W33: =IF(COUNT(W12,$F12)=2,W12*$F12,"N/D") -> 11215.135
C34: =C13 -> 46522 | L34: =IF(COUNT(L13,$F13)=2,L13*$F13,"N/D") -> 0 | M34: =IF(COUNT(M13,$F13)=2,M13*$F13,"N/D") -> 0 | N34: =IF(COUNT(N13,$F13)=2,N13*$F13,"N/D") -> 0 | O34: =IF(COUNT(O13,$F13)=2,O13*$F13,"N/D") -> 0 | P34: =IF(COUNT(P13,$F13)=2,P13*$F13,"N/D") -> 14024.111 | Q34: =IF(COUNT(Q13,$F13)=2,Q13*$F13,"N/D") -> 13303.694 | R34: =IF(COUNT(R13,$F13)=2,R13*$F13,"N/D") -> 12559.264 | S34: =IF(COUNT(S13,$F13)=2,S13*$F13,"N/D") -> 12103 | ... W34: =IF(COUNT(W13,$F13)=2,W13*$F13,"N/D") -> 11331.959
C35: =C14 -> 46553 | L35: =IF(COUNT(L14,$F14)=2,L14*$F14,"N/D") -> 0 | M35: =IF(COUNT(M14,$F14)=2,M14*$F14,"N/D") -> 0 | N35: =IF(COUNT(N14,$F14)=2,N14*$F14,"N/D") -> 0 | O35: =IF(COUNT(O14,$F14)=2,O14*$F14,"N/D") -> 0 | P35: =IF(COUNT(P14,$F14)=2,P14*$F14,"N/D") -> 0 | Q35: =IF(COUNT(Q14,$F14)=2,Q14*$F14,"N/D") -> 14048.125 | R35: =IF(COUNT(R14,$F14)=2,R14*$F14,"N/D") -> 13303.694 | S35: =IF(COUNT(S14,$F14)=2,S14*$F14,"N/D") -> 12559.264 | ... W35: =IF(COUNT(W14,$F14)=2,W14*$F14,"N/D") -> 11452.678
C36: =C15 -> 46583 | L36: =IF(COUNT(L15,$F15)=2,L15*$F15,"N/D") -> 0 | M36: =IF(COUNT(M15,$F15)=2,M15*$F15,"N/D") -> 0 | N36: =IF(COUNT(N15,$F15)=2,N15*$F15,"N/D") -> 0 | O36: =IF(COUNT(O15,$F15)=2,O15*$F15,"N/D") -> 0 | P36: =IF(COUNT(P15,$F15)=2,P15*$F15,"N/D") -> 0 | Q36: =IF(COUNT(Q15,$F15)=2,Q15*$F15,"N/D") -> 0 | R36: =IF(COUNT(R15,$F15)=2,R15*$F15,"N/D") -> 14024.111 | S36: =IF(COUNT(S15,$F15)=2,S15*$F15,"N/D") -> 13279.681 | ... W36: =IF(COUNT(W15,$F15)=2,W15*$F15,"N/D") -> 11614.718
C37: =C16 -> 46614 | L37: =IF(COUNT(L16,$F16)=2,L16*$F16,"N/D") -> 0 | M37: =IF(COUNT(M16,$F16)=2,M16*$F16,"N/D") -> 0 | N37: =IF(COUNT(N16,$F16)=2,N16*$F16,"N/D") -> 0 | O37: =IF(COUNT(O16,$F16)=2,O16*$F16,"N/D") -> 0 | P37: =IF(COUNT(P16,$F16)=2,P16*$F16,"N/D") -> 0 | Q37: =IF(COUNT(Q16,$F16)=2,Q16*$F16,"N/D") -> 0 | R37: =IF(COUNT(R16,$F16)=2,R16*$F16,"N/D") -> 0 | S37: =IF(COUNT(S16,$F16)=2,S16*$F16,"N/D") -> 14024.111 | ... W37: =IF(COUNT(W16,$F16)=2,W16*$F16,"N/D") -> 11862.861
C38: =C17 -> 46645 | L38: =IF(COUNT(L17,$F17)=2,L17*$F17,"N/D") -> 0 | M38: =IF(COUNT(M17,$F17)=2,M17*$F17,"N/D") -> 0 | N38: =IF(COUNT(N17,$F17)=2,N17*$F17,"N/D") -> 0 | O38: =IF(COUNT(O17,$F17)=2,O17*$F17,"N/D") -> 0 | P38: =IF(COUNT(P17,$F17)=2,P17*$F17,"N/D") -> 0 | Q38: =IF(COUNT(Q17,$F17)=2,Q17*$F17,"N/D") -> 0 | R38: =IF(COUNT(R17,$F17)=2,R17*$F17,"N/D") -> 0 | S38: =IF(COUNT(S17,$F17)=2,S17*$F17,"N/D") -> 0 | ... W38: =IF(COUNT(W17,$F17)=2,W17*$F17,"N/D") -> 12111.005
C39: =C18 -> 46675 | L39: =IF(COUNT(L18,$F18)=2,L18*$F18,"N/D") -> 0 | M39: =IF(COUNT(M18,$F18)=2,M18*$F18,"N/D") -> 0 | N39: =IF(COUNT(N18,$F18)=2,N18*$F18,"N/D") -> 0 | O39: =IF(COUNT(O18,$F18)=2,O18*$F18,"N/D") -> 0 | P39: =IF(COUNT(P18,$F18)=2,P18*$F18,"N/D") -> 0 | Q39: =IF(COUNT(Q18,$F18)=2,Q18*$F18,"N/D") -> 0 | R39: =IF(COUNT(R18,$F18)=2,R18*$F18,"N/D") -> 0 | S39: =IF(COUNT(S18,$F18)=2,S18*$F18,"N/D") -> 0 | ... W39: =IF(COUNT(W18,$F18)=2,W18*$F18,"N/D") -> 12559.264
C40: =C19 -> 46706 | L40: =IF(COUNT(L19,$F19)=2,L19*$F19,"N/D") -> 0 | M40: =IF(COUNT(M19,$F19)=2,M19*$F19,"N/D") -> 0 | N40: =IF(COUNT(N19,$F19)=2,N19*$F19,"N/D") -> 0 | O40: =IF(COUNT(O19,$F19)=2,O19*$F19,"N/D") -> 0 | P40: =IF(COUNT(P19,$F19)=2,P19*$F19,"N/D") -> 0 | Q40: =IF(COUNT(Q19,$F19)=2,Q19*$F19,"N/D") -> 0 | R40: =IF(COUNT(R19,$F19)=2,R19*$F19,"N/D") -> 0 | S40: =IF(COUNT(S19,$F19)=2,S19*$F19,"N/D") -> 0 | ... W40: =IF(COUNT(W19,$F19)=2,W19*$F19,"N/D") -> 13303.694
C41: =C20 -> 46736 | L41: =IF(COUNT(L20,$F20)=2,L20*$F20,"N/D") -> 0 | M41: =IF(COUNT(M20,$F20)=2,M20*$F20,"N/D") -> 0 | N41: =IF(COUNT(N20,$F20)=2,N20*$F20,"N/D") -> 0 | O41: =IF(COUNT(O20,$F20)=2,O20*$F20,"N/D") -> 0 | P41: =IF(COUNT(P20,$F20)=2,P20*$F20,"N/D") -> 0 | Q41: =IF(COUNT(Q20,$F20)=2,Q20*$F20,"N/D") -> 0 | R41: =IF(COUNT(R20,$F20)=2,R20*$F20,"N/D") -> 0 | S41: =IF(COUNT(S20,$F20)=2,S20*$F20,"N/D") -> 0 | ... W41: =IF(COUNT(W20,$F20)=2,W20*$F20,"N/D") -> 14024.111
C43: Saldo externo al cierre | L43: =IF(COUNT(L30:L41)=12,SUM(L30:L41),"N/D") -> 14024.111 | M43: =IF(COUNT(M30:M41)=12,SUM(M30:M41),"N/D") -> 27447.875 | N43: =IF(COUNT(N30:N41)=12,SUM(N30:N41),"N/D") -> 39983.125 | O43: =IF(COUNT(O30:O41)=12,SUM(O30:O41),"N/D") -> 52110.139 | P43: =IF(COUNT(P30:P41)=12,SUM(P30:P41),"N/D") -> 63892.954 | Q43: =IF(COUNT(Q30:Q41)=12,SUM(Q30:Q41),"N/D") -> 75571.708 | R43: =IF(COUNT(R30:R41)=12,SUM(R30:R41),"N/D") -> 86960.133 | S43: =IF(COUNT(S30:S41)=12,SUM(S30:S41),"N/D") -> 98243.848 | ... W43: =IF(COUNT(W30:W41)=12,SUM(W30:W41),"N/D") -> 142419.88
C48: Saldo medio externo mensual por cohorte | L48: M1 | M48: M2 | N48: M3 | O48: M4 | P48: M5 | Q48: M6 | R48: M7 | S48: M8 | T48: M9 | U48: M10 | V48: M11 | W48: M12
C50: =C9 -> 46402 | L50: =IF(COUNT($D9,$E9,$F9,L9,0,Supuestos!$D$45)=6,IF(0>=Supuestos!$D$45,0,IF($C9>EOMONTH(L$7,0),0,IF($C9>=DATE(YEAR(L$7),MONTH(L$7),1),($D9*$E9+L9)/2*(EOMONTH(L$7,0)-$C9+1)/DAY(EOMONTH(L$7,0)),(0+L9)/2))*$F9),"N/D") -> 7795.9928 | M50: =IF(COUNT($D9,$E9,$F9,M9,L9,Supuestos!$D$45)=6,IF(1>=Supuestos!$D$45,0,IF($C9>EOMONTH(M$7,0),0,IF($C9>=DATE(YEAR(M$7),MONTH(M$7),1),($D9*$E9+M9)/2*(EOMONTH(M$7,0)-$C9+1)/DAY(EOMONTH(M$7,0)),(L9+M9)/2))*$F9),"N/D") -> 13687.917 | N50: =IF(COUNT($D9,$E9,$F9,N9,M9,Supuestos!$D$45)=6,IF(2>=Supuestos!$D$45,0,IF($C9>EOMONTH(N$7,0),0,IF($C9>=DATE(YEAR(N$7),MONTH(N$7),1),($D9*$E9+N9)/2*(EOMONTH(N$7,0)-$C9+1)/DAY(EOMONTH(N$7,0)),(M9+N9)/2))*$F9),"N/D") -> 12979.507 | O50: =IF(COUNT($D9,$E9,$F9,O9,N9,Supuestos!$D$45)=6,IF(3>=Supuestos!$D$45,0,IF($C9>EOMONTH(O$7,0),0,IF($C9>=DATE(YEAR(O$7),MONTH(O$7),1),($D9*$E9+O9)/2*(EOMONTH(O$7,0)-$C9+1)/DAY(EOMONTH(O$7,0)),(N9+O9)/2))*$F9),"N/D") -> 12367.153 | P50: =IF(COUNT($D9,$E9,$F9,P9,O9,Supuestos!$D$45)=6,IF(4>=Supuestos!$D$45,0,IF($C9>EOMONTH(P$7,0),0,IF($C9>=DATE(YEAR(P$7),MONTH(P$7),1),($D9*$E9+P9)/2*(EOMONTH(P$7,0)-$C9+1)/DAY(EOMONTH(P$7,0)),(O9+P9)/2))*$F9),"N/D") -> 12002.942 | Q50: =IF(COUNT($D9,$E9,$F9,Q9,P9,Supuestos!$D$45)=6,IF(5>=Supuestos!$D$45,0,IF($C9>EOMONTH(Q$7,0),0,IF($C9>=DATE(YEAR(Q$7),MONTH(Q$7),1),($D9*$E9+Q9)/2*(EOMONTH(Q$7,0)-$C9+1)/DAY(EOMONTH(Q$7,0)),(P9+Q9)/2))*$F9),"N/D") -> 11758.801 | R50: =IF(COUNT($D9,$E9,$F9,R9,Q9,Supuestos!$D$45)=6,IF(6>=Supuestos!$D$45,0,IF($C9>EOMONTH(R$7,0),0,IF($C9>=DATE(YEAR(R$7),MONTH(R$7),1),($D9*$E9+R9)/2*(EOMONTH(R$7,0)-$C9+1)/DAY(EOMONTH(R$7,0)),(Q9+R9)/2))*$F9),"N/D") -> 11549.599 | S50: =IF(COUNT($D9,$E9,$F9,S9,R9,Supuestos!$D$45)=6,IF(7>=Supuestos!$D$45,0,IF($C9>EOMONTH(S$7,0),0,IF($C9>=DATE(YEAR(S$7),MONTH(S$7),1),($D9*$E9+S9)/2*(EOMONTH(S$7,0)-$C9+1)/DAY(EOMONTH(S$7,0)),(R9+S9)/2))*$F9),"N/D") -> 11400.107 | T50: =IF(COUNT($D9,$E9,$F9,T9,S9,Supuestos!$D$45)=6,IF(8>=Supuestos!$D$45,0,IF($C9>EOMONTH(T$7,0),0,IF($C9>=DATE(YEAR(T$7),MONTH(T$7),1),($D9*$E9+T9)/2*(EOMONTH(T$7,0)-$C9+1)/DAY(EOMONTH(T$7,0)),(S9+T9)/2))*$F9),"N/D") -> 11281.336 | U50: =IF(COUNT($D9,$E9,$F9,U9,T9,Supuestos!$D$45)=6,IF(9>=Supuestos!$D$45,0,IF($C9>EOMONTH(U$7,0),0,IF($C9>=DATE(YEAR(U$7),MONTH(U$7),1),($D9*$E9+U9)/2*(EOMONTH(U$7,0)-$C9+1)/DAY(EOMONTH(U$7,0)),(T9+U9)/2))*$F9),"N/D") -> 11162.564 | V50: =IF(COUNT($D9,$E9,$F9,V9,U9,Supuestos!$D$45)=6,IF(10>=Supuestos!$D$45,0,IF($C9>EOMONTH(V$7,0),0,IF($C9>=DATE(YEAR(V$7),MONTH(V$7),1),($D9*$E9+V9)/2*(EOMONTH(V$7,0)-$C9+1)/DAY(EOMONTH(V$7,0)),(U9+V9)/2))*$F9),"N/D") -> 11043.793 | W50: =IF(COUNT($D9,$E9,$F9,W9,V9,Supuestos!$D$45)=6,IF(11>=Supuestos!$D$45,0,IF($C9>EOMONTH(W$7,0),0,IF($C9>=DATE(YEAR(W$7),MONTH(W$7),1),($D9*$E9+W9)/2*(EOMONTH(W$7,0)-$C9+1)/DAY(EOMONTH(W$7,0)),(V9+W9)/2))*$F9),"N/D") -> 10925.021
C51: =C10 -> 46433 | L51: =IF(COUNT($D10,$E10,$F10,L10,0,Supuestos!$D$45)=6,IF(0>=Supuestos!$D$45,0,IF($C10>EOMONTH(L$7,0),0,IF($C10>=DATE(YEAR(L$7),MONTH(L$7),1),($D10*$E10+L10)/2*(EOMONTH(L$7,0)-$C10+1)/DAY(EOMONTH(L$7,0)),(0+L10)/2))*$F10),"N/D") -> 0 | M51: =IF(COUNT($D10,$E10,$F10,M10,L10,Supuestos!$D$45)=6,IF(1>=Supuestos!$D$45,0,IF($C10>EOMONTH(M$7,0),0,IF($C10>=DATE(YEAR(M$7),MONTH(M$7),1),($D10*$E10+M10)/2*(EOMONTH(M$7,0)-$C10+1)/DAY(EOMONTH(M$7,0)),(L10+M10)/2))*$F10),"N/D") -> 7126.1215 | N51: =IF(COUNT($D10,$E10,$F10,N10,M10,Supuestos!$D$45)=6,IF(2>=Supuestos!$D$45,0,IF($C10>EOMONTH(N$7,0),0,IF($C10>=DATE(YEAR(N$7),MONTH(N$7),1),($D10*$E10+N10)/2*(EOMONTH(N$7,0)-$C10+1)/DAY(EOMONTH(N$7,0)),(M10+N10)/2))*$F10),"N/D") -> 13723.938 | O51: =IF(COUNT($D10,$E10,$F10,O10,N10,Supuestos!$D$45)=6,IF(3>=Supuestos!$D$45,0,IF($C10>EOMONTH(O$7,0),0,IF($C10>=DATE(YEAR(O$7),MONTH(O$7),1),($D10*$E10+O10)/2*(EOMONTH(O$7,0)-$C10+1)/DAY(EOMONTH(O$7,0)),(N10+O10)/2))*$F10),"N/D") -> 12991.514 | P51: =IF(COUNT($D10,$E10,$F10,P10,O10,Supuestos!$D$45)=6,IF(4>=Supuestos!$D$45,0,IF($C10>EOMONTH(P$7,0),0,IF($C10>=DATE(YEAR(P$7),MONTH(P$7),1),($D10*$E10+P10)/2*(EOMONTH(P$7,0)-$C10+1)/DAY(EOMONTH(P$7,0)),(O10+P10)/2))*$F10),"N/D") -> 12379.16 | Q51: =IF(COUNT($D10,$E10,$F10,Q10,P10,Supuestos!$D$45)=6,IF(5>=Supuestos!$D$45,0,IF($C10>EOMONTH(Q$7,0),0,IF($C10>=DATE(YEAR(Q$7),MONTH(Q$7),1),($D10*$E10+Q10)/2*(EOMONTH(Q$7,0)-$C10+1)/DAY(EOMONTH(Q$7,0)),(P10+Q10)/2))*$F10),"N/D") -> 12006.944 | R51: =IF(COUNT($D10,$E10,$F10,R10,Q10,Supuestos!$D$45)=6,IF(6>=Supuestos!$D$45,0,IF($C10>EOMONTH(R$7,0),0,IF($C10>=DATE(YEAR(R$7),MONTH(R$7),1),($D10*$E10+R10)/2*(EOMONTH(R$7,0)-$C10+1)/DAY(EOMONTH(R$7,0)),(Q10+R10)/2))*$F10),"N/D") -> 11762.803 | S51: =IF(COUNT($D10,$E10,$F10,S10,R10,Supuestos!$D$45)=6,IF(7>=Supuestos!$D$45,0,IF($C10>EOMONTH(S$7,0),0,IF($C10>=DATE(YEAR(S$7),MONTH(S$7),1),($D10*$E10+S10)/2*(EOMONTH(S$7,0)-$C10+1)/DAY(EOMONTH(S$7,0)),(R10+S10)/2))*$F10),"N/D") -> 11549.599 | T51: =IF(COUNT($D10,$E10,$F10,T10,S10,Supuestos!$D$45)=6,IF(8>=Supuestos!$D$45,0,IF($C10>EOMONTH(T$7,0),0,IF($C10>=DATE(YEAR(T$7),MONTH(T$7),1),($D10*$E10+T10)/2*(EOMONTH(T$7,0)-$C10+1)/DAY(EOMONTH(T$7,0)),(S10+T10)/2))*$F10),"N/D") -> 11402.054 | U51: =IF(COUNT($D10,$E10,$F10,U10,T10,Supuestos!$D$45)=6,IF(9>=Supuestos!$D$45,0,IF($C10>EOMONTH(U$7,0),0,IF($C10>=DATE(YEAR(U$7),MONTH(U$7),1),($D10*$E10+U10)/2*(EOMONTH(U$7,0)-$C10+1)/DAY(EOMONTH(U$7,0)),(T10+U10)/2))*$F10),"N/D") -> 11283.283 | V51: =IF(COUNT($D10,$E10,$F10,V10,U10,Supuestos!$D$45)=6,IF(10>=Supuestos!$D$45,0,IF($C10>EOMONTH(V$7,0),0,IF($C10>=DATE(YEAR(V$7),MONTH(V$7),1),($D10*$E10+V10)/2*(EOMONTH(V$7,0)-$C10+1)/DAY(EOMONTH(V$7,0)),(U10+V10)/2))*$F10),"N/D") -> 11164.511 | W51: =IF(COUNT($D10,$E10,$F10,W10,V10,Supuestos!$D$45)=6,IF(11>=Supuestos!$D$45,0,IF($C10>EOMONTH(W$7,0),0,IF($C10>=DATE(YEAR(W$7),MONTH(W$7),1),($D10*$E10+W10)/2*(EOMONTH(W$7,0)-$C10+1)/DAY(EOMONTH(W$7,0)),(V10+W10)/2))*$F10),"N/D") -> 11045.74
C52: =C11 -> 46461 | L52: =IF(COUNT($D11,$E11,$F11,L11,0,Supuestos!$D$45)=6,IF(0>=Supuestos!$D$45,0,IF($C11>EOMONTH(L$7,0),0,IF($C11>=DATE(YEAR(L$7),MONTH(L$7),1),($D11*$E11+L11)/2*(EOMONTH(L$7,0)-$C11+1)/DAY(EOMONTH(L$7,0)),(0+L11)/2))*$F11),"N/D") -> 0 | M52: =IF(COUNT($D11,$E11,$F11,M11,L11,Supuestos!$D$45)=6,IF(1>=Supuestos!$D$45,0,IF($C11>EOMONTH(M$7,0),0,IF($C11>=DATE(YEAR(M$7),MONTH(M$7),1),($D11*$E11+M11)/2*(EOMONTH(M$7,0)-$C11+1)/DAY(EOMONTH(M$7,0)),(L11+M11)/2))*$F11),"N/D") -> 0 | N52: =IF(COUNT($D11,$E11,$F11,N11,M11,Supuestos!$D$45)=6,IF(2>=Supuestos!$D$45,0,IF($C11>EOMONTH(N$7,0),0,IF($C11>=DATE(YEAR(N$7),MONTH(N$7),1),($D11*$E11+N11)/2*(EOMONTH(N$7,0)-$C11+1)/DAY(EOMONTH(N$7,0)),(M11+N11)/2))*$F11),"N/D") -> 7795.9928 | O52: =IF(COUNT($D11,$E11,$F11,O11,N11,Supuestos!$D$45)=6,IF(3>=Supuestos!$D$45,0,IF($C11>EOMONTH(O$7,0),0,IF($C11>=DATE(YEAR(O$7),MONTH(O$7),1),($D11*$E11+O11)/2*(EOMONTH(O$7,0)-$C11+1)/DAY(EOMONTH(O$7,0)),(N11+O11)/2))*$F11),"N/D") -> 13663.903 | P52: =IF(COUNT($D11,$E11,$F11,P11,O11,Supuestos!$D$45)=6,IF(4>=Supuestos!$D$45,0,IF($C11>EOMONTH(P$7,0),0,IF($C11>=DATE(YEAR(P$7),MONTH(P$7),1),($D11*$E11+P11)/2*(EOMONTH(P$7,0)-$C11+1)/DAY(EOMONTH(P$7,0)),(O11+P11)/2))*$F11),"N/D") -> 12931.479 | Q52: =IF(COUNT($D11,$E11,$F11,Q11,P11,Supuestos!$D$45)=6,IF(5>=Supuestos!$D$45,0,IF($C11>EOMONTH(Q$7,0),0,IF($C11>=DATE(YEAR(Q$7),MONTH(Q$7),1),($D11*$E11+Q11)/2*(EOMONTH(Q$7,0)-$C11+1)/DAY(EOMONTH(Q$7,0)),(P11+Q11)/2))*$F11),"N/D") -> 12335.134 | R52: =IF(COUNT($D11,$E11,$F11,R11,Q11,Supuestos!$D$45)=6,IF(6>=Supuestos!$D$45,0,IF($C11>EOMONTH(R$7,0),0,IF($C11>=DATE(YEAR(R$7),MONTH(R$7),1),($D11*$E11+R11)/2*(EOMONTH(R$7,0)-$C11+1)/DAY(EOMONTH(R$7,0)),(Q11+R11)/2))*$F11),"N/D") -> 11986.933 | S52: =IF(COUNT($D11,$E11,$F11,S11,R11,Supuestos!$D$45)=6,IF(7>=Supuestos!$D$45,0,IF($C11>EOMONTH(S$7,0),0,IF($C11>=DATE(YEAR(S$7),MONTH(S$7),1),($D11*$E11+S11)/2*(EOMONTH(S$7,0)-$C11+1)/DAY(EOMONTH(S$7,0)),(R11+S11)/2))*$F11),"N/D") -> 11738.789 | T52: =IF(COUNT($D11,$E11,$F11,T11,S11,Supuestos!$D$45)=6,IF(8>=Supuestos!$D$45,0,IF($C11>EOMONTH(T$7,0),0,IF($C11>=DATE(YEAR(T$7),MONTH(T$7),1),($D11*$E11+T11)/2*(EOMONTH(T$7,0)-$C11+1)/DAY(EOMONTH(T$7,0)),(S11+T11)/2))*$F11),"N/D") -> 11533.698 | U52: =IF(COUNT($D11,$E11,$F11,U11,T11,Supuestos!$D$45)=6,IF(9>=Supuestos!$D$45,0,IF($C11>EOMONTH(U$7,0),0,IF($C11>=DATE(YEAR(U$7),MONTH(U$7),1),($D11*$E11+U11)/2*(EOMONTH(U$7,0)-$C11+1)/DAY(EOMONTH(U$7,0)),(T11+U11)/2))*$F11),"N/D") -> 11392.319 | V52: =IF(COUNT($D11,$E11,$F11,V11,U11,Supuestos!$D$45)=6,IF(10>=Supuestos!$D$45,0,IF($C11>EOMONTH(V$7,0),0,IF($C11>=DATE(YEAR(V$7),MONTH(V$7),1),($D11*$E11+V11)/2*(EOMONTH(V$7,0)-$C11+1)/DAY(EOMONTH(V$7,0)),(U11+V11)/2))*$F11),"N/D") -> 11273.547 | W52: =IF(COUNT($D11,$E11,$F11,W11,V11,Supuestos!$D$45)=6,IF(11>=Supuestos!$D$45,0,IF($C11>EOMONTH(W$7,0),0,IF($C11>=DATE(YEAR(W$7),MONTH(W$7),1),($D11*$E11+W11)/2*(EOMONTH(W$7,0)-$C11+1)/DAY(EOMONTH(W$7,0)),(V11+W11)/2))*$F11),"N/D") -> 11154.776
C53: =C12 -> 46492 | L53: =IF(COUNT($D12,$E12,$F12,L12,0,Supuestos!$D$45)=6,IF(0>=Supuestos!$D$45,0,IF($C12>EOMONTH(L$7,0),0,IF($C12>=DATE(YEAR(L$7),MONTH(L$7),1),($D12*$E12+L12)/2*(EOMONTH(L$7,0)-$C12+1)/DAY(EOMONTH(L$7,0)),(0+L12)/2))*$F12),"N/D") -> 0 | M53: =IF(COUNT($D12,$E12,$F12,M12,L12,Supuestos!$D$45)=6,IF(1>=Supuestos!$D$45,0,IF($C12>EOMONTH(M$7,0),0,IF($C12>=DATE(YEAR(M$7),MONTH(M$7),1),($D12*$E12+M12)/2*(EOMONTH(M$7,0)-$C12+1)/DAY(EOMONTH(M$7,0)),(L12+M12)/2))*$F12),"N/D") -> 0 | N53: =IF(COUNT($D12,$E12,$F12,N12,M12,Supuestos!$D$45)=6,IF(2>=Supuestos!$D$45,0,IF($C12>EOMONTH(N$7,0),0,IF($C12>=DATE(YEAR(N$7),MONTH(N$7),1),($D12*$E12+N12)/2*(EOMONTH(N$7,0)-$C12+1)/DAY(EOMONTH(N$7,0)),(M12+N12)/2))*$F12),"N/D") -> 0 | O53: =IF(COUNT($D12,$E12,$F12,O12,N12,Supuestos!$D$45)=6,IF(3>=Supuestos!$D$45,0,IF($C12>EOMONTH(O$7,0),0,IF($C12>=DATE(YEAR(O$7),MONTH(O$7),1),($D12*$E12+O12)/2*(EOMONTH(O$7,0)-$C12+1)/DAY(EOMONTH(O$7,0)),(N12+O12)/2))*$F12),"N/D") -> 7588.3889 | P53: =IF(COUNT($D12,$E12,$F12,P12,O12,Supuestos!$D$45)=6,IF(4>=Supuestos!$D$45,0,IF($C12>EOMONTH(P$7,0),0,IF($C12>=DATE(YEAR(P$7),MONTH(P$7),1),($D12*$E12+P12)/2*(EOMONTH(P$7,0)-$C12+1)/DAY(EOMONTH(P$7,0)),(O12+P12)/2))*$F12),"N/D") -> 13675.91 | Q53: =IF(COUNT($D12,$E12,$F12,Q12,P12,Supuestos!$D$45)=6,IF(5>=Supuestos!$D$45,0,IF($C12>EOMONTH(Q$7,0),0,IF($C12>=DATE(YEAR(Q$7),MONTH(Q$7),1),($D12*$E12+Q12)/2*(EOMONTH(Q$7,0)-$C12+1)/DAY(EOMONTH(Q$7,0)),(P12+Q12)/2))*$F12),"N/D") -> 12943.486 | R53: =IF(COUNT($D12,$E12,$F12,R12,Q12,Supuestos!$D$45)=6,IF(6>=Supuestos!$D$45,0,IF($C12>EOMONTH(R$7,0),0,IF($C12>=DATE(YEAR(R$7),MONTH(R$7),1),($D12*$E12+R12)/2*(EOMONTH(R$7,0)-$C12+1)/DAY(EOMONTH(R$7,0)),(Q12+R12)/2))*$F12),"N/D") -> 12347.141 | S53: =IF(COUNT($D12,$E12,$F12,S12,R12,Supuestos!$D$45)=6,IF(7>=Supuestos!$D$45,0,IF($C12>EOMONTH(S$7,0),0,IF($C12>=DATE(YEAR(S$7),MONTH(S$7),1),($D12*$E12+S12)/2*(EOMONTH(S$7,0)-$C12+1)/DAY(EOMONTH(S$7,0)),(R12+S12)/2))*$F12),"N/D") -> 11986.933 | T53: =IF(COUNT($D12,$E12,$F12,T12,S12,Supuestos!$D$45)=6,IF(8>=Supuestos!$D$45,0,IF($C12>EOMONTH(T$7,0),0,IF($C12>=DATE(YEAR(T$7),MONTH(T$7),1),($D12*$E12+T12)/2*(EOMONTH(T$7,0)-$C12+1)/DAY(EOMONTH(T$7,0)),(S12+T12)/2))*$F12),"N/D") -> 11742.792 | U53: =IF(COUNT($D12,$E12,$F12,U12,T12,Supuestos!$D$45)=6,IF(9>=Supuestos!$D$45,0,IF($C12>EOMONTH(U$7,0),0,IF($C12>=DATE(YEAR(U$7),MONTH(U$7),1),($D12*$E12+U12)/2*(EOMONTH(U$7,0)-$C12+1)/DAY(EOMONTH(U$7,0)),(T12+U12)/2))*$F12),"N/D") -> 11537.7 | V53: =IF(COUNT($D12,$E12,$F12,V12,U12,Supuestos!$D$45)=6,IF(10>=Supuestos!$D$45,0,IF($C12>EOMONTH(V$7,0),0,IF($C12>=DATE(YEAR(V$7),MONTH(V$7),1),($D12*$E12+V12)/2*(EOMONTH(V$7,0)-$C12+1)/DAY(EOMONTH(V$7,0)),(U12+V12)/2))*$F12),"N/D") -> 11394.266 | W53: =IF(COUNT($D12,$E12,$F12,W12,V12,Supuestos!$D$45)=6,IF(11>=Supuestos!$D$45,0,IF($C12>EOMONTH(W$7,0),0,IF($C12>=DATE(YEAR(W$7),MONTH(W$7),1),($D12*$E12+W12)/2*(EOMONTH(W$7,0)-$C12+1)/DAY(EOMONTH(W$7,0)),(V12+W12)/2))*$F12),"N/D") -> 11275.494
C54: =C13 -> 46522 | L54: =IF(COUNT($D13,$E13,$F13,L13,0,Supuestos!$D$45)=6,IF(0>=Supuestos!$D$45,0,IF($C13>EOMONTH(L$7,0),0,IF($C13>=DATE(YEAR(L$7),MONTH(L$7),1),($D13*$E13+L13)/2*(EOMONTH(L$7,0)-$C13+1)/DAY(EOMONTH(L$7,0)),(0+L13)/2))*$F13),"N/D") -> 0 | M54: =IF(COUNT($D13,$E13,$F13,M13,L13,Supuestos!$D$45)=6,IF(1>=Supuestos!$D$45,0,IF($C13>EOMONTH(M$7,0),0,IF($C13>=DATE(YEAR(M$7),MONTH(M$7),1),($D13*$E13+M13)/2*(EOMONTH(M$7,0)-$C13+1)/DAY(EOMONTH(M$7,0)),(L13+M13)/2))*$F13),"N/D") -> 0 | N54: =IF(COUNT($D13,$E13,$F13,N13,M13,Supuestos!$D$45)=6,IF(2>=Supuestos!$D$45,0,IF($C13>EOMONTH(N$7,0),0,IF($C13>=DATE(YEAR(N$7),MONTH(N$7),1),($D13*$E13+N13)/2*(EOMONTH(N$7,0)-$C13+1)/DAY(EOMONTH(N$7,0)),(M13+N13)/2))*$F13),"N/D") -> 0 | O54: =IF(COUNT($D13,$E13,$F13,O13,N13,Supuestos!$D$45)=6,IF(3>=Supuestos!$D$45,0,IF($C13>EOMONTH(O$7,0),0,IF($C13>=DATE(YEAR(O$7),MONTH(O$7),1),($D13*$E13+O13)/2*(EOMONTH(O$7,0)-$C13+1)/DAY(EOMONTH(O$7,0)),(N13+O13)/2))*$F13),"N/D") -> 0 | P54: =IF(COUNT($D13,$E13,$F13,P13,O13,Supuestos!$D$45)=6,IF(4>=Supuestos!$D$45,0,IF($C13>EOMONTH(P$7,0),0,IF($C13>=DATE(YEAR(P$7),MONTH(P$7),1),($D13*$E13+P13)/2*(EOMONTH(P$7,0)-$C13+1)/DAY(EOMONTH(P$7,0)),(O13+P13)/2))*$F13),"N/D") -> 7795.9928 | Q54: =IF(COUNT($D13,$E13,$F13,Q13,P13,Supuestos!$D$45)=6,IF(5>=Supuestos!$D$45,0,IF($C13>EOMONTH(Q$7,0),0,IF($C13>=DATE(YEAR(Q$7),MONTH(Q$7),1),($D13*$E13+Q13)/2*(EOMONTH(Q$7,0)-$C13+1)/DAY(EOMONTH(Q$7,0)),(P13+Q13)/2))*$F13),"N/D") -> 13663.903 | R54: =IF(COUNT($D13,$E13,$F13,R13,Q13,Supuestos!$D$45)=6,IF(6>=Supuestos!$D$45,0,IF($C13>EOMONTH(R$7,0),0,IF($C13>=DATE(YEAR(R$7),MONTH(R$7),1),($D13*$E13+R13)/2*(EOMONTH(R$7,0)-$C13+1)/DAY(EOMONTH(R$7,0)),(Q13+R13)/2))*$F13),"N/D") -> 12931.479 | S54: =IF(COUNT($D13,$E13,$F13,S13,R13,Supuestos!$D$45)=6,IF(7>=Supuestos!$D$45,0,IF($C13>EOMONTH(S$7,0),0,IF($C13>=DATE(YEAR(S$7),MONTH(S$7),1),($D13*$E13+S13)/2*(EOMONTH(S$7,0)-$C13+1)/DAY(EOMONTH(S$7,0)),(R13+S13)/2))*$F13),"N/D") -> 12331.132 | T54: =IF(COUNT($D13,$E13,$F13,T13,S13,Supuestos!$D$45)=6,IF(8>=Supuestos!$D$45,0,IF($C13>EOMONTH(T$7,0),0,IF($C13>=DATE(YEAR(T$7),MONTH(T$7),1),($D13*$E13+T13)/2*(EOMONTH(T$7,0)-$C13+1)/DAY(EOMONTH(T$7,0)),(S13+T13)/2))*$F13),"N/D") -> 11982.931 | U54: =IF(COUNT($D13,$E13,$F13,U13,T13,Supuestos!$D$45)=6,IF(9>=Supuestos!$D$45,0,IF($C13>EOMONTH(U$7,0),0,IF($C13>=DATE(YEAR(U$7),MONTH(U$7),1),($D13*$E13+U13)/2*(EOMONTH(U$7,0)-$C13+1)/DAY(EOMONTH(U$7,0)),(T13+U13)/2))*$F13),"N/D") -> 11738.789 | V54: =IF(COUNT($D13,$E13,$F13,V13,U13,Supuestos!$D$45)=6,IF(10>=Supuestos!$D$45,0,IF($C13>EOMONTH(V$7,0),0,IF($C13>=DATE(YEAR(V$7),MONTH(V$7),1),($D13*$E13+V13)/2*(EOMONTH(V$7,0)-$C13+1)/DAY(EOMONTH(V$7,0)),(U13+V13)/2))*$F13),"N/D") -> 11533.698 | W54: =IF(COUNT($D13,$E13,$F13,W13,V13,Supuestos!$D$45)=6,IF(11>=Supuestos!$D$45,0,IF($C13>EOMONTH(W$7,0),0,IF($C13>=DATE(YEAR(W$7),MONTH(W$7),1),($D13*$E13+W13)/2*(EOMONTH(W$7,0)-$C13+1)/DAY(EOMONTH(W$7,0)),(V13+W13)/2))*$F13),"N/D") -> 11392.319
C55: =C14 -> 46553 | L55: =IF(COUNT($D14,$E14,$F14,L14,0,Supuestos!$D$45)=6,IF(0>=Supuestos!$D$45,0,IF($C14>EOMONTH(L$7,0),0,IF($C14>=DATE(YEAR(L$7),MONTH(L$7),1),($D14*$E14+L14)/2*(EOMONTH(L$7,0)-$C14+1)/DAY(EOMONTH(L$7,0)),(0+L14)/2))*$F14),"N/D") -> 0 | M55: =IF(COUNT($D14,$E14,$F14,M14,L14,Supuestos!$D$45)=6,IF(1>=Supuestos!$D$45,0,IF($C14>EOMONTH(M$7,0),0,IF($C14>=DATE(YEAR(M$7),MONTH(M$7),1),($D14*$E14+M14)/2*(EOMONTH(M$7,0)-$C14+1)/DAY(EOMONTH(M$7,0)),(L14+M14)/2))*$F14),"N/D") -> 0 | N55: =IF(COUNT($D14,$E14,$F14,N14,M14,Supuestos!$D$45)=6,IF(2>=Supuestos!$D$45,0,IF($C14>EOMONTH(N$7,0),0,IF($C14>=DATE(YEAR(N$7),MONTH(N$7),1),($D14*$E14+N14)/2*(EOMONTH(N$7,0)-$C14+1)/DAY(EOMONTH(N$7,0)),(M14+N14)/2))*$F14),"N/D") -> 0 | O55: =IF(COUNT($D14,$E14,$F14,O14,N14,Supuestos!$D$45)=6,IF(3>=Supuestos!$D$45,0,IF($C14>EOMONTH(O$7,0),0,IF($C14>=DATE(YEAR(O$7),MONTH(O$7),1),($D14*$E14+O14)/2*(EOMONTH(O$7,0)-$C14+1)/DAY(EOMONTH(O$7,0)),(N14+O14)/2))*$F14),"N/D") -> 0 | P55: =IF(COUNT($D14,$E14,$F14,P14,O14,Supuestos!$D$45)=6,IF(4>=Supuestos!$D$45,0,IF($C14>EOMONTH(P$7,0),0,IF($C14>=DATE(YEAR(P$7),MONTH(P$7),1),($D14*$E14+P14)/2*(EOMONTH(P$7,0)-$C14+1)/DAY(EOMONTH(P$7,0)),(O14+P14)/2))*$F14),"N/D") -> 0 | Q55: =IF(COUNT($D14,$E14,$F14,Q14,P14,Supuestos!$D$45)=6,IF(5>=Supuestos!$D$45,0,IF($C14>EOMONTH(Q$7,0),0,IF($C14>=DATE(YEAR(Q$7),MONTH(Q$7),1),($D14*$E14+Q14)/2*(EOMONTH(Q$7,0)-$C14+1)/DAY(EOMONTH(Q$7,0)),(P14+Q14)/2))*$F14),"N/D") -> 7588.3889 | R55: =IF(COUNT($D14,$E14,$F14,R14,Q14,Supuestos!$D$45)=6,IF(6>=Supuestos!$D$45,0,IF($C14>EOMONTH(R$7,0),0,IF($C14>=DATE(YEAR(R$7),MONTH(R$7),1),($D14*$E14+R14)/2*(EOMONTH(R$7,0)-$C14+1)/DAY(EOMONTH(R$7,0)),(Q14+R14)/2))*$F14),"N/D") -> 13675.91 | S55: =IF(COUNT($D14,$E14,$F14,S14,R14,Supuestos!$D$45)=6,IF(7>=Supuestos!$D$45,0,IF($C14>EOMONTH(S$7,0),0,IF($C14>=DATE(YEAR(S$7),MONTH(S$7),1),($D14*$E14+S14)/2*(EOMONTH(S$7,0)-$C14+1)/DAY(EOMONTH(S$7,0)),(R14+S14)/2))*$F14),"N/D") -> 12931.479 | T55: =IF(COUNT($D14,$E14,$F14,T14,S14,Supuestos!$D$45)=6,IF(8>=Supuestos!$D$45,0,IF($C14>EOMONTH(T$7,0),0,IF($C14>=DATE(YEAR(T$7),MONTH(T$7),1),($D14*$E14+T14)/2*(EOMONTH(T$7,0)-$C14+1)/DAY(EOMONTH(T$7,0)),(S14+T14)/2))*$F14),"N/D") -> 12335.134 | U55: =IF(COUNT($D14,$E14,$F14,U14,T14,Supuestos!$D$45)=6,IF(9>=Supuestos!$D$45,0,IF($C14>EOMONTH(U$7,0),0,IF($C14>=DATE(YEAR(U$7),MONTH(U$7),1),($D14*$E14+U14)/2*(EOMONTH(U$7,0)-$C14+1)/DAY(EOMONTH(U$7,0)),(T14+U14)/2))*$F14),"N/D") -> 11986.933 | V55: =IF(COUNT($D14,$E14,$F14,V14,U14,Supuestos!$D$45)=6,IF(10>=Supuestos!$D$45,0,IF($C14>EOMONTH(V$7,0),0,IF($C14>=DATE(YEAR(V$7),MONTH(V$7),1),($D14*$E14+V14)/2*(EOMONTH(V$7,0)-$C14+1)/DAY(EOMONTH(V$7,0)),(U14+V14)/2))*$F14),"N/D") -> 11742.792 | W55: =IF(COUNT($D14,$E14,$F14,W14,V14,Supuestos!$D$45)=6,IF(11>=Supuestos!$D$45,0,IF($C14>EOMONTH(W$7,0),0,IF($C14>=DATE(YEAR(W$7),MONTH(W$7),1),($D14*$E14+W14)/2*(EOMONTH(W$7,0)-$C14+1)/DAY(EOMONTH(W$7,0)),(V14+W14)/2))*$F14),"N/D") -> 11537.7
C56: =C15 -> 46583 | L56: =IF(COUNT($D15,$E15,$F15,L15,0,Supuestos!$D$45)=6,IF(0>=Supuestos!$D$45,0,IF($C15>EOMONTH(L$7,0),0,IF($C15>=DATE(YEAR(L$7),MONTH(L$7),1),($D15*$E15+L15)/2*(EOMONTH(L$7,0)-$C15+1)/DAY(EOMONTH(L$7,0)),(0+L15)/2))*$F15),"N/D") -> 0 | M56: =IF(COUNT($D15,$E15,$F15,M15,L15,Supuestos!$D$45)=6,IF(1>=Supuestos!$D$45,0,IF($C15>EOMONTH(M$7,0),0,IF($C15>=DATE(YEAR(M$7),MONTH(M$7),1),($D15*$E15+M15)/2*(EOMONTH(M$7,0)-$C15+1)/DAY(EOMONTH(M$7,0)),(L15+M15)/2))*$F15),"N/D") -> 0 | N56: =IF(COUNT($D15,$E15,$F15,N15,M15,Supuestos!$D$45)=6,IF(2>=Supuestos!$D$45,0,IF($C15>EOMONTH(N$7,0),0,IF($C15>=DATE(YEAR(N$7),MONTH(N$7),1),($D15*$E15+N15)/2*(EOMONTH(N$7,0)-$C15+1)/DAY(EOMONTH(N$7,0)),(M15+N15)/2))*$F15),"N/D") -> 0 | O56: =IF(COUNT($D15,$E15,$F15,O15,N15,Supuestos!$D$45)=6,IF(3>=Supuestos!$D$45,0,IF($C15>EOMONTH(O$7,0),0,IF($C15>=DATE(YEAR(O$7),MONTH(O$7),1),($D15*$E15+O15)/2*(EOMONTH(O$7,0)-$C15+1)/DAY(EOMONTH(O$7,0)),(N15+O15)/2))*$F15),"N/D") -> 0 | P56: =IF(COUNT($D15,$E15,$F15,P15,O15,Supuestos!$D$45)=6,IF(4>=Supuestos!$D$45,0,IF($C15>EOMONTH(P$7,0),0,IF($C15>=DATE(YEAR(P$7),MONTH(P$7),1),($D15*$E15+P15)/2*(EOMONTH(P$7,0)-$C15+1)/DAY(EOMONTH(P$7,0)),(O15+P15)/2))*$F15),"N/D") -> 0 | Q56: =IF(COUNT($D15,$E15,$F15,Q15,P15,Supuestos!$D$45)=6,IF(5>=Supuestos!$D$45,0,IF($C15>EOMONTH(Q$7,0),0,IF($C15>=DATE(YEAR(Q$7),MONTH(Q$7),1),($D15*$E15+Q15)/2*(EOMONTH(Q$7,0)-$C15+1)/DAY(EOMONTH(Q$7,0)),(P15+Q15)/2))*$F15),"N/D") -> 0 | R56: =IF(COUNT($D15,$E15,$F15,R15,Q15,Supuestos!$D$45)=6,IF(6>=Supuestos!$D$45,0,IF($C15>EOMONTH(R$7,0),0,IF($C15>=DATE(YEAR(R$7),MONTH(R$7),1),($D15*$E15+R15)/2*(EOMONTH(R$7,0)-$C15+1)/DAY(EOMONTH(R$7,0)),(Q15+R15)/2))*$F15),"N/D") -> 7795.9928 | S56: =IF(COUNT($D15,$E15,$F15,S15,R15,Supuestos!$D$45)=6,IF(7>=Supuestos!$D$45,0,IF($C15>EOMONTH(S$7,0),0,IF($C15>=DATE(YEAR(S$7),MONTH(S$7),1),($D15*$E15+S15)/2*(EOMONTH(S$7,0)-$C15+1)/DAY(EOMONTH(S$7,0)),(R15+S15)/2))*$F15),"N/D") -> 13651.896 | T56: =IF(COUNT($D15,$E15,$F15,T15,S15,Supuestos!$D$45)=6,IF(8>=Supuestos!$D$45,0,IF($C15>EOMONTH(T$7,0),0,IF($C15>=DATE(YEAR(T$7),MONTH(T$7),1),($D15*$E15+T15)/2*(EOMONTH(T$7,0)-$C15+1)/DAY(EOMONTH(T$7,0)),(S15+T15)/2))*$F15),"N/D") -> 12919.472 | U56: =IF(COUNT($D15,$E15,$F15,U15,T15,Supuestos!$D$45)=6,IF(9>=Supuestos!$D$45,0,IF($C15>EOMONTH(U$7,0),0,IF($C15>=DATE(YEAR(U$7),MONTH(U$7),1),($D15*$E15+U15)/2*(EOMONTH(U$7,0)-$C15+1)/DAY(EOMONTH(U$7,0)),(T15+U15)/2))*$F15),"N/D") -> 12331.132 | V56: =IF(COUNT($D15,$E15,$F15,V15,U15,Supuestos!$D$45)=6,IF(10>=Supuestos!$D$45,0,IF($C15>EOMONTH(V$7,0),0,IF($C15>=DATE(YEAR(V$7),MONTH(V$7),1),($D15*$E15+V15)/2*(EOMONTH(V$7,0)-$C15+1)/DAY(EOMONTH(V$7,0)),(U15+V15)/2))*$F15),"N/D") -> 11982.931 | W56: =IF(COUNT($D15,$E15,$F15,W15,V15,Supuestos!$D$45)=6,IF(11>=Supuestos!$D$45,0,IF($C15>EOMONTH(W$7,0),0,IF($C15>=DATE(YEAR(W$7),MONTH(W$7),1),($D15*$E15+W15)/2*(EOMONTH(W$7,0)-$C15+1)/DAY(EOMONTH(W$7,0)),(V15+W15)/2))*$F15),"N/D") -> 11738.789
C57: =C16 -> 46614 | L57: =IF(COUNT($D16,$E16,$F16,L16,0,Supuestos!$D$45)=6,IF(0>=Supuestos!$D$45,0,IF($C16>EOMONTH(L$7,0),0,IF($C16>=DATE(YEAR(L$7),MONTH(L$7),1),($D16*$E16+L16)/2*(EOMONTH(L$7,0)-$C16+1)/DAY(EOMONTH(L$7,0)),(0+L16)/2))*$F16),"N/D") -> 0 | M57: =IF(COUNT($D16,$E16,$F16,M16,L16,Supuestos!$D$45)=6,IF(1>=Supuestos!$D$45,0,IF($C16>EOMONTH(M$7,0),0,IF($C16>=DATE(YEAR(M$7),MONTH(M$7),1),($D16*$E16+M16)/2*(EOMONTH(M$7,0)-$C16+1)/DAY(EOMONTH(M$7,0)),(L16+M16)/2))*$F16),"N/D") -> 0 | N57: =IF(COUNT($D16,$E16,$F16,N16,M16,Supuestos!$D$45)=6,IF(2>=Supuestos!$D$45,0,IF($C16>EOMONTH(N$7,0),0,IF($C16>=DATE(YEAR(N$7),MONTH(N$7),1),($D16*$E16+N16)/2*(EOMONTH(N$7,0)-$C16+1)/DAY(EOMONTH(N$7,0)),(M16+N16)/2))*$F16),"N/D") -> 0 | O57: =IF(COUNT($D16,$E16,$F16,O16,N16,Supuestos!$D$45)=6,IF(3>=Supuestos!$D$45,0,IF($C16>EOMONTH(O$7,0),0,IF($C16>=DATE(YEAR(O$7),MONTH(O$7),1),($D16*$E16+O16)/2*(EOMONTH(O$7,0)-$C16+1)/DAY(EOMONTH(O$7,0)),(N16+O16)/2))*$F16),"N/D") -> 0 | P57: =IF(COUNT($D16,$E16,$F16,P16,O16,Supuestos!$D$45)=6,IF(4>=Supuestos!$D$45,0,IF($C16>EOMONTH(P$7,0),0,IF($C16>=DATE(YEAR(P$7),MONTH(P$7),1),($D16*$E16+P16)/2*(EOMONTH(P$7,0)-$C16+1)/DAY(EOMONTH(P$7,0)),(O16+P16)/2))*$F16),"N/D") -> 0 | Q57: =IF(COUNT($D16,$E16,$F16,Q16,P16,Supuestos!$D$45)=6,IF(5>=Supuestos!$D$45,0,IF($C16>EOMONTH(Q$7,0),0,IF($C16>=DATE(YEAR(Q$7),MONTH(Q$7),1),($D16*$E16+Q16)/2*(EOMONTH(Q$7,0)-$C16+1)/DAY(EOMONTH(Q$7,0)),(P16+Q16)/2))*$F16),"N/D") -> 0 | R57: =IF(COUNT($D16,$E16,$F16,R16,Q16,Supuestos!$D$45)=6,IF(6>=Supuestos!$D$45,0,IF($C16>EOMONTH(R$7,0),0,IF($C16>=DATE(YEAR(R$7),MONTH(R$7),1),($D16*$E16+R16)/2*(EOMONTH(R$7,0)-$C16+1)/DAY(EOMONTH(R$7,0)),(Q16+R16)/2))*$F16),"N/D") -> 0 | S57: =IF(COUNT($D16,$E16,$F16,S16,R16,Supuestos!$D$45)=6,IF(7>=Supuestos!$D$45,0,IF($C16>EOMONTH(S$7,0),0,IF($C16>=DATE(YEAR(S$7),MONTH(S$7),1),($D16*$E16+S16)/2*(EOMONTH(S$7,0)-$C16+1)/DAY(EOMONTH(S$7,0)),(R16+S16)/2))*$F16),"N/D") -> 7795.9928 | T57: =IF(COUNT($D16,$E16,$F16,T16,S16,Supuestos!$D$45)=6,IF(8>=Supuestos!$D$45,0,IF($C16>EOMONTH(T$7,0),0,IF($C16>=DATE(YEAR(T$7),MONTH(T$7),1),($D16*$E16+T16)/2*(EOMONTH(T$7,0)-$C16+1)/DAY(EOMONTH(T$7,0)),(S16+T16)/2))*$F16),"N/D") -> 13663.903 | U57: =IF(COUNT($D16,$E16,$F16,U16,T16,Supuestos!$D$45)=6,IF(9>=Supuestos!$D$45,0,IF($C16>EOMONTH(U$7,0),0,IF($C16>=DATE(YEAR(U$7),MONTH(U$7),1),($D16*$E16+U16)/2*(EOMONTH(U$7,0)-$C16+1)/DAY(EOMONTH(U$7,0)),(T16+U16)/2))*$F16),"N/D") -> 12931.479 | V57: =IF(COUNT($D16,$E16,$F16,V16,U16,Supuestos!$D$45)=6,IF(10>=Supuestos!$D$45,0,IF($C16>EOMONTH(V$7,0),0,IF($C16>=DATE(YEAR(V$7),MONTH(V$7),1),($D16*$E16+V16)/2*(EOMONTH(V$7,0)-$C16+1)/DAY(EOMONTH(V$7,0)),(U16+V16)/2))*$F16),"N/D") -> 12335.134 | W57: =IF(COUNT($D16,$E16,$F16,W16,V16,Supuestos!$D$45)=6,IF(11>=Supuestos!$D$45,0,IF($C16>EOMONTH(W$7,0),0,IF($C16>=DATE(YEAR(W$7),MONTH(W$7),1),($D16*$E16+W16)/2*(EOMONTH(W$7,0)-$C16+1)/DAY(EOMONTH(W$7,0)),(V16+W16)/2))*$F16),"N/D") -> 11986.933
C58: =C17 -> 46645 | L58: =IF(COUNT($D17,$E17,$F17,L17,0,Supuestos!$D$45)=6,IF(0>=Supuestos!$D$45,0,IF($C17>EOMONTH(L$7,0),0,IF($C17>=DATE(YEAR(L$7),MONTH(L$7),1),($D17*$E17+L17)/2*(EOMONTH(L$7,0)-$C17+1)/DAY(EOMONTH(L$7,0)),(0+L17)/2))*$F17),"N/D") -> 0 | M58: =IF(COUNT($D17,$E17,$F17,M17,L17,Supuestos!$D$45)=6,IF(1>=Supuestos!$D$45,0,IF($C17>EOMONTH(M$7,0),0,IF($C17>=DATE(YEAR(M$7),MONTH(M$7),1),($D17*$E17+M17)/2*(EOMONTH(M$7,0)-$C17+1)/DAY(EOMONTH(M$7,0)),(L17+M17)/2))*$F17),"N/D") -> 0 | N58: =IF(COUNT($D17,$E17,$F17,N17,M17,Supuestos!$D$45)=6,IF(2>=Supuestos!$D$45,0,IF($C17>EOMONTH(N$7,0),0,IF($C17>=DATE(YEAR(N$7),MONTH(N$7),1),($D17*$E17+N17)/2*(EOMONTH(N$7,0)-$C17+1)/DAY(EOMONTH(N$7,0)),(M17+N17)/2))*$F17),"N/D") -> 0 | O58: =IF(COUNT($D17,$E17,$F17,O17,N17,Supuestos!$D$45)=6,IF(3>=Supuestos!$D$45,0,IF($C17>EOMONTH(O$7,0),0,IF($C17>=DATE(YEAR(O$7),MONTH(O$7),1),($D17*$E17+O17)/2*(EOMONTH(O$7,0)-$C17+1)/DAY(EOMONTH(O$7,0)),(N17+O17)/2))*$F17),"N/D") -> 0 | P58: =IF(COUNT($D17,$E17,$F17,P17,O17,Supuestos!$D$45)=6,IF(4>=Supuestos!$D$45,0,IF($C17>EOMONTH(P$7,0),0,IF($C17>=DATE(YEAR(P$7),MONTH(P$7),1),($D17*$E17+P17)/2*(EOMONTH(P$7,0)-$C17+1)/DAY(EOMONTH(P$7,0)),(O17+P17)/2))*$F17),"N/D") -> 0 | Q58: =IF(COUNT($D17,$E17,$F17,Q17,P17,Supuestos!$D$45)=6,IF(5>=Supuestos!$D$45,0,IF($C17>EOMONTH(Q$7,0),0,IF($C17>=DATE(YEAR(Q$7),MONTH(Q$7),1),($D17*$E17+Q17)/2*(EOMONTH(Q$7,0)-$C17+1)/DAY(EOMONTH(Q$7,0)),(P17+Q17)/2))*$F17),"N/D") -> 0 | R58: =IF(COUNT($D17,$E17,$F17,R17,Q17,Supuestos!$D$45)=6,IF(6>=Supuestos!$D$45,0,IF($C17>EOMONTH(R$7,0),0,IF($C17>=DATE(YEAR(R$7),MONTH(R$7),1),($D17*$E17+R17)/2*(EOMONTH(R$7,0)-$C17+1)/DAY(EOMONTH(R$7,0)),(Q17+R17)/2))*$F17),"N/D") -> 0 | S58: =IF(COUNT($D17,$E17,$F17,S17,R17,Supuestos!$D$45)=6,IF(7>=Supuestos!$D$45,0,IF($C17>EOMONTH(S$7,0),0,IF($C17>=DATE(YEAR(S$7),MONTH(S$7),1),($D17*$E17+S17)/2*(EOMONTH(S$7,0)-$C17+1)/DAY(EOMONTH(S$7,0)),(R17+S17)/2))*$F17),"N/D") -> 0 | T58: =IF(COUNT($D17,$E17,$F17,T17,S17,Supuestos!$D$45)=6,IF(8>=Supuestos!$D$45,0,IF($C17>EOMONTH(T$7,0),0,IF($C17>=DATE(YEAR(T$7),MONTH(T$7),1),($D17*$E17+T17)/2*(EOMONTH(T$7,0)-$C17+1)/DAY(EOMONTH(T$7,0)),(S17+T17)/2))*$F17),"N/D") -> 7588.3889 | U58: =IF(COUNT($D17,$E17,$F17,U17,T17,Supuestos!$D$45)=6,IF(9>=Supuestos!$D$45,0,IF($C17>EOMONTH(U$7,0),0,IF($C17>=DATE(YEAR(U$7),MONTH(U$7),1),($D17*$E17+U17)/2*(EOMONTH(U$7,0)-$C17+1)/DAY(EOMONTH(U$7,0)),(T17+U17)/2))*$F17),"N/D") -> 13675.91 | V58: =IF(COUNT($D17,$E17,$F17,V17,U17,Supuestos!$D$45)=6,IF(10>=Supuestos!$D$45,0,IF($C17>EOMONTH(V$7,0),0,IF($C17>=DATE(YEAR(V$7),MONTH(V$7),1),($D17*$E17+V17)/2*(EOMONTH(V$7,0)-$C17+1)/DAY(EOMONTH(V$7,0)),(U17+V17)/2))*$F17),"N/D") -> 12943.486 | W58: =IF(COUNT($D17,$E17,$F17,W17,V17,Supuestos!$D$45)=6,IF(11>=Supuestos!$D$45,0,IF($C17>EOMONTH(W$7,0),0,IF($C17>=DATE(YEAR(W$7),MONTH(W$7),1),($D17*$E17+W17)/2*(EOMONTH(W$7,0)-$C17+1)/DAY(EOMONTH(W$7,0)),(V17+W17)/2))*$F17),"N/D") -> 12347.141
C59: =C18 -> 46675 | L59: =IF(COUNT($D18,$E18,$F18,L18,0,Supuestos!$D$45)=6,IF(0>=Supuestos!$D$45,0,IF($C18>EOMONTH(L$7,0),0,IF($C18>=DATE(YEAR(L$7),MONTH(L$7),1),($D18*$E18+L18)/2*(EOMONTH(L$7,0)-$C18+1)/DAY(EOMONTH(L$7,0)),(0+L18)/2))*$F18),"N/D") -> 0 | M59: =IF(COUNT($D18,$E18,$F18,M18,L18,Supuestos!$D$45)=6,IF(1>=Supuestos!$D$45,0,IF($C18>EOMONTH(M$7,0),0,IF($C18>=DATE(YEAR(M$7),MONTH(M$7),1),($D18*$E18+M18)/2*(EOMONTH(M$7,0)-$C18+1)/DAY(EOMONTH(M$7,0)),(L18+M18)/2))*$F18),"N/D") -> 0 | N59: =IF(COUNT($D18,$E18,$F18,N18,M18,Supuestos!$D$45)=6,IF(2>=Supuestos!$D$45,0,IF($C18>EOMONTH(N$7,0),0,IF($C18>=DATE(YEAR(N$7),MONTH(N$7),1),($D18*$E18+N18)/2*(EOMONTH(N$7,0)-$C18+1)/DAY(EOMONTH(N$7,0)),(M18+N18)/2))*$F18),"N/D") -> 0 | O59: =IF(COUNT($D18,$E18,$F18,O18,N18,Supuestos!$D$45)=6,IF(3>=Supuestos!$D$45,0,IF($C18>EOMONTH(O$7,0),0,IF($C18>=DATE(YEAR(O$7),MONTH(O$7),1),($D18*$E18+O18)/2*(EOMONTH(O$7,0)-$C18+1)/DAY(EOMONTH(O$7,0)),(N18+O18)/2))*$F18),"N/D") -> 0 | P59: =IF(COUNT($D18,$E18,$F18,P18,O18,Supuestos!$D$45)=6,IF(4>=Supuestos!$D$45,0,IF($C18>EOMONTH(P$7,0),0,IF($C18>=DATE(YEAR(P$7),MONTH(P$7),1),($D18*$E18+P18)/2*(EOMONTH(P$7,0)-$C18+1)/DAY(EOMONTH(P$7,0)),(O18+P18)/2))*$F18),"N/D") -> 0 | Q59: =IF(COUNT($D18,$E18,$F18,Q18,P18,Supuestos!$D$45)=6,IF(5>=Supuestos!$D$45,0,IF($C18>EOMONTH(Q$7,0),0,IF($C18>=DATE(YEAR(Q$7),MONTH(Q$7),1),($D18*$E18+Q18)/2*(EOMONTH(Q$7,0)-$C18+1)/DAY(EOMONTH(Q$7,0)),(P18+Q18)/2))*$F18),"N/D") -> 0 | R59: =IF(COUNT($D18,$E18,$F18,R18,Q18,Supuestos!$D$45)=6,IF(6>=Supuestos!$D$45,0,IF($C18>EOMONTH(R$7,0),0,IF($C18>=DATE(YEAR(R$7),MONTH(R$7),1),($D18*$E18+R18)/2*(EOMONTH(R$7,0)-$C18+1)/DAY(EOMONTH(R$7,0)),(Q18+R18)/2))*$F18),"N/D") -> 0 | S59: =IF(COUNT($D18,$E18,$F18,S18,R18,Supuestos!$D$45)=6,IF(7>=Supuestos!$D$45,0,IF($C18>EOMONTH(S$7,0),0,IF($C18>=DATE(YEAR(S$7),MONTH(S$7),1),($D18*$E18+S18)/2*(EOMONTH(S$7,0)-$C18+1)/DAY(EOMONTH(S$7,0)),(R18+S18)/2))*$F18),"N/D") -> 0 | T59: =IF(COUNT($D18,$E18,$F18,T18,S18,Supuestos!$D$45)=6,IF(8>=Supuestos!$D$45,0,IF($C18>EOMONTH(T$7,0),0,IF($C18>=DATE(YEAR(T$7),MONTH(T$7),1),($D18*$E18+T18)/2*(EOMONTH(T$7,0)-$C18+1)/DAY(EOMONTH(T$7,0)),(S18+T18)/2))*$F18),"N/D") -> 0 | U59: =IF(COUNT($D18,$E18,$F18,U18,T18,Supuestos!$D$45)=6,IF(9>=Supuestos!$D$45,0,IF($C18>EOMONTH(U$7,0),0,IF($C18>=DATE(YEAR(U$7),MONTH(U$7),1),($D18*$E18+U18)/2*(EOMONTH(U$7,0)-$C18+1)/DAY(EOMONTH(U$7,0)),(T18+U18)/2))*$F18),"N/D") -> 7795.9928 | V59: =IF(COUNT($D18,$E18,$F18,V18,U18,Supuestos!$D$45)=6,IF(10>=Supuestos!$D$45,0,IF($C18>EOMONTH(V$7,0),0,IF($C18>=DATE(YEAR(V$7),MONTH(V$7),1),($D18*$E18+V18)/2*(EOMONTH(V$7,0)-$C18+1)/DAY(EOMONTH(V$7,0)),(U18+V18)/2))*$F18),"N/D") -> 13663.903 | W59: =IF(COUNT($D18,$E18,$F18,W18,V18,Supuestos!$D$45)=6,IF(11>=Supuestos!$D$45,0,IF($C18>EOMONTH(W$7,0),0,IF($C18>=DATE(YEAR(W$7),MONTH(W$7),1),($D18*$E18+W18)/2*(EOMONTH(W$7,0)-$C18+1)/DAY(EOMONTH(W$7,0)),(V18+W18)/2))*$F18),"N/D") -> 12931.479
C60: =C19 -> 46706 | L60: =IF(COUNT($D19,$E19,$F19,L19,0,Supuestos!$D$45)=6,IF(0>=Supuestos!$D$45,0,IF($C19>EOMONTH(L$7,0),0,IF($C19>=DATE(YEAR(L$7),MONTH(L$7),1),($D19*$E19+L19)/2*(EOMONTH(L$7,0)-$C19+1)/DAY(EOMONTH(L$7,0)),(0+L19)/2))*$F19),"N/D") -> 0 | M60: =IF(COUNT($D19,$E19,$F19,M19,L19,Supuestos!$D$45)=6,IF(1>=Supuestos!$D$45,0,IF($C19>EOMONTH(M$7,0),0,IF($C19>=DATE(YEAR(M$7),MONTH(M$7),1),($D19*$E19+M19)/2*(EOMONTH(M$7,0)-$C19+1)/DAY(EOMONTH(M$7,0)),(L19+M19)/2))*$F19),"N/D") -> 0 | N60: =IF(COUNT($D19,$E19,$F19,N19,M19,Supuestos!$D$45)=6,IF(2>=Supuestos!$D$45,0,IF($C19>EOMONTH(N$7,0),0,IF($C19>=DATE(YEAR(N$7),MONTH(N$7),1),($D19*$E19+N19)/2*(EOMONTH(N$7,0)-$C19+1)/DAY(EOMONTH(N$7,0)),(M19+N19)/2))*$F19),"N/D") -> 0 | O60: =IF(COUNT($D19,$E19,$F19,O19,N19,Supuestos!$D$45)=6,IF(3>=Supuestos!$D$45,0,IF($C19>EOMONTH(O$7,0),0,IF($C19>=DATE(YEAR(O$7),MONTH(O$7),1),($D19*$E19+O19)/2*(EOMONTH(O$7,0)-$C19+1)/DAY(EOMONTH(O$7,0)),(N19+O19)/2))*$F19),"N/D") -> 0 | P60: =IF(COUNT($D19,$E19,$F19,P19,O19,Supuestos!$D$45)=6,IF(4>=Supuestos!$D$45,0,IF($C19>EOMONTH(P$7,0),0,IF($C19>=DATE(YEAR(P$7),MONTH(P$7),1),($D19*$E19+P19)/2*(EOMONTH(P$7,0)-$C19+1)/DAY(EOMONTH(P$7,0)),(O19+P19)/2))*$F19),"N/D") -> 0 | Q60: =IF(COUNT($D19,$E19,$F19,Q19,P19,Supuestos!$D$45)=6,IF(5>=Supuestos!$D$45,0,IF($C19>EOMONTH(Q$7,0),0,IF($C19>=DATE(YEAR(Q$7),MONTH(Q$7),1),($D19*$E19+Q19)/2*(EOMONTH(Q$7,0)-$C19+1)/DAY(EOMONTH(Q$7,0)),(P19+Q19)/2))*$F19),"N/D") -> 0 | R60: =IF(COUNT($D19,$E19,$F19,R19,Q19,Supuestos!$D$45)=6,IF(6>=Supuestos!$D$45,0,IF($C19>EOMONTH(R$7,0),0,IF($C19>=DATE(YEAR(R$7),MONTH(R$7),1),($D19*$E19+R19)/2*(EOMONTH(R$7,0)-$C19+1)/DAY(EOMONTH(R$7,0)),(Q19+R19)/2))*$F19),"N/D") -> 0 | S60: =IF(COUNT($D19,$E19,$F19,S19,R19,Supuestos!$D$45)=6,IF(7>=Supuestos!$D$45,0,IF($C19>EOMONTH(S$7,0),0,IF($C19>=DATE(YEAR(S$7),MONTH(S$7),1),($D19*$E19+S19)/2*(EOMONTH(S$7,0)-$C19+1)/DAY(EOMONTH(S$7,0)),(R19+S19)/2))*$F19),"N/D") -> 0 | T60: =IF(COUNT($D19,$E19,$F19,T19,S19,Supuestos!$D$45)=6,IF(8>=Supuestos!$D$45,0,IF($C19>EOMONTH(T$7,0),0,IF($C19>=DATE(YEAR(T$7),MONTH(T$7),1),($D19*$E19+T19)/2*(EOMONTH(T$7,0)-$C19+1)/DAY(EOMONTH(T$7,0)),(S19+T19)/2))*$F19),"N/D") -> 0 | U60: =IF(COUNT($D19,$E19,$F19,U19,T19,Supuestos!$D$45)=6,IF(9>=Supuestos!$D$45,0,IF($C19>EOMONTH(U$7,0),0,IF($C19>=DATE(YEAR(U$7),MONTH(U$7),1),($D19*$E19+U19)/2*(EOMONTH(U$7,0)-$C19+1)/DAY(EOMONTH(U$7,0)),(T19+U19)/2))*$F19),"N/D") -> 0 | V60: =IF(COUNT($D19,$E19,$F19,V19,U19,Supuestos!$D$45)=6,IF(10>=Supuestos!$D$45,0,IF($C19>EOMONTH(V$7,0),0,IF($C19>=DATE(YEAR(V$7),MONTH(V$7),1),($D19*$E19+V19)/2*(EOMONTH(V$7,0)-$C19+1)/DAY(EOMONTH(V$7,0)),(U19+V19)/2))*$F19),"N/D") -> 7588.3889 | W60: =IF(COUNT($D19,$E19,$F19,W19,V19,Supuestos!$D$45)=6,IF(11>=Supuestos!$D$45,0,IF($C19>EOMONTH(W$7,0),0,IF($C19>=DATE(YEAR(W$7),MONTH(W$7),1),($D19*$E19+W19)/2*(EOMONTH(W$7,0)-$C19+1)/DAY(EOMONTH(W$7,0)),(V19+W19)/2))*$F19),"N/D") -> 13675.91
C61: =C20 -> 46736 | L61: =IF(COUNT($D20,$E20,$F20,L20,0,Supuestos!$D$45)=6,IF(0>=Supuestos!$D$45,0,IF($C20>EOMONTH(L$7,0),0,IF($C20>=DATE(YEAR(L$7),MONTH(L$7),1),($D20*$E20+L20)/2*(EOMONTH(L$7,0)-$C20+1)/DAY(EOMONTH(L$7,0)),(0+L20)/2))*$F20),"N/D") -> 0 | M61: =IF(COUNT($D20,$E20,$F20,M20,L20,Supuestos!$D$45)=6,IF(1>=Supuestos!$D$45,0,IF($C20>EOMONTH(M$7,0),0,IF($C20>=DATE(YEAR(M$7),MONTH(M$7),1),($D20*$E20+M20)/2*(EOMONTH(M$7,0)-$C20+1)/DAY(EOMONTH(M$7,0)),(L20+M20)/2))*$F20),"N/D") -> 0 | N61: =IF(COUNT($D20,$E20,$F20,N20,M20,Supuestos!$D$45)=6,IF(2>=Supuestos!$D$45,0,IF($C20>EOMONTH(N$7,0),0,IF($C20>=DATE(YEAR(N$7),MONTH(N$7),1),($D20*$E20+N20)/2*(EOMONTH(N$7,0)-$C20+1)/DAY(EOMONTH(N$7,0)),(M20+N20)/2))*$F20),"N/D") -> 0 | O61: =IF(COUNT($D20,$E20,$F20,O20,N20,Supuestos!$D$45)=6,IF(3>=Supuestos!$D$45,0,IF($C20>EOMONTH(O$7,0),0,IF($C20>=DATE(YEAR(O$7),MONTH(O$7),1),($D20*$E20+O20)/2*(EOMONTH(O$7,0)-$C20+1)/DAY(EOMONTH(O$7,0)),(N20+O20)/2))*$F20),"N/D") -> 0 | P61: =IF(COUNT($D20,$E20,$F20,P20,O20,Supuestos!$D$45)=6,IF(4>=Supuestos!$D$45,0,IF($C20>EOMONTH(P$7,0),0,IF($C20>=DATE(YEAR(P$7),MONTH(P$7),1),($D20*$E20+P20)/2*(EOMONTH(P$7,0)-$C20+1)/DAY(EOMONTH(P$7,0)),(O20+P20)/2))*$F20),"N/D") -> 0 | Q61: =IF(COUNT($D20,$E20,$F20,Q20,P20,Supuestos!$D$45)=6,IF(5>=Supuestos!$D$45,0,IF($C20>EOMONTH(Q$7,0),0,IF($C20>=DATE(YEAR(Q$7),MONTH(Q$7),1),($D20*$E20+Q20)/2*(EOMONTH(Q$7,0)-$C20+1)/DAY(EOMONTH(Q$7,0)),(P20+Q20)/2))*$F20),"N/D") -> 0 | R61: =IF(COUNT($D20,$E20,$F20,R20,Q20,Supuestos!$D$45)=6,IF(6>=Supuestos!$D$45,0,IF($C20>EOMONTH(R$7,0),0,IF($C20>=DATE(YEAR(R$7),MONTH(R$7),1),($D20*$E20+R20)/2*(EOMONTH(R$7,0)-$C20+1)/DAY(EOMONTH(R$7,0)),(Q20+R20)/2))*$F20),"N/D") -> 0 | S61: =IF(COUNT($D20,$E20,$F20,S20,R20,Supuestos!$D$45)=6,IF(7>=Supuestos!$D$45,0,IF($C20>EOMONTH(S$7,0),0,IF($C20>=DATE(YEAR(S$7),MONTH(S$7),1),($D20*$E20+S20)/2*(EOMONTH(S$7,0)-$C20+1)/DAY(EOMONTH(S$7,0)),(R20+S20)/2))*$F20),"N/D") -> 0 | T61: =IF(COUNT($D20,$E20,$F20,T20,S20,Supuestos!$D$45)=6,IF(8>=Supuestos!$D$45,0,IF($C20>EOMONTH(T$7,0),0,IF($C20>=DATE(YEAR(T$7),MONTH(T$7),1),($D20*$E20+T20)/2*(EOMONTH(T$7,0)-$C20+1)/DAY(EOMONTH(T$7,0)),(S20+T20)/2))*$F20),"N/D") -> 0 | U61: =IF(COUNT($D20,$E20,$F20,U20,T20,Supuestos!$D$45)=6,IF(9>=Supuestos!$D$45,0,IF($C20>EOMONTH(U$7,0),0,IF($C20>=DATE(YEAR(U$7),MONTH(U$7),1),($D20*$E20+U20)/2*(EOMONTH(U$7,0)-$C20+1)/DAY(EOMONTH(U$7,0)),(T20+U20)/2))*$F20),"N/D") -> 0 | V61: =IF(COUNT($D20,$E20,$F20,V20,U20,Supuestos!$D$45)=6,IF(10>=Supuestos!$D$45,0,IF($C20>EOMONTH(V$7,0),0,IF($C20>=DATE(YEAR(V$7),MONTH(V$7),1),($D20*$E20+V20)/2*(EOMONTH(V$7,0)-$C20+1)/DAY(EOMONTH(V$7,0)),(U20+V20)/2))*$F20),"N/D") -> 0 | W61: =IF(COUNT($D20,$E20,$F20,W20,V20,Supuestos!$D$45)=6,IF(11>=Supuestos!$D$45,0,IF($C20>EOMONTH(W$7,0),0,IF($C20>=DATE(YEAR(W$7),MONTH(W$7),1),($D20*$E20+W20)/2*(EOMONTH(W$7,0)-$C20+1)/DAY(EOMONTH(W$7,0)),(V20+W20)/2))*$F20),"N/D") -> 7795.9928
C63: Saldo medio externo | L63: =IF(COUNT(L50:L61)=12,SUM(L50:L61),"N/D") -> 7795.9928 | M63: =IF(COUNT(M50:M61)=12,SUM(M50:M61),"N/D") -> 20814.038 | N63: =IF(COUNT(N50:N61)=12,SUM(N50:N61),"N/D") -> 34499.437 | O63: =IF(COUNT(O50:O61)=12,SUM(O50:O61),"N/D") -> 46610.958 | P63: =IF(COUNT(P50:P61)=12,SUM(P50:P61),"N/D") -> 58785.484 | Q63: =IF(COUNT(Q50:Q61)=12,SUM(Q50:Q61),"N/D") -> 70296.657 | R63: =IF(COUNT(R50:R61)=12,SUM(R50:R61),"N/D") -> 82049.858 | S63: =IF(COUNT(S50:S61)=12,SUM(S50:S61),"N/D") -> 93385.928 | ... W63: =IF(COUNT(W50:W61)=12,SUM(W50:W61),"N/D") -> 137807.3
C66: Primer fondeo | D66: Cuentas | E66: Saldo30d | F66: Saldo60d | G66: Saldo90d | H66: Saldo180d | I66: Saldo365d
C67: =C9 -> 46402 | D67: =D9 -> 8.2333333 | E67: =IF(COUNT($C9,Supuestos!$D$45)=2,IF($C9+30>EOMONTH(INDEX(Supuestos!$F$31:$Q$31,1,Supuestos!$D$45),0),"Fuera ventana",IF(COUNT($D9,$E9,$G9)=3,$D9*$E9*$G9,"N/D")),"N/D") -> 19554.167 | F67: =IF(COUNT($C9,Supuestos!$D$45)=2,IF($C9+60>EOMONTH(INDEX(Supuestos!$F$31:$Q$31,1,Supuestos!$D$45),0),"Fuera ventana",IF(COUNT($D9,$E9,$H9)=3,$D9*$E9*$H9,"N/D")),"N/D") -> 18525 | G67: =IF(COUNT($C9,Supuestos!$D$45)=2,IF($C9+90>EOMONTH(INDEX(Supuestos!$F$31:$Q$31,1,Supuestos!$D$45),0),"Fuera ventana",IF(COUNT($D9,$E9,$I9)=3,$D9*$E9*$I9,"N/D")),"N/D") -> 17495.833 | H67: =IF(COUNT($C9,Supuestos!$D$45)=2,IF($C9+180>EOMONTH(INDEX(Supuestos!$F$31:$Q$31,1,Supuestos!$D$45),0),"Fuera ventana",IF(COUNT($D9,$E9,$J9)=3,$D9*$E9*$J9,"N/D")),"N/D") -> 16466.667 | I67: =IF(COUNT($C9,Supuestos!$D$45)=2,IF($C9+365>EOMONTH(INDEX(Supuestos!$F$31:$Q$31,1,Supuestos!$D$45),0),"Fuera ventana",IF(COUNT($D9,$E9,$K9)=3,$D9*$E9*$K9,"N/D")),"N/D") -> Fuera ventana
C68: =C10 -> 46433 | D68: =D10 -> 8.2333333 | E68: =IF(COUNT($C10,Supuestos!$D$45)=2,IF($C10+30>EOMONTH(INDEX(Supuestos!$F$31:$Q$31,1,Supuestos!$D$45),0),"Fuera ventana",IF(COUNT($D10,$E10,$G10)=3,$D10*$E10*$G10,"N/D")),"N/D") -> 19554.167 | F68: =IF(COUNT($C10,Supuestos!$D$45)=2,IF($C10+60>EOMONTH(INDEX(Supuestos!$F$31:$Q$31,1,Supuestos!$D$45),0),"Fuera ventana",IF(COUNT($D10,$E10,$H10)=3,$D10*$E10*$H10,"N/D")),"N/D") -> 18525 | G68: =IF(COUNT($C10,Supuestos!$D$45)=2,IF($C10+90>EOMONTH(INDEX(Supuestos!$F$31:$Q$31,1,Supuestos!$D$45),0),"Fuera ventana",IF(COUNT($D10,$E10,$I10)=3,$D10*$E10*$I10,"N/D")),"N/D") -> 17495.833 | H68: =IF(COUNT($C10,Supuestos!$D$45)=2,IF($C10+180>EOMONTH(INDEX(Supuestos!$F$31:$Q$31,1,Supuestos!$D$45),0),"Fuera ventana",IF(COUNT($D10,$E10,$J10)=3,$D10*$E10*$J10,"N/D")),"N/D") -> 16466.667 | I68: =IF(COUNT($C10,Supuestos!$D$45)=2,IF($C10+365>EOMONTH(INDEX(Supuestos!$F$31:$Q$31,1,Supuestos!$D$45),0),"Fuera ventana",IF(COUNT($D10,$E10,$K10)=3,$D10*$E10*$K10,"N/D")),"N/D") -> Fuera ventana
C69: =C11 -> 46461 | D69: =D11 -> 8.2333333 | E69: =IF(COUNT($C11,Supuestos!$D$45)=2,IF($C11+30>EOMONTH(INDEX(Supuestos!$F$31:$Q$31,1,Supuestos!$D$45),0),"Fuera ventana",IF(COUNT($D11,$E11,$G11)=3,$D11*$E11*$G11,"N/D")),"N/D") -> 19554.167 | F69: =IF(COUNT($C11,Supuestos!$D$45)=2,IF($C11+60>EOMONTH(INDEX(Supuestos!$F$31:$Q$31,1,Supuestos!$D$45),0),"Fuera ventana",IF(COUNT($D11,$E11,$H11)=3,$D11*$E11*$H11,"N/D")),"N/D") -> 18525 | G69: =IF(COUNT($C11,Supuestos!$D$45)=2,IF($C11+90>EOMONTH(INDEX(Supuestos!$F$31:$Q$31,1,Supuestos!$D$45),0),"Fuera ventana",IF(COUNT($D11,$E11,$I11)=3,$D11*$E11*$I11,"N/D")),"N/D") -> 17495.833 | H69: =IF(COUNT($C11,Supuestos!$D$45)=2,IF($C11+180>EOMONTH(INDEX(Supuestos!$F$31:$Q$31,1,Supuestos!$D$45),0),"Fuera ventana",IF(COUNT($D11,$E11,$J11)=3,$D11*$E11*$J11,"N/D")),"N/D") -> 16466.667 | I69: =IF(COUNT($C11,Supuestos!$D$45)=2,IF($C11+365>EOMONTH(INDEX(Supuestos!$F$31:$Q$31,1,Supuestos!$D$45),0),"Fuera ventana",IF(COUNT($D11,$E11,$K11)=3,$D11*$E11*$K11,"N/D")),"N/D") -> Fuera ventana
C70: =C12 -> 46492 | D70: =D12 -> 8.2333333 | E70: =IF(COUNT($C12,Supuestos!$D$45)=2,IF($C12+30>EOMONTH(INDEX(Supuestos!$F$31:$Q$31,1,Supuestos!$D$45),0),"Fuera ventana",IF(COUNT($D12,$E12,$G12)=3,$D12*$E12*$G12,"N/D")),"N/D") -> 19554.167 | F70: =IF(COUNT($C12,Supuestos!$D$45)=2,IF($C12+60>EOMONTH(INDEX(Supuestos!$F$31:$Q$31,1,Supuestos!$D$45),0),"Fuera ventana",IF(COUNT($D12,$E12,$H12)=3,$D12*$E12*$H12,"N/D")),"N/D") -> 18525 | G70: =IF(COUNT($C12,Supuestos!$D$45)=2,IF($C12+90>EOMONTH(INDEX(Supuestos!$F$31:$Q$31,1,Supuestos!$D$45),0),"Fuera ventana",IF(COUNT($D12,$E12,$I12)=3,$D12*$E12*$I12,"N/D")),"N/D") -> 17495.833 | H70: =IF(COUNT($C12,Supuestos!$D$45)=2,IF($C12+180>EOMONTH(INDEX(Supuestos!$F$31:$Q$31,1,Supuestos!$D$45),0),"Fuera ventana",IF(COUNT($D12,$E12,$J12)=3,$D12*$E12*$J12,"N/D")),"N/D") -> 16466.667 | I70: =IF(COUNT($C12,Supuestos!$D$45)=2,IF($C12+365>EOMONTH(INDEX(Supuestos!$F$31:$Q$31,1,Supuestos!$D$45),0),"Fuera ventana",IF(COUNT($D12,$E12,$K12)=3,$D12*$E12*$K12,"N/D")),"N/D") -> Fuera ventana
C71: =C13 -> 46522 | D71: =D13 -> 8.2333333 | E71: =IF(COUNT($C13,Supuestos!$D$45)=2,IF($C13+30>EOMONTH(INDEX(Supuestos!$F$31:$Q$31,1,Supuestos!$D$45),0),"Fuera ventana",IF(COUNT($D13,$E13,$G13)=3,$D13*$E13*$G13,"N/D")),"N/D") -> 19554.167 | F71: =IF(COUNT($C13,Supuestos!$D$45)=2,IF($C13+60>EOMONTH(INDEX(Supuestos!$F$31:$Q$31,1,Supuestos!$D$45),0),"Fuera ventana",IF(COUNT($D13,$E13,$H13)=3,$D13*$E13*$H13,"N/D")),"N/D") -> 18525 | G71: =IF(COUNT($C13,Supuestos!$D$45)=2,IF($C13+90>EOMONTH(INDEX(Supuestos!$F$31:$Q$31,1,Supuestos!$D$45),0),"Fuera ventana",IF(COUNT($D13,$E13,$I13)=3,$D13*$E13*$I13,"N/D")),"N/D") -> 17495.833 | H71: =IF(COUNT($C13,Supuestos!$D$45)=2,IF($C13+180>EOMONTH(INDEX(Supuestos!$F$31:$Q$31,1,Supuestos!$D$45),0),"Fuera ventana",IF(COUNT($D13,$E13,$J13)=3,$D13*$E13*$J13,"N/D")),"N/D") -> 16466.667 | I71: =IF(COUNT($C13,Supuestos!$D$45)=2,IF($C13+365>EOMONTH(INDEX(Supuestos!$F$31:$Q$31,1,Supuestos!$D$45),0),"Fuera ventana",IF(COUNT($D13,$E13,$K13)=3,$D13*$E13*$K13,"N/D")),"N/D") -> Fuera ventana
C72: =C14 -> 46553 | D72: =D14 -> 8.2333333 | E72: =IF(COUNT($C14,Supuestos!$D$45)=2,IF($C14+30>EOMONTH(INDEX(Supuestos!$F$31:$Q$31,1,Supuestos!$D$45),0),"Fuera ventana",IF(COUNT($D14,$E14,$G14)=3,$D14*$E14*$G14,"N/D")),"N/D") -> 19554.167 | F72: =IF(COUNT($C14,Supuestos!$D$45)=2,IF($C14+60>EOMONTH(INDEX(Supuestos!$F$31:$Q$31,1,Supuestos!$D$45),0),"Fuera ventana",IF(COUNT($D14,$E14,$H14)=3,$D14*$E14*$H14,"N/D")),"N/D") -> 18525 | G72: =IF(COUNT($C14,Supuestos!$D$45)=2,IF($C14+90>EOMONTH(INDEX(Supuestos!$F$31:$Q$31,1,Supuestos!$D$45),0),"Fuera ventana",IF(COUNT($D14,$E14,$I14)=3,$D14*$E14*$I14,"N/D")),"N/D") -> 17495.833 | H72: =IF(COUNT($C14,Supuestos!$D$45)=2,IF($C14+180>EOMONTH(INDEX(Supuestos!$F$31:$Q$31,1,Supuestos!$D$45),0),"Fuera ventana",IF(COUNT($D14,$E14,$J14)=3,$D14*$E14*$J14,"N/D")),"N/D") -> 16466.667 | I72: =IF(COUNT($C14,Supuestos!$D$45)=2,IF($C14+365>EOMONTH(INDEX(Supuestos!$F$31:$Q$31,1,Supuestos!$D$45),0),"Fuera ventana",IF(COUNT($D14,$E14,$K14)=3,$D14*$E14*$K14,"N/D")),"N/D") -> Fuera ventana
C73: =C15 -> 46583 | D73: =D15 -> 8.2333333 | E73: =IF(COUNT($C15,Supuestos!$D$45)=2,IF($C15+30>EOMONTH(INDEX(Supuestos!$F$31:$Q$31,1,Supuestos!$D$45),0),"Fuera ventana",IF(COUNT($D15,$E15,$G15)=3,$D15*$E15*$G15,"N/D")),"N/D") -> 19554.167 | F73: =IF(COUNT($C15,Supuestos!$D$45)=2,IF($C15+60>EOMONTH(INDEX(Supuestos!$F$31:$Q$31,1,Supuestos!$D$45),0),"Fuera ventana",IF(COUNT($D15,$E15,$H15)=3,$D15*$E15*$H15,"N/D")),"N/D") -> 18525 | G73: =IF(COUNT($C15,Supuestos!$D$45)=2,IF($C15+90>EOMONTH(INDEX(Supuestos!$F$31:$Q$31,1,Supuestos!$D$45),0),"Fuera ventana",IF(COUNT($D15,$E15,$I15)=3,$D15*$E15*$I15,"N/D")),"N/D") -> 17495.833 | H73: =IF(COUNT($C15,Supuestos!$D$45)=2,IF($C15+180>EOMONTH(INDEX(Supuestos!$F$31:$Q$31,1,Supuestos!$D$45),0),"Fuera ventana",IF(COUNT($D15,$E15,$J15)=3,$D15*$E15*$J15,"N/D")),"N/D") -> Fuera ventana | I73: =IF(COUNT($C15,Supuestos!$D$45)=2,IF($C15+365>EOMONTH(INDEX(Supuestos!$F$31:$Q$31,1,Supuestos!$D$45),0),"Fuera ventana",IF(COUNT($D15,$E15,$K15)=3,$D15*$E15*$K15,"N/D")),"N/D") -> Fuera ventana
C74: =C16 -> 46614 | D74: =D16 -> 8.2333333 | E74: =IF(COUNT($C16,Supuestos!$D$45)=2,IF($C16+30>EOMONTH(INDEX(Supuestos!$F$31:$Q$31,1,Supuestos!$D$45),0),"Fuera ventana",IF(COUNT($D16,$E16,$G16)=3,$D16*$E16*$G16,"N/D")),"N/D") -> 19554.167 | F74: =IF(COUNT($C16,Supuestos!$D$45)=2,IF($C16+60>EOMONTH(INDEX(Supuestos!$F$31:$Q$31,1,Supuestos!$D$45),0),"Fuera ventana",IF(COUNT($D16,$E16,$H16)=3,$D16*$E16*$H16,"N/D")),"N/D") -> 18525 | G74: =IF(COUNT($C16,Supuestos!$D$45)=2,IF($C16+90>EOMONTH(INDEX(Supuestos!$F$31:$Q$31,1,Supuestos!$D$45),0),"Fuera ventana",IF(COUNT($D16,$E16,$I16)=3,$D16*$E16*$I16,"N/D")),"N/D") -> 17495.833 | H74: =IF(COUNT($C16,Supuestos!$D$45)=2,IF($C16+180>EOMONTH(INDEX(Supuestos!$F$31:$Q$31,1,Supuestos!$D$45),0),"Fuera ventana",IF(COUNT($D16,$E16,$J16)=3,$D16*$E16*$J16,"N/D")),"N/D") -> Fuera ventana | I74: =IF(COUNT($C16,Supuestos!$D$45)=2,IF($C16+365>EOMONTH(INDEX(Supuestos!$F$31:$Q$31,1,Supuestos!$D$45),0),"Fuera ventana",IF(COUNT($D16,$E16,$K16)=3,$D16*$E16*$K16,"N/D")),"N/D") -> Fuera ventana
C75: =C17 -> 46645 | D75: =D17 -> 8.2333333 | E75: =IF(COUNT($C17,Supuestos!$D$45)=2,IF($C17+30>EOMONTH(INDEX(Supuestos!$F$31:$Q$31,1,Supuestos!$D$45),0),"Fuera ventana",IF(COUNT($D17,$E17,$G17)=3,$D17*$E17*$G17,"N/D")),"N/D") -> 19554.167 | F75: =IF(COUNT($C17,Supuestos!$D$45)=2,IF($C17+60>EOMONTH(INDEX(Supuestos!$F$31:$Q$31,1,Supuestos!$D$45),0),"Fuera ventana",IF(COUNT($D17,$E17,$H17)=3,$D17*$E17*$H17,"N/D")),"N/D") -> 18525 | G75: =IF(COUNT($C17,Supuestos!$D$45)=2,IF($C17+90>EOMONTH(INDEX(Supuestos!$F$31:$Q$31,1,Supuestos!$D$45),0),"Fuera ventana",IF(COUNT($D17,$E17,$I17)=3,$D17*$E17*$I17,"N/D")),"N/D") -> 17495.833 | H75: =IF(COUNT($C17,Supuestos!$D$45)=2,IF($C17+180>EOMONTH(INDEX(Supuestos!$F$31:$Q$31,1,Supuestos!$D$45),0),"Fuera ventana",IF(COUNT($D17,$E17,$J17)=3,$D17*$E17*$J17,"N/D")),"N/D") -> Fuera ventana | I75: =IF(COUNT($C17,Supuestos!$D$45)=2,IF($C17+365>EOMONTH(INDEX(Supuestos!$F$31:$Q$31,1,Supuestos!$D$45),0),"Fuera ventana",IF(COUNT($D17,$E17,$K17)=3,$D17*$E17*$K17,"N/D")),"N/D") -> Fuera ventana
C76: =C18 -> 46675 | D76: =D18 -> 8.2333333 | E76: =IF(COUNT($C18,Supuestos!$D$45)=2,IF($C18+30>EOMONTH(INDEX(Supuestos!$F$31:$Q$31,1,Supuestos!$D$45),0),"Fuera ventana",IF(COUNT($D18,$E18,$G18)=3,$D18*$E18*$G18,"N/D")),"N/D") -> 19554.167 | F76: =IF(COUNT($C18,Supuestos!$D$45)=2,IF($C18+60>EOMONTH(INDEX(Supuestos!$F$31:$Q$31,1,Supuestos!$D$45),0),"Fuera ventana",IF(COUNT($D18,$E18,$H18)=3,$D18*$E18*$H18,"N/D")),"N/D") -> 18525 | G76: =IF(COUNT($C18,Supuestos!$D$45)=2,IF($C18+90>EOMONTH(INDEX(Supuestos!$F$31:$Q$31,1,Supuestos!$D$45),0),"Fuera ventana",IF(COUNT($D18,$E18,$I18)=3,$D18*$E18*$I18,"N/D")),"N/D") -> Fuera ventana | H76: =IF(COUNT($C18,Supuestos!$D$45)=2,IF($C18+180>EOMONTH(INDEX(Supuestos!$F$31:$Q$31,1,Supuestos!$D$45),0),"Fuera ventana",IF(COUNT($D18,$E18,$J18)=3,$D18*$E18*$J18,"N/D")),"N/D") -> Fuera ventana | I76: =IF(COUNT($C18,Supuestos!$D$45)=2,IF($C18+365>EOMONTH(INDEX(Supuestos!$F$31:$Q$31,1,Supuestos!$D$45),0),"Fuera ventana",IF(COUNT($D18,$E18,$K18)=3,$D18*$E18*$K18,"N/D")),"N/D") -> Fuera ventana
C77: =C19 -> 46706 | D77: =D19 -> 8.2333333 | E77: =IF(COUNT($C19,Supuestos!$D$45)=2,IF($C19+30>EOMONTH(INDEX(Supuestos!$F$31:$Q$31,1,Supuestos!$D$45),0),"Fuera ventana",IF(COUNT($D19,$E19,$G19)=3,$D19*$E19*$G19,"N/D")),"N/D") -> 19554.167 | F77: =IF(COUNT($C19,Supuestos!$D$45)=2,IF($C19+60>EOMONTH(INDEX(Supuestos!$F$31:$Q$31,1,Supuestos!$D$45),0),"Fuera ventana",IF(COUNT($D19,$E19,$H19)=3,$D19*$E19*$H19,"N/D")),"N/D") -> Fuera ventana | G77: =IF(COUNT($C19,Supuestos!$D$45)=2,IF($C19+90>EOMONTH(INDEX(Supuestos!$F$31:$Q$31,1,Supuestos!$D$45),0),"Fuera ventana",IF(COUNT($D19,$E19,$I19)=3,$D19*$E19*$I19,"N/D")),"N/D") -> Fuera ventana | H77: =IF(COUNT($C19,Supuestos!$D$45)=2,IF($C19+180>EOMONTH(INDEX(Supuestos!$F$31:$Q$31,1,Supuestos!$D$45),0),"Fuera ventana",IF(COUNT($D19,$E19,$J19)=3,$D19*$E19*$J19,"N/D")),"N/D") -> Fuera ventana | I77: =IF(COUNT($C19,Supuestos!$D$45)=2,IF($C19+365>EOMONTH(INDEX(Supuestos!$F$31:$Q$31,1,Supuestos!$D$45),0),"Fuera ventana",IF(COUNT($D19,$E19,$K19)=3,$D19*$E19*$K19,"N/D")),"N/D") -> Fuera ventana
C78: =C20 -> 46736 | D78: =D20 -> 8.2333333 | E78: =IF(COUNT($C20,Supuestos!$D$45)=2,IF($C20+30>EOMONTH(INDEX(Supuestos!$F$31:$Q$31,1,Supuestos!$D$45),0),"Fuera ventana",IF(COUNT($D20,$E20,$G20)=3,$D20*$E20*$G20,"N/D")),"N/D") -> Fuera ventana | F78: =IF(COUNT($C20,Supuestos!$D$45)=2,IF($C20+60>EOMONTH(INDEX(Supuestos!$F$31:$Q$31,1,Supuestos!$D$45),0),"Fuera ventana",IF(COUNT($D20,$E20,$H20)=3,$D20*$E20*$H20,"N/D")),"N/D") -> Fuera ventana | G78: =IF(COUNT($C20,Supuestos!$D$45)=2,IF($C20+90>EOMONTH(INDEX(Supuestos!$F$31:$Q$31,1,Supuestos!$D$45),0),"Fuera ventana",IF(COUNT($D20,$E20,$I20)=3,$D20*$E20*$I20,"N/D")),"N/D") -> Fuera ventana | H78: =IF(COUNT($C20,Supuestos!$D$45)=2,IF($C20+180>EOMONTH(INDEX(Supuestos!$F$31:$Q$31,1,Supuestos!$D$45),0),"Fuera ventana",IF(COUNT($D20,$E20,$J20)=3,$D20*$E20*$J20,"N/D")),"N/D") -> Fuera ventana | I78: =IF(COUNT($C20,Supuestos!$D$45)=2,IF($C20+365>EOMONTH(INDEX(Supuestos!$F$31:$Q$31,1,Supuestos!$D$45),0),"Fuera ventana",IF(COUNT($D20,$E20,$K20)=3,$D20*$E20*$K20,"N/D")),"N/D") -> Fuera ventana
C80: Edad en días al cierre | L80: M1 | M80: M2 | N80: M3 | O80: M4 | P80: M5 | Q80: M6 | R80: M7 | S80: M8 | T80: M9 | U80: M10 | V80: M11 | W80: M12
C82: =C9 -> 46402 | L82: =IF(COUNT(L$7,$C9)=2,EOMONTH(L$7,0)-$C9,"N/D") -> 16 | M82: =IF(COUNT(M$7,$C9)=2,EOMONTH(M$7,0)-$C9,"N/D") -> 44 | N82: =IF(COUNT(N$7,$C9)=2,EOMONTH(N$7,0)-$C9,"N/D") -> 75 | O82: =IF(COUNT(O$7,$C9)=2,EOMONTH(O$7,0)-$C9,"N/D") -> 105 | P82: =IF(COUNT(P$7,$C9)=2,EOMONTH(P$7,0)-$C9,"N/D") -> 136 | Q82: =IF(COUNT(Q$7,$C9)=2,EOMONTH(Q$7,0)-$C9,"N/D") -> 166 | R82: =IF(COUNT(R$7,$C9)=2,EOMONTH(R$7,0)-$C9,"N/D") -> 197 | S82: =IF(COUNT(S$7,$C9)=2,EOMONTH(S$7,0)-$C9,"N/D") -> 228 | ... W82: =IF(COUNT(W$7,$C9)=2,EOMONTH(W$7,0)-$C9,"N/D") -> 350
C83: =C10 -> 46433 | L83: =IF(COUNT(L$7,$C10)=2,EOMONTH(L$7,0)-$C10,"N/D") -> -15 | M83: =IF(COUNT(M$7,$C10)=2,EOMONTH(M$7,0)-$C10,"N/D") -> 13 | N83: =IF(COUNT(N$7,$C10)=2,EOMONTH(N$7,0)-$C10,"N/D") -> 44 | O83: =IF(COUNT(O$7,$C10)=2,EOMONTH(O$7,0)-$C10,"N/D") -> 74 | P83: =IF(COUNT(P$7,$C10)=2,EOMONTH(P$7,0)-$C10,"N/D") -> 105 | Q83: =IF(COUNT(Q$7,$C10)=2,EOMONTH(Q$7,0)-$C10,"N/D") -> 135 | R83: =IF(COUNT(R$7,$C10)=2,EOMONTH(R$7,0)-$C10,"N/D") -> 166 | S83: =IF(COUNT(S$7,$C10)=2,EOMONTH(S$7,0)-$C10,"N/D") -> 197 | ... W83: =IF(COUNT(W$7,$C10)=2,EOMONTH(W$7,0)-$C10,"N/D") -> 319
C84: =C11 -> 46461 | L84: =IF(COUNT(L$7,$C11)=2,EOMONTH(L$7,0)-$C11,"N/D") -> -43 | M84: =IF(COUNT(M$7,$C11)=2,EOMONTH(M$7,0)-$C11,"N/D") -> -15 | N84: =IF(COUNT(N$7,$C11)=2,EOMONTH(N$7,0)-$C11,"N/D") -> 16 | O84: =IF(COUNT(O$7,$C11)=2,EOMONTH(O$7,0)-$C11,"N/D") -> 46 | P84: =IF(COUNT(P$7,$C11)=2,EOMONTH(P$7,0)-$C11,"N/D") -> 77 | Q84: =IF(COUNT(Q$7,$C11)=2,EOMONTH(Q$7,0)-$C11,"N/D") -> 107 | R84: =IF(COUNT(R$7,$C11)=2,EOMONTH(R$7,0)-$C11,"N/D") -> 138 | S84: =IF(COUNT(S$7,$C11)=2,EOMONTH(S$7,0)-$C11,"N/D") -> 169 | ... W84: =IF(COUNT(W$7,$C11)=2,EOMONTH(W$7,0)-$C11,"N/D") -> 291
C85: =C12 -> 46492 | L85: =IF(COUNT(L$7,$C12)=2,EOMONTH(L$7,0)-$C12,"N/D") -> -74 | M85: =IF(COUNT(M$7,$C12)=2,EOMONTH(M$7,0)-$C12,"N/D") -> -46 | N85: =IF(COUNT(N$7,$C12)=2,EOMONTH(N$7,0)-$C12,"N/D") -> -15 | O85: =IF(COUNT(O$7,$C12)=2,EOMONTH(O$7,0)-$C12,"N/D") -> 15 | P85: =IF(COUNT(P$7,$C12)=2,EOMONTH(P$7,0)-$C12,"N/D") -> 46 | Q85: =IF(COUNT(Q$7,$C12)=2,EOMONTH(Q$7,0)-$C12,"N/D") -> 76 | R85: =IF(COUNT(R$7,$C12)=2,EOMONTH(R$7,0)-$C12,"N/D") -> 107 | S85: =IF(COUNT(S$7,$C12)=2,EOMONTH(S$7,0)-$C12,"N/D") -> 138 | ... W85: =IF(COUNT(W$7,$C12)=2,EOMONTH(W$7,0)-$C12,"N/D") -> 260
C86: =C13 -> 46522 | L86: =IF(COUNT(L$7,$C13)=2,EOMONTH(L$7,0)-$C13,"N/D") -> -104 | M86: =IF(COUNT(M$7,$C13)=2,EOMONTH(M$7,0)-$C13,"N/D") -> -76 | N86: =IF(COUNT(N$7,$C13)=2,EOMONTH(N$7,0)-$C13,"N/D") -> -45 | O86: =IF(COUNT(O$7,$C13)=2,EOMONTH(O$7,0)-$C13,"N/D") -> -15 | P86: =IF(COUNT(P$7,$C13)=2,EOMONTH(P$7,0)-$C13,"N/D") -> 16 | Q86: =IF(COUNT(Q$7,$C13)=2,EOMONTH(Q$7,0)-$C13,"N/D") -> 46 | R86: =IF(COUNT(R$7,$C13)=2,EOMONTH(R$7,0)-$C13,"N/D") -> 77 | S86: =IF(COUNT(S$7,$C13)=2,EOMONTH(S$7,0)-$C13,"N/D") -> 108 | ... W86: =IF(COUNT(W$7,$C13)=2,EOMONTH(W$7,0)-$C13,"N/D") -> 230
C87: =C14 -> 46553 | L87: =IF(COUNT(L$7,$C14)=2,EOMONTH(L$7,0)-$C14,"N/D") -> -135 | M87: =IF(COUNT(M$7,$C14)=2,EOMONTH(M$7,0)-$C14,"N/D") -> -107 | N87: =IF(COUNT(N$7,$C14)=2,EOMONTH(N$7,0)-$C14,"N/D") -> -76 | O87: =IF(COUNT(O$7,$C14)=2,EOMONTH(O$7,0)-$C14,"N/D") -> -46 | P87: =IF(COUNT(P$7,$C14)=2,EOMONTH(P$7,0)-$C14,"N/D") -> -15 | Q87: =IF(COUNT(Q$7,$C14)=2,EOMONTH(Q$7,0)-$C14,"N/D") -> 15 | R87: =IF(COUNT(R$7,$C14)=2,EOMONTH(R$7,0)-$C14,"N/D") -> 46 | S87: =IF(COUNT(S$7,$C14)=2,EOMONTH(S$7,0)-$C14,"N/D") -> 77 | ... W87: =IF(COUNT(W$7,$C14)=2,EOMONTH(W$7,0)-$C14,"N/D") -> 199
C88: =C15 -> 46583 | L88: =IF(COUNT(L$7,$C15)=2,EOMONTH(L$7,0)-$C15,"N/D") -> -165 | M88: =IF(COUNT(M$7,$C15)=2,EOMONTH(M$7,0)-$C15,"N/D") -> -137 | N88: =IF(COUNT(N$7,$C15)=2,EOMONTH(N$7,0)-$C15,"N/D") -> -106 | O88: =IF(COUNT(O$7,$C15)=2,EOMONTH(O$7,0)-$C15,"N/D") -> -76 | P88: =IF(COUNT(P$7,$C15)=2,EOMONTH(P$7,0)-$C15,"N/D") -> -45 | Q88: =IF(COUNT(Q$7,$C15)=2,EOMONTH(Q$7,0)-$C15,"N/D") -> -15 | R88: =IF(COUNT(R$7,$C15)=2,EOMONTH(R$7,0)-$C15,"N/D") -> 16 | S88: =IF(COUNT(S$7,$C15)=2,EOMONTH(S$7,0)-$C15,"N/D") -> 47 | ... W88: =IF(COUNT(W$7,$C15)=2,EOMONTH(W$7,0)-$C15,"N/D") -> 169
C89: =C16 -> 46614 | L89: =IF(COUNT(L$7,$C16)=2,EOMONTH(L$7,0)-$C16,"N/D") -> -196 | M89: =IF(COUNT(M$7,$C16)=2,EOMONTH(M$7,0)-$C16,"N/D") -> -168 | N89: =IF(COUNT(N$7,$C16)=2,EOMONTH(N$7,0)-$C16,"N/D") -> -137 | O89: =IF(COUNT(O$7,$C16)=2,EOMONTH(O$7,0)-$C16,"N/D") -> -107 | P89: =IF(COUNT(P$7,$C16)=2,EOMONTH(P$7,0)-$C16,"N/D") -> -76 | Q89: =IF(COUNT(Q$7,$C16)=2,EOMONTH(Q$7,0)-$C16,"N/D") -> -46 | R89: =IF(COUNT(R$7,$C16)=2,EOMONTH(R$7,0)-$C16,"N/D") -> -15 | S89: =IF(COUNT(S$7,$C16)=2,EOMONTH(S$7,0)-$C16,"N/D") -> 16 | ... W89: =IF(COUNT(W$7,$C16)=2,EOMONTH(W$7,0)-$C16,"N/D") -> 138
C90: =C17 -> 46645 | L90: =IF(COUNT(L$7,$C17)=2,EOMONTH(L$7,0)-$C17,"N/D") -> -227 | M90: =IF(COUNT(M$7,$C17)=2,EOMONTH(M$7,0)-$C17,"N/D") -> -199 | N90: =IF(COUNT(N$7,$C17)=2,EOMONTH(N$7,0)-$C17,"N/D") -> -168 | O90: =IF(COUNT(O$7,$C17)=2,EOMONTH(O$7,0)-$C17,"N/D") -> -138 | P90: =IF(COUNT(P$7,$C17)=2,EOMONTH(P$7,0)-$C17,"N/D") -> -107 | Q90: =IF(COUNT(Q$7,$C17)=2,EOMONTH(Q$7,0)-$C17,"N/D") -> -77 | R90: =IF(COUNT(R$7,$C17)=2,EOMONTH(R$7,0)-$C17,"N/D") -> -46 | S90: =IF(COUNT(S$7,$C17)=2,EOMONTH(S$7,0)-$C17,"N/D") -> -15 | ... W90: =IF(COUNT(W$7,$C17)=2,EOMONTH(W$7,0)-$C17,"N/D") -> 107
C91: =C18 -> 46675 | L91: =IF(COUNT(L$7,$C18)=2,EOMONTH(L$7,0)-$C18,"N/D") -> -257 | M91: =IF(COUNT(M$7,$C18)=2,EOMONTH(M$7,0)-$C18,"N/D") -> -229 | N91: =IF(COUNT(N$7,$C18)=2,EOMONTH(N$7,0)-$C18,"N/D") -> -198 | O91: =IF(COUNT(O$7,$C18)=2,EOMONTH(O$7,0)-$C18,"N/D") -> -168 | P91: =IF(COUNT(P$7,$C18)=2,EOMONTH(P$7,0)-$C18,"N/D") -> -137 | Q91: =IF(COUNT(Q$7,$C18)=2,EOMONTH(Q$7,0)-$C18,"N/D") -> -107 | R91: =IF(COUNT(R$7,$C18)=2,EOMONTH(R$7,0)-$C18,"N/D") -> -76 | S91: =IF(COUNT(S$7,$C18)=2,EOMONTH(S$7,0)-$C18,"N/D") -> -45 | ... W91: =IF(COUNT(W$7,$C18)=2,EOMONTH(W$7,0)-$C18,"N/D") -> 77
C92: =C19 -> 46706 | L92: =IF(COUNT(L$7,$C19)=2,EOMONTH(L$7,0)-$C19,"N/D") -> -288 | M92: =IF(COUNT(M$7,$C19)=2,EOMONTH(M$7,0)-$C19,"N/D") -> -260 | N92: =IF(COUNT(N$7,$C19)=2,EOMONTH(N$7,0)-$C19,"N/D") -> -229 | O92: =IF(COUNT(O$7,$C19)=2,EOMONTH(O$7,0)-$C19,"N/D") -> -199 | P92: =IF(COUNT(P$7,$C19)=2,EOMONTH(P$7,0)-$C19,"N/D") -> -168 | Q92: =IF(COUNT(Q$7,$C19)=2,EOMONTH(Q$7,0)-$C19,"N/D") -> -138 | R92: =IF(COUNT(R$7,$C19)=2,EOMONTH(R$7,0)-$C19,"N/D") -> -107 | S92: =IF(COUNT(S$7,$C19)=2,EOMONTH(S$7,0)-$C19,"N/D") -> -76 | ... W92: =IF(COUNT(W$7,$C19)=2,EOMONTH(W$7,0)-$C19,"N/D") -> 46
C93: =C20 -> 46736 | L93: =IF(COUNT(L$7,$C20)=2,EOMONTH(L$7,0)-$C20,"N/D") -> -318 | M93: =IF(COUNT(M$7,$C20)=2,EOMONTH(M$7,0)-$C20,"N/D") -> -290 | N93: =IF(COUNT(N$7,$C20)=2,EOMONTH(N$7,0)-$C20,"N/D") -> -259 | O93: =IF(COUNT(O$7,$C20)=2,EOMONTH(O$7,0)-$C20,"N/D") -> -229 | P93: =IF(COUNT(P$7,$C20)=2,EOMONTH(P$7,0)-$C20,"N/D") -> -198 | Q93: =IF(COUNT(Q$7,$C20)=2,EOMONTH(Q$7,0)-$C20,"N/D") -> -168 | R93: =IF(COUNT(R$7,$C20)=2,EOMONTH(R$7,0)-$C20,"N/D") -> -137 | S93: =IF(COUNT(S$7,$C20)=2,EOMONTH(S$7,0)-$C20,"N/D") -> -106 | ... W93: =IF(COUNT(W$7,$C20)=2,EOMONTH(W$7,0)-$C20,"N/D") -> 16
C94: Saldo relativo interpolado | L94: M1 | M94: M2 | N94: M3 | O94: M4 | P94: M5 | Q94: M6 | R94: M7 | S94: M8 | T94: M9 | U94: M10 | V94: M11 | W94: M12
C95: =C9 -> 46402 | L95: =IF(COUNT(L82,$G9:$K9,Supuestos!$D$45)=7,IF(0>=Supuestos!$D$45,0,IF(L82<0,0,IF(L82<30,1+($G9-1)*L82/30,IF(L82<60,$G9+($H9-$G9)*(L82-30)/30,IF(L82<90,$H9+($I9-$H9)*(L82-60)/30,IF(L82<180,$I9+($J9-$I9)*(L82-90)/90,IF(L82<=365,$J9+($K9-$J9)*(L82-180)/185,$K9))))))),"N/D") -> 0.97333333 | M95: =IF(COUNT(M82,$G9:$K9,Supuestos!$D$45)=7,IF(1>=Supuestos!$D$45,0,IF(M82<0,0,IF(M82<30,1+($G9-1)*M82/30,IF(M82<60,$G9+($H9-$G9)*(M82-30)/30,IF(M82<90,$H9+($I9-$H9)*(M82-60)/30,IF(M82<180,$I9+($J9-$I9)*(M82-90)/90,IF(M82<=365,$J9+($K9-$J9)*(M82-180)/185,$K9))))))),"N/D") -> 0.92666667 | N95: =IF(COUNT(N82,$G9:$K9,Supuestos!$D$45)=7,IF(2>=Supuestos!$D$45,0,IF(N82<0,0,IF(N82<30,1+($G9-1)*N82/30,IF(N82<60,$G9+($H9-$G9)*(N82-30)/30,IF(N82<90,$H9+($I9-$H9)*(N82-60)/30,IF(N82<180,$I9+($J9-$I9)*(N82-90)/90,IF(N82<=365,$J9+($K9-$J9)*(N82-180)/185,$K9))))))),"N/D") -> 0.875 | O95: =IF(COUNT(O82,$G9:$K9,Supuestos!$D$45)=7,IF(3>=Supuestos!$D$45,0,IF(O82<0,0,IF(O82<30,1+($G9-1)*O82/30,IF(O82<60,$G9+($H9-$G9)*(O82-30)/30,IF(O82<90,$H9+($I9-$H9)*(O82-60)/30,IF(O82<180,$I9+($J9-$I9)*(O82-90)/90,IF(O82<=365,$J9+($K9-$J9)*(O82-180)/185,$K9))))))),"N/D") -> 0.84166667 | P95: =IF(COUNT(P82,$G9:$K9,Supuestos!$D$45)=7,IF(4>=Supuestos!$D$45,0,IF(P82<0,0,IF(P82<30,1+($G9-1)*P82/30,IF(P82<60,$G9+($H9-$G9)*(P82-30)/30,IF(P82<90,$H9+($I9-$H9)*(P82-60)/30,IF(P82<180,$I9+($J9-$I9)*(P82-90)/90,IF(P82<=365,$J9+($K9-$J9)*(P82-180)/185,$K9))))))),"N/D") -> 0.82444444 | Q95: =IF(COUNT(Q82,$G9:$K9,Supuestos!$D$45)=7,IF(5>=Supuestos!$D$45,0,IF(Q82<0,0,IF(Q82<30,1+($G9-1)*Q82/30,IF(Q82<60,$G9+($H9-$G9)*(Q82-30)/30,IF(Q82<90,$H9+($I9-$H9)*(Q82-60)/30,IF(Q82<180,$I9+($J9-$I9)*(Q82-90)/90,IF(Q82<=365,$J9+($K9-$J9)*(Q82-180)/185,$K9))))))),"N/D") -> 0.80777778 | R95: =IF(COUNT(R82,$G9:$K9,Supuestos!$D$45)=7,IF(6>=Supuestos!$D$45,0,IF(R82<0,0,IF(R82<30,1+($G9-1)*R82/30,IF(R82<60,$G9+($H9-$G9)*(R82-30)/30,IF(R82<90,$H9+($I9-$H9)*(R82-60)/30,IF(R82<180,$I9+($J9-$I9)*(R82-90)/90,IF(R82<=365,$J9+($K9-$J9)*(R82-180)/185,$K9))))))),"N/D") -> 0.79540541 | S95: =IF(COUNT(S82,$G9:$K9,Supuestos!$D$45)=7,IF(7>=Supuestos!$D$45,0,IF(S82<0,0,IF(S82<30,1+($G9-1)*S82/30,IF(S82<60,$G9+($H9-$G9)*(S82-30)/30,IF(S82<90,$H9+($I9-$H9)*(S82-60)/30,IF(S82<180,$I9+($J9-$I9)*(S82-90)/90,IF(S82<=365,$J9+($K9-$J9)*(S82-180)/185,$K9))))))),"N/D") -> 0.78702703 | T95: =IF(COUNT(T82,$G9:$K9,Supuestos!$D$45)=7,IF(8>=Supuestos!$D$45,0,IF(T82<0,0,IF(T82<30,1+($G9-1)*T82/30,IF(T82<60,$G9+($H9-$G9)*(T82-30)/30,IF(T82<90,$H9+($I9-$H9)*(T82-60)/30,IF(T82<180,$I9+($J9-$I9)*(T82-90)/90,IF(T82<=365,$J9+($K9-$J9)*(T82-180)/185,$K9))))))),"N/D") -> 0.77891892 | U95: =IF(COUNT(U82,$G9:$K9,Supuestos!$D$45)=7,IF(9>=Supuestos!$D$45,0,IF(U82<0,0,IF(U82<30,1+($G9-1)*U82/30,IF(U82<60,$G9+($H9-$G9)*(U82-30)/30,IF(U82<90,$H9+($I9-$H9)*(U82-60)/30,IF(U82<180,$I9+($J9-$I9)*(U82-90)/90,IF(U82<=365,$J9+($K9-$J9)*(U82-180)/185,$K9))))))),"N/D") -> 0.77054054 | V95: =IF(COUNT(V82,$G9:$K9,Supuestos!$D$45)=7,IF(10>=Supuestos!$D$45,0,IF(V82<0,0,IF(V82<30,1+($G9-1)*V82/30,IF(V82<60,$G9+($H9-$G9)*(V82-30)/30,IF(V82<90,$H9+($I9-$H9)*(V82-60)/30,IF(V82<180,$I9+($J9-$I9)*(V82-90)/90,IF(V82<=365,$J9+($K9-$J9)*(V82-180)/185,$K9))))))),"N/D") -> 0.76243243 | W95: =IF(COUNT(W82,$G9:$K9,Supuestos!$D$45)=7,IF(11>=Supuestos!$D$45,0,IF(W82<0,0,IF(W82<30,1+($G9-1)*W82/30,IF(W82<60,$G9+($H9-$G9)*(W82-30)/30,IF(W82<90,$H9+($I9-$H9)*(W82-60)/30,IF(W82<180,$I9+($J9-$I9)*(W82-90)/90,IF(W82<=365,$J9+($K9-$J9)*(W82-180)/185,$K9))))))),"N/D") -> 0.75405405
C96: =C10 -> 46433 | L96: =IF(COUNT(L83,$G10:$K10,Supuestos!$D$45)=7,IF(0>=Supuestos!$D$45,0,IF(L83<0,0,IF(L83<30,1+($G10-1)*L83/30,IF(L83<60,$G10+($H10-$G10)*(L83-30)/30,IF(L83<90,$H10+($I10-$H10)*(L83-60)/30,IF(L83<180,$I10+($J10-$I10)*(L83-90)/90,IF(L83<=365,$J10+($K10-$J10)*(L83-180)/185,$K10))))))),"N/D") -> 0 | M96: =IF(COUNT(M83,$G10:$K10,Supuestos!$D$45)=7,IF(1>=Supuestos!$D$45,0,IF(M83<0,0,IF(M83<30,1+($G10-1)*M83/30,IF(M83<60,$G10+($H10-$G10)*(M83-30)/30,IF(M83<90,$H10+($I10-$H10)*(M83-60)/30,IF(M83<180,$I10+($J10-$I10)*(M83-90)/90,IF(M83<=365,$J10+($K10-$J10)*(M83-180)/185,$K10))))))),"N/D") -> 0.97833333 | N96: =IF(COUNT(N83,$G10:$K10,Supuestos!$D$45)=7,IF(2>=Supuestos!$D$45,0,IF(N83<0,0,IF(N83<30,1+($G10-1)*N83/30,IF(N83<60,$G10+($H10-$G10)*(N83-30)/30,IF(N83<90,$H10+($I10-$H10)*(N83-60)/30,IF(N83<180,$I10+($J10-$I10)*(N83-90)/90,IF(N83<=365,$J10+($K10-$J10)*(N83-180)/185,$K10))))))),"N/D") -> 0.92666667 | O96: =IF(COUNT(O83,$G10:$K10,Supuestos!$D$45)=7,IF(3>=Supuestos!$D$45,0,IF(O83<0,0,IF(O83<30,1+($G10-1)*O83/30,IF(O83<60,$G10+($H10-$G10)*(O83-30)/30,IF(O83<90,$H10+($I10-$H10)*(O83-60)/30,IF(O83<180,$I10+($J10-$I10)*(O83-90)/90,IF(O83<=365,$J10+($K10-$J10)*(O83-180)/185,$K10))))))),"N/D") -> 0.87666667 | P96: =IF(COUNT(P83,$G10:$K10,Supuestos!$D$45)=7,IF(4>=Supuestos!$D$45,0,IF(P83<0,0,IF(P83<30,1+($G10-1)*P83/30,IF(P83<60,$G10+($H10-$G10)*(P83-30)/30,IF(P83<90,$H10+($I10-$H10)*(P83-60)/30,IF(P83<180,$I10+($J10-$I10)*(P83-90)/90,IF(P83<=365,$J10+($K10-$J10)*(P83-180)/185,$K10))))))),"N/D") -> 0.84166667 | Q96: =IF(COUNT(Q83,$G10:$K10,Supuestos!$D$45)=7,IF(5>=Supuestos!$D$45,0,IF(Q83<0,0,IF(Q83<30,1+($G10-1)*Q83/30,IF(Q83<60,$G10+($H10-$G10)*(Q83-30)/30,IF(Q83<90,$H10+($I10-$H10)*(Q83-60)/30,IF(Q83<180,$I10+($J10-$I10)*(Q83-90)/90,IF(Q83<=365,$J10+($K10-$J10)*(Q83-180)/185,$K10))))))),"N/D") -> 0.825 | R96: =IF(COUNT(R83,$G10:$K10,Supuestos!$D$45)=7,IF(6>=Supuestos!$D$45,0,IF(R83<0,0,IF(R83<30,1+($G10-1)*R83/30,IF(R83<60,$G10+($H10-$G10)*(R83-30)/30,IF(R83<90,$H10+($I10-$H10)*(R83-60)/30,IF(R83<180,$I10+($J10-$I10)*(R83-90)/90,IF(R83<=365,$J10+($K10-$J10)*(R83-180)/185,$K10))))))),"N/D") -> 0.80777778 | S96: =IF(COUNT(S83,$G10:$K10,Supuestos!$D$45)=7,IF(7>=Supuestos!$D$45,0,IF(S83<0,0,IF(S83<30,1+($G10-1)*S83/30,IF(S83<60,$G10+($H10-$G10)*(S83-30)/30,IF(S83<90,$H10+($I10-$H10)*(S83-60)/30,IF(S83<180,$I10+($J10-$I10)*(S83-90)/90,IF(S83<=365,$J10+($K10-$J10)*(S83-180)/185,$K10))))))),"N/D") -> 0.79540541 | T96: =IF(COUNT(T83,$G10:$K10,Supuestos!$D$45)=7,IF(8>=Supuestos!$D$45,0,IF(T83<0,0,IF(T83<30,1+($G10-1)*T83/30,IF(T83<60,$G10+($H10-$G10)*(T83-30)/30,IF(T83<90,$H10+($I10-$H10)*(T83-60)/30,IF(T83<180,$I10+($J10-$I10)*(T83-90)/90,IF(T83<=365,$J10+($K10-$J10)*(T83-180)/185,$K10))))))),"N/D") -> 0.7872973 | U96: =IF(COUNT(U83,$G10:$K10,Supuestos!$D$45)=7,IF(9>=Supuestos!$D$45,0,IF(U83<0,0,IF(U83<30,1+($G10-1)*U83/30,IF(U83<60,$G10+($H10-$G10)*(U83-30)/30,IF(U83<90,$H10+($I10-$H10)*(U83-60)/30,IF(U83<180,$I10+($J10-$I10)*(U83-90)/90,IF(U83<=365,$J10+($K10-$J10)*(U83-180)/185,$K10))))))),"N/D") -> 0.77891892 | V96: =IF(COUNT(V83,$G10:$K10,Supuestos!$D$45)=7,IF(10>=Supuestos!$D$45,0,IF(V83<0,0,IF(V83<30,1+($G10-1)*V83/30,IF(V83<60,$G10+($H10-$G10)*(V83-30)/30,IF(V83<90,$H10+($I10-$H10)*(V83-60)/30,IF(V83<180,$I10+($J10-$I10)*(V83-90)/90,IF(V83<=365,$J10+($K10-$J10)*(V83-180)/185,$K10))))))),"N/D") -> 0.77081081 | W96: =IF(COUNT(W83,$G10:$K10,Supuestos!$D$45)=7,IF(11>=Supuestos!$D$45,0,IF(W83<0,0,IF(W83<30,1+($G10-1)*W83/30,IF(W83<60,$G10+($H10-$G10)*(W83-30)/30,IF(W83<90,$H10+($I10-$H10)*(W83-60)/30,IF(W83<180,$I10+($J10-$I10)*(W83-90)/90,IF(W83<=365,$J10+($K10-$J10)*(W83-180)/185,$K10))))))),"N/D") -> 0.76243243
C97: =C11 -> 46461 | L97: =IF(COUNT(L84,$G11:$K11,Supuestos!$D$45)=7,IF(0>=Supuestos!$D$45,0,IF(L84<0,0,IF(L84<30,1+($G11-1)*L84/30,IF(L84<60,$G11+($H11-$G11)*(L84-30)/30,IF(L84<90,$H11+($I11-$H11)*(L84-60)/30,IF(L84<180,$I11+($J11-$I11)*(L84-90)/90,IF(L84<=365,$J11+($K11-$J11)*(L84-180)/185,$K11))))))),"N/D") -> 0 | M97: =IF(COUNT(M84,$G11:$K11,Supuestos!$D$45)=7,IF(1>=Supuestos!$D$45,0,IF(M84<0,0,IF(M84<30,1+($G11-1)*M84/30,IF(M84<60,$G11+($H11-$G11)*(M84-30)/30,IF(M84<90,$H11+($I11-$H11)*(M84-60)/30,IF(M84<180,$I11+($J11-$I11)*(M84-90)/90,IF(M84<=365,$J11+($K11-$J11)*(M84-180)/185,$K11))))))),"N/D") -> 0 | N97: =IF(COUNT(N84,$G11:$K11,Supuestos!$D$45)=7,IF(2>=Supuestos!$D$45,0,IF(N84<0,0,IF(N84<30,1+($G11-1)*N84/30,IF(N84<60,$G11+($H11-$G11)*(N84-30)/30,IF(N84<90,$H11+($I11-$H11)*(N84-60)/30,IF(N84<180,$I11+($J11-$I11)*(N84-90)/90,IF(N84<=365,$J11+($K11-$J11)*(N84-180)/185,$K11))))))),"N/D") -> 0.97333333 | O97: =IF(COUNT(O84,$G11:$K11,Supuestos!$D$45)=7,IF(3>=Supuestos!$D$45,0,IF(O84<0,0,IF(O84<30,1+($G11-1)*O84/30,IF(O84<60,$G11+($H11-$G11)*(O84-30)/30,IF(O84<90,$H11+($I11-$H11)*(O84-60)/30,IF(O84<180,$I11+($J11-$I11)*(O84-90)/90,IF(O84<=365,$J11+($K11-$J11)*(O84-180)/185,$K11))))))),"N/D") -> 0.92333333 | P97: =IF(COUNT(P84,$G11:$K11,Supuestos!$D$45)=7,IF(4>=Supuestos!$D$45,0,IF(P84<0,0,IF(P84<30,1+($G11-1)*P84/30,IF(P84<60,$G11+($H11-$G11)*(P84-30)/30,IF(P84<90,$H11+($I11-$H11)*(P84-60)/30,IF(P84<180,$I11+($J11-$I11)*(P84-90)/90,IF(P84<=365,$J11+($K11-$J11)*(P84-180)/185,$K11))))))),"N/D") -> 0.87166667 | Q97: =IF(COUNT(Q84,$G11:$K11,Supuestos!$D$45)=7,IF(5>=Supuestos!$D$45,0,IF(Q84<0,0,IF(Q84<30,1+($G11-1)*Q84/30,IF(Q84<60,$G11+($H11-$G11)*(Q84-30)/30,IF(Q84<90,$H11+($I11-$H11)*(Q84-60)/30,IF(Q84<180,$I11+($J11-$I11)*(Q84-90)/90,IF(Q84<=365,$J11+($K11-$J11)*(Q84-180)/185,$K11))))))),"N/D") -> 0.84055556 | R97: =IF(COUNT(R84,$G11:$K11,Supuestos!$D$45)=7,IF(6>=Supuestos!$D$45,0,IF(R84<0,0,IF(R84<30,1+($G11-1)*R84/30,IF(R84<60,$G11+($H11-$G11)*(R84-30)/30,IF(R84<90,$H11+($I11-$H11)*(R84-60)/30,IF(R84<180,$I11+($J11-$I11)*(R84-90)/90,IF(R84<=365,$J11+($K11-$J11)*(R84-180)/185,$K11))))))),"N/D") -> 0.82333333 | S97: =IF(COUNT(S84,$G11:$K11,Supuestos!$D$45)=7,IF(7>=Supuestos!$D$45,0,IF(S84<0,0,IF(S84<30,1+($G11-1)*S84/30,IF(S84<60,$G11+($H11-$G11)*(S84-30)/30,IF(S84<90,$H11+($I11-$H11)*(S84-60)/30,IF(S84<180,$I11+($J11-$I11)*(S84-90)/90,IF(S84<=365,$J11+($K11-$J11)*(S84-180)/185,$K11))))))),"N/D") -> 0.80611111 | T97: =IF(COUNT(T84,$G11:$K11,Supuestos!$D$45)=7,IF(8>=Supuestos!$D$45,0,IF(T84<0,0,IF(T84<30,1+($G11-1)*T84/30,IF(T84<60,$G11+($H11-$G11)*(T84-30)/30,IF(T84<90,$H11+($I11-$H11)*(T84-60)/30,IF(T84<180,$I11+($J11-$I11)*(T84-90)/90,IF(T84<=365,$J11+($K11-$J11)*(T84-180)/185,$K11))))))),"N/D") -> 0.79486486 | U97: =IF(COUNT(U84,$G11:$K11,Supuestos!$D$45)=7,IF(9>=Supuestos!$D$45,0,IF(U84<0,0,IF(U84<30,1+($G11-1)*U84/30,IF(U84<60,$G11+($H11-$G11)*(U84-30)/30,IF(U84<90,$H11+($I11-$H11)*(U84-60)/30,IF(U84<180,$I11+($J11-$I11)*(U84-90)/90,IF(U84<=365,$J11+($K11-$J11)*(U84-180)/185,$K11))))))),"N/D") -> 0.78648649 | V97: =IF(COUNT(V84,$G11:$K11,Supuestos!$D$45)=7,IF(10>=Supuestos!$D$45,0,IF(V84<0,0,IF(V84<30,1+($G11-1)*V84/30,IF(V84<60,$G11+($H11-$G11)*(V84-30)/30,IF(V84<90,$H11+($I11-$H11)*(V84-60)/30,IF(V84<180,$I11+($J11-$I11)*(V84-90)/90,IF(V84<=365,$J11+($K11-$J11)*(V84-180)/185,$K11))))))),"N/D") -> 0.77837838 | W97: =IF(COUNT(W84,$G11:$K11,Supuestos!$D$45)=7,IF(11>=Supuestos!$D$45,0,IF(W84<0,0,IF(W84<30,1+($G11-1)*W84/30,IF(W84<60,$G11+($H11-$G11)*(W84-30)/30,IF(W84<90,$H11+($I11-$H11)*(W84-60)/30,IF(W84<180,$I11+($J11-$I11)*(W84-90)/90,IF(W84<=365,$J11+($K11-$J11)*(W84-180)/185,$K11))))))),"N/D") -> 0.77
C98: =C12 -> 46492 | L98: =IF(COUNT(L85,$G12:$K12,Supuestos!$D$45)=7,IF(0>=Supuestos!$D$45,0,IF(L85<0,0,IF(L85<30,1+($G12-1)*L85/30,IF(L85<60,$G12+($H12-$G12)*(L85-30)/30,IF(L85<90,$H12+($I12-$H12)*(L85-60)/30,IF(L85<180,$I12+($J12-$I12)*(L85-90)/90,IF(L85<=365,$J12+($K12-$J12)*(L85-180)/185,$K12))))))),"N/D") -> 0 | M98: =IF(COUNT(M85,$G12:$K12,Supuestos!$D$45)=7,IF(1>=Supuestos!$D$45,0,IF(M85<0,0,IF(M85<30,1+($G12-1)*M85/30,IF(M85<60,$G12+($H12-$G12)*(M85-30)/30,IF(M85<90,$H12+($I12-$H12)*(M85-60)/30,IF(M85<180,$I12+($J12-$I12)*(M85-90)/90,IF(M85<=365,$J12+($K12-$J12)*(M85-180)/185,$K12))))))),"N/D") -> 0 | N98: =IF(COUNT(N85,$G12:$K12,Supuestos!$D$45)=7,IF(2>=Supuestos!$D$45,0,IF(N85<0,0,IF(N85<30,1+($G12-1)*N85/30,IF(N85<60,$G12+($H12-$G12)*(N85-30)/30,IF(N85<90,$H12+($I12-$H12)*(N85-60)/30,IF(N85<180,$I12+($J12-$I12)*(N85-90)/90,IF(N85<=365,$J12+($K12-$J12)*(N85-180)/185,$K12))))))),"N/D") -> 0 | O98: =IF(COUNT(O85,$G12:$K12,Supuestos!$D$45)=7,IF(3>=Supuestos!$D$45,0,IF(O85<0,0,IF(O85<30,1+($G12-1)*O85/30,IF(O85<60,$G12+($H12-$G12)*(O85-30)/30,IF(O85<90,$H12+($I12-$H12)*(O85-60)/30,IF(O85<180,$I12+($J12-$I12)*(O85-90)/90,IF(O85<=365,$J12+($K12-$J12)*(O85-180)/185,$K12))))))),"N/D") -> 0.975 | P98: =IF(COUNT(P85,$G12:$K12,Supuestos!$D$45)=7,IF(4>=Supuestos!$D$45,0,IF(P85<0,0,IF(P85<30,1+($G12-1)*P85/30,IF(P85<60,$G12+($H12-$G12)*(P85-30)/30,IF(P85<90,$H12+($I12-$H12)*(P85-60)/30,IF(P85<180,$I12+($J12-$I12)*(P85-90)/90,IF(P85<=365,$J12+($K12-$J12)*(P85-180)/185,$K12))))))),"N/D") -> 0.92333333 | Q98: =IF(COUNT(Q85,$G12:$K12,Supuestos!$D$45)=7,IF(5>=Supuestos!$D$45,0,IF(Q85<0,0,IF(Q85<30,1+($G12-1)*Q85/30,IF(Q85<60,$G12+($H12-$G12)*(Q85-30)/30,IF(Q85<90,$H12+($I12-$H12)*(Q85-60)/30,IF(Q85<180,$I12+($J12-$I12)*(Q85-90)/90,IF(Q85<=365,$J12+($K12-$J12)*(Q85-180)/185,$K12))))))),"N/D") -> 0.87333333 | R98: =IF(COUNT(R85,$G12:$K12,Supuestos!$D$45)=7,IF(6>=Supuestos!$D$45,0,IF(R85<0,0,IF(R85<30,1+($G12-1)*R85/30,IF(R85<60,$G12+($H12-$G12)*(R85-30)/30,IF(R85<90,$H12+($I12-$H12)*(R85-60)/30,IF(R85<180,$I12+($J12-$I12)*(R85-90)/90,IF(R85<=365,$J12+($K12-$J12)*(R85-180)/185,$K12))))))),"N/D") -> 0.84055556 | S98: =IF(COUNT(S85,$G12:$K12,Supuestos!$D$45)=7,IF(7>=Supuestos!$D$45,0,IF(S85<0,0,IF(S85<30,1+($G12-1)*S85/30,IF(S85<60,$G12+($H12-$G12)*(S85-30)/30,IF(S85<90,$H12+($I12-$H12)*(S85-60)/30,IF(S85<180,$I12+($J12-$I12)*(S85-90)/90,IF(S85<=365,$J12+($K12-$J12)*(S85-180)/185,$K12))))))),"N/D") -> 0.82333333 | T98: =IF(COUNT(T85,$G12:$K12,Supuestos!$D$45)=7,IF(8>=Supuestos!$D$45,0,IF(T85<0,0,IF(T85<30,1+($G12-1)*T85/30,IF(T85<60,$G12+($H12-$G12)*(T85-30)/30,IF(T85<90,$H12+($I12-$H12)*(T85-60)/30,IF(T85<180,$I12+($J12-$I12)*(T85-90)/90,IF(T85<=365,$J12+($K12-$J12)*(T85-180)/185,$K12))))))),"N/D") -> 0.80666667 | U98: =IF(COUNT(U85,$G12:$K12,Supuestos!$D$45)=7,IF(9>=Supuestos!$D$45,0,IF(U85<0,0,IF(U85<30,1+($G12-1)*U85/30,IF(U85<60,$G12+($H12-$G12)*(U85-30)/30,IF(U85<90,$H12+($I12-$H12)*(U85-60)/30,IF(U85<180,$I12+($J12-$I12)*(U85-90)/90,IF(U85<=365,$J12+($K12-$J12)*(U85-180)/185,$K12))))))),"N/D") -> 0.79486486 | V98: =IF(COUNT(V85,$G12:$K12,Supuestos!$D$45)=7,IF(10>=Supuestos!$D$45,0,IF(V85<0,0,IF(V85<30,1+($G12-1)*V85/30,IF(V85<60,$G12+($H12-$G12)*(V85-30)/30,IF(V85<90,$H12+($I12-$H12)*(V85-60)/30,IF(V85<180,$I12+($J12-$I12)*(V85-90)/90,IF(V85<=365,$J12+($K12-$J12)*(V85-180)/185,$K12))))))),"N/D") -> 0.78675676 | W98: =IF(COUNT(W85,$G12:$K12,Supuestos!$D$45)=7,IF(11>=Supuestos!$D$45,0,IF(W85<0,0,IF(W85<30,1+($G12-1)*W85/30,IF(W85<60,$G12+($H12-$G12)*(W85-30)/30,IF(W85<90,$H12+($I12-$H12)*(W85-60)/30,IF(W85<180,$I12+($J12-$I12)*(W85-90)/90,IF(W85<=365,$J12+($K12-$J12)*(W85-180)/185,$K12))))))),"N/D") -> 0.77837838
C99: =C13 -> 46522 | L99: =IF(COUNT(L86,$G13:$K13,Supuestos!$D$45)=7,IF(0>=Supuestos!$D$45,0,IF(L86<0,0,IF(L86<30,1+($G13-1)*L86/30,IF(L86<60,$G13+($H13-$G13)*(L86-30)/30,IF(L86<90,$H13+($I13-$H13)*(L86-60)/30,IF(L86<180,$I13+($J13-$I13)*(L86-90)/90,IF(L86<=365,$J13+($K13-$J13)*(L86-180)/185,$K13))))))),"N/D") -> 0 | M99: =IF(COUNT(M86,$G13:$K13,Supuestos!$D$45)=7,IF(1>=Supuestos!$D$45,0,IF(M86<0,0,IF(M86<30,1+($G13-1)*M86/30,IF(M86<60,$G13+($H13-$G13)*(M86-30)/30,IF(M86<90,$H13+($I13-$H13)*(M86-60)/30,IF(M86<180,$I13+($J13-$I13)*(M86-90)/90,IF(M86<=365,$J13+($K13-$J13)*(M86-180)/185,$K13))))))),"N/D") -> 0 | N99: =IF(COUNT(N86,$G13:$K13,Supuestos!$D$45)=7,IF(2>=Supuestos!$D$45,0,IF(N86<0,0,IF(N86<30,1+($G13-1)*N86/30,IF(N86<60,$G13+($H13-$G13)*(N86-30)/30,IF(N86<90,$H13+($I13-$H13)*(N86-60)/30,IF(N86<180,$I13+($J13-$I13)*(N86-90)/90,IF(N86<=365,$J13+($K13-$J13)*(N86-180)/185,$K13))))))),"N/D") -> 0 | O99: =IF(COUNT(O86,$G13:$K13,Supuestos!$D$45)=7,IF(3>=Supuestos!$D$45,0,IF(O86<0,0,IF(O86<30,1+($G13-1)*O86/30,IF(O86<60,$G13+($H13-$G13)*(O86-30)/30,IF(O86<90,$H13+($I13-$H13)*(O86-60)/30,IF(O86<180,$I13+($J13-$I13)*(O86-90)/90,IF(O86<=365,$J13+($K13-$J13)*(O86-180)/185,$K13))))))),"N/D") -> 0 | P99: =IF(COUNT(P86,$G13:$K13,Supuestos!$D$45)=7,IF(4>=Supuestos!$D$45,0,IF(P86<0,0,IF(P86<30,1+($G13-1)*P86/30,IF(P86<60,$G13+($H13-$G13)*(P86-30)/30,IF(P86<90,$H13+($I13-$H13)*(P86-60)/30,IF(P86<180,$I13+($J13-$I13)*(P86-90)/90,IF(P86<=365,$J13+($K13-$J13)*(P86-180)/185,$K13))))))),"N/D") -> 0.97333333 | Q99: =IF(COUNT(Q86,$G13:$K13,Supuestos!$D$45)=7,IF(5>=Supuestos!$D$45,0,IF(Q86<0,0,IF(Q86<30,1+($G13-1)*Q86/30,IF(Q86<60,$G13+($H13-$G13)*(Q86-30)/30,IF(Q86<90,$H13+($I13-$H13)*(Q86-60)/30,IF(Q86<180,$I13+($J13-$I13)*(Q86-90)/90,IF(Q86<=365,$J13+($K13-$J13)*(Q86-180)/185,$K13))))))),"N/D") -> 0.92333333 | R99: =IF(COUNT(R86,$G13:$K13,Supuestos!$D$45)=7,IF(6>=Supuestos!$D$45,0,IF(R86<0,0,IF(R86<30,1+($G13-1)*R86/30,IF(R86<60,$G13+($H13-$G13)*(R86-30)/30,IF(R86<90,$H13+($I13-$H13)*(R86-60)/30,IF(R86<180,$I13+($J13-$I13)*(R86-90)/90,IF(R86<=365,$J13+($K13-$J13)*(R86-180)/185,$K13))))))),"N/D") -> 0.87166667 | S99: =IF(COUNT(S86,$G13:$K13,Supuestos!$D$45)=7,IF(7>=Supuestos!$D$45,0,IF(S86<0,0,IF(S86<30,1+($G13-1)*S86/30,IF(S86<60,$G13+($H13-$G13)*(S86-30)/30,IF(S86<90,$H13+($I13-$H13)*(S86-60)/30,IF(S86<180,$I13+($J13-$I13)*(S86-90)/90,IF(S86<=365,$J13+($K13-$J13)*(S86-180)/185,$K13))))))),"N/D") -> 0.84 | T99: =IF(COUNT(T86,$G13:$K13,Supuestos!$D$45)=7,IF(8>=Supuestos!$D$45,0,IF(T86<0,0,IF(T86<30,1+($G13-1)*T86/30,IF(T86<60,$G13+($H13-$G13)*(T86-30)/30,IF(T86<90,$H13+($I13-$H13)*(T86-60)/30,IF(T86<180,$I13+($J13-$I13)*(T86-90)/90,IF(T86<=365,$J13+($K13-$J13)*(T86-180)/185,$K13))))))),"N/D") -> 0.82333333 | U99: =IF(COUNT(U86,$G13:$K13,Supuestos!$D$45)=7,IF(9>=Supuestos!$D$45,0,IF(U86<0,0,IF(U86<30,1+($G13-1)*U86/30,IF(U86<60,$G13+($H13-$G13)*(U86-30)/30,IF(U86<90,$H13+($I13-$H13)*(U86-60)/30,IF(U86<180,$I13+($J13-$I13)*(U86-90)/90,IF(U86<=365,$J13+($K13-$J13)*(U86-180)/185,$K13))))))),"N/D") -> 0.80611111 | V99: =IF(COUNT(V86,$G13:$K13,Supuestos!$D$45)=7,IF(10>=Supuestos!$D$45,0,IF(V86<0,0,IF(V86<30,1+($G13-1)*V86/30,IF(V86<60,$G13+($H13-$G13)*(V86-30)/30,IF(V86<90,$H13+($I13-$H13)*(V86-60)/30,IF(V86<180,$I13+($J13-$I13)*(V86-90)/90,IF(V86<=365,$J13+($K13-$J13)*(V86-180)/185,$K13))))))),"N/D") -> 0.79486486 | W99: =IF(COUNT(W86,$G13:$K13,Supuestos!$D$45)=7,IF(11>=Supuestos!$D$45,0,IF(W86<0,0,IF(W86<30,1+($G13-1)*W86/30,IF(W86<60,$G13+($H13-$G13)*(W86-30)/30,IF(W86<90,$H13+($I13-$H13)*(W86-60)/30,IF(W86<180,$I13+($J13-$I13)*(W86-90)/90,IF(W86<=365,$J13+($K13-$J13)*(W86-180)/185,$K13))))))),"N/D") -> 0.78648649
C100: =C14 -> 46553 | L100: =IF(COUNT(L87,$G14:$K14,Supuestos!$D$45)=7,IF(0>=Supuestos!$D$45,0,IF(L87<0,0,IF(L87<30,1+($G14-1)*L87/30,IF(L87<60,$G14+($H14-$G14)*(L87-30)/30,IF(L87<90,$H14+($I14-$H14)*(L87-60)/30,IF(L87<180,$I14+($J14-$I14)*(L87-90)/90,IF(L87<=365,$J14+($K14-$J14)*(L87-180)/185,$K14))))))),"N/D") -> 0 | M100: =IF(COUNT(M87,$G14:$K14,Supuestos!$D$45)=7,IF(1>=Supuestos!$D$45,0,IF(M87<0,0,IF(M87<30,1+($G14-1)*M87/30,IF(M87<60,$G14+($H14-$G14)*(M87-30)/30,IF(M87<90,$H14+($I14-$H14)*(M87-60)/30,IF(M87<180,$I14+($J14-$I14)*(M87-90)/90,IF(M87<=365,$J14+($K14-$J14)*(M87-180)/185,$K14))))))),"N/D") -> 0 | N100: =IF(COUNT(N87,$G14:$K14,Supuestos!$D$45)=7,IF(2>=Supuestos!$D$45,0,IF(N87<0,0,IF(N87<30,1+($G14-1)*N87/30,IF(N87<60,$G14+($H14-$G14)*(N87-30)/30,IF(N87<90,$H14+($I14-$H14)*(N87-60)/30,IF(N87<180,$I14+($J14-$I14)*(N87-90)/90,IF(N87<=365,$J14+($K14-$J14)*(N87-180)/185,$K14))))))),"N/D") -> 0 | O100: =IF(COUNT(O87,$G14:$K14,Supuestos!$D$45)=7,IF(3>=Supuestos!$D$45,0,IF(O87<0,0,IF(O87<30,1+($G14-1)*O87/30,IF(O87<60,$G14+($H14-$G14)*(O87-30)/30,IF(O87<90,$H14+($I14-$H14)*(O87-60)/30,IF(O87<180,$I14+($J14-$I14)*(O87-90)/90,IF(O87<=365,$J14+($K14-$J14)*(O87-180)/185,$K14))))))),"N/D") -> 0 | P100: =IF(COUNT(P87,$G14:$K14,Supuestos!$D$45)=7,IF(4>=Supuestos!$D$45,0,IF(P87<0,0,IF(P87<30,1+($G14-1)*P87/30,IF(P87<60,$G14+($H14-$G14)*(P87-30)/30,IF(P87<90,$H14+($I14-$H14)*(P87-60)/30,IF(P87<180,$I14+($J14-$I14)*(P87-90)/90,IF(P87<=365,$J14+($K14-$J14)*(P87-180)/185,$K14))))))),"N/D") -> 0 | Q100: =IF(COUNT(Q87,$G14:$K14,Supuestos!$D$45)=7,IF(5>=Supuestos!$D$45,0,IF(Q87<0,0,IF(Q87<30,1+($G14-1)*Q87/30,IF(Q87<60,$G14+($H14-$G14)*(Q87-30)/30,IF(Q87<90,$H14+($I14-$H14)*(Q87-60)/30,IF(Q87<180,$I14+($J14-$I14)*(Q87-90)/90,IF(Q87<=365,$J14+($K14-$J14)*(Q87-180)/185,$K14))))))),"N/D") -> 0.975 | R100: =IF(COUNT(R87,$G14:$K14,Supuestos!$D$45)=7,IF(6>=Supuestos!$D$45,0,IF(R87<0,0,IF(R87<30,1+($G14-1)*R87/30,IF(R87<60,$G14+($H14-$G14)*(R87-30)/30,IF(R87<90,$H14+($I14-$H14)*(R87-60)/30,IF(R87<180,$I14+($J14-$I14)*(R87-90)/90,IF(R87<=365,$J14+($K14-$J14)*(R87-180)/185,$K14))))))),"N/D") -> 0.92333333 | S100: =IF(COUNT(S87,$G14:$K14,Supuestos!$D$45)=7,IF(7>=Supuestos!$D$45,0,IF(S87<0,0,IF(S87<30,1+($G14-1)*S87/30,IF(S87<60,$G14+($H14-$G14)*(S87-30)/30,IF(S87<90,$H14+($I14-$H14)*(S87-60)/30,IF(S87<180,$I14+($J14-$I14)*(S87-90)/90,IF(S87<=365,$J14+($K14-$J14)*(S87-180)/185,$K14))))))),"N/D") -> 0.87166667 | T100: =IF(COUNT(T87,$G14:$K14,Supuestos!$D$45)=7,IF(8>=Supuestos!$D$45,0,IF(T87<0,0,IF(T87<30,1+($G14-1)*T87/30,IF(T87<60,$G14+($H14-$G14)*(T87-30)/30,IF(T87<90,$H14+($I14-$H14)*(T87-60)/30,IF(T87<180,$I14+($J14-$I14)*(T87-90)/90,IF(T87<=365,$J14+($K14-$J14)*(T87-180)/185,$K14))))))),"N/D") -> 0.84055556 | U100: =IF(COUNT(U87,$G14:$K14,Supuestos!$D$45)=7,IF(9>=Supuestos!$D$45,0,IF(U87<0,0,IF(U87<30,1+($G14-1)*U87/30,IF(U87<60,$G14+($H14-$G14)*(U87-30)/30,IF(U87<90,$H14+($I14-$H14)*(U87-60)/30,IF(U87<180,$I14+($J14-$I14)*(U87-90)/90,IF(U87<=365,$J14+($K14-$J14)*(U87-180)/185,$K14))))))),"N/D") -> 0.82333333 | V100: =IF(COUNT(V87,$G14:$K14,Supuestos!$D$45)=7,IF(10>=Supuestos!$D$45,0,IF(V87<0,0,IF(V87<30,1+($G14-1)*V87/30,IF(V87<60,$G14+($H14-$G14)*(V87-30)/30,IF(V87<90,$H14+($I14-$H14)*(V87-60)/30,IF(V87<180,$I14+($J14-$I14)*(V87-90)/90,IF(V87<=365,$J14+($K14-$J14)*(V87-180)/185,$K14))))))),"N/D") -> 0.80666667 | W100: =IF(COUNT(W87,$G14:$K14,Supuestos!$D$45)=7,IF(11>=Supuestos!$D$45,0,IF(W87<0,0,IF(W87<30,1+($G14-1)*W87/30,IF(W87<60,$G14+($H14-$G14)*(W87-30)/30,IF(W87<90,$H14+($I14-$H14)*(W87-60)/30,IF(W87<180,$I14+($J14-$I14)*(W87-90)/90,IF(W87<=365,$J14+($K14-$J14)*(W87-180)/185,$K14))))))),"N/D") -> 0.79486486
C101: =C15 -> 46583 | L101: =IF(COUNT(L88,$G15:$K15,Supuestos!$D$45)=7,IF(0>=Supuestos!$D$45,0,IF(L88<0,0,IF(L88<30,1+($G15-1)*L88/30,IF(L88<60,$G15+($H15-$G15)*(L88-30)/30,IF(L88<90,$H15+($I15-$H15)*(L88-60)/30,IF(L88<180,$I15+($J15-$I15)*(L88-90)/90,IF(L88<=365,$J15+($K15-$J15)*(L88-180)/185,$K15))))))),"N/D") -> 0 | M101: =IF(COUNT(M88,$G15:$K15,Supuestos!$D$45)=7,IF(1>=Supuestos!$D$45,0,IF(M88<0,0,IF(M88<30,1+($G15-1)*M88/30,IF(M88<60,$G15+($H15-$G15)*(M88-30)/30,IF(M88<90,$H15+($I15-$H15)*(M88-60)/30,IF(M88<180,$I15+($J15-$I15)*(M88-90)/90,IF(M88<=365,$J15+($K15-$J15)*(M88-180)/185,$K15))))))),"N/D") -> 0 | N101: =IF(COUNT(N88,$G15:$K15,Supuestos!$D$45)=7,IF(2>=Supuestos!$D$45,0,IF(N88<0,0,IF(N88<30,1+($G15-1)*N88/30,IF(N88<60,$G15+($H15-$G15)*(N88-30)/30,IF(N88<90,$H15+($I15-$H15)*(N88-60)/30,IF(N88<180,$I15+($J15-$I15)*(N88-90)/90,IF(N88<=365,$J15+($K15-$J15)*(N88-180)/185,$K15))))))),"N/D") -> 0 | O101: =IF(COUNT(O88,$G15:$K15,Supuestos!$D$45)=7,IF(3>=Supuestos!$D$45,0,IF(O88<0,0,IF(O88<30,1+($G15-1)*O88/30,IF(O88<60,$G15+($H15-$G15)*(O88-30)/30,IF(O88<90,$H15+($I15-$H15)*(O88-60)/30,IF(O88<180,$I15+($J15-$I15)*(O88-90)/90,IF(O88<=365,$J15+($K15-$J15)*(O88-180)/185,$K15))))))),"N/D") -> 0 | P101: =IF(COUNT(P88,$G15:$K15,Supuestos!$D$45)=7,IF(4>=Supuestos!$D$45,0,IF(P88<0,0,IF(P88<30,1+($G15-1)*P88/30,IF(P88<60,$G15+($H15-$G15)*(P88-30)/30,IF(P88<90,$H15+($I15-$H15)*(P88-60)/30,IF(P88<180,$I15+($J15-$I15)*(P88-90)/90,IF(P88<=365,$J15+($K15-$J15)*(P88-180)/185,$K15))))))),"N/D") -> 0 | Q101: =IF(COUNT(Q88,$G15:$K15,Supuestos!$D$45)=7,IF(5>=Supuestos!$D$45,0,IF(Q88<0,0,IF(Q88<30,1+($G15-1)*Q88/30,IF(Q88<60,$G15+($H15-$G15)*(Q88-30)/30,IF(Q88<90,$H15+($I15-$H15)*(Q88-60)/30,IF(Q88<180,$I15+($J15-$I15)*(Q88-90)/90,IF(Q88<=365,$J15+($K15-$J15)*(Q88-180)/185,$K15))))))),"N/D") -> 0 | R101: =IF(COUNT(R88,$G15:$K15,Supuestos!$D$45)=7,IF(6>=Supuestos!$D$45,0,IF(R88<0,0,IF(R88<30,1+($G15-1)*R88/30,IF(R88<60,$G15+($H15-$G15)*(R88-30)/30,IF(R88<90,$H15+($I15-$H15)*(R88-60)/30,IF(R88<180,$I15+($J15-$I15)*(R88-90)/90,IF(R88<=365,$J15+($K15-$J15)*(R88-180)/185,$K15))))))),"N/D") -> 0.97333333 | S101: =IF(COUNT(S88,$G15:$K15,Supuestos!$D$45)=7,IF(7>=Supuestos!$D$45,0,IF(S88<0,0,IF(S88<30,1+($G15-1)*S88/30,IF(S88<60,$G15+($H15-$G15)*(S88-30)/30,IF(S88<90,$H15+($I15-$H15)*(S88-60)/30,IF(S88<180,$I15+($J15-$I15)*(S88-90)/90,IF(S88<=365,$J15+($K15-$J15)*(S88-180)/185,$K15))))))),"N/D") -> 0.92166667 | T101: =IF(COUNT(T88,$G15:$K15,Supuestos!$D$45)=7,IF(8>=Supuestos!$D$45,0,IF(T88<0,0,IF(T88<30,1+($G15-1)*T88/30,IF(T88<60,$G15+($H15-$G15)*(T88-30)/30,IF(T88<90,$H15+($I15-$H15)*(T88-60)/30,IF(T88<180,$I15+($J15-$I15)*(T88-90)/90,IF(T88<=365,$J15+($K15-$J15)*(T88-180)/185,$K15))))))),"N/D") -> 0.87166667 | U101: =IF(COUNT(U88,$G15:$K15,Supuestos!$D$45)=7,IF(9>=Supuestos!$D$45,0,IF(U88<0,0,IF(U88<30,1+($G15-1)*U88/30,IF(U88<60,$G15+($H15-$G15)*(U88-30)/30,IF(U88<90,$H15+($I15-$H15)*(U88-60)/30,IF(U88<180,$I15+($J15-$I15)*(U88-90)/90,IF(U88<=365,$J15+($K15-$J15)*(U88-180)/185,$K15))))))),"N/D") -> 0.84 | V101: =IF(COUNT(V88,$G15:$K15,Supuestos!$D$45)=7,IF(10>=Supuestos!$D$45,0,IF(V88<0,0,IF(V88<30,1+($G15-1)*V88/30,IF(V88<60,$G15+($H15-$G15)*(V88-30)/30,IF(V88<90,$H15+($I15-$H15)*(V88-60)/30,IF(V88<180,$I15+($J15-$I15)*(V88-90)/90,IF(V88<=365,$J15+($K15-$J15)*(V88-180)/185,$K15))))))),"N/D") -> 0.82333333 | W101: =IF(COUNT(W88,$G15:$K15,Supuestos!$D$45)=7,IF(11>=Supuestos!$D$45,0,IF(W88<0,0,IF(W88<30,1+($G15-1)*W88/30,IF(W88<60,$G15+($H15-$G15)*(W88-30)/30,IF(W88<90,$H15+($I15-$H15)*(W88-60)/30,IF(W88<180,$I15+($J15-$I15)*(W88-90)/90,IF(W88<=365,$J15+($K15-$J15)*(W88-180)/185,$K15))))))),"N/D") -> 0.80611111
C102: =C16 -> 46614 | L102: =IF(COUNT(L89,$G16:$K16,Supuestos!$D$45)=7,IF(0>=Supuestos!$D$45,0,IF(L89<0,0,IF(L89<30,1+($G16-1)*L89/30,IF(L89<60,$G16+($H16-$G16)*(L89-30)/30,IF(L89<90,$H16+($I16-$H16)*(L89-60)/30,IF(L89<180,$I16+($J16-$I16)*(L89-90)/90,IF(L89<=365,$J16+($K16-$J16)*(L89-180)/185,$K16))))))),"N/D") -> 0 | M102: =IF(COUNT(M89,$G16:$K16,Supuestos!$D$45)=7,IF(1>=Supuestos!$D$45,0,IF(M89<0,0,IF(M89<30,1+($G16-1)*M89/30,IF(M89<60,$G16+($H16-$G16)*(M89-30)/30,IF(M89<90,$H16+($I16-$H16)*(M89-60)/30,IF(M89<180,$I16+($J16-$I16)*(M89-90)/90,IF(M89<=365,$J16+($K16-$J16)*(M89-180)/185,$K16))))))),"N/D") -> 0 | N102: =IF(COUNT(N89,$G16:$K16,Supuestos!$D$45)=7,IF(2>=Supuestos!$D$45,0,IF(N89<0,0,IF(N89<30,1+($G16-1)*N89/30,IF(N89<60,$G16+($H16-$G16)*(N89-30)/30,IF(N89<90,$H16+($I16-$H16)*(N89-60)/30,IF(N89<180,$I16+($J16-$I16)*(N89-90)/90,IF(N89<=365,$J16+($K16-$J16)*(N89-180)/185,$K16))))))),"N/D") -> 0 | O102: =IF(COUNT(O89,$G16:$K16,Supuestos!$D$45)=7,IF(3>=Supuestos!$D$45,0,IF(O89<0,0,IF(O89<30,1+($G16-1)*O89/30,IF(O89<60,$G16+($H16-$G16)*(O89-30)/30,IF(O89<90,$H16+($I16-$H16)*(O89-60)/30,IF(O89<180,$I16+($J16-$I16)*(O89-90)/90,IF(O89<=365,$J16+($K16-$J16)*(O89-180)/185,$K16))))))),"N/D") -> 0 | P102: =IF(COUNT(P89,$G16:$K16,Supuestos!$D$45)=7,IF(4>=Supuestos!$D$45,0,IF(P89<0,0,IF(P89<30,1+($G16-1)*P89/30,IF(P89<60,$G16+($H16-$G16)*(P89-30)/30,IF(P89<90,$H16+($I16-$H16)*(P89-60)/30,IF(P89<180,$I16+($J16-$I16)*(P89-90)/90,IF(P89<=365,$J16+($K16-$J16)*(P89-180)/185,$K16))))))),"N/D") -> 0 | Q102: =IF(COUNT(Q89,$G16:$K16,Supuestos!$D$45)=7,IF(5>=Supuestos!$D$45,0,IF(Q89<0,0,IF(Q89<30,1+($G16-1)*Q89/30,IF(Q89<60,$G16+($H16-$G16)*(Q89-30)/30,IF(Q89<90,$H16+($I16-$H16)*(Q89-60)/30,IF(Q89<180,$I16+($J16-$I16)*(Q89-90)/90,IF(Q89<=365,$J16+($K16-$J16)*(Q89-180)/185,$K16))))))),"N/D") -> 0 | R102: =IF(COUNT(R89,$G16:$K16,Supuestos!$D$45)=7,IF(6>=Supuestos!$D$45,0,IF(R89<0,0,IF(R89<30,1+($G16-1)*R89/30,IF(R89<60,$G16+($H16-$G16)*(R89-30)/30,IF(R89<90,$H16+($I16-$H16)*(R89-60)/30,IF(R89<180,$I16+($J16-$I16)*(R89-90)/90,IF(R89<=365,$J16+($K16-$J16)*(R89-180)/185,$K16))))))),"N/D") -> 0 | S102: =IF(COUNT(S89,$G16:$K16,Supuestos!$D$45)=7,IF(7>=Supuestos!$D$45,0,IF(S89<0,0,IF(S89<30,1+($G16-1)*S89/30,IF(S89<60,$G16+($H16-$G16)*(S89-30)/30,IF(S89<90,$H16+($I16-$H16)*(S89-60)/30,IF(S89<180,$I16+($J16-$I16)*(S89-90)/90,IF(S89<=365,$J16+($K16-$J16)*(S89-180)/185,$K16))))))),"N/D") -> 0.97333333 | T102: =IF(COUNT(T89,$G16:$K16,Supuestos!$D$45)=7,IF(8>=Supuestos!$D$45,0,IF(T89<0,0,IF(T89<30,1+($G16-1)*T89/30,IF(T89<60,$G16+($H16-$G16)*(T89-30)/30,IF(T89<90,$H16+($I16-$H16)*(T89-60)/30,IF(T89<180,$I16+($J16-$I16)*(T89-90)/90,IF(T89<=365,$J16+($K16-$J16)*(T89-180)/185,$K16))))))),"N/D") -> 0.92333333 | U102: =IF(COUNT(U89,$G16:$K16,Supuestos!$D$45)=7,IF(9>=Supuestos!$D$45,0,IF(U89<0,0,IF(U89<30,1+($G16-1)*U89/30,IF(U89<60,$G16+($H16-$G16)*(U89-30)/30,IF(U89<90,$H16+($I16-$H16)*(U89-60)/30,IF(U89<180,$I16+($J16-$I16)*(U89-90)/90,IF(U89<=365,$J16+($K16-$J16)*(U89-180)/185,$K16))))))),"N/D") -> 0.87166667 | V102: =IF(COUNT(V89,$G16:$K16,Supuestos!$D$45)=7,IF(10>=Supuestos!$D$45,0,IF(V89<0,0,IF(V89<30,1+($G16-1)*V89/30,IF(V89<60,$G16+($H16-$G16)*(V89-30)/30,IF(V89<90,$H16+($I16-$H16)*(V89-60)/30,IF(V89<180,$I16+($J16-$I16)*(V89-90)/90,IF(V89<=365,$J16+($K16-$J16)*(V89-180)/185,$K16))))))),"N/D") -> 0.84055556 | W102: =IF(COUNT(W89,$G16:$K16,Supuestos!$D$45)=7,IF(11>=Supuestos!$D$45,0,IF(W89<0,0,IF(W89<30,1+($G16-1)*W89/30,IF(W89<60,$G16+($H16-$G16)*(W89-30)/30,IF(W89<90,$H16+($I16-$H16)*(W89-60)/30,IF(W89<180,$I16+($J16-$I16)*(W89-90)/90,IF(W89<=365,$J16+($K16-$J16)*(W89-180)/185,$K16))))))),"N/D") -> 0.82333333
C103: =C17 -> 46645 | L103: =IF(COUNT(L90,$G17:$K17,Supuestos!$D$45)=7,IF(0>=Supuestos!$D$45,0,IF(L90<0,0,IF(L90<30,1+($G17-1)*L90/30,IF(L90<60,$G17+($H17-$G17)*(L90-30)/30,IF(L90<90,$H17+($I17-$H17)*(L90-60)/30,IF(L90<180,$I17+($J17-$I17)*(L90-90)/90,IF(L90<=365,$J17+($K17-$J17)*(L90-180)/185,$K17))))))),"N/D") -> 0 | M103: =IF(COUNT(M90,$G17:$K17,Supuestos!$D$45)=7,IF(1>=Supuestos!$D$45,0,IF(M90<0,0,IF(M90<30,1+($G17-1)*M90/30,IF(M90<60,$G17+($H17-$G17)*(M90-30)/30,IF(M90<90,$H17+($I17-$H17)*(M90-60)/30,IF(M90<180,$I17+($J17-$I17)*(M90-90)/90,IF(M90<=365,$J17+($K17-$J17)*(M90-180)/185,$K17))))))),"N/D") -> 0 | N103: =IF(COUNT(N90,$G17:$K17,Supuestos!$D$45)=7,IF(2>=Supuestos!$D$45,0,IF(N90<0,0,IF(N90<30,1+($G17-1)*N90/30,IF(N90<60,$G17+($H17-$G17)*(N90-30)/30,IF(N90<90,$H17+($I17-$H17)*(N90-60)/30,IF(N90<180,$I17+($J17-$I17)*(N90-90)/90,IF(N90<=365,$J17+($K17-$J17)*(N90-180)/185,$K17))))))),"N/D") -> 0 | O103: =IF(COUNT(O90,$G17:$K17,Supuestos!$D$45)=7,IF(3>=Supuestos!$D$45,0,IF(O90<0,0,IF(O90<30,1+($G17-1)*O90/30,IF(O90<60,$G17+($H17-$G17)*(O90-30)/30,IF(O90<90,$H17+($I17-$H17)*(O90-60)/30,IF(O90<180,$I17+($J17-$I17)*(O90-90)/90,IF(O90<=365,$J17+($K17-$J17)*(O90-180)/185,$K17))))))),"N/D") -> 0 | P103: =IF(COUNT(P90,$G17:$K17,Supuestos!$D$45)=7,IF(4>=Supuestos!$D$45,0,IF(P90<0,0,IF(P90<30,1+($G17-1)*P90/30,IF(P90<60,$G17+($H17-$G17)*(P90-30)/30,IF(P90<90,$H17+($I17-$H17)*(P90-60)/30,IF(P90<180,$I17+($J17-$I17)*(P90-90)/90,IF(P90<=365,$J17+($K17-$J17)*(P90-180)/185,$K17))))))),"N/D") -> 0 | Q103: =IF(COUNT(Q90,$G17:$K17,Supuestos!$D$45)=7,IF(5>=Supuestos!$D$45,0,IF(Q90<0,0,IF(Q90<30,1+($G17-1)*Q90/30,IF(Q90<60,$G17+($H17-$G17)*(Q90-30)/30,IF(Q90<90,$H17+($I17-$H17)*(Q90-60)/30,IF(Q90<180,$I17+($J17-$I17)*(Q90-90)/90,IF(Q90<=365,$J17+($K17-$J17)*(Q90-180)/185,$K17))))))),"N/D") -> 0 | R103: =IF(COUNT(R90,$G17:$K17,Supuestos!$D$45)=7,IF(6>=Supuestos!$D$45,0,IF(R90<0,0,IF(R90<30,1+($G17-1)*R90/30,IF(R90<60,$G17+($H17-$G17)*(R90-30)/30,IF(R90<90,$H17+($I17-$H17)*(R90-60)/30,IF(R90<180,$I17+($J17-$I17)*(R90-90)/90,IF(R90<=365,$J17+($K17-$J17)*(R90-180)/185,$K17))))))),"N/D") -> 0 | S103: =IF(COUNT(S90,$G17:$K17,Supuestos!$D$45)=7,IF(7>=Supuestos!$D$45,0,IF(S90<0,0,IF(S90<30,1+($G17-1)*S90/30,IF(S90<60,$G17+($H17-$G17)*(S90-30)/30,IF(S90<90,$H17+($I17-$H17)*(S90-60)/30,IF(S90<180,$I17+($J17-$I17)*(S90-90)/90,IF(S90<=365,$J17+($K17-$J17)*(S90-180)/185,$K17))))))),"N/D") -> 0 | T103: =IF(COUNT(T90,$G17:$K17,Supuestos!$D$45)=7,IF(8>=Supuestos!$D$45,0,IF(T90<0,0,IF(T90<30,1+($G17-1)*T90/30,IF(T90<60,$G17+($H17-$G17)*(T90-30)/30,IF(T90<90,$H17+($I17-$H17)*(T90-60)/30,IF(T90<180,$I17+($J17-$I17)*(T90-90)/90,IF(T90<=365,$J17+($K17-$J17)*(T90-180)/185,$K17))))))),"N/D") -> 0.975 | U103: =IF(COUNT(U90,$G17:$K17,Supuestos!$D$45)=7,IF(9>=Supuestos!$D$45,0,IF(U90<0,0,IF(U90<30,1+($G17-1)*U90/30,IF(U90<60,$G17+($H17-$G17)*(U90-30)/30,IF(U90<90,$H17+($I17-$H17)*(U90-60)/30,IF(U90<180,$I17+($J17-$I17)*(U90-90)/90,IF(U90<=365,$J17+($K17-$J17)*(U90-180)/185,$K17))))))),"N/D") -> 0.92333333 | V103: =IF(COUNT(V90,$G17:$K17,Supuestos!$D$45)=7,IF(10>=Supuestos!$D$45,0,IF(V90<0,0,IF(V90<30,1+($G17-1)*V90/30,IF(V90<60,$G17+($H17-$G17)*(V90-30)/30,IF(V90<90,$H17+($I17-$H17)*(V90-60)/30,IF(V90<180,$I17+($J17-$I17)*(V90-90)/90,IF(V90<=365,$J17+($K17-$J17)*(V90-180)/185,$K17))))))),"N/D") -> 0.87333333 | W103: =IF(COUNT(W90,$G17:$K17,Supuestos!$D$45)=7,IF(11>=Supuestos!$D$45,0,IF(W90<0,0,IF(W90<30,1+($G17-1)*W90/30,IF(W90<60,$G17+($H17-$G17)*(W90-30)/30,IF(W90<90,$H17+($I17-$H17)*(W90-60)/30,IF(W90<180,$I17+($J17-$I17)*(W90-90)/90,IF(W90<=365,$J17+($K17-$J17)*(W90-180)/185,$K17))))))),"N/D") -> 0.84055556
C104: =C18 -> 46675 | L104: =IF(COUNT(L91,$G18:$K18,Supuestos!$D$45)=7,IF(0>=Supuestos!$D$45,0,IF(L91<0,0,IF(L91<30,1+($G18-1)*L91/30,IF(L91<60,$G18+($H18-$G18)*(L91-30)/30,IF(L91<90,$H18+($I18-$H18)*(L91-60)/30,IF(L91<180,$I18+($J18-$I18)*(L91-90)/90,IF(L91<=365,$J18+($K18-$J18)*(L91-180)/185,$K18))))))),"N/D") -> 0 | M104: =IF(COUNT(M91,$G18:$K18,Supuestos!$D$45)=7,IF(1>=Supuestos!$D$45,0,IF(M91<0,0,IF(M91<30,1+($G18-1)*M91/30,IF(M91<60,$G18+($H18-$G18)*(M91-30)/30,IF(M91<90,$H18+($I18-$H18)*(M91-60)/30,IF(M91<180,$I18+($J18-$I18)*(M91-90)/90,IF(M91<=365,$J18+($K18-$J18)*(M91-180)/185,$K18))))))),"N/D") -> 0 | N104: =IF(COUNT(N91,$G18:$K18,Supuestos!$D$45)=7,IF(2>=Supuestos!$D$45,0,IF(N91<0,0,IF(N91<30,1+($G18-1)*N91/30,IF(N91<60,$G18+($H18-$G18)*(N91-30)/30,IF(N91<90,$H18+($I18-$H18)*(N91-60)/30,IF(N91<180,$I18+($J18-$I18)*(N91-90)/90,IF(N91<=365,$J18+($K18-$J18)*(N91-180)/185,$K18))))))),"N/D") -> 0 | O104: =IF(COUNT(O91,$G18:$K18,Supuestos!$D$45)=7,IF(3>=Supuestos!$D$45,0,IF(O91<0,0,IF(O91<30,1+($G18-1)*O91/30,IF(O91<60,$G18+($H18-$G18)*(O91-30)/30,IF(O91<90,$H18+($I18-$H18)*(O91-60)/30,IF(O91<180,$I18+($J18-$I18)*(O91-90)/90,IF(O91<=365,$J18+($K18-$J18)*(O91-180)/185,$K18))))))),"N/D") -> 0 | P104: =IF(COUNT(P91,$G18:$K18,Supuestos!$D$45)=7,IF(4>=Supuestos!$D$45,0,IF(P91<0,0,IF(P91<30,1+($G18-1)*P91/30,IF(P91<60,$G18+($H18-$G18)*(P91-30)/30,IF(P91<90,$H18+($I18-$H18)*(P91-60)/30,IF(P91<180,$I18+($J18-$I18)*(P91-90)/90,IF(P91<=365,$J18+($K18-$J18)*(P91-180)/185,$K18))))))),"N/D") -> 0 | Q104: =IF(COUNT(Q91,$G18:$K18,Supuestos!$D$45)=7,IF(5>=Supuestos!$D$45,0,IF(Q91<0,0,IF(Q91<30,1+($G18-1)*Q91/30,IF(Q91<60,$G18+($H18-$G18)*(Q91-30)/30,IF(Q91<90,$H18+($I18-$H18)*(Q91-60)/30,IF(Q91<180,$I18+($J18-$I18)*(Q91-90)/90,IF(Q91<=365,$J18+($K18-$J18)*(Q91-180)/185,$K18))))))),"N/D") -> 0 | R104: =IF(COUNT(R91,$G18:$K18,Supuestos!$D$45)=7,IF(6>=Supuestos!$D$45,0,IF(R91<0,0,IF(R91<30,1+($G18-1)*R91/30,IF(R91<60,$G18+($H18-$G18)*(R91-30)/30,IF(R91<90,$H18+($I18-$H18)*(R91-60)/30,IF(R91<180,$I18+($J18-$I18)*(R91-90)/90,IF(R91<=365,$J18+($K18-$J18)*(R91-180)/185,$K18))))))),"N/D") -> 0 | S104: =IF(COUNT(S91,$G18:$K18,Supuestos!$D$45)=7,IF(7>=Supuestos!$D$45,0,IF(S91<0,0,IF(S91<30,1+($G18-1)*S91/30,IF(S91<60,$G18+($H18-$G18)*(S91-30)/30,IF(S91<90,$H18+($I18-$H18)*(S91-60)/30,IF(S91<180,$I18+($J18-$I18)*(S91-90)/90,IF(S91<=365,$J18+($K18-$J18)*(S91-180)/185,$K18))))))),"N/D") -> 0 | T104: =IF(COUNT(T91,$G18:$K18,Supuestos!$D$45)=7,IF(8>=Supuestos!$D$45,0,IF(T91<0,0,IF(T91<30,1+($G18-1)*T91/30,IF(T91<60,$G18+($H18-$G18)*(T91-30)/30,IF(T91<90,$H18+($I18-$H18)*(T91-60)/30,IF(T91<180,$I18+($J18-$I18)*(T91-90)/90,IF(T91<=365,$J18+($K18-$J18)*(T91-180)/185,$K18))))))),"N/D") -> 0 | U104: =IF(COUNT(U91,$G18:$K18,Supuestos!$D$45)=7,IF(9>=Supuestos!$D$45,0,IF(U91<0,0,IF(U91<30,1+($G18-1)*U91/30,IF(U91<60,$G18+($H18-$G18)*(U91-30)/30,IF(U91<90,$H18+($I18-$H18)*(U91-60)/30,IF(U91<180,$I18+($J18-$I18)*(U91-90)/90,IF(U91<=365,$J18+($K18-$J18)*(U91-180)/185,$K18))))))),"N/D") -> 0.97333333 | V104: =IF(COUNT(V91,$G18:$K18,Supuestos!$D$45)=7,IF(10>=Supuestos!$D$45,0,IF(V91<0,0,IF(V91<30,1+($G18-1)*V91/30,IF(V91<60,$G18+($H18-$G18)*(V91-30)/30,IF(V91<90,$H18+($I18-$H18)*(V91-60)/30,IF(V91<180,$I18+($J18-$I18)*(V91-90)/90,IF(V91<=365,$J18+($K18-$J18)*(V91-180)/185,$K18))))))),"N/D") -> 0.92333333 | W104: =IF(COUNT(W91,$G18:$K18,Supuestos!$D$45)=7,IF(11>=Supuestos!$D$45,0,IF(W91<0,0,IF(W91<30,1+($G18-1)*W91/30,IF(W91<60,$G18+($H18-$G18)*(W91-30)/30,IF(W91<90,$H18+($I18-$H18)*(W91-60)/30,IF(W91<180,$I18+($J18-$I18)*(W91-90)/90,IF(W91<=365,$J18+($K18-$J18)*(W91-180)/185,$K18))))))),"N/D") -> 0.87166667
C105: =C19 -> 46706 | L105: =IF(COUNT(L92,$G19:$K19,Supuestos!$D$45)=7,IF(0>=Supuestos!$D$45,0,IF(L92<0,0,IF(L92<30,1+($G19-1)*L92/30,IF(L92<60,$G19+($H19-$G19)*(L92-30)/30,IF(L92<90,$H19+($I19-$H19)*(L92-60)/30,IF(L92<180,$I19+($J19-$I19)*(L92-90)/90,IF(L92<=365,$J19+($K19-$J19)*(L92-180)/185,$K19))))))),"N/D") -> 0 | M105: =IF(COUNT(M92,$G19:$K19,Supuestos!$D$45)=7,IF(1>=Supuestos!$D$45,0,IF(M92<0,0,IF(M92<30,1+($G19-1)*M92/30,IF(M92<60,$G19+($H19-$G19)*(M92-30)/30,IF(M92<90,$H19+($I19-$H19)*(M92-60)/30,IF(M92<180,$I19+($J19-$I19)*(M92-90)/90,IF(M92<=365,$J19+($K19-$J19)*(M92-180)/185,$K19))))))),"N/D") -> 0 | N105: =IF(COUNT(N92,$G19:$K19,Supuestos!$D$45)=7,IF(2>=Supuestos!$D$45,0,IF(N92<0,0,IF(N92<30,1+($G19-1)*N92/30,IF(N92<60,$G19+($H19-$G19)*(N92-30)/30,IF(N92<90,$H19+($I19-$H19)*(N92-60)/30,IF(N92<180,$I19+($J19-$I19)*(N92-90)/90,IF(N92<=365,$J19+($K19-$J19)*(N92-180)/185,$K19))))))),"N/D") -> 0 | O105: =IF(COUNT(O92,$G19:$K19,Supuestos!$D$45)=7,IF(3>=Supuestos!$D$45,0,IF(O92<0,0,IF(O92<30,1+($G19-1)*O92/30,IF(O92<60,$G19+($H19-$G19)*(O92-30)/30,IF(O92<90,$H19+($I19-$H19)*(O92-60)/30,IF(O92<180,$I19+($J19-$I19)*(O92-90)/90,IF(O92<=365,$J19+($K19-$J19)*(O92-180)/185,$K19))))))),"N/D") -> 0 | P105: =IF(COUNT(P92,$G19:$K19,Supuestos!$D$45)=7,IF(4>=Supuestos!$D$45,0,IF(P92<0,0,IF(P92<30,1+($G19-1)*P92/30,IF(P92<60,$G19+($H19-$G19)*(P92-30)/30,IF(P92<90,$H19+($I19-$H19)*(P92-60)/30,IF(P92<180,$I19+($J19-$I19)*(P92-90)/90,IF(P92<=365,$J19+($K19-$J19)*(P92-180)/185,$K19))))))),"N/D") -> 0 | Q105: =IF(COUNT(Q92,$G19:$K19,Supuestos!$D$45)=7,IF(5>=Supuestos!$D$45,0,IF(Q92<0,0,IF(Q92<30,1+($G19-1)*Q92/30,IF(Q92<60,$G19+($H19-$G19)*(Q92-30)/30,IF(Q92<90,$H19+($I19-$H19)*(Q92-60)/30,IF(Q92<180,$I19+($J19-$I19)*(Q92-90)/90,IF(Q92<=365,$J19+($K19-$J19)*(Q92-180)/185,$K19))))))),"N/D") -> 0 | R105: =IF(COUNT(R92,$G19:$K19,Supuestos!$D$45)=7,IF(6>=Supuestos!$D$45,0,IF(R92<0,0,IF(R92<30,1+($G19-1)*R92/30,IF(R92<60,$G19+($H19-$G19)*(R92-30)/30,IF(R92<90,$H19+($I19-$H19)*(R92-60)/30,IF(R92<180,$I19+($J19-$I19)*(R92-90)/90,IF(R92<=365,$J19+($K19-$J19)*(R92-180)/185,$K19))))))),"N/D") -> 0 | S105: =IF(COUNT(S92,$G19:$K19,Supuestos!$D$45)=7,IF(7>=Supuestos!$D$45,0,IF(S92<0,0,IF(S92<30,1+($G19-1)*S92/30,IF(S92<60,$G19+($H19-$G19)*(S92-30)/30,IF(S92<90,$H19+($I19-$H19)*(S92-60)/30,IF(S92<180,$I19+($J19-$I19)*(S92-90)/90,IF(S92<=365,$J19+($K19-$J19)*(S92-180)/185,$K19))))))),"N/D") -> 0 | T105: =IF(COUNT(T92,$G19:$K19,Supuestos!$D$45)=7,IF(8>=Supuestos!$D$45,0,IF(T92<0,0,IF(T92<30,1+($G19-1)*T92/30,IF(T92<60,$G19+($H19-$G19)*(T92-30)/30,IF(T92<90,$H19+($I19-$H19)*(T92-60)/30,IF(T92<180,$I19+($J19-$I19)*(T92-90)/90,IF(T92<=365,$J19+($K19-$J19)*(T92-180)/185,$K19))))))),"N/D") -> 0 | U105: =IF(COUNT(U92,$G19:$K19,Supuestos!$D$45)=7,IF(9>=Supuestos!$D$45,0,IF(U92<0,0,IF(U92<30,1+($G19-1)*U92/30,IF(U92<60,$G19+($H19-$G19)*(U92-30)/30,IF(U92<90,$H19+($I19-$H19)*(U92-60)/30,IF(U92<180,$I19+($J19-$I19)*(U92-90)/90,IF(U92<=365,$J19+($K19-$J19)*(U92-180)/185,$K19))))))),"N/D") -> 0 | V105: =IF(COUNT(V92,$G19:$K19,Supuestos!$D$45)=7,IF(10>=Supuestos!$D$45,0,IF(V92<0,0,IF(V92<30,1+($G19-1)*V92/30,IF(V92<60,$G19+($H19-$G19)*(V92-30)/30,IF(V92<90,$H19+($I19-$H19)*(V92-60)/30,IF(V92<180,$I19+($J19-$I19)*(V92-90)/90,IF(V92<=365,$J19+($K19-$J19)*(V92-180)/185,$K19))))))),"N/D") -> 0.975 | W105: =IF(COUNT(W92,$G19:$K19,Supuestos!$D$45)=7,IF(11>=Supuestos!$D$45,0,IF(W92<0,0,IF(W92<30,1+($G19-1)*W92/30,IF(W92<60,$G19+($H19-$G19)*(W92-30)/30,IF(W92<90,$H19+($I19-$H19)*(W92-60)/30,IF(W92<180,$I19+($J19-$I19)*(W92-90)/90,IF(W92<=365,$J19+($K19-$J19)*(W92-180)/185,$K19))))))),"N/D") -> 0.92333333
C106: =C20 -> 46736 | L106: =IF(COUNT(L93,$G20:$K20,Supuestos!$D$45)=7,IF(0>=Supuestos!$D$45,0,IF(L93<0,0,IF(L93<30,1+($G20-1)*L93/30,IF(L93<60,$G20+($H20-$G20)*(L93-30)/30,IF(L93<90,$H20+($I20-$H20)*(L93-60)/30,IF(L93<180,$I20+($J20-$I20)*(L93-90)/90,IF(L93<=365,$J20+($K20-$J20)*(L93-180)/185,$K20))))))),"N/D") -> 0 | M106: =IF(COUNT(M93,$G20:$K20,Supuestos!$D$45)=7,IF(1>=Supuestos!$D$45,0,IF(M93<0,0,IF(M93<30,1+($G20-1)*M93/30,IF(M93<60,$G20+($H20-$G20)*(M93-30)/30,IF(M93<90,$H20+($I20-$H20)*(M93-60)/30,IF(M93<180,$I20+($J20-$I20)*(M93-90)/90,IF(M93<=365,$J20+($K20-$J20)*(M93-180)/185,$K20))))))),"N/D") -> 0 | N106: =IF(COUNT(N93,$G20:$K20,Supuestos!$D$45)=7,IF(2>=Supuestos!$D$45,0,IF(N93<0,0,IF(N93<30,1+($G20-1)*N93/30,IF(N93<60,$G20+($H20-$G20)*(N93-30)/30,IF(N93<90,$H20+($I20-$H20)*(N93-60)/30,IF(N93<180,$I20+($J20-$I20)*(N93-90)/90,IF(N93<=365,$J20+($K20-$J20)*(N93-180)/185,$K20))))))),"N/D") -> 0 | O106: =IF(COUNT(O93,$G20:$K20,Supuestos!$D$45)=7,IF(3>=Supuestos!$D$45,0,IF(O93<0,0,IF(O93<30,1+($G20-1)*O93/30,IF(O93<60,$G20+($H20-$G20)*(O93-30)/30,IF(O93<90,$H20+($I20-$H20)*(O93-60)/30,IF(O93<180,$I20+($J20-$I20)*(O93-90)/90,IF(O93<=365,$J20+($K20-$J20)*(O93-180)/185,$K20))))))),"N/D") -> 0 | P106: =IF(COUNT(P93,$G20:$K20,Supuestos!$D$45)=7,IF(4>=Supuestos!$D$45,0,IF(P93<0,0,IF(P93<30,1+($G20-1)*P93/30,IF(P93<60,$G20+($H20-$G20)*(P93-30)/30,IF(P93<90,$H20+($I20-$H20)*(P93-60)/30,IF(P93<180,$I20+($J20-$I20)*(P93-90)/90,IF(P93<=365,$J20+($K20-$J20)*(P93-180)/185,$K20))))))),"N/D") -> 0 | Q106: =IF(COUNT(Q93,$G20:$K20,Supuestos!$D$45)=7,IF(5>=Supuestos!$D$45,0,IF(Q93<0,0,IF(Q93<30,1+($G20-1)*Q93/30,IF(Q93<60,$G20+($H20-$G20)*(Q93-30)/30,IF(Q93<90,$H20+($I20-$H20)*(Q93-60)/30,IF(Q93<180,$I20+($J20-$I20)*(Q93-90)/90,IF(Q93<=365,$J20+($K20-$J20)*(Q93-180)/185,$K20))))))),"N/D") -> 0 | R106: =IF(COUNT(R93,$G20:$K20,Supuestos!$D$45)=7,IF(6>=Supuestos!$D$45,0,IF(R93<0,0,IF(R93<30,1+($G20-1)*R93/30,IF(R93<60,$G20+($H20-$G20)*(R93-30)/30,IF(R93<90,$H20+($I20-$H20)*(R93-60)/30,IF(R93<180,$I20+($J20-$I20)*(R93-90)/90,IF(R93<=365,$J20+($K20-$J20)*(R93-180)/185,$K20))))))),"N/D") -> 0 | S106: =IF(COUNT(S93,$G20:$K20,Supuestos!$D$45)=7,IF(7>=Supuestos!$D$45,0,IF(S93<0,0,IF(S93<30,1+($G20-1)*S93/30,IF(S93<60,$G20+($H20-$G20)*(S93-30)/30,IF(S93<90,$H20+($I20-$H20)*(S93-60)/30,IF(S93<180,$I20+($J20-$I20)*(S93-90)/90,IF(S93<=365,$J20+($K20-$J20)*(S93-180)/185,$K20))))))),"N/D") -> 0 | T106: =IF(COUNT(T93,$G20:$K20,Supuestos!$D$45)=7,IF(8>=Supuestos!$D$45,0,IF(T93<0,0,IF(T93<30,1+($G20-1)*T93/30,IF(T93<60,$G20+($H20-$G20)*(T93-30)/30,IF(T93<90,$H20+($I20-$H20)*(T93-60)/30,IF(T93<180,$I20+($J20-$I20)*(T93-90)/90,IF(T93<=365,$J20+($K20-$J20)*(T93-180)/185,$K20))))))),"N/D") -> 0 | U106: =IF(COUNT(U93,$G20:$K20,Supuestos!$D$45)=7,IF(9>=Supuestos!$D$45,0,IF(U93<0,0,IF(U93<30,1+($G20-1)*U93/30,IF(U93<60,$G20+($H20-$G20)*(U93-30)/30,IF(U93<90,$H20+($I20-$H20)*(U93-60)/30,IF(U93<180,$I20+($J20-$I20)*(U93-90)/90,IF(U93<=365,$J20+($K20-$J20)*(U93-180)/185,$K20))))))),"N/D") -> 0 | V106: =IF(COUNT(V93,$G20:$K20,Supuestos!$D$45)=7,IF(10>=Supuestos!$D$45,0,IF(V93<0,0,IF(V93<30,1+($G20-1)*V93/30,IF(V93<60,$G20+($H20-$G20)*(V93-30)/30,IF(V93<90,$H20+($I20-$H20)*(V93-60)/30,IF(V93<180,$I20+($J20-$I20)*(V93-90)/90,IF(V93<=365,$J20+($K20-$J20)*(V93-180)/185,$K20))))))),"N/D") -> 0 | W106: =IF(COUNT(W93,$G20:$K20,Supuestos!$D$45)=7,IF(11>=Supuestos!$D$45,0,IF(W93<0,0,IF(W93<30,1+($G20-1)*W93/30,IF(W93<60,$G20+($H20-$G20)*(W93-30)/30,IF(W93<90,$H20+($I20-$H20)*(W93-60)/30,IF(W93<180,$I20+($J20-$I20)*(W93-90)/90,IF(W93<=365,$J20+($K20-$J20)*(W93-180)/185,$K20))))))),"N/D") -> 0.97333333

Sheet Economia
C2: Techo bancario y piso operativo: decisión condicionada
C6: Condición económica | D6: Resultado | E6: Unidad
C8: Valor banco por UN método/horizonte | D8: =IF(Supuestos!D16="Sí",IF(Supuestos!D52="Saldo medio externo",IF(COUNT(Supuestos!D17,Decision!D11,Supuestos!D45)=3,Decision!D11*Supuestos!D17*Supuestos!D45/12,"N/D"),IF(COUNT(Supuestos!D54,Decision!D20)=2,Supuestos!D54*Decision!D20,"N/D")),"N/D") -> N/D
C9: Techo inversión para ROI exigido | D9: =IF(COUNT(D8,Supuestos!D18)=2,IF(Supuestos!D18>=0,D8/(1+Supuestos!D18),"N/D"),"N/D") -> N/D
C11: Costo humano enfocado fully loaded | D11: =IF(AND(Supuestos!D20="Sí",COUNT(Supuestos!D21,Supuestos!D23)=2,Supuestos!D21>=0),Supuestos!D21*Supuestos!D23,"N/D") -> N/D
C12: Otros costos explícitos, sin doble overhead | D12: =IF(COUNT(Supuestos!D25)=1,IF(Supuestos!D25>=0,Supuestos!D25,"N/D"),"N/D") -> N/D
C13: Costo total interno condicionado | D13: =IF(COUNT(D11:D12)=2,SUM(D11:D12),"N/D") -> N/D
C15: Piso comercial con margen autorizado | D15: =IF(COUNT(D13,Supuestos!D22)=2,IF(AND(Supuestos!D20="Sí",Supuestos!D22>=0,Supuestos!D22<1),D13/(1-Supuestos!D22),"N/D"),"N/D") -> N/D
C17: Horas compatibles con techo bancario | D17: =IF(COUNT(D9,D12,Supuestos!D21,Supuestos!D22)=4,IF(AND(Supuestos!D20="Sí",Supuestos!D21>0,Supuestos!D22>=0,Supuestos!D22<1),MAX(0,(D9*(1-Supuestos!D22)-D12)/Supuestos!D21),"N/D"),"N/D") -> N/D
C18: Brecha techo menos piso | D18: =IF(COUNT(D9,D15)=2,D9-D15,"N/D") -> N/D
C20: El piso cubre costos internos con margen autorizado; el techo responde al valor del banco. Ninguno es fee aprobado ni ahorro realizado.
C23: Tasa neta anual hipotética | D23: Valor si banda se alcanza | E23: Techo para retorno exigido | F23: Naturaleza
C24: 0.01 | D24: =IF(COUNT(Decision!D11,Supuestos!D45)=2,Decision!D11*C24*Supuestos!D45/12,"N/D") -> 749.16492 | E24: =IF(COUNT(D24,Supuestos!D18)=2,IF(Supuestos!D18>=0,D24/(1+Supuestos!D18),"N/D"),"N/D") -> 749.16492 | F24: Experimento; no benchmark
C25: 0.02 | D25: =IF(COUNT(Decision!D11,Supuestos!D45)=2,Decision!D11*C25*Supuestos!D45/12,"N/D") -> 1498.3298 | E25: =IF(COUNT(D25,Supuestos!D18)=2,IF(Supuestos!D18>=0,D25/(1+Supuestos!D18),"N/D"),"N/D") -> 1498.3298 | F25: Experimento; no benchmark
C26: 0.04 | D26: =IF(COUNT(Decision!D11,Supuestos!D45)=2,Decision!D11*C26*Supuestos!D45/12,"N/D") -> 2996.6597 | E26: =IF(COUNT(D26,Supuestos!D18)=2,IF(Supuestos!D18>=0,D26/(1+Supuestos!D18),"N/D"),"N/D") -> 2996.6597 | F26: Experimento; no benchmark
C27: 0.06 | D27: =IF(COUNT(Decision!D11,Supuestos!D45)=2,Decision!D11*C27*Supuestos!D45/12,"N/D") -> 4494.9895 | E27: =IF(COUNT(D27,Supuestos!D18)=2,IF(Supuestos!D18>=0,D27/(1+Supuestos!D18),"N/D"),"N/D") -> 4494.9895 | F27: Extremo; no recomendado
C29: 1/2/4/6% prueban aritmética del valor neto, no tasas bancarias observadas. 6% es extremo sin evidencia y no se recomienda.
C32: Capacidad | D32: Base horas | E32: Reserva horas | F32: Total horas | G32: Estado
C33: Enfocado candidato | D33: 814 | E33: 110 | F33: 924 | G33: Root: bottom-up, pendiente
C34: Foco previo histórico | D34: 1828 | E34: 216 | F34: 2044 | G34: Cuestionado; no base actual
C35: Integral previo histórico | D35: 2560 | E35: 336 | F35: 2896 | G35: Cuestionado; no base actual
C37: Mayor capacidad no produce por sí sola más cuentas. El candidato enfocado limita entregables y requiere implementación/QA coordinados.
C39: La valoración usa UN método Finance neto sobre saldo medio externo. No sumar FTP+ahorro si representan el mismo beneficio.
C40: Las transferencias internas son canibalización potencial; saldo bruto, depósito inicial y capital no son ingreso ni beneficio.
C42: Horizonte de valor 24/36m: sólo valor neto por fondeada aprobado por Finance (incluye descuento/costos). Sin tasa×2/3 ni cashflow futuro inventado.
C43: Servicio sigue12m. El método por cuenta no produce ROI/payback dentro del año; la distribución temporal de beneficios futuros está pendiente.
C45: Inversión hipotética, no quote | D45: Valor mínimo por fondeada | E45: Naturaleza
C46: 10000 | D46: =IF(COUNT(Decision!D20)=1,IF(Decision!D20>0,C46*(1+Supuestos!D18)/Decision!D20,"N/D"),"N/D") -> 101.21457 | E46: Requisito; no valor observado
C47: 25000 | D47: =IF(COUNT(Decision!D20)=1,IF(Decision!D20>0,C47*(1+Supuestos!D18)/Decision!D20,"N/D"),"N/D") -> 253.03644 | E47: Requisito; no valor observado
C48: 50000 | D48: =IF(COUNT(Decision!D20)=1,IF(Decision!D20>0,C48*(1+Supuestos!D18)/Decision!D20,"N/D"),"N/D") -> 506.07287 | E48: Requisito; no valor observado

Sheet Evidencia
C2: Cobertura, carriles y autoridad de cada dato
I5: Panel directo parcial | J5: 3690
C7: Carril | D7: Evidencia disponible | E7: Proxy/medida | F7: Qué permitiría valorar | G7: Baseline actual
C8: Adquisición genérica | D8: Panel curado de5 representantes | E8: 3690 | F8: Captura elegible→visitas→fondeo; panel parcial | G8: N/D
C9: Adquisición condicional | D9: Digital1300 + alto rendimientoPE390 | E9: 1690 | F9: Producto/intención/overlap antes de incluir | G9: N/D
C10: Educación/confianza | D10: TREA/FSD/ahorro/transferencias | E10: 4070 | F10: Asistencia medida; no sumarla a adquisición | G10: N/D
C11: Marca | D11: 140 histórico prelaunch: no baseline actual | E11: Histórico separado | F11: Protección/activación; visitas actuales necesarias | G11: N/D
C12: Conversión multicanal | D12: Recorrido web→registro→app | E12: N/D | F12: Incremento respecto al contrafactual medido | G12: N/D
C13: Retención/origen externo | D13: Cohortes/saldos banco pendientes | E13: N/D | F13: Valor neto incremental, sin doble conteo | G13: N/D
C14: Producto USD futuro | D14: Consulta cuentaUSD | E14: 480 | F14: No pertenece al producto actual público Soles | G14: N/D
C18: 3690 es una canasta de5 consultas de investigación; no censo del programa ni TAM. Dataset ampliado y familias nuevas se documentan aparte.
C19: Sin GSC/analytics, marca postlaunch, aperturas o cohortes: retornos adicionales N/D. No comprar APIs ni inflar proxies para cerrar un ROI.
C22: ID / naturaleza | D22: Fuente | E22: Alcance | F22: Autoridad / estado
C23: Meta provisional | D23: Reunión06/10/2026 y operador | E23: 15200×2500≈US38m; periodo/definición pendientes | F23: Banco no confirmó
C24: Panel observado | D24: docs/commercial/prospects/banco-pichincha-peru-seo-2026/research/pibank-expanded-2026-10-06/monthly-demand-inputs.json | E24: PE/es, cinco representantes con overlap residual | F24: DataForSEO; no TAM
C25: Proyecciones retiradas | D25: modelo-anual/results.json | E25: 10/50/147 no forecasts. Se conservan históricos | F25: Withdrawn for client use
C26: Capacidad candidata | D26: Root: envelope bottom-up06/10 | E26: 814h base +110h reserva, doce meses | F26: Operations/Commercial pendientes
C27: Hipótesis de requisitos | D27: inputs.json | E27: Tasas, distribución, saldos, origen y calendario | F27: Pruebas; no benchmark
C28: Valor bancario | D28: Finance banco: método único pendiente | E28: Tasa neta anual × saldo medio externo dentro2027 | F28: N/D
C29: Costo/quote | D29: Finance/Operations/Commercial pendientes | E29: Fully loaded, otros costos, margen, fee, impuestos | F29: N/D
C32: Retirar de uso con cliente no elimina evidencia histórica: modelo-anual y modelo permanecen byte-for-byte intactos.
C34: M1 readiness/delivery; M3/6/9/12 optimización. Ejecución/caracterización técnica no garantizan rankings, citas ni apertura/fondeo.

Sheet Retrolanzamiento
C2: Retrolanzamiento: ventana desconocida y contrafactual
C5: Jesús pidió qué aperturas habría podido cubrir SEO/GEO desde el lanzamiento de este año. Fecha exacta y ventana no están confirmadas.
C7: Seleccionar Supuestos D29=Retrolanzamiento, cargar fecha D30 y meses D35. El mismo build calcula requisitos y maduración sólo en esa ventana.
C9: Sin fecha/ventana, el modo retrospectivo propaga N/D. Programa2027 mantiene doce meses y no hereda una anualidad no declarada por el banco.
C11: Las bandas152/760/1520 se interpretan como aperturas por defecto. Fondeo y saldo son calidad posterior; selector Fondeadas cambia el requisito.
C13: La simulación es un contrafactual ilustrativo de requisitos; no aperturas históricas perdidas ni causalidad demostrada del lanzamiento.
C15: No existe baseline histórico ni controles de exposición suficientes. Validar ventanas, condiciones de oferta, capacidad de indexación y funnel antes de atribuir.
C17: No transferir un quote/valor aprobado de un contexto a otro sin validación. Los beneficios24/36m futuros se distinguen del saldo/valor dentro de ventana.
C19: Para próximos lanzamientos: preparar arquitectura/contenidos/métricas antes del go-live, medir recorridos y optimizar cohortes durante el programa.
